Workbook
Name L_Family_Members: '⚙️ Settings'!$A$13:$A$18
Name L_Account_Master: '⚙️ Settings'!$C$13:$C$28
Name L_Categories: '⚙️ Settings'!$E$13:$E$23
Name L_Subcategories: '⚙️ Settings'!$G$13:$G$77
Name L_Income_Sources: '⚙️ Settings'!$I$13:$I$23
Name L_Pay_Frequencies: '⚙️ Settings'!$K$13:$K$17
Name L_Account_Types: '⚙️ Settings'!$M$13:$M$28
Name L_Payment_Methods: '⚙️ Settings'!$O$13:$O$19
Name L_Transaction_Types: '⚙️ Settings'!$Q$13:$Q$15
Name L_Bill_Frequencies: '⚙️ Settings'!$S$13:$S$19
Name L_Yes_No: '⚙️ Settings'!$U$13:$U$14
Name L_Essential_Discretionary: '⚙️ Settings'!$W$13:$W$14
Name L_Months: '⚙️ Settings'!$Y$13:$Y$24
Name L_Filing_Status: '⚙️ Settings'!$AA$13:$AA$17
Name L_Debt_Types: '⚙️ Settings'!$AC$13:$AC$18
Name L_Goal_Types: '⚙️ Settings'!$AE$13:$AE$23
Name L_Investment_Types: '⚙️ Settings'!$AG$13:$AG$23
Name C_Date: '⚙️ Settings'!$B$5
Name C_Month: '⚙️ Settings'!$B$6
Name C_Year: '⚙️ Settings'!$B$7

Sheet 🏠 Dashboard
A1: 🏠 Family Financial Dashboard
A2: Your entire household on one screen. Every number below flows automatically from the other tabs.
A4: Report Period | B4: =TEXT(C_Date,"mmmm yyyy")
A6: MONTHLY SNAPSHOT
A7: Gross Monthly Income | B7: =SUMIFS('💰 Income'!$M$4:$M$203,'💰 Income'!$O$4:$O$203,C_Month,'💰 Income'!$P$4:$P$203,C_Year)
A8: Monthly Spending | B8: =SUMIFS('💳 Transactions'!$F$4:$F$403,'💳 Transactions'!$B$4:$B$403,"Expense",'💳 Transactions'!$O$4:$O$403,C_Month,'💳 Transactions'!$P$4:$P$403,C_Year)
A9: Surplus / (Deficit) | B9: =B7-B8
A10: Savings Rate | B10: =IF(B7=0,"",B9/B7)
A11: Bills Due This Month | B11: =SUMIFS('🧾 Bills & Subs'!$B$4:$B$303,'🧾 Bills & Subs'!$K$4:$K$303,C_Month,'🧾 Bills & Subs'!$L$4:$L$303,C_Year)
A12: Monthly Budget | B12: ='📋 Budget'!$C$81
A13: Budget vs Actual Variance | B13: =B12-B8
A14: YTD Spending | B14: =SUMIFS('💳 Transactions'!$F$4:$F$403,'💳 Transactions'!$B$4:$B$403,"Expense",'💳 Transactions'!$P$4:$P$403,C_Year)
A16: CASH & DEBT POSITION
A17: Total Assets | B17: =SUMIF('🏦 Accounts'!$B$4:$B$103,"Checking",'🏦 Accounts'!$D$4:$D$103)+SUMIF('🏦 Accounts'!$B$4:$B$103,"Savings",'🏦 Accounts'!$D$4:$D$103)+SUMIF('🏦 Accounts'!$B$4:$B$103,"HYSA",'🏦 Accounts'!$D$4:$D$103)+SUMIF('🏦 Accounts'!$B$4:$B$103,"Cash",'🏦 Accounts'!$D$4:$D$103)+SUMIF('🏦 Accounts'!$B$4:$B$103,"401(k)",'🏦 Accounts'!$D$4:$D$103)+SUMIF('🏦 Accounts'!$B$4:$B$103,"403(b)",'🏦 Accounts'!$D$4:$D$103)+SUMIF('🏦 Accounts'!$B$4:$B$103,"IRA",'🏦 Accounts'!$D$4:$D$103)+SUMIF('🏦 Accounts'!$B$4:$B$103,"Roth IRA",'🏦 Accounts'!$D$4:$D$103)+SUMIF('🏦 Accounts'!$B$4:$B$103,"Brokerage",'🏦 Accounts'!$D$4:$D$103)+SUMIF('🏦 Accounts'!$B$4:$B$103,"529",'🏦 Accounts'!$D$4:$D$103)+SUMIF('🏦 Accounts'!$B$4:$B$103,"HSA",'🏦 Accounts'!$D$4:$D$103)+SUMIF('🏦 Accounts'!$B$4:$B$103,"FSA",'🏦 Accounts'!$D$4:$D$103)+SUMIF('🏦 Accounts'!$B$4:$B$103,"CD",'🏦 Accounts'!$D$4:$D$103)+SUMIF('🏦 Accounts'!$B$4:$B$103,"Other Investment",'🏦 Accounts'!$D$4:$D$103)+'🏡 Home & Mortgage'!$B$5+SUM('🚗 Vehicles'!$L$4:$L$33)
A18: Total Liabilities | B18: =SUMIFS('🏦 Accounts'!$D$4:$D$103,'🏦 Accounts'!$B$4:$B$103,"Credit Card")+SUMIFS('💸 Debt Manager'!$D$8:$D$107,'💸 Debt Manager'!$C$8:$C$107,"<>Credit Card")+'🏡 Home & Mortgage'!$B$10
A19: Net Worth | B19: =B17-B18
A20: Total Debt | B20: =SUMIFS('🏦 Accounts'!$D$4:$D$103,'🏦 Accounts'!$B$4:$B$103,"Credit Card")+SUMIFS('💸 Debt Manager'!$D$8:$D$107,'💸 Debt Manager'!$C$8:$C$107,"<>Credit Card")+'🏡 Home & Mortgage'!$B$10
A21: Cash Available | B21: =SUMIF('🏦 Accounts'!$B$4:$B$103,"Checking",'🏦 Accounts'!$D$4:$D$103)+SUMIF('🏦 Accounts'!$B$4:$B$103,"Savings",'🏦 Accounts'!$D$4:$D$103)+SUMIF('🏦 Accounts'!$B$4:$B$103,"HYSA",'🏦 Accounts'!$D$4:$D$103)+SUMIF('🏦 Accounts'!$B$4:$B$103,"Cash",'🏦 Accounts'!$D$4:$D$103)
A22: Emergency Fund (liquid) | B22: =SUMIFS('🏦 Accounts'!$D$4:$D$103,'🏦 Accounts'!$B$4:$B$103,"Savings")+SUMIFS('🏦 Accounts'!$D$4:$D$103,'🏦 Accounts'!$B$4:$B$103,"HYSA")+SUMIFS('🏦 Accounts'!$D$4:$D$103,'🏦 Accounts'!$B$4:$B$103,"Cash")
A23: Credit Available | B23: =SUMIF('🏦 Accounts'!$B$4:$B$103,"Credit Card",'🏦 Accounts'!$E$4:$E$103)-SUMIFS('🏦 Accounts'!$D$4:$D$103,'🏦 Accounts'!$B$4:$B$103,"Credit Card")
A25: YEAR-TO-DATE
A26: YTD Savings | B26: =B7-B8
A27: YTD Savings Rate | B27: =IFERROR((B7-B8)/B7,"")
A28: Avg Monthly Spend | B28: ='📊 Analytics'!$H$6
A29: Subscriptions (YTD) | B29: =SUMIFS('💳 Transactions'!$F$4:$F$403,'💳 Transactions'!$D$4:$D$403,"Subscriptions",'💳 Transactions'!$P$4:$P$403,C_Year)
A30: Goals Completion % | B30: =IF(SUM('🎯 Goals & Funds'!$C$4:$C$103)=0,"",SUM('🎯 Goals & Funds'!$D$4:$D$103)/SUM('🎯 Goals & Funds'!$C$4:$C$103))
A31: Goals Total Saved | B31: =SUM('🎯 Goals & Funds'!$D$4:$D$103)
A32: Goals Total Target | B32: =SUM('🎯 Goals & Funds'!$C$4:$C$103)
A34: ALERTS
A35: Emergency Fund (months covered) | B35: =IFERROR((SUMIFS('🏦 Accounts'!$D$4:$D$103,'🏦 Accounts'!$B$4:$B$103,"Savings")+SUMIFS('🏦 Accounts'!$D$4:$D$103,'🏦 Accounts'!$B$4:$B$103,"HYSA")+SUMIFS('🏦 Accounts'!$D$4:$D$103,'🏦 Accounts'!$B$4:$B$103,"Cash"))/'📊 Analytics'!$H$6,"") | C35: =IF(B35="","",IF(B35<3,"🔴 Under 3 months",IF(B35<6,"🟡 3-6 months","🟢 6+ months")))
A36: Budget Status (this month) | B36: =B13 | C36: =IF(B36="","",IF(B36<0,"🟡 Over budget","🟢 Under budget"))
A37: Savings Rate vs 20% target | B37: =IF(B7=0,"",B9/B7) | C37: =IF(B37="","",IF(B37>=0.2,"🟢 20%+ saved","🟡 Below 20% target"))
A38: Credit Utilization | B38: =IF(SUMIF('🏦 Accounts'!$B$4:$B$103,"Credit Card",'🏦 Accounts'!$E$4:$E$103)=0,"",SUMIFS('🏦 Accounts'!$D$4:$D$103,'🏦 Accounts'!$B$4:$B$103,"Credit Card")/SUMIF('🏦 Accounts'!$B$4:$B$103,"Credit Card",'🏦 Accounts'!$E$4:$E$103)) | C38: =IF(B38="","",IF(B38>0.3,"🔴 High utilization",IF(B38>0.1,"🟡 Moderate","🟢 Low utilization")))
A41: GOALS & SINKING FUNDS
A42: Goal | B42: Target | C42: Current | D42: % Complete | E42: Status
A43: ='🎯 Goals & Funds'!$A$4 | B43: ='🎯 Goals & Funds'!$C$4 | C43: ='🎯 Goals & Funds'!$D$4 | D43: ='🎯 Goals & Funds'!$H$4 | E43: =IF(D43="","",IF(D43>=1,"🏆 Complete","🔵 In progress"))
A44: ='🎯 Goals & Funds'!$A$5 | B44: ='🎯 Goals & Funds'!$C$5 | C44: ='🎯 Goals & Funds'!$D$5 | D44: ='🎯 Goals & Funds'!$H$5 | E44: =IF(D44="","",IF(D44>=1,"🏆 Complete","🔵 In progress"))
A45: ='🎯 Goals & Funds'!$A$6 | B45: ='🎯 Goals & Funds'!$C$6 | C45: ='🎯 Goals & Funds'!$D$6 | D45: ='🎯 Goals & Funds'!$H$6 | E45: =IF(D45="","",IF(D45>=1,"🏆 Complete","🔵 In progress"))
A46: ='🎯 Goals & Funds'!$A$7 | B46: ='🎯 Goals & Funds'!$C$7 | C46: ='🎯 Goals & Funds'!$D$7 | D46: ='🎯 Goals & Funds'!$H$7 | E46: =IF(D46="","",IF(D46>=1,"🏆 Complete","🔵 In progress"))
A47: ='🎯 Goals & Funds'!$A$8 | B47: ='🎯 Goals & Funds'!$C$8 | C47: ='🎯 Goals & Funds'!$D$8 | D47: ='🎯 Goals & Funds'!$H$8 | E47: =IF(D47="","",IF(D47>=1,"🏆 Complete","🔵 In progress"))
A48: ='🎯 Goals & Funds'!$A$9 | B48: ='🎯 Goals & Funds'!$C$9 | C48: ='🎯 Goals & Funds'!$D$9 | D48: ='🎯 Goals & Funds'!$H$9 | E48: =IF(D48="","",IF(D48>=1,"🏆 Complete","🔵 In progress"))

Sheet 💰 Income
A1: 💰 Income Tracker
A2: List every paycheck & income stream. Net take-home is auto-computed from gross minus deductions.
A3: Earner | B3: Source | C3: Pay Frequency | D3: Pay Date | E3: Gross | F3: Federal Tax | G3: State/Local Tax | H3: Social Security Tax | I3: Medicare Tax | J3: 401(k)/403(b) | K3: HSA/FSA | L3: Other Deductions | M3: Net Take-Home | N3: Remarks | O3: Month | P3: Year | Q3: Day
A4: Parent 1 | B4: Salary | C4: Biweekly | D4: 46027 | E4: 2600 | F4: 210 | G4: 95 | H4: 161 | I4: 38 | J4: 260 | K4: 0 | L4: 60 | M4: =IF(E4="","",E4-SUM(F4:L4)) | O4: =IF(D4="","",MONTH(D4)) | P4: =IF(D4="","",YEAR(D4)) | Q4: =IF(D4="","",DAY(D4))
A5: Parent 1 | B5: Salary | C5: Biweekly | D5: 46041 | E5: 2600 | F5: 210 | G5: 95 | H5: 161 | I5: 38 | J5: 260 | K5: 0 | L5: 60 | M5: =IF(E5="","",E5-SUM(F5:L5)) | O5: =IF(D5="","",MONTH(D5)) | P5: =IF(D5="","",YEAR(D5)) | Q5: =IF(D5="","",DAY(D5))
A6: Parent 2 | B6: Salary | C6: Twice Monthly | D6: 46030 | E6: 1720 | F6: 140 | G6: 62 | H6: 107 | I6: 25 | J6: 170 | K6: 0 | L6: 40 | M6: =IF(E6="","",E6-SUM(F6:L6)) | O6: =IF(D6="","",MONTH(D6)) | P6: =IF(D6="","",YEAR(D6)) | Q6: =IF(D6="","",DAY(D6))
A7: Parent 2 | B7: Salary | C7: Twice Monthly | D7: 46045 | E7: 1720 | F7: 140 | G7: 62 | H7: 107 | I7: 25 | J7: 170 | K7: 0 | L7: 40 | M7: =IF(E7="","",E7-SUM(F7:L7)) | O7: =IF(D7="","",MONTH(D7)) | P7: =IF(D7="","",YEAR(D7)) | Q7: =IF(D7="","",DAY(D7))
A8: Parent 1 | B8: Salary | C8: Biweekly | D8: 46058 | E8: 2600 | F8: 210 | G8: 95 | H8: 161 | I8: 38 | J8: 260 | K8: 0 | L8: 60 | M8: =IF(E8="","",E8-SUM(F8:L8)) | O8: =IF(D8="","",MONTH(D8)) | P8: =IF(D8="","",YEAR(D8)) | Q8: =IF(D8="","",DAY(D8))
A9: Parent 1 | B9: Salary | C9: Biweekly | D9: 46072 | E9: 2600 | F9: 210 | G9: 95 | H9: 161 | I9: 38 | J9: 260 | K9: 0 | L9: 60 | M9: =IF(E9="","",E9-SUM(F9:L9)) | O9: =IF(D9="","",MONTH(D9)) | P9: =IF(D9="","",YEAR(D9)) | Q9: =IF(D9="","",DAY(D9))
A10: Parent 2 | B10: Salary | C10: Twice Monthly | D10: 46061 | E10: 1720 | F10: 140 | G10: 62 | H10: 107 | I10: 25 | J10: 170 | K10: 0 | L10: 40 | M10: =IF(E10="","",E10-SUM(F10:L10)) | O10: =IF(D10="","",MONTH(D10)) | P10: =IF(D10="","",YEAR(D10)) | Q10: =IF(D10="","",DAY(D10))
A11: Parent 2 | B11: Salary | C11: Twice Monthly | D11: 46076 | E11: 1720 | F11: 140 | G11: 62 | H11: 107 | I11: 25 | J11: 170 | K11: 0 | L11: 40 | M11: =IF(E11="","",E11-SUM(F11:L11)) | O11: =IF(D11="","",MONTH(D11)) | P11: =IF(D11="","",YEAR(D11)) | Q11: =IF(D11="","",DAY(D11))
A12: Parent 1 | B12: Salary | C12: Biweekly | D12: 46086 | E12: 2600 | F12: 210 | G12: 95 | H12: 161 | I12: 38 | J12: 260 | K12: 0 | L12: 60 | M12: =IF(E12="","",E12-SUM(F12:L12)) | O12: =IF(D12="","",MONTH(D12)) | P12: =IF(D12="","",YEAR(D12)) | Q12: =IF(D12="","",DAY(D12))
A13: Parent 1 | B13: Salary | C13: Biweekly | D13: 46100 | E13: 2600 | F13: 210 | G13: 95 | H13: 161 | I13: 38 | J13: 260 | K13: 0 | L13: 60 | M13: =IF(E13="","",E13-SUM(F13:L13)) | O13: =IF(D13="","",MONTH(D13)) | P13: =IF(D13="","",YEAR(D13)) | Q13: =IF(D13="","",DAY(D13))
A14: Parent 2 | B14: Salary | C14: Twice Monthly | D14: 46089 | E14: 1720 | F14: 140 | G14: 62 | H14: 107 | I14: 25 | J14: 170 | K14: 0 | L14: 40 | M14: =IF(E14="","",E14-SUM(F14:L14)) | O14: =IF(D14="","",MONTH(D14)) | P14: =IF(D14="","",YEAR(D14)) | Q14: =IF(D14="","",DAY(D14))
A15: Parent 2 | B15: Salary | C15: Twice Monthly | D15: 46104 | E15: 1720 | F15: 140 | G15: 62 | H15: 107 | I15: 25 | J15: 170 | K15: 0 | L15: 40 | M15: =IF(E15="","",E15-SUM(F15:L15)) | O15: =IF(D15="","",MONTH(D15)) | P15: =IF(D15="","",YEAR(D15)) | Q15: =IF(D15="","",DAY(D15))
... A37: Parent 1 | B37: Freelance/Side Hustle | C37: Irregular | D37: 46254 | E37: 650 | F37: 0 | G37: 0 | H37: 0 | I37: 0 | J37: 0 | K37: 0 | L37: 0 | M37: =IF(E37="","",E37-SUM(F37:L37)) | O37: =IF(D37="","",MONTH(D37)) | P37: =IF(D37="","",YEAR(D37)) | Q37: =IF(D37="","",DAY(D37))
M38: =IF(E38="","",E38-SUM(F38:L38)) | O38: =IF(D38="","",MONTH(D38)) | P38: =IF(D38="","",YEAR(D38)) | Q38: =IF(D38="","",DAY(D38))
M39: =IF(E39="","",E39-SUM(F39:L39)) | O39: =IF(D39="","",MONTH(D39)) | P39: =IF(D39="","",YEAR(D39)) | Q39: =IF(D39="","",DAY(D39))
M40: =IF(E40="","",E40-SUM(F40:L40)) | O40: =IF(D40="","",MONTH(D40)) | P40: =IF(D40="","",YEAR(D40)) | Q40: =IF(D40="","",DAY(D40))
M41: =IF(E41="","",E41-SUM(F41:L41)) | O41: =IF(D41="","",MONTH(D41)) | P41: =IF(D41="","",YEAR(D41)) | Q41: =IF(D41="","",DAY(D41))
M42: =IF(E42="","",E42-SUM(F42:L42)) | O42: =IF(D42="","",MONTH(D42)) | P42: =IF(D42="","",YEAR(D42)) | Q42: =IF(D42="","",DAY(D42))
M43: =IF(E43="","",E43-SUM(F43:L43)) | O43: =IF(D43="","",MONTH(D43)) | P43: =IF(D43="","",YEAR(D43)) | Q43: =IF(D43="","",DAY(D43))
M44: =IF(E44="","",E44-SUM(F44:L44)) | O44: =IF(D44="","",MONTH(D44)) | P44: =IF(D44="","",YEAR(D44)) | Q44: =IF(D44="","",DAY(D44))
M45: =IF(E45="","",E45-SUM(F45:L45)) | O45: =IF(D45="","",MONTH(D45)) | P45: =IF(D45="","",YEAR(D45)) | Q45: =IF(D45="","",DAY(D45))
M46: =IF(E46="","",E46-SUM(F46:L46)) | O46: =IF(D46="","",MONTH(D46)) | P46: =IF(D46="","",YEAR(D46)) | Q46: =IF(D46="","",DAY(D46))
M47: =IF(E47="","",E47-SUM(F47:L47)) | O47: =IF(D47="","",MONTH(D47)) | P47: =IF(D47="","",YEAR(D47)) | Q47: =IF(D47="","",DAY(D47))
M48: =IF(E48="","",E48-SUM(F48:L48)) | O48: =IF(D48="","",MONTH(D48)) | P48: =IF(D48="","",YEAR(D48)) | Q48: =IF(D48="","",DAY(D48))
M49: =IF(E49="","",E49-SUM(F49:L49)) | O49: =IF(D49="","",MONTH(D49)) | P49: =IF(D49="","",YEAR(D49)) | Q49: =IF(D49="","",DAY(D49))
... M203: =IF(E203="","",E203-SUM(F203:L203)) | O203: =IF(D203="","",MONTH(D203)) | P203: =IF(D203="","",YEAR(D203)) | Q203: =IF(D203="","",DAY(D203))

Sheet 💳 Transactions
A1: 💳 Transaction Ledger
A2: Your single source of truth. Enter each transaction once — the Dashboard, Budget and Analytics read from here. Cream cells are input.
A3: Date | B3: Type | C3: Category | D3: Subcategory | E3: Merchant | F3: Amount | G3: Account | H3: Payment Method | I3: Family Member | J3: Recurring? | K3: Ess/Discretionary | L3: Notes | M3: Tax Deductible? | N3: Reimbursable? | O3: Month | P3: Year | Q3: Day
A4: 46086 | B4: Expense | C4: Housing | D4: Utilities | E4: Water & Sewer | F4: 52.67 | G4: Checking | H4: Checking | I4: Parent 2 | J4: No | K4: Essential | M4: No | N4: No | O4: =IF(A4="","",MONTH(A4)) | P4: =IF(A4="","",YEAR(A4)) | Q4: =IF(A4="","",DAY(A4))
A5: 46087 | B5: Expense | C5: Family | D5: Baby Expenses | E5: Buy Buy Baby | F5: 44.26 | G5: HYSA | H5: Cash | I5: Household | J5: No | K5: Discretionary | M5: No | N5: No | O5: =IF(A5="","",MONTH(A5)) | P5: =IF(A5="","",YEAR(A5)) | Q5: =IF(A5="","",DAY(A5))
A6: 46087 | B6: Expense | C6: Financial | D6: Retirement | E6: 401(k) Contribution | F6: 518.71 | G6: Credit Card | H6: Credit Card | I6: Household | J6: Yes | K6: Essential | M6: No | N6: No | O6: =IF(A6="","",MONTH(A6)) | P6: =IF(A6="","",YEAR(A6)) | Q6: =IF(A6="","",DAY(A6))
A7: 46088 | B7: Expense | C7: Housing | D7: Repairs/Maintenance | E7: Handyman | F7: 129.99 | G7: Checking | H7: Checking | I7: Parent 1 | J7: No | K7: Discretionary | M7: No | N7: No | O7: =IF(A7="","",MONTH(A7)) | P7: =IF(A7="","",YEAR(A7)) | Q7: =IF(A7="","",DAY(A7))
A8: 46088 | B8: Expense | C8: Healthcare | D8: Health Insurance | E8: BCBS | F8: 46.82 | G8: HYSA | H8: Cash | I8: Parent 1 | J8: No | K8: Discretionary | M8: No | N8: No | O8: =IF(A8="","",MONTH(A8)) | P8: =IF(A8="","",YEAR(A8)) | Q8: =IF(A8="","",DAY(A8))
A9: 46089 | B9: Expense | C9: Housing | D9: Mortgage/Rent | E9: Home Mortgage | F9: 23.15 | G9: HYSA | H9: Cash | I9: Parent 2 | J9: No | K9: Discretionary | M9: No | N9: No | O9: =IF(A9="","",MONTH(A9)) | P9: =IF(A9="","",YEAR(A9)) | Q9: =IF(A9="","",DAY(A9))
A10: 46089 | B10: Expense | C10: Lifestyle | D10: Personal Care | E10: Ulta | F10: 41.79 | G10: Checking | H10: Checking | I10: Household | J10: No | K10: Discretionary | M10: No | N10: No | O10: =IF(A10="","",MONTH(A10)) | P10: =IF(A10="","",YEAR(A10)) | Q10: =IF(A10="","",DAY(A10))
A11: 46090 | B11: Expense | C11: Food | D11: Groceries | E11: Kroger | F11: 38.88 | G11: Credit Card | H11: Credit Card | I11: Household | J11: No | K11: Discretionary | M11: No | N11: No | O11: =IF(A11="","",MONTH(A11)) | P11: =IF(A11="","",YEAR(A11)) | Q11: =IF(A11="","",DAY(A11))
A12: 46090 | B12: Expense | C12: Lifestyle | D12: Shopping | E12: Amazon | F12: 56.69 | G12: HYSA | H12: Cash | I12: Household | J12: No | K12: Discretionary | M12: No | N12: No | O12: =IF(A12="","",MONTH(A12)) | P12: =IF(A12="","",YEAR(A12)) | Q12: =IF(A12="","",DAY(A12))
A13: 46090 | B13: Expense | C13: Pets | D13: Food | E13: PetSmart | F13: 58.61 | G13: Savings | H13: Savings | I13: Parent 2 | J13: No | K13: Discretionary | M13: No | N13: No | O13: =IF(A13="","",MONTH(A13)) | P13: =IF(A13="","",YEAR(A13)) | Q13: =IF(A13="","",DAY(A13))
A14: 46091 | B14: Expense | C14: Transportation | D14: Maintenance/Repairs | E14: Auto Shop | F14: 26.74 | G14: Credit Card | H14: Credit Card | I14: Parent 1 | J14: No | K14: Discretionary | M14: No | N14: No | O14: =IF(A14="","",MONTH(A14)) | P14: =IF(A14="","",YEAR(A14)) | Q14: =IF(A14="","",DAY(A14))
A15: 46091 | B15: Expense | C15: Healthcare | D15: Medical Expenses | E15: Dr. Office | F15: 38.51 | G15: Checking | H15: Checking | I15: Household | J15: No | K15: Essential | M15: No | N15: No | O15: =IF(A15="","",MONTH(A15)) | P15: =IF(A15="","",YEAR(A15)) | Q15: =IF(A15="","",DAY(A15))
... A216: 46261 | B216: Expense | C216: Giving | D216: Charity | E216: Red Cross | F216: 31.55 | G216: HYSA | H216: Cash | I216: Household | J216: No | K216: Discretionary | M216: No | N216: No | O216: =IF(A216="","",MONTH(A216)) | P216: =IF(A216="","",YEAR(A216)) | Q216: =IF(A216="","",DAY(A216))
O217: =IF(A217="","",MONTH(A217)) | P217: =IF(A217="","",YEAR(A217)) | Q217: =IF(A217="","",DAY(A217))
O218: =IF(A218="","",MONTH(A218)) | P218: =IF(A218="","",YEAR(A218)) | Q218: =IF(A218="","",DAY(A218))
O219: =IF(A219="","",MONTH(A219)) | P219: =IF(A219="","",YEAR(A219)) | Q219: =IF(A219="","",DAY(A219))
O220: =IF(A220="","",MONTH(A220)) | P220: =IF(A220="","",YEAR(A220)) | Q220: =IF(A220="","",DAY(A220))
O221: =IF(A221="","",MONTH(A221)) | P221: =IF(A221="","",YEAR(A221)) | Q221: =IF(A221="","",DAY(A221))
O222: =IF(A222="","",MONTH(A222)) | P222: =IF(A222="","",YEAR(A222)) | Q222: =IF(A222="","",DAY(A222))
O223: =IF(A223="","",MONTH(A223)) | P223: =IF(A223="","",YEAR(A223)) | Q223: =IF(A223="","",DAY(A223))
O224: =IF(A224="","",MONTH(A224)) | P224: =IF(A224="","",YEAR(A224)) | Q224: =IF(A224="","",DAY(A224))
O225: =IF(A225="","",MONTH(A225)) | P225: =IF(A225="","",YEAR(A225)) | Q225: =IF(A225="","",DAY(A225))
O226: =IF(A226="","",MONTH(A226)) | P226: =IF(A226="","",YEAR(A226)) | Q226: =IF(A226="","",DAY(A226))
O227: =IF(A227="","",MONTH(A227)) | P227: =IF(A227="","",YEAR(A227)) | Q227: =IF(A227="","",DAY(A227))
O228: =IF(A228="","",MONTH(A228)) | P228: =IF(A228="","",YEAR(A228)) | Q228: =IF(A228="","",DAY(A228))
... O403: =IF(A403="","",MONTH(A403)) | P403: =IF(A403="","",YEAR(A403)) | Q403: =IF(A403="","",DAY(A403))

Sheet 📋 Budget
A1: 📋 Complete Family Budget
A2: Set a monthly limit per subcategory. Actuals pull live from the Transaction Ledger; variance is automatic.
A3: Category | B3: Subcategory | C3: Monthly Budget | D3: Actual This Month | E3: Actual YTD | F3: Variance (This Month) | G3: % of Budget | H3: Notes
A4: Housing | B4: Mortgage/Rent | C4: 1250 | D4: =SUMIFS('💳 Transactions'!$F$4:$F$403,'💳 Transactions'!$C$4:$C$403,A4,'💳 Transactions'!$D$4:$D$403,B4,'💳 Transactions'!$B$4:$B$403,"Expense",'💳 Transactions'!$O$4:$O$403,C_Month,'💳 Transactions'!$P$4:$P$403,C_Year) | E4: =SUMIFS('💳 Transactions'!$F$4:$F$403,'💳 Transactions'!$C$4:$C$403,A4,'💳 Transactions'!$D$4:$D$403,B4,'💳 Transactions'!$B$4:$B$403,"Expense",'💳 Transactions'!$P$4:$P$403,C_Year) | F4: =IF(C4="","",C4-D4) | G4: =IF(C4="","",IF(C4=0,"",D4/C4))
A5: Housing | B5: Property Tax | C5: 185 | D5: =SUMIFS('💳 Transactions'!$F$4:$F$403,'💳 Transactions'!$C$4:$C$403,A5,'💳 Transactions'!$D$4:$D$403,B5,'💳 Transactions'!$B$4:$B$403,"Expense",'💳 Transactions'!$O$4:$O$403,C_Month,'💳 Transactions'!$P$4:$P$403,C_Year) | E5: =SUMIFS('💳 Transactions'!$F$4:$F$403,'💳 Transactions'!$C$4:$C$403,A5,'💳 Transactions'!$D$4:$D$403,B5,'💳 Transactions'!$B$4:$B$403,"Expense",'💳 Transactions'!$P$4:$P$403,C_Year) | F5: =IF(C5="","",C5-D5) | G5: =IF(C5="","",IF(C5=0,"",D5/C5))
A6: Housing | B6: HOA | C6: 35 | D6: =SUMIFS('💳 Transactions'!$F$4:$F$403,'💳 Transactions'!$C$4:$C$403,A6,'💳 Transactions'!$D$4:$D$403,B6,'💳 Transactions'!$B$4:$B$403,"Expense",'💳 Transactions'!$O$4:$O$403,C_Month,'💳 Transactions'!$P$4:$P$403,C_Year) | E6: =SUMIFS('💳 Transactions'!$F$4:$F$403,'💳 Transactions'!$C$4:$C$403,A6,'💳 Transactions'!$D$4:$D$403,B6,'💳 Transactions'!$B$4:$B$403,"Expense",'💳 Transactions'!$P$4:$P$403,C_Year) | F6: =IF(C6="","",C6-D6) | G6: =IF(C6="","",IF(C6=0,"",D6/C6))
A7: Housing | B7: Home Insurance | C7: 90 | D7: =SUMIFS('💳 Transactions'!$F$4:$F$403,'💳 Transactions'!$C$4:$C$403,A7,'💳 Transactions'!$D$4:$D$403,B7,'💳 Transactions'!$B$4:$B$403,"Expense",'💳 Transactions'!$O$4:$O$403,C_Month,'💳 Transactions'!$P$4:$P$403,C_Year) | E7: =SUMIFS('💳 Transactions'!$F$4:$F$403,'💳 Transactions'!$C$4:$C$403,A7,'💳 Transactions'!$D$4:$D$403,B7,'💳 Transactions'!$B$4:$B$403,"Expense",'💳 Transactions'!$P$4:$P$403,C_Year) | F7: =IF(C7="","",C7-D7) | G7: =IF(C7="","",IF(C7=0,"",D7/C7))
A8: Housing | B8: Repairs/Maintenance | C8: 85 | D8: =SUMIFS('💳 Transactions'!$F$4:$F$403,'💳 Transactions'!$C$4:$C$403,A8,'💳 Transactions'!$D$4:$D$403,B8,'💳 Transactions'!$B$4:$B$403,"Expense",'💳 Transactions'!$O$4:$O$403,C_Month,'💳 Transactions'!$P$4:$P$403,C_Year) | E8: =SUMIFS('💳 Transactions'!$F$4:$F$403,'💳 Transactions'!$C$4:$C$403,A8,'💳 Transactions'!$D$4:$D$403,B8,'💳 Transactions'!$B$4:$B$403,"Expense",'💳 Transactions'!$P$4:$P$403,C_Year) | F8: =IF(C8="","",C8-D8) | G8: =IF(C8="","",IF(C8=0,"",D8/C8))
A9: Housing | B9: Utilities | C9: 235 | D9: =SUMIFS('💳 Transactions'!$F$4:$F$403,'💳 Transactions'!$C$4:$C$403,A9,'💳 Transactions'!$D$4:$D$403,B9,'💳 Transactions'!$B$4:$B$403,"Expense",'💳 Transactions'!$O$4:$O$403,C_Month,'💳 Transactions'!$P$4:$P$403,C_Year) | E9: =SUMIFS('💳 Transactions'!$F$4:$F$403,'💳 Transactions'!$C$4:$C$403,A9,'💳 Transactions'!$D$4:$D$403,B9,'💳 Transactions'!$B$4:$B$403,"Expense",'💳 Transactions'!$P$4:$P$403,C_Year) | F9: =IF(C9="","",C9-D9) | G9: =IF(C9="","",IF(C9=0,"",D9/C9))
A10: Housing | B10: Other Housing | D10: =SUMIFS('💳 Transactions'!$F$4:$F$403,'💳 Transactions'!$C$4:$C$403,A10,'💳 Transactions'!$D$4:$D$403,B10,'💳 Transactions'!$B$4:$B$403,"Expense",'💳 Transactions'!$O$4:$O$403,C_Month,'💳 Transactions'!$P$4:$P$403,C_Year) | E10: =SUMIFS('💳 Transactions'!$F$4:$F$403,'💳 Transactions'!$C$4:$C$403,A10,'💳 Transactions'!$D$4:$D$403,B10,'💳 Transactions'!$B$4:$B$403,"Expense",'💳 Transactions'!$P$4:$P$403,C_Year) | F10: =IF(C10="","",C10-D10) | G10: =IF(C10="","",IF(C10=0,"",D10/C10))
A11: Housing | B11: Category Subtotal | C11: =SUM(C4:C10) | D11: =SUM(D4:D10) | E11: =SUM(E4:E10) | F11: =SUM(F4:F10) | G11: =IF(C11=0,"",D11/C11)
A12: Transportation | B12: Car Payments | C12: 265 | D12: =SUMIFS('💳 Transactions'!$F$4:$F$403,'💳 Transactions'!$C$4:$C$403,A12,'💳 Transactions'!$D$4:$D$403,B12,'💳 Transactions'!$B$4:$B$403,"Expense",'💳 Transactions'!$O$4:$O$403,C_Month,'💳 Transactions'!$P$4:$P$403,C_Year) | E12: =SUMIFS('💳 Transactions'!$F$4:$F$403,'💳 Transactions'!$C$4:$C$403,A12,'💳 Transactions'!$D$4:$D$403,B12,'💳 Transactions'!$B$4:$B$403,"Expense",'💳 Transactions'!$P$4:$P$403,C_Year) | F12: =IF(C12="","",C12-D12) | G12: =IF(C12="","",IF(C12=0,"",D12/C12))
A13: Transportation | B13: Gas | C13: 140 | D13: =SUMIFS('💳 Transactions'!$F$4:$F$403,'💳 Transactions'!$C$4:$C$403,A13,'💳 Transactions'!$D$4:$D$403,B13,'💳 Transactions'!$B$4:$B$403,"Expense",'💳 Transactions'!$O$4:$O$403,C_Month,'💳 Transactions'!$P$4:$P$403,C_Year) | E13: =SUMIFS('💳 Transactions'!$F$4:$F$403,'💳 Transactions'!$C$4:$C$403,A13,'💳 Transactions'!$D$4:$D$403,B13,'💳 Transactions'!$B$4:$B$403,"Expense",'💳 Transactions'!$P$4:$P$403,C_Year) | F13: =IF(C13="","",C13-D13) | G13: =IF(C13="","",IF(C13=0,"",D13/C13))
A14: Transportation | B14: Auto Insurance | C14: 85 | D14: =SUMIFS('💳 Transactions'!$F$4:$F$403,'💳 Transactions'!$C$4:$C$403,A14,'💳 Transactions'!$D$4:$D$403,B14,'💳 Transactions'!$B$4:$B$403,"Expense",'💳 Transactions'!$O$4:$O$403,C_Month,'💳 Transactions'!$P$4:$P$403,C_Year) | E14: =SUMIFS('💳 Transactions'!$F$4:$F$403,'💳 Transactions'!$C$4:$C$403,A14,'💳 Transactions'!$D$4:$D$403,B14,'💳 Transactions'!$B$4:$B$403,"Expense",'💳 Transactions'!$P$4:$P$403,C_Year) | F14: =IF(C14="","",C14-D14) | G14: =IF(C14="","",IF(C14=0,"",D14/C14))
A15: Transportation | B15: Maintenance/Repairs | C15: 65 | D15: =SUMIFS('💳 Transactions'!$F$4:$F$403,'💳 Transactions'!$C$4:$C$403,A15,'💳 Transactions'!$D$4:$D$403,B15,'💳 Transactions'!$B$4:$B$403,"Expense",'💳 Transactions'!$O$4:$O$403,C_Month,'💳 Transactions'!$P$4:$P$403,C_Year) | E15: =SUMIFS('💳 Transactions'!$F$4:$F$403,'💳 Transactions'!$C$4:$C$403,A15,'💳 Transactions'!$D$4:$D$403,B15,'💳 Transactions'!$B$4:$B$403,"Expense",'💳 Transactions'!$P$4:$P$403,C_Year) | F15: =IF(C15="","",C15-D15) | G15: =IF(C15="","",IF(C15=0,"",D15/C15))
A16: Transportation | B16: Registration | C16: 25 | D16: =SUMIFS('💳 Transactions'!$F$4:$F$403,'💳 Transactions'!$C$4:$C$403,A16,'💳 Transactions'!$D$4:$D$403,B16,'💳 Transactions'!$B$4:$B$403,"Expense",'💳 Transactions'!$O$4:$O$403,C_Month,'💳 Transactions'!$P$4:$P$403,C_Year) | E16: =SUMIFS('💳 Transactions'!$F$4:$F$403,'💳 Transactions'!$C$4:$C$403,A16,'💳 Transactions'!$D$4:$D$403,B16,'💳 Transactions'!$B$4:$B$403,"Expense",'💳 Transactions'!$P$4:$P$403,C_Year) | F16: =IF(C16="","",C16-D16) | G16: =IF(C16="","",IF(C16=0,"",D16/C16))
A17: Transportation | B17: Parking/Tolls | C17: 35 | D17: =SUMIFS('💳 Transactions'!$F$4:$F$403,'💳 Transactions'!$C$4:$C$403,A17,'💳 Transactions'!$D$4:$D$403,B17,'💳 Transactions'!$B$4:$B$403,"Expense",'💳 Transactions'!$O$4:$O$403,C_Month,'💳 Transactions'!$P$4:$P$403,C_Year) | E17: =SUMIFS('💳 Transactions'!$F$4:$F$403,'💳 Transactions'!$C$4:$C$403,A17,'💳 Transactions'!$D$4:$D$403,B17,'💳 Transactions'!$B$4:$B$403,"Expense",'💳 Transactions'!$P$4:$P$403,C_Year) | F17: =IF(C17="","",C17-D17) | G17: =IF(C17="","",IF(C17=0,"",D17/C17))
A18: Transportation | B18: Public Transportation | C18: 20 | D18: =SUMIFS('💳 Transactions'!$F$4:$F$403,'💳 Transactions'!$C$4:$C$403,A18,'💳 Transactions'!$D$4:$D$403,B18,'💳 Transactions'!$B$4:$B$403,"Expense",'💳 Transactions'!$O$4:$O$403,C_Month,'💳 Transactions'!$P$4:$P$403,C_Year) | E18: =SUMIFS('💳 Transactions'!$F$4:$F$403,'💳 Transactions'!$C$4:$C$403,A18,'💳 Transactions'!$D$4:$D$403,B18,'💳 Transactions'!$B$4:$B$403,"Expense",'💳 Transactions'!$P$4:$P$403,C_Year) | F18: =IF(C18="","",C18-D18) | G18: =IF(C18="","",IF(C18=0,"",D18/C18))
A19: Transportation | B19: Category Subtotal | C19: =SUM(C12:C18) | D19: =SUM(D12:D18) | E19: =SUM(E12:E18) | F19: =SUM(F12:F18) | G19: =IF(C19=0,"",D19/C19)
A20: Food | B20: Groceries | C20: 435 | D20: =SUMIFS('💳 Transactions'!$F$4:$F$403,'💳 Transactions'!$C$4:$C$403,A20,'💳 Transactions'!$D$4:$D$403,B20,'💳 Transactions'!$B$4:$B$403,"Expense",'💳 Transactions'!$O$4:$O$403,C_Month,'💳 Transactions'!$P$4:$P$403,C_Year) | E20: =SUMIFS('💳 Transactions'!$F$4:$F$403,'💳 Transactions'!$C$4:$C$403,A20,'💳 Transactions'!$D$4:$D$403,B20,'💳 Transactions'!$B$4:$B$403,"Expense",'💳 Transactions'!$P$4:$P$403,C_Year) | F20: =IF(C20="","",C20-D20) | G20: =IF(C20="","",IF(C20=0,"",D20/C20))
A21: Food | B21: Restaurants | C21: 140 | D21: =SUMIFS('💳 Transactions'!$F$4:$F$403,'💳 Transactions'!$C$4:$C$403,A21,'💳 Transactions'!$D$4:$D$403,B21,'💳 Transactions'!$B$4:$B$403,"Expense",'💳 Transactions'!$O$4:$O$403,C_Month,'💳 Transactions'!$P$4:$P$403,C_Year) | E21: =SUMIFS('💳 Transactions'!$F$4:$F$403,'💳 Transactions'!$C$4:$C$403,A21,'💳 Transactions'!$D$4:$D$403,B21,'💳 Transactions'!$B$4:$B$403,"Expense",'💳 Transactions'!$P$4:$P$403,C_Year) | F21: =IF(C21="","",C21-D21) | G21: =IF(C21="","",IF(C21=0,"",D21/C21))
A22: Food | B22: Takeout/Delivery | C22: 45 | D22: =SUMIFS('💳 Transactions'!$F$4:$F$403,'💳 Transactions'!$C$4:$C$403,A22,'💳 Transactions'!$D$4:$D$403,B22,'💳 Transactions'!$B$4:$B$403,"Expense",'💳 Transactions'!$O$4:$O$403,C_Month,'💳 Transactions'!$P$4:$P$403,C_Year) | E22: =SUMIFS('💳 Transactions'!$F$4:$F$403,'💳 Transactions'!$C$4:$C$403,A22,'💳 Transactions'!$D$4:$D$403,B22,'💳 Transactions'!$B$4:$B$403,"Expense",'💳 Transactions'!$P$4:$P$403,C_Year) | F22: =IF(C22="","",C22-D22) | G22: =IF(C22="","",IF(C22=0,"",D22/C22))
A23: Food | B23: Coffee | C23: 35 | D23: =SUMIFS('💳 Transactions'!$F$4:$F$403,'💳 Transactions'!$C$4:$C$403,A23,'💳 Transactions'!$D$4:$D$403,B23,'💳 Transactions'!$B$4:$B$403,"Expense",'💳 Transactions'!$O$4:$O$403,C_Month,'💳 Transactions'!$P$4:$P$403,C_Year) | E23: =SUMIFS('💳 Transactions'!$F$4:$F$403,'💳 Transactions'!$C$4:$C$403,A23,'💳 Transactions'!$D$4:$D$403,B23,'💳 Transactions'!$B$4:$B$403,"Expense",'💳 Transactions'!$P$4:$P$403,C_Year) | F23: =IF(C23="","",C23-D23) | G23: =IF(C23="","",IF(C23=0,"",D23/C23))
A24: Food | B24: Other Food | D24: =SUMIFS('💳 Transactions'!$F$4:$F$403,'💳 Transactions'!$C$4:$C$403,A24,'💳 Transactions'!$D$4:$D$403,B24,'💳 Transactions'!$B$4:$B$403,"Expense",'💳 Transactions'!$O$4:$O$403,C_Month,'💳 Transactions'!$P$4:$P$403,C_Year) | E24: =SUMIFS('💳 Transactions'!$F$4:$F$403,'💳 Transactions'!$C$4:$C$403,A24,'💳 Transactions'!$D$4:$D$403,B24,'💳 Transactions'!$B$4:$B$403,"Expense",'💳 Transactions'!$P$4:$P$403,C_Year) | F24: =IF(C24="","",C24-D24) | G24: =IF(C24="","",IF(C24=0,"",D24/C24))
A25: Food | B25: Category Subtotal | C25: =SUM(C20:C24) | D25: =SUM(D20:D24) | E25: =SUM(E20:E24) | F25: =SUM(F20:F24) | G25: =IF(C25=0,"",D25/C25)
A26: Family | B26: Childcare | C26: 585 | D26: =SUMIFS('💳 Transactions'!$F$4:$F$403,'💳 Transactions'!$C$4:$C$403,A26,'💳 Transactions'!$D$4:$D$403,B26,'💳 Transactions'!$B$4:$B$403,"Expense",'💳 Transactions'!$O$4:$O$403,C_Month,'💳 Transactions'!$P$4:$P$403,C_Year) | E26: =SUMIFS('💳 Transactions'!$F$4:$F$403,'💳 Transactions'!$C$4:$C$403,A26,'💳 Transactions'!$D$4:$D$403,B26,'💳 Transactions'!$B$4:$B$403,"Expense",'💳 Transactions'!$P$4:$P$403,C_Year) | F26: =IF(C26="","",C26-D26) | G26: =IF(C26="","",IF(C26=0,"",D26/C26))
A27: Family | B27: School | C27: 60 | D27: =SUMIFS('💳 Transactions'!$F$4:$F$403,'💳 Transactions'!$C$4:$C$403,A27,'💳 Transactions'!$D$4:$D$403,B27,'💳 Transactions'!$B$4:$B$403,"Expense",'💳 Transactions'!$O$4:$O$403,C_Month,'💳 Transactions'!$P$4:$P$403,C_Year) | E27: =SUMIFS('💳 Transactions'!$F$4:$F$403,'💳 Transactions'!$C$4:$C$403,A27,'💳 Transactions'!$D$4:$D$403,B27,'💳 Transactions'!$B$4:$B$403,"Expense",'💳 Transactions'!$P$4:$P$403,C_Year) | F27: =IF(C27="","",C27-D27) | G27: =IF(C27="","",IF(C27=0,"",D27/C27))
A28: Family | B28: Activities/Sports | C28: 75 | D28: =SUMIFS('💳 Transactions'!$F$4:$F$403,'💳 Transactions'!$C$4:$C$403,A28,'💳 Transactions'!$D$4:$D$403,B28,'💳 Transactions'!$B$4:$B$403,"Expense",'💳 Transactions'!$O$4:$O$403,C_Month,'💳 Transactions'!$P$4:$P$403,C_Year) | E28: =SUMIFS('💳 Transactions'!$F$4:$F$403,'💳 Transactions'!$C$4:$C$403,A28,'💳 Transactions'!$D$4:$D$403,B28,'💳 Transactions'!$B$4:$B$403,"Expense",'💳 Transactions'!$P$4:$P$403,C_Year) | F28: =IF(C28="","",C28-D28) | G28: =IF(C28="","",IF(C28=0,"",D28/C28))
A29: Family | B29: Clothing | C29: 65 | D29: =SUMIFS('💳 Transactions'!$F$4:$F$403,'💳 Transactions'!$C$4:$C$403,A29,'💳 Transactions'!$D$4:$D$403,B29,'💳 Transactions'!$B$4:$B$403,"Expense",'💳 Transactions'!$O$4:$O$403,C_Month,'💳 Transactions'!$P$4:$P$403,C_Year) | E29: =SUMIFS('💳 Transactions'!$F$4:$F$403,'💳 Transactions'!$C$4:$C$403,A29,'💳 Transactions'!$D$4:$D$403,B29,'💳 Transactions'!$B$4:$B$403,"Expense",'💳 Transactions'!$P$4:$P$403,C_Year) | F29: =IF(C29="","",C29-D29) | G29: =IF(C29="","",IF(C29=0,"",D29/C29))
A30: Family | B30: Allowances | C30: 25 | D30: =SUMIFS('💳 Transactions'!$F$4:$F$403,'💳 Transactions'!$C$4:$C$403,A30,'💳 Transactions'!$D$4:$D$403,B30,'💳 Transactions'!$B$4:$B$403,"Expense",'💳 Transactions'!$O$4:$O$403,C_Month,'💳 Transactions'!$P$4:$P$403,C_Year) | E30: =SUMIFS('💳 Transactions'!$F$4:$F$403,'💳 Transactions'!$C$4:$C$403,A30,'💳 Transactions'!$D$4:$D$403,B30,'💳 Transactions'!$B$4:$B$403,"Expense",'💳 Transactions'!$P$4:$P$403,C_Year) | F30: =IF(C30="","",C30-D30) | G30: =IF(C30="","",IF(C30=0,"",D30/C30))
A31: Family | B31: Baby Expenses | C31: 40 | D31: =SUMIFS('💳 Transactions'!$F$4:$F$403,'💳 Transactions'!$C$4:$C$403,A31,'💳 Transactions'!$D$4:$D$403,B31,'💳 Transactions'!$B$4:$B$403,"Expense",'💳 Transactions'!$O$4:$O$403,C_Month,'💳 Transactions'!$P$4:$P$403,C_Year) | E31: =SUMIFS('💳 Transactions'!$F$4:$F$403,'💳 Transactions'!$C$4:$C$403,A31,'💳 Transactions'!$D$4:$D$403,B31,'💳 Transactions'!$B$4:$B$403,"Expense",'💳 Transactions'!$P$4:$P$403,C_Year) | F31: =IF(C31="","",C31-D31) | G31: =IF(C31="","",IF(C31=0,"",D31/C31))
A32: Family | B32: College Savings | C32: 125 | D32: =SUMIFS('💳 Transactions'!$F$4:$F$403,'💳 Transactions'!$C$4:$C$403,A32,'💳 Transactions'!$D$4:$D$403,B32,'💳 Transactions'!$B$4:$B$403,"Expense",'💳 Transactions'!$O$4:$O$403,C_Month,'💳 Transactions'!$P$4:$P$403,C_Year) | E32: =SUMIFS('💳 Transactions'!$F$4:$F$403,'💳 Transactions'!$C$4:$C$403,A32,'💳 Transactions'!$D$4:$D$403,B32,'💳 Transactions'!$B$4:$B$403,"Expense",'💳 Transactions'!$P$4:$P$403,C_Year) | F32: =IF(C32="","",C32-D32) | G32: =IF(C32="","",IF(C32=0,"",D32/C32))
A33: Family | B33: Other Family | D33: =SUMIFS('💳 Transactions'!$F$4:$F$403,'💳 Transactions'!$C$4:$C$403,A33,'💳 Transactions'!$D$4:$D$403,B33,'💳 Transactions'!$B$4:$B$403,"Expense",'💳 Transactions'!$O$4:$O$403,C_Month,'💳 Transactions'!$P$4:$P$403,C_Year) | E33: =SUMIFS('💳 Transactions'!$F$4:$F$403,'💳 Transactions'!$C$4:$C$403,A33,'💳 Transactions'!$D$4:$D$403,B33,'💳 Transactions'!$B$4:$B$403,"Expense",'💳 Transactions'!$P$4:$P$403,C_Year) | F33: =IF(C33="","",C33-D33) | G33: =IF(C33="","",IF(C33=0,"",D33/C33))
A34: Family | B34: Category Subtotal | C34: =SUM(C26:C33) | D34: =SUM(D26:D33) | E34: =SUM(E26:E33) | F34: =SUM(F26:F33) | G34: =IF(C34=0,"",D34/C34)
A35: Healthcare | B35: Health Insurance | C35: 290 | D35: =SUMIFS('💳 Transactions'!$F$4:$F$403,'💳 Transactions'!$C$4:$C$403,A35,'💳 Transactions'!$D$4:$D$403,B35,'💳 Transactions'!$B$4:$B$403,"Expense",'💳 Transactions'!$O$4:$O$403,C_Month,'💳 Transactions'!$P$4:$P$403,C_Year) | E35: =SUMIFS('💳 Transactions'!$F$4:$F$403,'💳 Transactions'!$C$4:$C$403,A35,'💳 Transactions'!$D$4:$D$403,B35,'💳 Transactions'!$B$4:$B$403,"Expense",'💳 Transactions'!$P$4:$P$403,C_Year) | F35: =IF(C35="","",C35-D35) | G35: =IF(C35="","",IF(C35=0,"",D35/C35))
A36: Healthcare | B36: Dental | C36: 20 | D36: =SUMIFS('💳 Transactions'!$F$4:$F$403,'💳 Transactions'!$C$4:$C$403,A36,'💳 Transactions'!$D$4:$D$403,B36,'💳 Transactions'!$B$4:$B$403,"Expense",'💳 Transactions'!$O$4:$O$403,C_Month,'💳 Transactions'!$P$4:$P$403,C_Year) | E36: =SUMIFS('💳 Transactions'!$F$4:$F$403,'💳 Transactions'!$C$4:$C$403,A36,'💳 Transactions'!$D$4:$D$403,B36,'💳 Transactions'!$B$4:$B$403,"Expense",'💳 Transactions'!$P$4:$P$403,C_Year) | F36: =IF(C36="","",C36-D36) | G36: =IF(C36="","",IF(C36=0,"",D36/C36))
A37: Healthcare | B37: Vision | C37: 15 | D37: =SUMIFS('💳 Transactions'!$F$4:$F$403,'💳 Transactions'!$C$4:$C$403,A37,'💳 Transactions'!$D$4:$D$403,B37,'💳 Transactions'!$B$4:$B$403,"Expense",'💳 Transactions'!$O$4:$O$403,C_Month,'💳 Transactions'!$P$4:$P$403,C_Year) | E37: =SUMIFS('💳 Transactions'!$F$4:$F$403,'💳 Transactions'!$C$4:$C$403,A37,'💳 Transactions'!$D$4:$D$403,B37,'💳 Transactions'!$B$4:$B$403,"Expense",'💳 Transactions'!$P$4:$P$403,C_Year) | F37: =IF(C37="","",C37-D37) | G37: =IF(C37="","",IF(C37=0,"",D37/C37))
A38: Healthcare | B38: Prescriptions | C38: 35 | D38: =SUMIFS('💳 Transactions'!$F$4:$F$403,'💳 Transactions'!$C$4:$C$403,A38,'💳 Transactions'!$D$4:$D$403,B38,'💳 Transactions'!$B$4:$B$403,"Expense",'💳 Transactions'!$O$4:$O$403,C_Month,'💳 Transactions'!$P$4:$P$403,C_Year) | E38: =SUMIFS('💳 Transactions'!$F$4:$F$403,'💳 Transactions'!$C$4:$C$403,A38,'💳 Transactions'!$D$4:$D$403,B38,'💳 Transactions'!$B$4:$B$403,"Expense",'💳 Transactions'!$P$4:$P$403,C_Year) | F38: =IF(C38="","",C38-D38) | G38: =IF(C38="","",IF(C38=0,"",D38/C38))
A39: Healthcare | B39: Medical Expenses | C39: 65 | D39: =SUMIFS('💳 Transactions'!$F$4:$F$403,'💳 Transactions'!$C$4:$C$403,A39,'💳 Transactions'!$D$4:$D$403,B39,'💳 Transactions'!$B$4:$B$403,"Expense",'💳 Transactions'!$O$4:$O$403,C_Month,'💳 Transactions'!$P$4:$P$403,C_Year) | E39: =SUMIFS('💳 Transactions'!$F$4:$F$403,'💳 Transactions'!$C$4:$C$403,A39,'💳 Transactions'!$D$4:$D$403,B39,'💳 Transactions'!$B$4:$B$403,"Expense",'💳 Transactions'!$P$4:$P$403,C_Year) | F39: =IF(C39="","",C39-D39) | G39: =IF(C39="","",IF(C39=0,"",D39/C39))
A40: Healthcare | B40: Other Healthcare | D40: =SUMIFS('💳 Transactions'!$F$4:$F$403,'💳 Transactions'!$C$4:$C$403,A40,'💳 Transactions'!$D$4:$D$403,B40,'💳 Transactions'!$B$4:$B$403,"Expense",'💳 Transactions'!$O$4:$O$403,C_Month,'💳 Transactions'!$P$4:$P$403,C_Year) | E40: =SUMIFS('💳 Transactions'!$F$4:$F$403,'💳 Transactions'!$C$4:$C$403,A40,'💳 Transactions'!$D$4:$D$403,B40,'💳 Transactions'!$B$4:$B$403,"Expense",'💳 Transactions'!$P$4:$P$403,C_Year) | F40: =IF(C40="","",C40-D40) | G40: =IF(C40="","",IF(C40=0,"",D40/C40))
A41: Healthcare | B41: Category Subtotal | C41: =SUM(C35:C40) | D41: =SUM(D35:D40) | E41: =SUM(E35:E40) | F41: =SUM(F35:F40) | G41: =IF(C41=0,"",D41/C41)
A42: Lifestyle | B42: Entertainment | C42: 90 | D42: =SUMIFS('💳 Transactions'!$F$4:$F$403,'💳 Transactions'!$C$4:$C$403,A42,'💳 Transactions'!$D$4:$D$403,B42,'💳 Transactions'!$B$4:$B$403,"Expense",'💳 Transactions'!$O$4:$O$403,C_Month,'💳 Transactions'!$P$4:$P$403,C_Year) | E42: =SUMIFS('💳 Transactions'!$F$4:$F$403,'💳 Transactions'!$C$4:$C$403,A42,'💳 Transactions'!$D$4:$D$403,B42,'💳 Transactions'!$B$4:$B$403,"Expense",'💳 Transactions'!$P$4:$P$403,C_Year) | F42: =IF(C42="","",C42-D42) | G42: =IF(C42="","",IF(C42=0,"",D42/C42))
A43: Lifestyle | B43: Subscriptions | C43: 60 | D43: =SUMIFS('💳 Transactions'!$F$4:$F$403,'💳 Transactions'!$C$4:$C$403,A43,'💳 Transactions'!$D$4:$D$403,B43,'💳 Transactions'!$B$4:$B$403,"Expense",'💳 Transactions'!$O$4:$O$403,C_Month,'💳 Transactions'!$P$4:$P$403,C_Year) | E43: =SUMIFS('💳 Transactions'!$F$4:$F$403,'💳 Transactions'!$C$4:$C$403,A43,'💳 Transactions'!$D$4:$D$403,B43,'💳 Transactions'!$B$4:$B$403,"Expense",'💳 Transactions'!$P$4:$P$403,C_Year) | F43: =IF(C43="","",C43-D43) | G43: =IF(C43="","",IF(C43=0,"",D43/C43))
A44: Lifestyle | B44: Travel | C44: 150 | D44: =SUMIFS('💳 Transactions'!$F$4:$F$403,'💳 Transactions'!$C$4:$C$403,A44,'💳 Transactions'!$D$4:$D$403,B44,'💳 Transactions'!$B$4:$B$403,"Expense",'💳 Transactions'!$O$4:$O$403,C_Month,'💳 Transactions'!$P$4:$P$403,C_Year) | E44: =SUMIFS('💳 Transactions'!$F$4:$F$403,'💳 Transactions'!$C$4:$C$403,A44,'💳 Transactions'!$D$4:$D$403,B44,'💳 Transactions'!$B$4:$B$403,"Expense",'💳 Transactions'!$P$4:$P$403,C_Year) | F44: =IF(C44="","",C44-D44) | G44: =IF(C44="","",IF(C44=0,"",D44/C44))
A45: Lifestyle | B45: Hobbies | C45: 45 | D45: =SUMIFS('💳 Transactions'!$F$4:$F$403,'💳 Transactions'!$C$4:$C$403,A45,'💳 Transactions'!$D$4:$D$403,B45,'💳 Transactions'!$B$4:$B$403,"Expense",'💳 Transactions'!$O$4:$O$403,C_Month,'💳 Transactions'!$P$4:$P$403,C_Year) | E45: =SUMIFS('💳 Transactions'!$F$4:$F$403,'💳 Transactions'!$C$4:$C$403,A45,'💳 Transactions'!$D$4:$D$403,B45,'💳 Transactions'!$B$4:$B$403,"Expense",'💳 Transactions'!$P$4:$P$403,C_Year) | F45: =IF(C45="","",C45-D45) | G45: =IF(C45="","",IF(C45=0,"",D45/C45))
A46: Lifestyle | B46: Personal Care | C46: 40 | D46: =SUMIFS('💳 Transactions'!$F$4:$F$403,'💳 Transactions'!$C$4:$C$403,A46,'💳 Transactions'!$D$4:$D$403,B46,'💳 Transactions'!$B$4:$B$403,"Expense",'💳 Transactions'!$O$4:$O$403,C_Month,'💳 Transactions'!$P$4:$P$403,C_Year) | E46: =SUMIFS('💳 Transactions'!$F$4:$F$403,'💳 Transactions'!$C$4:$C$403,A46,'💳 Transactions'!$D$4:$D$403,B46,'💳 Transactions'!$B$4:$B$403,"Expense",'💳 Transactions'!$P$4:$P$403,C_Year) | F46: =IF(C46="","",C46-D46) | G46: =IF(C46="","",IF(C46=0,"",D46/C46))
A47: Lifestyle | B47: Shopping | C47: 90 | D47: =SUMIFS('💳 Transactions'!$F$4:$F$403,'💳 Transactions'!$C$4:$C$403,A47,'💳 Transactions'!$D$4:$D$403,B47,'💳 Transactions'!$B$4:$B$403,"Expense",'💳 Transactions'!$O$4:$O$403,C_Month,'💳 Transactions'!$P$4:$P$403,C_Year) | E47: =SUMIFS('💳 Transactions'!$F$4:$F$403,'💳 Transactions'!$C$4:$C$403,A47,'💳 Transactions'!$D$4:$D$403,B47,'💳 Transactions'!$B$4:$B$403,"Expense",'💳 Transactions'!$P$4:$P$403,C_Year) | F47: =IF(C47="","",C47-D47) | G47: =IF(C47="","",IF(C47=0,"",D47/C47))
A48: Lifestyle | B48: Other Lifestyle | D48: =SUMIFS('💳 Transactions'!$F$4:$F$403,'💳 Transactions'!$C$4:$C$403,A48,'💳 Transactions'!$D$4:$D$403,B48,'💳 Transactions'!$B$4:$B$403,"Expense",'💳 Transactions'!$O$4:$O$403,C_Month,'💳 Transactions'!$P$4:$P$403,C_Year) | E48: =SUMIFS('💳 Transactions'!$F$4:$F$403,'💳 Transactions'!$C$4:$C$403,A48,'💳 Transactions'!$D$4:$D$403,B48,'💳 Transactions'!$B$4:$B$403,"Expense",'💳 Transactions'!$P$4:$P$403,C_Year) | F48: =IF(C48="","",C48-D48) | G48: =IF(C48="","",IF(C48=0,"",D48/C48))
A49: Lifestyle | B49: Category Subtotal | C49: =SUM(C42:C48) | D49: =SUM(D42:D48) | E49: =SUM(E42:E48) | F49: =SUM(F42:F48) | G49: =IF(C49=0,"",D49/C49)
A50: Financial | B50: Credit Cards | C50: 150 | D50: =SUMIFS('💳 Transactions'!$F$4:$F$403,'💳 Transactions'!$C$4:$C$403,A50,'💳 Transactions'!$D$4:$D$403,B50,'💳 Transactions'!$B$4:$B$403,"Expense",'💳 Transactions'!$O$4:$O$403,C_Month,'💳 Transactions'!$P$4:$P$403,C_Year) | E50: =SUMIFS('💳 Transactions'!$F$4:$F$403,'💳 Transactions'!$C$4:$C$403,A50,'💳 Transactions'!$D$4:$D$403,B50,'💳 Transactions'!$B$4:$B$403,"Expense",'💳 Transactions'!$P$4:$P$403,C_Year) | F50: =IF(C50="","",C50-D50) | G50: =IF(C50="","",IF(C50=0,"",D50/C50))
A51: Financial | B51: Student Loans | C51: 165 | D51: =SUMIFS('💳 Transactions'!$F$4:$F$403,'💳 Transactions'!$C$4:$C$403,A51,'💳 Transactions'!$D$4:$D$403,B51,'💳 Transactions'!$B$4:$B$403,"Expense",'💳 Transactions'!$O$4:$O$403,C_Month,'💳 Transactions'!$P$4:$P$403,C_Year) | E51: =SUMIFS('💳 Transactions'!$F$4:$F$403,'💳 Transactions'!$C$4:$C$403,A51,'💳 Transactions'!$D$4:$D$403,B51,'💳 Transactions'!$B$4:$B$403,"Expense",'💳 Transactions'!$P$4:$P$403,C_Year) | F51: =IF(C51="","",C51-D51) | G51: =IF(C51="","",IF(C51=0,"",D51/C51))
A52: Financial | B52: Auto Loans | C52: 210 | D52: =SUMIFS('💳 Transactions'!$F$4:$F$403,'💳 Transactions'!$C$4:$C$403,A52,'💳 Transactions'!$D$4:$D$403,B52,'💳 Transactions'!$B$4:$B$403,"Expense",'💳 Transactions'!$O$4:$O$403,C_Month,'💳 Transactions'!$P$4:$P$403,C_Year) | E52: =SUMIFS('💳 Transactions'!$F$4:$F$403,'💳 Transactions'!$C$4:$C$403,A52,'💳 Transactions'!$D$4:$D$403,B52,'💳 Transactions'!$B$4:$B$403,"Expense",'💳 Transactions'!$P$4:$P$403,C_Year) | F52: =IF(C52="","",C52-D52) | G52: =IF(C52="","",IF(C52=0,"",D52/C52))
A53: Financial | B53: Personal Loans | C53: 75 | D53: =SUMIFS('💳 Transactions'!$F$4:$F$403,'💳 Transactions'!$C$4:$C$403,A53,'💳 Transactions'!$D$4:$D$403,B53,'💳 Transactions'!$B$4:$B$403,"Expense",'💳 Transactions'!$O$4:$O$403,C_Month,'💳 Transactions'!$P$4:$P$403,C_Year) | E53: =SUMIFS('💳 Transactions'!$F$4:$F$403,'💳 Transactions'!$C$4:$C$403,A53,'💳 Transactions'!$D$4:$D$403,B53,'💳 Transactions'!$B$4:$B$403,"Expense",'💳 Transactions'!$P$4:$P$403,C_Year) | F53: =IF(C53="","",C53-D53) | G53: =IF(C53="","",IF(C53=0,"",D53/C53))
A54: Financial | B54: Savings | C54: 210 | D54: =SUMIFS('💳 Transactions'!$F$4:$F$403,'💳 Transactions'!$C$4:$C$403,A54,'💳 Transactions'!$D$4:$D$403,B54,'💳 Transactions'!$B$4:$B$403,"Expense",'💳 Transactions'!$O$4:$O$403,C_Month,'💳 Transactions'!$P$4:$P$403,C_Year) | E54: =SUMIFS('💳 Transactions'!$F$4:$F$403,'💳 Transactions'!$C$4:$C$403,A54,'💳 Transactions'!$D$4:$D$403,B54,'💳 Transactions'!$B$4:$B$403,"Expense",'💳 Transactions'!$P$4:$P$403,C_Year) | F54: =IF(C54="","",C54-D54) | G54: =IF(C54="","",IF(C54=0,"",D54/C54))
A55: Financial | B55: Investments | C55: 125 | D55: =SUMIFS('💳 Transactions'!$F$4:$F$403,'💳 Transactions'!$C$4:$C$403,A55,'💳 Transactions'!$D$4:$D$403,B55,'💳 Transactions'!$B$4:$B$403,"Expense",'💳 Transactions'!$O$4:$O$403,C_Month,'💳 Transactions'!$P$4:$P$403,C_Year) | E55: =SUMIFS('💳 Transactions'!$F$4:$F$403,'💳 Transactions'!$C$4:$C$403,A55,'💳 Transactions'!$D$4:$D$403,B55,'💳 Transactions'!$B$4:$B$403,"Expense",'💳 Transactions'!$P$4:$P$403,C_Year) | F55: =IF(C55="","",C55-D55) | G55: =IF(C55="","",IF(C55=0,"",D55/C55))
A56: Financial | B56: Retirement | C56: 250 | D56: =SUMIFS('💳 Transactions'!$F$4:$F$403,'💳 Transactions'!$C$4:$C$403,A56,'💳 Transactions'!$D$4:$D$403,B56,'💳 Transactions'!$B$4:$B$403,"Expense",'💳 Transactions'!$O$4:$O$403,C_Month,'💳 Transactions'!$P$4:$P$403,C_Year) | E56: =SUMIFS('💳 Transactions'!$F$4:$F$403,'💳 Transactions'!$C$4:$C$403,A56,'💳 Transactions'!$D$4:$D$403,B56,'💳 Transactions'!$B$4:$B$403,"Expense",'💳 Transactions'!$P$4:$P$403,C_Year) | F56: =IF(C56="","",C56-D56) | G56: =IF(C56="","",IF(C56=0,"",D56/C56))
A57: Financial | B57: Other Financial | D57: =SUMIFS('💳 Transactions'!$F$4:$F$403,'💳 Transactions'!$C$4:$C$403,A57,'💳 Transactions'!$D$4:$D$403,B57,'💳 Transactions'!$B$4:$B$403,"Expense",'💳 Transactions'!$O$4:$O$403,C_Month,'💳 Transactions'!$P$4:$P$403,C_Year) | E57: =SUMIFS('💳 Transactions'!$F$4:$F$403,'💳 Transactions'!$C$4:$C$403,A57,'💳 Transactions'!$D$4:$D$403,B57,'💳 Transactions'!$B$4:$B$403,"Expense",'💳 Transactions'!$P$4:$P$403,C_Year) | F57: =IF(C57="","",C57-D57) | G57: =IF(C57="","",IF(C57=0,"",D57/C57))
A58: Financial | B58: Category Subtotal | C58: =SUM(C50:C57) | D58: =SUM(D50:D57) | E58: =SUM(E50:E57) | F58: =SUM(F50:F57) | G58: =IF(C58=0,"",D58/C58)
A59: Giving | B59: Charity | C59: 85 | D59: =SUMIFS('💳 Transactions'!$F$4:$F$403,'💳 Transactions'!$C$4:$C$403,A59,'💳 Transactions'!$D$4:$D$403,B59,'💳 Transactions'!$B$4:$B$403,"Expense",'💳 Transactions'!$O$4:$O$403,C_Month,'💳 Transactions'!$P$4:$P$403,C_Year) | E59: =SUMIFS('💳 Transactions'!$F$4:$F$403,'💳 Transactions'!$C$4:$C$403,A59,'💳 Transactions'!$D$4:$D$403,B59,'💳 Transactions'!$B$4:$B$403,"Expense",'💳 Transactions'!$P$4:$P$403,C_Year) | F59: =IF(C59="","",C59-D59) | G59: =IF(C59="","",IF(C59=0,"",D59/C59))
A60: Giving | B60: Gifts | C60: 35 | D60: =SUMIFS('💳 Transactions'!$F$4:$F$403,'💳 Transactions'!$C$4:$C$403,A60,'💳 Transactions'!$D$4:$D$403,B60,'💳 Transactions'!$B$4:$B$403,"Expense",'💳 Transactions'!$O$4:$O$403,C_Month,'💳 Transactions'!$P$4:$P$403,C_Year) | E60: =SUMIFS('💳 Transactions'!$F$4:$F$403,'💳 Transactions'!$C$4:$C$403,A60,'💳 Transactions'!$D$4:$D$403,B60,'💳 Transactions'!$B$4:$B$403,"Expense",'💳 Transactions'!$P$4:$P$403,C_Year) | F60: =IF(C60="","",C60-D60) | G60: =IF(C60="","",IF(C60=0,"",D60/C60))
A61: Giving | B61: Tithe | D61: =SUMIFS('💳 Transactions'!$F$4:$F$403,'💳 Transactions'!$C$4:$C$403,A61,'💳 Transactions'!$D$4:$D$403,B61,'💳 Transactions'!$B$4:$B$403,"Expense",'💳 Transactions'!$O$4:$O$403,C_Month,'💳 Transactions'!$P$4:$P$403,C_Year) | E61: =SUMIFS('💳 Transactions'!$F$4:$F$403,'💳 Transactions'!$C$4:$C$403,A61,'💳 Transactions'!$D$4:$D$403,B61,'💳 Transactions'!$B$4:$B$403,"Expense",'💳 Transactions'!$P$4:$P$403,C_Year) | F61: =IF(C61="","",C61-D61) | G61: =IF(C61="","",IF(C61=0,"",D61/C61))
A62: Giving | B62: Other Giving | D62: =SUMIFS('💳 Transactions'!$F$4:$F$403,'💳 Transactions'!$C$4:$C$403,A62,'💳 Transactions'!$D$4:$D$403,B62,'💳 Transactions'!$B$4:$B$403,"Expense",'💳 Transactions'!$O$4:$O$403,C_Month,'💳 Transactions'!$P$4:$P$403,C_Year) | E62: =SUMIFS('💳 Transactions'!$F$4:$F$403,'💳 Transactions'!$C$4:$C$403,A62,'💳 Transactions'!$D$4:$D$403,B62,'💳 Transactions'!$B$4:$B$403,"Expense",'💳 Transactions'!$P$4:$P$403,C_Year) | F62: =IF(C62="","",C62-D62) | G62: =IF(C62="","",IF(C62=0,"",D62/C62))
A63: Giving | B63: Category Subtotal | C63: =SUM(C59:C62) | D63: =SUM(D59:D62) | E63: =SUM(E59:E62) | F63: =SUM(F59:F62) | G63: =IF(C63=0,"",D63/C63)
A64: Pets | B64: Food | C64: 60 | D64: =SUMIFS('💳 Transactions'!$F$4:$F$403,'💳 Transactions'!$C$4:$C$403,A64,'💳 Transactions'!$D$4:$D$403,B64,'💳 Transactions'!$B$4:$B$403,"Expense",'💳 Transactions'!$O$4:$O$403,C_Month,'💳 Transactions'!$P$4:$P$403,C_Year) | E64: =SUMIFS('💳 Transactions'!$F$4:$F$403,'💳 Transactions'!$C$4:$C$403,A64,'💳 Transactions'!$D$4:$D$403,B64,'💳 Transactions'!$B$4:$B$403,"Expense",'💳 Transactions'!$P$4:$P$403,C_Year) | F64: =IF(C64="","",C64-D64) | G64: =IF(C64="","",IF(C64=0,"",D64/C64))
A65: Pets | B65: Vet | C65: 35 | D65: =SUMIFS('💳 Transactions'!$F$4:$F$403,'💳 Transactions'!$C$4:$C$403,A65,'💳 Transactions'!$D$4:$D$403,B65,'💳 Transactions'!$B$4:$B$403,"Expense",'💳 Transactions'!$O$4:$O$403,C_Month,'💳 Transactions'!$P$4:$P$403,C_Year) | E65: =SUMIFS('💳 Transactions'!$F$4:$F$403,'💳 Transactions'!$C$4:$C$403,A65,'💳 Transactions'!$D$4:$D$403,B65,'💳 Transactions'!$B$4:$B$403,"Expense",'💳 Transactions'!$P$4:$P$403,C_Year) | F65: =IF(C65="","",C65-D65) | G65: =IF(C65="","",IF(C65=0,"",D65/C65))
A66: Pets | B66: Grooming | D66: =SUMIFS('💳 Transactions'!$F$4:$F$403,'💳 Transactions'!$C$4:$C$403,A66,'💳 Transactions'!$D$4:$D$403,B66,'💳 Transactions'!$B$4:$B$403,"Expense",'💳 Transactions'!$O$4:$O$403,C_Month,'💳 Transactions'!$P$4:$P$403,C_Year) | E66: =SUMIFS('💳 Transactions'!$F$4:$F$403,'💳 Transactions'!$C$4:$C$403,A66,'💳 Transactions'!$D$4:$D$403,B66,'💳 Transactions'!$B$4:$B$403,"Expense",'💳 Transactions'!$P$4:$P$403,C_Year) | F66: =IF(C66="","",C66-D66) | G66: =IF(C66="","",IF(C66=0,"",D66/C66))
A67: Pets | B67: Supplies | C67: 20 | D67: =SUMIFS('💳 Transactions'!$F$4:$F$403,'💳 Transactions'!$C$4:$C$403,A67,'💳 Transactions'!$D$4:$D$403,B67,'💳 Transactions'!$B$4:$B$403,"Expense",'💳 Transactions'!$O$4:$O$403,C_Month,'💳 Transactions'!$P$4:$P$403,C_Year) | E67: =SUMIFS('💳 Transactions'!$F$4:$F$403,'💳 Transactions'!$C$4:$C$403,A67,'💳 Transactions'!$D$4:$D$403,B67,'💳 Transactions'!$B$4:$B$403,"Expense",'💳 Transactions'!$P$4:$P$403,C_Year) | F67: =IF(C67="","",C67-D67) | G67: =IF(C67="","",IF(C67=0,"",D67/C67))
A68: Pets | B68: Other Pets | D68: =SUMIFS('💳 Transactions'!$F$4:$F$403,'💳 Transactions'!$C$4:$C$403,A68,'💳 Transactions'!$D$4:$D$403,B68,'💳 Transactions'!$B$4:$B$403,"Expense",'💳 Transactions'!$O$4:$O$403,C_Month,'💳 Transactions'!$P$4:$P$403,C_Year) | E68: =SUMIFS('💳 Transactions'!$F$4:$F$403,'💳 Transactions'!$C$4:$C$403,A68,'💳 Transactions'!$D$4:$D$403,B68,'💳 Transactions'!$B$4:$B$403,"Expense",'💳 Transactions'!$P$4:$P$403,C_Year) | F68: =IF(C68="","",C68-D68) | G68: =IF(C68="","",IF(C68=0,"",D68/C68))
A69: Pets | B69: Category Subtotal | C69: =SUM(C64:C68) | D69: =SUM(D64:D68) | E69: =SUM(E64:E68) | F69: =SUM(F64:F68) | G69: =IF(C69=0,"",D69/C69)
A70: Travel | B70: Transport | D70: =SUMIFS('💳 Transactions'!$F$4:$F$403,'💳 Transactions'!$C$4:$C$403,A70,'💳 Transactions'!$D$4:$D$403,B70,'💳 Transactions'!$B$4:$B$403,"Expense",'💳 Transactions'!$O$4:$O$403,C_Month,'💳 Transactions'!$P$4:$P$403,C_Year) | E70: =SUMIFS('💳 Transactions'!$F$4:$F$403,'💳 Transactions'!$C$4:$C$403,A70,'💳 Transactions'!$D$4:$D$403,B70,'💳 Transactions'!$B$4:$B$403,"Expense",'💳 Transactions'!$P$4:$P$403,C_Year) | F70: =IF(C70="","",C70-D70) | G70: =IF(C70="","",IF(C70=0,"",D70/C70))
A71: Travel | B71: Lodging | D71: =SUMIFS('💳 Transactions'!$F$4:$F$403,'💳 Transactions'!$C$4:$C$403,A71,'💳 Transactions'!$D$4:$D$403,B71,'💳 Transactions'!$B$4:$B$403,"Expense",'💳 Transactions'!$O$4:$O$403,C_Month,'💳 Transactions'!$P$4:$P$403,C_Year) | E71: =SUMIFS('💳 Transactions'!$F$4:$F$403,'💳 Transactions'!$C$4:$C$403,A71,'💳 Transactions'!$D$4:$D$403,B71,'💳 Transactions'!$B$4:$B$403,"Expense",'💳 Transactions'!$P$4:$P$403,C_Year) | F71: =IF(C71="","",C71-D71) | G71: =IF(C71="","",IF(C71=0,"",D71/C71))
A72: Travel | B72: Food & Dining | D72: =SUMIFS('💳 Transactions'!$F$4:$F$403,'💳 Transactions'!$C$4:$C$403,A72,'💳 Transactions'!$D$4:$D$403,B72,'💳 Transactions'!$B$4:$B$403,"Expense",'💳 Transactions'!$O$4:$O$403,C_Month,'💳 Transactions'!$P$4:$P$403,C_Year) | E72: =SUMIFS('💳 Transactions'!$F$4:$F$403,'💳 Transactions'!$C$4:$C$403,A72,'💳 Transactions'!$D$4:$D$403,B72,'💳 Transactions'!$B$4:$B$403,"Expense",'💳 Transactions'!$P$4:$P$403,C_Year) | F72: =IF(C72="","",C72-D72) | G72: =IF(C72="","",IF(C72=0,"",D72/C72))
A73: Travel | B73: Activities | D73: =SUMIFS('💳 Transactions'!$F$4:$F$403,'💳 Transactions'!$C$4:$C$403,A73,'💳 Transactions'!$D$4:$D$403,B73,'💳 Transactions'!$B$4:$B$403,"Expense",'💳 Transactions'!$O$4:$O$403,C_Month,'💳 Transactions'!$P$4:$P$403,C_Year) | E73: =SUMIFS('💳 Transactions'!$F$4:$F$403,'💳 Transactions'!$C$4:$C$403,A73,'💳 Transactions'!$D$4:$D$403,B73,'💳 Transactions'!$B$4:$B$403,"Expense",'💳 Transactions'!$P$4:$P$403,C_Year) | F73: =IF(C73="","",C73-D73) | G73: =IF(C73="","",IF(C73=0,"",D73/C73))
A74: Travel | B74: Other Travel | D74: =SUMIFS('💳 Transactions'!$F$4:$F$403,'💳 Transactions'!$C$4:$C$403,A74,'💳 Transactions'!$D$4:$D$403,B74,'💳 Transactions'!$B$4:$B$403,"Expense",'💳 Transactions'!$O$4:$O$403,C_Month,'💳 Transactions'!$P$4:$P$403,C_Year) | E74: =SUMIFS('💳 Transactions'!$F$4:$F$403,'💳 Transactions'!$C$4:$C$403,A74,'💳 Transactions'!$D$4:$D$403,B74,'💳 Transactions'!$B$4:$B$403,"Expense",'💳 Transactions'!$P$4:$P$403,C_Year) | F74: =IF(C74="","",C74-D74) | G74: =IF(C74="","",IF(C74=0,"",D74/C74))
A75: Travel | B75: Category Subtotal | C75: =SUM(C70:C74) | D75: =SUM(D70:D74) | E75: =SUM(E70:E74) | F75: =SUM(F70:F74) | G75: =IF(C75=0,"",D75/C75)
A76: Miscellaneous | B76: Fees | C76: 25 | D76: =SUMIFS('💳 Transactions'!$F$4:$F$403,'💳 Transactions'!$C$4:$C$403,A76,'💳 Transactions'!$D$4:$D$403,B76,'💳 Transactions'!$B$4:$B$403,"Expense",'💳 Transactions'!$O$4:$O$403,C_Month,'💳 Transactions'!$P$4:$P$403,C_Year) | E76: =SUMIFS('💳 Transactions'!$F$4:$F$403,'💳 Transactions'!$C$4:$C$403,A76,'💳 Transactions'!$D$4:$D$403,B76,'💳 Transactions'!$B$4:$B$403,"Expense",'💳 Transactions'!$P$4:$P$403,C_Year) | F76: =IF(C76="","",C76-D76) | G76: =IF(C76="","",IF(C76=0,"",D76/C76))
A77: Miscellaneous | B77: Gifts | D77: =SUMIFS('💳 Transactions'!$F$4:$F$403,'💳 Transactions'!$C$4:$C$403,A77,'💳 Transactions'!$D$4:$D$403,B77,'💳 Transactions'!$B$4:$B$403,"Expense",'💳 Transactions'!$O$4:$O$403,C_Month,'💳 Transactions'!$P$4:$P$403,C_Year) | E77: =SUMIFS('💳 Transactions'!$F$4:$F$403,'💳 Transactions'!$C$4:$C$403,A77,'💳 Transactions'!$D$4:$D$403,B77,'💳 Transactions'!$B$4:$B$403,"Expense",'💳 Transactions'!$P$4:$P$403,C_Year) | F77: =IF(C77="","",C77-D77) | G77: =IF(C77="","",IF(C77=0,"",D77/C77))
A78: Miscellaneous | B78: Other Misc | D78: =SUMIFS('💳 Transactions'!$F$4:$F$403,'💳 Transactions'!$C$4:$C$403,A78,'💳 Transactions'!$D$4:$D$403,B78,'💳 Transactions'!$B$4:$B$403,"Expense",'💳 Transactions'!$O$4:$O$403,C_Month,'💳 Transactions'!$P$4:$P$403,C_Year) | E78: =SUMIFS('💳 Transactions'!$F$4:$F$403,'💳 Transactions'!$C$4:$C$403,A78,'💳 Transactions'!$D$4:$D$403,B78,'💳 Transactions'!$B$4:$B$403,"Expense",'💳 Transactions'!$P$4:$P$403,C_Year) | F78: =IF(C78="","",C78-D78) | G78: =IF(C78="","",IF(C78=0,"",D78/C78))
A79: Miscellaneous | B79: Category Subtotal | C79: =SUM(C76:C78) | D79: =SUM(D76:D78) | E79: =SUM(E76:E78) | F79: =SUM(F76:F78) | G79: =IF(C79=0,"",D79/C79)
A81: TOTAL | B81: Grand Total | C81: =SUM(C11,C19,C25,C34,C41,C49,C58,C63,C69,C75,C79) | D81: =SUM(D11,D19,D25,D34,D41,D49,D58,D63,D69,D75,D79) | E81: =SUM(E11,E19,E25,E34,E41,E49,E58,E63,E69,E75,E79) | F81: =SUM(F11,F19,F25,F34,F41,F49,F58,F63,F69,F75,F79) | G81: =IF(C81=0,"",D81/C81)

Sheet 🧾 Bills & Subs
A1: 🧾 Bills & Subscriptions Calendar
A2: Track every recurring payment. Annual cost & next month computation are automatic.
A3: Bill Name | B3: Amount | C3: Due Date | D3: Frequency | E3: Category | F3: Account Charged | G3: Autopay? | H3: Paid? | I3: Notes | J3: Annual Cost | K3: Month | L3: Year | M3: Day
A4: Home Mortgage | B4: 1850 | C4: 46235 | D4: Monthly | E4: Housing | F4: Checking | G4: Yes | H4: Yes | J4: =IF(C4="","",IF(D4="Monthly",B4*12,IF(D4="Weekly",B4*52,IF(D4="Biweekly",B4*26,IF(D4="Twice Monthly",B4*24,IF(D4="Quarterly",B4*4,IF(D4="Annually",B4,IF(D4="One-time",B4,"")))))))) | K4: =IF(C4="","",MONTH(C4)) | L4: =IF(C4="","",YEAR(C4)) | M4: =IF(C4="","",DAY(C4))
A5: Electric | B5: 145 | C5: 46242 | D5: Monthly | E5: Housing | F5: Checking | G5: Yes | H5: Yes | J5: =IF(C5="","",IF(D5="Monthly",B5*12,IF(D5="Weekly",B5*52,IF(D5="Biweekly",B5*26,IF(D5="Twice Monthly",B5*24,IF(D5="Quarterly",B5*4,IF(D5="Annually",B5,IF(D5="One-time",B5,"")))))))) | K5: =IF(C5="","",MONTH(C5)) | L5: =IF(C5="","",YEAR(C5)) | M5: =IF(C5="","",DAY(C5))
A6: Internet | B6: 60 | C6: 46246 | D6: Monthly | E6: Housing | F6: Credit Card | G6: Yes | H6: Yes | J6: =IF(C6="","",IF(D6="Monthly",B6*12,IF(D6="Weekly",B6*52,IF(D6="Biweekly",B6*26,IF(D6="Twice Monthly",B6*24,IF(D6="Quarterly",B6*4,IF(D6="Annually",B6,IF(D6="One-time",B6,"")))))))) | K6: =IF(C6="","",MONTH(C6)) | L6: =IF(C6="","",YEAR(C6)) | M6: =IF(C6="","",DAY(C6))
A7: Water & Sewer | B7: 55 | C7: 46249 | D7: Monthly | E7: Housing | F7: Checking | G7: Yes | H7: Yes | J7: =IF(C7="","",IF(D7="Monthly",B7*12,IF(D7="Weekly",B7*52,IF(D7="Biweekly",B7*26,IF(D7="Twice Monthly",B7*24,IF(D7="Quarterly",B7*4,IF(D7="Annually",B7,IF(D7="One-time",B7,"")))))))) | K7: =IF(C7="","",MONTH(C7)) | L7: =IF(C7="","",YEAR(C7)) | M7: =IF(C7="","",DAY(C7))
A8: Home Insurance | B8: 120 | C8: 46254 | D8: Monthly | E8: Housing | F8: Checking | G8: Yes | H8: Yes | J8: =IF(C8="","",IF(D8="Monthly",B8*12,IF(D8="Weekly",B8*52,IF(D8="Biweekly",B8*26,IF(D8="Twice Monthly",B8*24,IF(D8="Quarterly",B8*4,IF(D8="Annually",B8,IF(D8="One-time",B8,"")))))))) | K8: =IF(C8="","",MONTH(C8)) | L8: =IF(C8="","",YEAR(C8)) | M8: =IF(C8="","",DAY(C8))
A9: Auto Insurance | B9: 130 | C9: 46256 | D9: Monthly | E9: Transportation | F9: Credit Card | G9: Yes | H9: Yes | J9: =IF(C9="","",IF(D9="Monthly",B9*12,IF(D9="Weekly",B9*52,IF(D9="Biweekly",B9*26,IF(D9="Twice Monthly",B9*24,IF(D9="Quarterly",B9*4,IF(D9="Annually",B9,IF(D9="One-time",B9,"")))))))) | K9: =IF(C9="","",MONTH(C9)) | L9: =IF(C9="","",YEAR(C9)) | M9: =IF(C9="","",DAY(C9))
A10: Cell Phone | B10: 90 | C10: 46259 | D10: Monthly | E10: Lifestyle | F10: Credit Card | G10: Yes | H10: Yes | J10: =IF(C10="","",IF(D10="Monthly",B10*12,IF(D10="Weekly",B10*52,IF(D10="Biweekly",B10*26,IF(D10="Twice Monthly",B10*24,IF(D10="Quarterly",B10*4,IF(D10="Annually",B10,IF(D10="One-time",B10,"")))))))) | K10: =IF(C10="","",MONTH(C10)) | L10: =IF(C10="","",YEAR(C10)) | M10: =IF(C10="","",DAY(C10))
A11: Netflix | B11: 15.5 | C11: 46239 | D11: Monthly | E11: Lifestyle | F11: Credit Card | G11: Yes | H11: Yes | J11: =IF(C11="","",IF(D11="Monthly",B11*12,IF(D11="Weekly",B11*52,IF(D11="Biweekly",B11*26,IF(D11="Twice Monthly",B11*24,IF(D11="Quarterly",B11*4,IF(D11="Annually",B11,IF(D11="One-time",B11,"")))))))) | K11: =IF(C11="","",MONTH(C11)) | L11: =IF(C11="","",YEAR(C11)) | M11: =IF(C11="","",DAY(C11))
A12: Spotify | B12: 11 | C12: 46240 | D12: Monthly | E12: Lifestyle | F12: Credit Card | G12: Yes | H12: Yes | J12: =IF(C12="","",IF(D12="Monthly",B12*12,IF(D12="Weekly",B12*52,IF(D12="Biweekly",B12*26,IF(D12="Twice Monthly",B12*24,IF(D12="Quarterly",B12*4,IF(D12="Annually",B12,IF(D12="One-time",B12,"")))))))) | K12: =IF(C12="","",MONTH(C12)) | L12: =IF(C12="","",YEAR(C12)) | M12: =IF(C12="","",DAY(C12))
A13: Amazon Prime | B13: 14.5 | C13: 46241 | D13: Annually | E13: Lifestyle | F13: Credit Card | G13: Yes | H13: Yes | J13: =IF(C13="","",IF(D13="Monthly",B13*12,IF(D13="Weekly",B13*52,IF(D13="Biweekly",B13*26,IF(D13="Twice Monthly",B13*24,IF(D13="Quarterly",B13*4,IF(D13="Annually",B13,IF(D13="One-time",B13,"")))))))) | K13: =IF(C13="","",MONTH(C13)) | L13: =IF(C13="","",YEAR(C13)) | M13: =IF(C13="","",DAY(C13))
A14: Gym Membership | B14: 45 | C14: 46237 | D14: Monthly | E14: Lifestyle | F14: Credit Card | G14: Yes | H14: No | J14: =IF(C14="","",IF(D14="Monthly",B14*12,IF(D14="Weekly",B14*52,IF(D14="Biweekly",B14*26,IF(D14="Twice Monthly",B14*24,IF(D14="Quarterly",B14*4,IF(D14="Annually",B14,IF(D14="One-time",B14,"")))))))) | K14: =IF(C14="","",MONTH(C14)) | L14: =IF(C14="","",YEAR(C14)) | M14: =IF(C14="","",DAY(C14))
A15: Student Loan | B15: 220 | C15: 46252 | D15: Monthly | E15: Financial | F15: Checking | G15: Yes | H15: Yes | J15: =IF(C15="","",IF(D15="Monthly",B15*12,IF(D15="Weekly",B15*52,IF(D15="Biweekly",B15*26,IF(D15="Twice Monthly",B15*24,IF(D15="Quarterly",B15*4,IF(D15="Annually",B15,IF(D15="One-time",B15,"")))))))) | K15: =IF(C15="","",MONTH(C15)) | L15: =IF(C15="","",YEAR(C15)) | M15: =IF(C15="","",DAY(C15))
... A17: Life Insurance | B17: 55 | C17: 46244 | D17: Monthly | E17: Healthcare | F17: Checking | G17: Yes | H17: Yes | J17: =IF(C17="","",IF(D17="Monthly",B17*12,IF(D17="Weekly",B17*52,IF(D17="Biweekly",B17*26,IF(D17="Twice Monthly",B17*24,IF(D17="Quarterly",B17*4,IF(D17="Annually",B17,IF(D17="One-time",B17,"")))))))) | K17: =IF(C17="","",MONTH(C17)) | L17: =IF(C17="","",YEAR(C17)) | M17: =IF(C17="","",DAY(C17))
J18: =IF(C18="","",IF(D18="Monthly",B18*12,IF(D18="Weekly",B18*52,IF(D18="Biweekly",B18*26,IF(D18="Twice Monthly",B18*24,IF(D18="Quarterly",B18*4,IF(D18="Annually",B18,IF(D18="One-time",B18,"")))))))) | K18: =IF(C18="","",MONTH(C18)) | L18: =IF(C18="","",YEAR(C18)) | M18: =IF(C18="","",DAY(C18))
J19: =IF(C19="","",IF(D19="Monthly",B19*12,IF(D19="Weekly",B19*52,IF(D19="Biweekly",B19*26,IF(D19="Twice Monthly",B19*24,IF(D19="Quarterly",B19*4,IF(D19="Annually",B19,IF(D19="One-time",B19,"")))))))) | K19: =IF(C19="","",MONTH(C19)) | L19: =IF(C19="","",YEAR(C19)) | M19: =IF(C19="","",DAY(C19))
J20: =IF(C20="","",IF(D20="Monthly",B20*12,IF(D20="Weekly",B20*52,IF(D20="Biweekly",B20*26,IF(D20="Twice Monthly",B20*24,IF(D20="Quarterly",B20*4,IF(D20="Annually",B20,IF(D20="One-time",B20,"")))))))) | K20: =IF(C20="","",MONTH(C20)) | L20: =IF(C20="","",YEAR(C20)) | M20: =IF(C20="","",DAY(C20))
J21: =IF(C21="","",IF(D21="Monthly",B21*12,IF(D21="Weekly",B21*52,IF(D21="Biweekly",B21*26,IF(D21="Twice Monthly",B21*24,IF(D21="Quarterly",B21*4,IF(D21="Annually",B21,IF(D21="One-time",B21,"")))))))) | K21: =IF(C21="","",MONTH(C21)) | L21: =IF(C21="","",YEAR(C21)) | M21: =IF(C21="","",DAY(C21))
J22: =IF(C22="","",IF(D22="Monthly",B22*12,IF(D22="Weekly",B22*52,IF(D22="Biweekly",B22*26,IF(D22="Twice Monthly",B22*24,IF(D22="Quarterly",B22*4,IF(D22="Annually",B22,IF(D22="One-time",B22,"")))))))) | K22: =IF(C22="","",MONTH(C22)) | L22: =IF(C22="","",YEAR(C22)) | M22: =IF(C22="","",DAY(C22))
J23: =IF(C23="","",IF(D23="Monthly",B23*12,IF(D23="Weekly",B23*52,IF(D23="Biweekly",B23*26,IF(D23="Twice Monthly",B23*24,IF(D23="Quarterly",B23*4,IF(D23="Annually",B23,IF(D23="One-time",B23,"")))))))) | K23: =IF(C23="","",MONTH(C23)) | L23: =IF(C23="","",YEAR(C23)) | M23: =IF(C23="","",DAY(C23))
J24: =IF(C24="","",IF(D24="Monthly",B24*12,IF(D24="Weekly",B24*52,IF(D24="Biweekly",B24*26,IF(D24="Twice Monthly",B24*24,IF(D24="Quarterly",B24*4,IF(D24="Annually",B24,IF(D24="One-time",B24,"")))))))) | K24: =IF(C24="","",MONTH(C24)) | L24: =IF(C24="","",YEAR(C24)) | M24: =IF(C24="","",DAY(C24))
J25: =IF(C25="","",IF(D25="Monthly",B25*12,IF(D25="Weekly",B25*52,IF(D25="Biweekly",B25*26,IF(D25="Twice Monthly",B25*24,IF(D25="Quarterly",B25*4,IF(D25="Annually",B25,IF(D25="One-time",B25,"")))))))) | K25: =IF(C25="","",MONTH(C25)) | L25: =IF(C25="","",YEAR(C25)) | M25: =IF(C25="","",DAY(C25))
J26: =IF(C26="","",IF(D26="Monthly",B26*12,IF(D26="Weekly",B26*52,IF(D26="Biweekly",B26*26,IF(D26="Twice Monthly",B26*24,IF(D26="Quarterly",B26*4,IF(D26="Annually",B26,IF(D26="One-time",B26,"")))))))) | K26: =IF(C26="","",MONTH(C26)) | L26: =IF(C26="","",YEAR(C26)) | M26: =IF(C26="","",DAY(C26))
J27: =IF(C27="","",IF(D27="Monthly",B27*12,IF(D27="Weekly",B27*52,IF(D27="Biweekly",B27*26,IF(D27="Twice Monthly",B27*24,IF(D27="Quarterly",B27*4,IF(D27="Annually",B27,IF(D27="One-time",B27,"")))))))) | K27: =IF(C27="","",MONTH(C27)) | L27: =IF(C27="","",YEAR(C27)) | M27: =IF(C27="","",DAY(C27))
J28: =IF(C28="","",IF(D28="Monthly",B28*12,IF(D28="Weekly",B28*52,IF(D28="Biweekly",B28*26,IF(D28="Twice Monthly",B28*24,IF(D28="Quarterly",B28*4,IF(D28="Annually",B28,IF(D28="One-time",B28,"")))))))) | K28: =IF(C28="","",MONTH(C28)) | L28: =IF(C28="","",YEAR(C28)) | M28: =IF(C28="","",DAY(C28))
J29: =IF(C29="","",IF(D29="Monthly",B29*12,IF(D29="Weekly",B29*52,IF(D29="Biweekly",B29*26,IF(D29="Twice Monthly",B29*24,IF(D29="Quarterly",B29*4,IF(D29="Annually",B29,IF(D29="One-time",B29,"")))))))) | K29: =IF(C29="","",MONTH(C29)) | L29: =IF(C29="","",YEAR(C29)) | M29: =IF(C29="","",DAY(C29))
... J303: =IF(C303="","",IF(D303="Monthly",B303*12,IF(D303="Weekly",B303*52,IF(D303="Biweekly",B303*26,IF(D303="Twice Monthly",B303*24,IF(D303="Quarterly",B303*4,IF(D303="Annually",B303,IF(D303="One-time",B303,"")))))))) | K303: =IF(C303="","",MONTH(C303)) | L303: =IF(C303="","",YEAR(C303)) | M303: =IF(C303="","",DAY(C303))

Sheet 🏦 Accounts
A1: 🏦 Account Tracker
A2: Every household account with current balance, limits and rates. Available credit is auto-computed.
A3: Account Name | B3: Account Type | C3: Owner | D3: Current Balance | E3: Credit Limit | F3: Available Credit | G3: Rate / APY | H3: Last Updated | I3: Month | J3: Year | K3: Notes
A4: Chase Checking | B4: Checking | C4: Parent 1 | D4: 9200 | F4: =IF(E4="","",IF(E4=0,"",E4-ABS(D4))) | H4: 46244 | I4: =IF(H4="","",MONTH(H4)) | J4: =IF(H4="","",YEAR(H4)) | K4: Checking
A5: Wells Fargo Checking | B5: Checking | C5: Parent 2 | D5: 4300 | F5: =IF(E5="","",IF(E5=0,"",E5-ABS(D5))) | H5: 46244 | I5: =IF(H5="","",MONTH(H5)) | J5: =IF(H5="","",YEAR(H5)) | K5: Checking
A6: Ally Savings | B6: Savings | C6: Household | D6: 14500 | F6: =IF(E6="","",IF(E6=0,"",E6-ABS(D6))) | G6: 0.042 | H6: 46254 | I6: =IF(H6="","",MONTH(H6)) | J6: =IF(H6="","",YEAR(H6)) | K6: Savings
A7: Ally HYSA | B7: HYSA | C7: Household | D7: 28000 | F7: =IF(E7="","",IF(E7=0,"",E7-ABS(D7))) | G7: 0.047 | H7: 46255 | I7: =IF(H7="","",MONTH(H7)) | J7: =IF(H7="","",YEAR(H7)) | K7: Savings
A8: Cash | B8: Cash | C8: Household | D8: 450 | F8: =IF(E8="","",IF(E8=0,"",E8-ABS(D8))) | H8: 46260 | I8: =IF(H8="","",MONTH(H8)) | J8: =IF(H8="","",YEAR(H8)) | K8: Cash
A9: Capital One Credit | B9: Credit Card | C9: Parent 1 | D9: 2100 | E9: 12000 | F9: =IF(E9="","",IF(E9=0,"",E9-ABS(D9))) | G9: 0.2499 | H9: 46249 | I9: =IF(H9="","",MONTH(H9)) | J9: =IF(H9="","",YEAR(H9)) | K9: Credit Card
A10: Visa Credit | B10: Credit Card | C10: Parent 2 | D10: 830 | E10: 6000 | F10: =IF(E10="","",IF(E10=0,"",E10-ABS(D10))) | G10: 0.2299 | H10: 46252 | I10: =IF(H10="","",MONTH(H10)) | J10: =IF(H10="","",YEAR(H10)) | K10: Credit Card
A11: 401(k) - Fidelity | B11: 401(k) | C11: Parent 1 | D11: 128000 | F11: =IF(E11="","",IF(E11=0,"",E11-ABS(D11))) | G11: 0.07 | H11: 46262 | I11: =IF(H11="","",MONTH(H11)) | J11: =IF(H11="","",YEAR(H11)) | K11: Retirement
A12: 403(b) - TIAA | B12: 403(b) | C12: Parent 2 | D12: 76000 | F12: =IF(E12="","",IF(E12=0,"",E12-ABS(D12))) | G12: 0.065 | H12: 46262 | I12: =IF(H12="","",MONTH(H12)) | J12: =IF(H12="","",YEAR(H12)) | K12: Retirement
A13: Roth IRA | B13: Roth IRA | C13: Parent 1 | D13: 24000 | F13: =IF(E13="","",IF(E13=0,"",E13-ABS(D13))) | G13: 0.06 | H13: 46262 | I13: =IF(H13="","",MONTH(H13)) | J13: =IF(H13="","",YEAR(H13)) | K13: Retirement
A14: Brokerage - Vanguard | B14: Brokerage | C14: Parent 1 | D14: 54000 | F14: =IF(E14="","",IF(E14=0,"",E14-ABS(D14))) | H14: 46262 | I14: =IF(H14="","",MONTH(H14)) | J14: =IF(H14="","",YEAR(H14)) | K14: Investment
A15: 529 - College | B15: 529 | C15: Child 1 | D15: 21000 | F15: =IF(E15="","",IF(E15=0,"",E15-ABS(D15))) | G15: 0.05 | H15: 46262 | I15: =IF(H15="","",MONTH(H15)) | J15: =IF(H15="","",YEAR(H15)) | K15: Education
A16: HSA - Fidelity | B16: HSA | C16: Parent 1 | D16: 9800 | F16: =IF(E16="","",IF(E16=0,"",E16-ABS(D16))) | G16: 0.03 | H16: 46262 | I16: =IF(H16="","",MONTH(H16)) | J16: =IF(H16="","",YEAR(H16)) | K16: Retirement
A17: CD - 12 mo | B17: CD | C17: Household | D17: 10000 | F17: =IF(E17="","",IF(E17=0,"",E17-ABS(D17))) | G17: 0.048 | H17: 46262 | I17: =IF(H17="","",MONTH(H17)) | J17: =IF(H17="","",YEAR(H17)) | K17: Savings
F18: =IF(E18="","",IF(E18=0,"",E18-ABS(D18))) | I18: =IF(H18="","",MONTH(H18)) | J18: =IF(H18="","",YEAR(H18))
F19: =IF(E19="","",IF(E19=0,"",E19-ABS(D19))) | I19: =IF(H19="","",MONTH(H19)) | J19: =IF(H19="","",YEAR(H19))
F20: =IF(E20="","",IF(E20=0,"",E20-ABS(D20))) | I20: =IF(H20="","",MONTH(H20)) | J20: =IF(H20="","",YEAR(H20))
F21: =IF(E21="","",IF(E21=0,"",E21-ABS(D21))) | I21: =IF(H21="","",MONTH(H21)) | J21: =IF(H21="","",YEAR(H21))
F22: =IF(E22="","",IF(E22=0,"",E22-ABS(D22))) | I22: =IF(H22="","",MONTH(H22)) | J22: =IF(H22="","",YEAR(H22))
F23: =IF(E23="","",IF(E23=0,"",E23-ABS(D23))) | I23: =IF(H23="","",MONTH(H23)) | J23: =IF(H23="","",YEAR(H23))
F24: =IF(E24="","",IF(E24=0,"",E24-ABS(D24))) | I24: =IF(H24="","",MONTH(H24)) | J24: =IF(H24="","",YEAR(H24))
F25: =IF(E25="","",IF(E25=0,"",E25-ABS(D25))) | I25: =IF(H25="","",MONTH(H25)) | J25: =IF(H25="","",YEAR(H25))
F26: =IF(E26="","",IF(E26=0,"",E26-ABS(D26))) | I26: =IF(H26="","",MONTH(H26)) | J26: =IF(H26="","",YEAR(H26))
F27: =IF(E27="","",IF(E27=0,"",E27-ABS(D27))) | I27: =IF(H27="","",MONTH(H27)) | J27: =IF(H27="","",YEAR(H27))
F28: =IF(E28="","",IF(E28=0,"",E28-ABS(D28))) | I28: =IF(H28="","",MONTH(H28)) | J28: =IF(H28="","",YEAR(H28))
F29: =IF(E29="","",IF(E29=0,"",E29-ABS(D29))) | I29: =IF(H29="","",MONTH(H29)) | J29: =IF(H29="","",YEAR(H29))
... F103: =IF(E103="","",IF(E103=0,"",E103-ABS(D103))) | I103: =IF(H103="","",MONTH(H103)) | J103: =IF(H103="","",YEAR(H103))

Sheet 💸 Debt Manager
A1: 💸 Debt Payoff Planner
A2: Snowball & avalanche strategies built in. Interest saved and debt-free date are auto-estimated.
A4: DEBT SUMMARY
A5: Total Debt | B5: =SUM(D8:D107)
A6: Total Minimum Payment | B6: =SUM(G8:G107)
A7: Total Extra Payment | B7: =SUM(H8:H107)
A8: Visa Credit | B8: Capital One | C8: Credit Card | D8: 2100 | E8: 2500 | F8: 0.2499 | G8: 63 | H8: 150 | I8: 46249 | J8: =IF(I8="","",MONTH(I8)) | K8: =IF(I8="","",YEAR(I8)) | L8: =IF(I8="","",DAY(I8)) | M8: =IF(N8="","",EDATE(TODAY(),ROUNDUP(N8,0))) | N8: =IF(D8="","",IFERROR(NPER(F8/12,-(G8+H8),D8),"")) | O8: =IF(N8="","",(G8+H8)*N8-D8) | Q8: =IF(D8="","",RANK(D8,$D$8:$D$107,1)) | R8: =IF(F8="","",RANK(F8,$F$8:$F$107,0))
A9: Mastercard | B9: Bank of America | C9: Credit Card | D9: 830 | E9: 2000 | F9: 0.2299 | G9: 28 | H9: 50 | I9: 46252 | J9: =IF(I9="","",MONTH(I9)) | K9: =IF(I9="","",YEAR(I9)) | L9: =IF(I9="","",DAY(I9)) | M9: =IF(N9="","",EDATE(TODAY(),ROUNDUP(N9,0))) | N9: =IF(D9="","",IFERROR(NPER(F9/12,-(G9+H9),D9),"")) | O9: =IF(N9="","",(G9+H9)*N9-D9) | Q9: =IF(D9="","",RANK(D9,$D$8:$D$107,1)) | R9: =IF(F9="","",RANK(F9,$F$8:$F$107,0))
A10: Student Loan | B10: Navient | C10: Student Loan | D10: 14500 | E10: 25000 | F10: 0.045 | G10: 220 | H10: 100 | I10: 46239 | J10: =IF(I10="","",MONTH(I10)) | K10: =IF(I10="","",YEAR(I10)) | L10: =IF(I10="","",DAY(I10)) | M10: =IF(N10="","",EDATE(TODAY(),ROUNDUP(N10,0))) | N10: =IF(D10="","",IFERROR(NPER(F10/12,-(G10+H10),D10),"")) | O10: =IF(N10="","",(G10+H10)*N10-D10) | Q10: =IF(D10="","",RANK(D10,$D$8:$D$107,1)) | R10: =IF(F10="","",RANK(F10,$F$8:$F$107,0))
A11: Auto Loan | B11: Toyota Finance | C11: Auto Loan | D11: 14800 | E11: 26000 | F11: 0.055 | G11: 420 | H11: 100 | I11: 46246 | J11: =IF(I11="","",MONTH(I11)) | K11: =IF(I11="","",YEAR(I11)) | L11: =IF(I11="","",DAY(I11)) | M11: =IF(N11="","",EDATE(TODAY(),ROUNDUP(N11,0))) | N11: =IF(D11="","",IFERROR(NPER(F11/12,-(G11+H11),D11),"")) | O11: =IF(N11="","",(G11+H11)*N11-D11) | Q11: =IF(D11="","",RANK(D11,$D$8:$D$107,1)) | R11: =IF(F11="","",RANK(F11,$F$8:$F$107,0))
A12: Personal Loan | B12: SoFi | C12: Personal Loan | D12: 5800 | E12: 8000 | F12: 0.089 | G12: 145 | H12: 50 | I12: 46244 | J12: =IF(I12="","",MONTH(I12)) | K12: =IF(I12="","",YEAR(I12)) | L12: =IF(I12="","",DAY(I12)) | M12: =IF(N12="","",EDATE(TODAY(),ROUNDUP(N12,0))) | N12: =IF(D12="","",IFERROR(NPER(F12/12,-(G12+H12),D12),"")) | O12: =IF(N12="","",(G12+H12)*N12-D12) | Q12: =IF(D12="","",RANK(D12,$D$8:$D$107,1)) | R12: =IF(F12="","",RANK(F12,$F$8:$F$107,0))
J13: =IF(I13="","",MONTH(I13)) | K13: =IF(I13="","",YEAR(I13)) | L13: =IF(I13="","",DAY(I13)) | M13: =IF(N13="","",EDATE(TODAY(),ROUNDUP(N13,0))) | N13: =IF(D13="","",IFERROR(NPER(F13/12,-(G13+H13),D13),"")) | O13: =IF(N13="","",(G13+H13)*N13-D13) | Q13: =IF(D13="","",RANK(D13,$D$8:$D$107,1)) | R13: =IF(F13="","",RANK(F13,$F$8:$F$107,0))
J14: =IF(I14="","",MONTH(I14)) | K14: =IF(I14="","",YEAR(I14)) | L14: =IF(I14="","",DAY(I14)) | M14: =IF(N14="","",EDATE(TODAY(),ROUNDUP(N14,0))) | N14: =IF(D14="","",IFERROR(NPER(F14/12,-(G14+H14),D14),"")) | O14: =IF(N14="","",(G14+H14)*N14-D14) | Q14: =IF(D14="","",RANK(D14,$D$8:$D$107,1)) | R14: =IF(F14="","",RANK(F14,$F$8:$F$107,0))
J15: =IF(I15="","",MONTH(I15)) | K15: =IF(I15="","",YEAR(I15)) | L15: =IF(I15="","",DAY(I15)) | M15: =IF(N15="","",EDATE(TODAY(),ROUNDUP(N15,0))) | N15: =IF(D15="","",IFERROR(NPER(F15/12,-(G15+H15),D15),"")) | O15: =IF(N15="","",(G15+H15)*N15-D15) | Q15: =IF(D15="","",RANK(D15,$D$8:$D$107,1)) | R15: =IF(F15="","",RANK(F15,$F$8:$F$107,0))
J16: =IF(I16="","",MONTH(I16)) | K16: =IF(I16="","",YEAR(I16)) | L16: =IF(I16="","",DAY(I16)) | M16: =IF(N16="","",EDATE(TODAY(),ROUNDUP(N16,0))) | N16: =IF(D16="","",IFERROR(NPER(F16/12,-(G16+H16),D16),"")) | O16: =IF(N16="","",(G16+H16)*N16-D16) | Q16: =IF(D16="","",RANK(D16,$D$8:$D$107,1)) | R16: =IF(F16="","",RANK(F16,$F$8:$F$107,0))
J17: =IF(I17="","",MONTH(I17)) | K17: =IF(I17="","",YEAR(I17)) | L17: =IF(I17="","",DAY(I17)) | M17: =IF(N17="","",EDATE(TODAY(),ROUNDUP(N17,0))) | N17: =IF(D17="","",IFERROR(NPER(F17/12,-(G17+H17),D17),"")) | O17: =IF(N17="","",(G17+H17)*N17-D17) | Q17: =IF(D17="","",RANK(D17,$D$8:$D$107,1)) | R17: =IF(F17="","",RANK(F17,$F$8:$F$107,0))
J18: =IF(I18="","",MONTH(I18)) | K18: =IF(I18="","",YEAR(I18)) | L18: =IF(I18="","",DAY(I18)) | M18: =IF(N18="","",EDATE(TODAY(),ROUNDUP(N18,0))) | N18: =IF(D18="","",IFERROR(NPER(F18/12,-(G18+H18),D18),"")) | O18: =IF(N18="","",(G18+H18)*N18-D18) | Q18: =IF(D18="","",RANK(D18,$D$8:$D$107,1)) | R18: =IF(F18="","",RANK(F18,$F$8:$F$107,0))
J19: =IF(I19="","",MONTH(I19)) | K19: =IF(I19="","",YEAR(I19)) | L19: =IF(I19="","",DAY(I19)) | M19: =IF(N19="","",EDATE(TODAY(),ROUNDUP(N19,0))) | N19: =IF(D19="","",IFERROR(NPER(F19/12,-(G19+H19),D19),"")) | O19: =IF(N19="","",(G19+H19)*N19-D19) | Q19: =IF(D19="","",RANK(D19,$D$8:$D$107,1)) | R19: =IF(F19="","",RANK(F19,$F$8:$F$107,0))
J20: =IF(I20="","",MONTH(I20)) | K20: =IF(I20="","",YEAR(I20)) | L20: =IF(I20="","",DAY(I20)) | M20: =IF(N20="","",EDATE(TODAY(),ROUNDUP(N20,0))) | N20: =IF(D20="","",IFERROR(NPER(F20/12,-(G20+H20),D20),"")) | O20: =IF(N20="","",(G20+H20)*N20-D20) | Q20: =IF(D20="","",RANK(D20,$D$8:$D$107,1)) | R20: =IF(F20="","",RANK(F20,$F$8:$F$107,0))
J21: =IF(I21="","",MONTH(I21)) | K21: =IF(I21="","",YEAR(I21)) | L21: =IF(I21="","",DAY(I21)) | M21: =IF(N21="","",EDATE(TODAY(),ROUNDUP(N21,0))) | N21: =IF(D21="","",IFERROR(NPER(F21/12,-(G21+H21),D21),"")) | O21: =IF(N21="","",(G21+H21)*N21-D21) | Q21: =IF(D21="","",RANK(D21,$D$8:$D$107,1)) | R21: =IF(F21="","",RANK(F21,$F$8:$F$107,0))
J22: =IF(I22="","",MONTH(I22)) | K22: =IF(I22="","",YEAR(I22)) | L22: =IF(I22="","",DAY(I22)) | M22: =IF(N22="","",EDATE(TODAY(),ROUNDUP(N22,0))) | N22: =IF(D22="","",IFERROR(NPER(F22/12,-(G22+H22),D22),"")) | O22: =IF(N22="","",(G22+H22)*N22-D22) | Q22: =IF(D22="","",RANK(D22,$D$8:$D$107,1)) | R22: =IF(F22="","",RANK(F22,$F$8:$F$107,0))
J23: =IF(I23="","",MONTH(I23)) | K23: =IF(I23="","",YEAR(I23)) | L23: =IF(I23="","",DAY(I23)) | M23: =IF(N23="","",EDATE(TODAY(),ROUNDUP(N23,0))) | N23: =IF(D23="","",IFERROR(NPER(F23/12,-(G23+H23),D23),"")) | O23: =IF(N23="","",(G23+H23)*N23-D23) | Q23: =IF(D23="","",RANK(D23,$D$8:$D$107,1)) | R23: =IF(F23="","",RANK(F23,$F$8:$F$107,0))
J24: =IF(I24="","",MONTH(I24)) | K24: =IF(I24="","",YEAR(I24)) | L24: =IF(I24="","",DAY(I24)) | M24: =IF(N24="","",EDATE(TODAY(),ROUNDUP(N24,0))) | N24: =IF(D24="","",IFERROR(NPER(F24/12,-(G24+H24),D24),"")) | O24: =IF(N24="","",(G24+H24)*N24-D24) | Q24: =IF(D24="","",RANK(D24,$D$8:$D$107,1)) | R24: =IF(F24="","",RANK(F24,$F$8:$F$107,0))
... J107: =IF(I107="","",MONTH(I107)) | K107: =IF(I107="","",YEAR(I107)) | L107: =IF(I107="","",DAY(I107)) | M107: =IF(N107="","",EDATE(TODAY(),ROUNDUP(N107,0))) | N107: =IF(D107="","",IFERROR(NPER(F107/12,-(G107+H107),D107),"")) | O107: =IF(N107="","",(G107+H107)*N107-D107) | Q107: =IF(D107="","",RANK(D107,$D$8:$D$107,1)) | R107: =IF(F107="","",RANK(F107,$F$8:$F$107,0))

Sheet 🎯 Goals & Funds
A1: 🎯 Financial Goals & Sinking Funds
A2: Unlimited goals with auto % complete, per-paycheck amount and projected completion date.
A3: Goal Name | B3: Goal Type | C3: Target | D3: Current Saved | E3: Monthly Contribution | F3: Deadline | G3: Per Paycheck | H3: % Complete | I3: Monthly Needed | J3: Projected Completion | K3: Notes
A4: Emergency Fund | B4: Emergency Fund | C4: 60000 | D4: 42500 | E4: 500 | F4: 46387 | G4: =IF(E4="","",E4/2) | H4: =IF(C4="","",IF(C4=0,"",D4/C4)) | I4: =IF(OR(C4="",F4=""),"",IF(D4>=C4,0,IFERROR((C4-D4)/MAX(1,DATEDIF(TODAY(),F4,"m")),""))) | J4: =IF(E4="","",IF(D4>=C4,"Done",IFERROR(EDATE(TODAY(),(C4-D4)/E4),"")))
A5: Christmas 2026 | B5: Christmas | C5: 2500 | D5: 900 | E5: 150 | F5: 46387 | G5: =IF(E5="","",E5/2) | H5: =IF(C5="","",IF(C5=0,"",D5/C5)) | I5: =IF(OR(C5="",F5=""),"",IF(D5>=C5,0,IFERROR((C5-D5)/MAX(1,DATEDIF(TODAY(),F5,"m")),""))) | J5: =IF(E5="","",IF(D5>=C5,"Done",IFERROR(EDATE(TODAY(),(C5-D5)/E5),"")))
A6: Family Vacation | B6: Vacation | C6: 8000 | D6: 2200 | E6: 400 | F6: 46387 | G6: =IF(E6="","",E6/2) | H6: =IF(C6="","",IF(C6=0,"",D6/C6)) | I6: =IF(OR(C6="",F6=""),"",IF(D6>=C6,0,IFERROR((C6-D6)/MAX(1,DATEDIF(TODAY(),F6,"m")),""))) | J6: =IF(E6="","",IF(D6>=C6,"Done",IFERROR(EDATE(TODAY(),(C6-D6)/E6),"")))
A7: New Car Fund | B7: Major Purchase | C7: 20000 | D7: 5000 | E7: 500 | F7: 46387 | G7: =IF(E7="","",E7/2) | H7: =IF(C7="","",IF(C7=0,"",D7/C7)) | I7: =IF(OR(C7="",F7=""),"",IF(D7>=C7,0,IFERROR((C7-D7)/MAX(1,DATEDIF(TODAY(),F7,"m")),""))) | J7: =IF(E7="","",IF(D7>=C7,"Done",IFERROR(EDATE(TODAY(),(C7-D7)/E7),"")))
A8: Home Renovation | B8: Home Repairs | C8: 15000 | D8: 3000 | E8: 300 | F8: 46387 | G8: =IF(E8="","",E8/2) | H8: =IF(C8="","",IF(C8=0,"",D8/C8)) | I8: =IF(OR(C8="",F8=""),"",IF(D8>=C8,0,IFERROR((C8-D8)/MAX(1,DATEDIF(TODAY(),F8,"m")),""))) | J8: =IF(E8="","",IF(D8>=C8,"Done",IFERROR(EDATE(TODAY(),(C8-D8)/E8),"")))
A9: College - Child 1 | B9: College | C9: 50000 | D9: 21000 | E9: 300 | F9: 46387 | G9: =IF(E9="","",E9/2) | H9: =IF(C9="","",IF(C9=0,"",D9/C9)) | I9: =IF(OR(C9="",F9=""),"",IF(D9>=C9,0,IFERROR((C9-D9)/MAX(1,DATEDIF(TODAY(),F9,"m")),""))) | J9: =IF(E9="","",IF(D9>=C9,"Done",IFERROR(EDATE(TODAY(),(C9-D9)/E9),"")))
G10: =IF(E10="","",E10/2) | H10: =IF(C10="","",IF(C10=0,"",D10/C10)) | I10: =IF(OR(C10="",F10=""),"",IF(D10>=C10,0,IFERROR((C10-D10)/MAX(1,DATEDIF(TODAY(),F10,"m")),""))) | J10: =IF(E10="","",IF(D10>=C10,"Done",IFERROR(EDATE(TODAY(),(C10-D10)/E10),"")))
G11: =IF(E11="","",E11/2) | H11: =IF(C11="","",IF(C11=0,"",D11/C11)) | I11: =IF(OR(C11="",F11=""),"",IF(D11>=C11,0,IFERROR((C11-D11)/MAX(1,DATEDIF(TODAY(),F11,"m")),""))) | J11: =IF(E11="","",IF(D11>=C11,"Done",IFERROR(EDATE(TODAY(),(C11-D11)/E11),"")))
G12: =IF(E12="","",E12/2) | H12: =IF(C12="","",IF(C12=0,"",D12/C12)) | I12: =IF(OR(C12="",F12=""),"",IF(D12>=C12,0,IFERROR((C12-D12)/MAX(1,DATEDIF(TODAY(),F12,"m")),""))) | J12: =IF(E12="","",IF(D12>=C12,"Done",IFERROR(EDATE(TODAY(),(C12-D12)/E12),"")))
G13: =IF(E13="","",E13/2) | H13: =IF(C13="","",IF(C13=0,"",D13/C13)) | I13: =IF(OR(C13="",F13=""),"",IF(D13>=C13,0,IFERROR((C13-D13)/MAX(1,DATEDIF(TODAY(),F13,"m")),""))) | J13: =IF(E13="","",IF(D13>=C13,"Done",IFERROR(EDATE(TODAY(),(C13-D13)/E13),"")))
G14: =IF(E14="","",E14/2) | H14: =IF(C14="","",IF(C14=0,"",D14/C14)) | I14: =IF(OR(C14="",F14=""),"",IF(D14>=C14,0,IFERROR((C14-D14)/MAX(1,DATEDIF(TODAY(),F14,"m")),""))) | J14: =IF(E14="","",IF(D14>=C14,"Done",IFERROR(EDATE(TODAY(),(C14-D14)/E14),"")))
G15: =IF(E15="","",E15/2) | H15: =IF(C15="","",IF(C15=0,"",D15/C15)) | I15: =IF(OR(C15="",F15=""),"",IF(D15>=C15,0,IFERROR((C15-D15)/MAX(1,DATEDIF(TODAY(),F15,"m")),""))) | J15: =IF(E15="","",IF(D15>=C15,"Done",IFERROR(EDATE(TODAY(),(C15-D15)/E15),"")))
G16: =IF(E16="","",E16/2) | H16: =IF(C16="","",IF(C16=0,"",D16/C16)) | I16: =IF(OR(C16="",F16=""),"",IF(D16>=C16,0,IFERROR((C16-D16)/MAX(1,DATEDIF(TODAY(),F16,"m")),""))) | J16: =IF(E16="","",IF(D16>=C16,"Done",IFERROR(EDATE(TODAY(),(C16-D16)/E16),"")))
G17: =IF(E17="","",E17/2) | H17: =IF(C17="","",IF(C17=0,"",D17/C17)) | I17: =IF(OR(C17="",F17=""),"",IF(D17>=C17,0,IFERROR((C17-D17)/MAX(1,DATEDIF(TODAY(),F17,"m")),""))) | J17: =IF(E17="","",IF(D17>=C17,"Done",IFERROR(EDATE(TODAY(),(C17-D17)/E17),"")))
G18: =IF(E18="","",E18/2) | H18: =IF(C18="","",IF(C18=0,"",D18/C18)) | I18: =IF(OR(C18="",F18=""),"",IF(D18>=C18,0,IFERROR((C18-D18)/MAX(1,DATEDIF(TODAY(),F18,"m")),""))) | J18: =IF(E18="","",IF(D18>=C18,"Done",IFERROR(EDATE(TODAY(),(C18-D18)/E18),"")))
G19: =IF(E19="","",E19/2) | H19: =IF(C19="","",IF(C19=0,"",D19/C19)) | I19: =IF(OR(C19="",F19=""),"",IF(D19>=C19,0,IFERROR((C19-D19)/MAX(1,DATEDIF(TODAY(),F19,"m")),""))) | J19: =IF(E19="","",IF(D19>=C19,"Done",IFERROR(EDATE(TODAY(),(C19-D19)/E19),"")))
G20: =IF(E20="","",E20/2) | H20: =IF(C20="","",IF(C20=0,"",D20/C20)) | I20: =IF(OR(C20="",F20=""),"",IF(D20>=C20,0,IFERROR((C20-D20)/MAX(1,DATEDIF(TODAY(),F20,"m")),""))) | J20: =IF(E20="","",IF(D20>=C20,"Done",IFERROR(EDATE(TODAY(),(C20-D20)/E20),"")))
G21: =IF(E21="","",E21/2) | H21: =IF(C21="","",IF(C21=0,"",D21/C21)) | I21: =IF(OR(C21="",F21=""),"",IF(D21>=C21,0,IFERROR((C21-D21)/MAX(1,DATEDIF(TODAY(),F21,"m")),""))) | J21: =IF(E21="","",IF(D21>=C21,"Done",IFERROR(EDATE(TODAY(),(C21-D21)/E21),"")))
... G103: =IF(E103="","",E103/2) | H103: =IF(C103="","",IF(C103=0,"",D103/C103)) | I103: =IF(OR(C103="",F103=""),"",IF(D103>=C103,0,IFERROR((C103-D103)/MAX(1,DATEDIF(TODAY(),F103,"m")),""))) | J103: =IF(E103="","",IF(D103>=C103,"Done",IFERROR(EDATE(TODAY(),(C103-D103)/E103),"")))

Sheet 📈 Savings & Invest
A1: 📈 Savings & Investments
A2: Current balances pull automatically from the Account Tracker. Track contributions, employer match and goal progress.
A3: Investment Type | B3: Current Balance | C3: Monthly Contribution | D3: YTD Contributions | E3: Employer Match % | F3: Employer Match $ | G3: Annual Max | H3: Goal | I3: Progress | J3: Notes
A5: 401(k) | B5: =SUMIF('🏦 Accounts'!$B$4:$B$103,"401(k)",'🏦 Accounts'!$D$4:$D$103) | F5: =IF(AND(C5="",E5=""),"",IFERROR(C5*E5,0)) | I5: =IF(OR(B5="",H5=""),"",IF(H5=0,"",B5/H5))
A6: 403(b) | B6: =SUMIF('🏦 Accounts'!$B$4:$B$103,"403(b)",'🏦 Accounts'!$D$4:$D$103) | F6: =IF(AND(C6="",E6=""),"",IFERROR(C6*E6,0)) | I6: =IF(OR(B6="",H6=""),"",IF(H6=0,"",B6/H6))
A7: IRA | B7: =SUMIF('🏦 Accounts'!$B$4:$B$103,"IRA",'🏦 Accounts'!$D$4:$D$103) | F7: =IF(AND(C7="",E7=""),"",IFERROR(C7*E7,0)) | I7: =IF(OR(B7="",H7=""),"",IF(H7=0,"",B7/H7))
A8: Roth IRA | B8: =SUMIF('🏦 Accounts'!$B$4:$B$103,"Roth IRA",'🏦 Accounts'!$D$4:$D$103) | F8: =IF(AND(C8="",E8=""),"",IFERROR(C8*E8,0)) | I8: =IF(OR(B8="",H8=""),"",IF(H8=0,"",B8/H8))
A9: Brokerage | B9: =SUMIF('🏦 Accounts'!$B$4:$B$103,"Brokerage",'🏦 Accounts'!$D$4:$D$103) | F9: =IF(AND(C9="",E9=""),"",IFERROR(C9*E9,0)) | I9: =IF(OR(B9="",H9=""),"",IF(H9=0,"",B9/H9))
A10: HSA | B10: =SUMIF('🏦 Accounts'!$B$4:$B$103,"HSA",'🏦 Accounts'!$D$4:$D$103) | F10: =IF(AND(C10="",E10=""),"",IFERROR(C10*E10,0)) | I10: =IF(OR(B10="",H10=""),"",IF(H10=0,"",B10/H10))
A11: 529 | B11: =SUMIF('🏦 Accounts'!$B$4:$B$103,"529",'🏦 Accounts'!$D$4:$D$103) | F11: =IF(AND(C11="",E11=""),"",IFERROR(C11*E11,0)) | I11: =IF(OR(B11="",H11=""),"",IF(H11=0,"",B11/H11))
A12: CD | B12: =SUMIF('🏦 Accounts'!$B$4:$B$103,"CD",'🏦 Accounts'!$D$4:$D$103) | F12: =IF(AND(C12="",E12=""),"",IFERROR(C12*E12,0)) | I12: =IF(OR(B12="",H12=""),"",IF(H12=0,"",B12/H12))
A13: HYSA | B13: =SUMIF('🏦 Accounts'!$B$4:$B$103,"HYSA",'🏦 Accounts'!$D$4:$D$103) | F13: =IF(AND(C13="",E13=""),"",IFERROR(C13*E13,0)) | I13: =IF(OR(B13="",H13=""),"",IF(H13=0,"",B13/H13))
A14: Cash | B14: =SUMIF('🏦 Accounts'!$B$4:$B$103,"Cash",'🏦 Accounts'!$D$4:$D$103) | F14: =IF(AND(C14="",E14=""),"",IFERROR(C14*E14,0)) | I14: =IF(OR(B14="",H14=""),"",IF(H14=0,"",B14/H14))
A15: Emergency Fund | B15: =SUMIF('🏦 Accounts'!$B$4:$B$103,"HYSA",'🏦 Accounts'!$D$4:$D$103)+SUMIF('🏦 Accounts'!$B$4:$B$103,"Savings",'🏦 Accounts'!$D$4:$D$103) | F15: =IF(AND(C15="",E15=""),"",IFERROR(C15*E15,0)) | I15: =IF(OR(B15="",H15=""),"",IF(H15=0,"",B15/H15))
A17: TOTAL | B17: =SUM(B5:B15) | C17: =SUM(C5:C15) | F17: =SUM(F5:F15)

Sheet 🏡 Home & Mortgage
A1: 🏡 Home & Mortgage
A2: Home equity, total monthly cost and a full mortgage amortization schedule — all auto-calculated.
A4: HOME / MORTGAGE INPUTS
A5: Home Value | B5: 420000
A6: Annual Property Tax | B6: 5000
A7: Monthly HOA | B7: 90
A8: Annual Home Insurance | B8: 1400
A9: Monthly Maintenance (avg) | B9: 150
A10: Mortgage Balance | B10: 285000
A11: Interest Rate (APR) | B11: 0.055
A12: Loan Term (years) | B12: 30
A13: Monthly P&I Payment | B13: =IFERROR(-PMT(B11/12,B12*12,B10),0)
A14: Monthly Escrow (Tax+Ins+HOA) | B14: =IFERROR(B6/12+B8/12+B7,0)
A15: Total Monthly Housing Cost | B15: =B13+B14+B9
A16: Annual Carrying Cost | B16: =B15*12
A17: Home Equity | B17: =B5-B10
A18: Loan % Paid | B18: =IF(OR(B10="",B5=""),"",1-B10/B5)
A19: Months Remaining | B19: =IFERROR(NPER(B11/12,-B13,B10),"")
A20: Projected Payoff Date | B20: =IFERROR(EDATE(TODAY(),ROUNDUP(B19,0)),"")
A22: MORTGAGE AMORTIZATION SCHEDULE
A23: Payment # | B23: Payment | C23: Interest | D23: Principal | E23: Balance
A24: Start | E24: =$B$10
A25: 1 | B25: =IF(E24<=0,"",$B$13) | C25: =IF(E24<=0,"",E24*$B$11/12) | D25: =IF(E24<=0,"",B25-C25) | E25: =IF(E24<=0,"",E24-D25)
A26: 2 | B26: =IF(E25<=0,"",$B$13) | C26: =IF(E25<=0,"",E25*$B$11/12) | D26: =IF(E25<=0,"",B26-C26) | E26: =IF(E25<=0,"",E25-D26)
A27: 3 | B27: =IF(E26<=0,"",$B$13) | C27: =IF(E26<=0,"",E26*$B$11/12) | D27: =IF(E26<=0,"",B27-C27) | E27: =IF(E26<=0,"",E26-D27)
A28: 4 | B28: =IF(E27<=0,"",$B$13) | C28: =IF(E27<=0,"",E27*$B$11/12) | D28: =IF(E27<=0,"",B28-C28) | E28: =IF(E27<=0,"",E27-D28)
A29: 5 | B29: =IF(E28<=0,"",$B$13) | C29: =IF(E28<=0,"",E28*$B$11/12) | D29: =IF(E28<=0,"",B29-C29) | E29: =IF(E28<=0,"",E28-D29)
A30: 6 | B30: =IF(E29<=0,"",$B$13) | C30: =IF(E29<=0,"",E29*$B$11/12) | D30: =IF(E29<=0,"",B30-C30) | E30: =IF(E29<=0,"",E29-D30)
A31: 7 | B31: =IF(E30<=0,"",$B$13) | C31: =IF(E30<=0,"",E30*$B$11/12) | D31: =IF(E30<=0,"",B31-C31) | E31: =IF(E30<=0,"",E30-D31)
A32: 8 | B32: =IF(E31<=0,"",$B$13) | C32: =IF(E31<=0,"",E31*$B$11/12) | D32: =IF(E31<=0,"",B32-C32) | E32: =IF(E31<=0,"",E31-D32)
A33: 9 | B33: =IF(E32<=0,"",$B$13) | C33: =IF(E32<=0,"",E32*$B$11/12) | D33: =IF(E32<=0,"",B33-C33) | E33: =IF(E32<=0,"",E32-D33)
A34: 10 | B34: =IF(E33<=0,"",$B$13) | C34: =IF(E33<=0,"",E33*$B$11/12) | D34: =IF(E33<=0,"",B34-C34) | E34: =IF(E33<=0,"",E33-D34)
A35: 11 | B35: =IF(E34<=0,"",$B$13) | C35: =IF(E34<=0,"",E34*$B$11/12) | D35: =IF(E34<=0,"",B35-C35) | E35: =IF(E34<=0,"",E34-D35)
A36: 12 | B36: =IF(E35<=0,"",$B$13) | C36: =IF(E35<=0,"",E35*$B$11/12) | D36: =IF(E35<=0,"",B36-C36) | E36: =IF(E35<=0,"",E35-D36)
... A384: 360 | B384: =IF(E383<=0,"",$B$13) | C384: =IF(E383<=0,"",E383*$B$11/12) | D384: =IF(E383<=0,"",B384-C384) | E384: =IF(E383<=0,"",E383-D384)

Sheet 🚗 Vehicles
A1: 🚗 Vehicle Costs
A2: Track the true cost of each vehicle — including cost per mile — automatically.
A3: Vehicle | B3: Owner | C3: Loan Payment | D3: Insurance | E3: Gas | F3: Maintenance | G3: Repairs | H3: Registration (ann) | I3: Tires (ann) | J3: Parking/Tolls | K3: Annual Miles | L3: Current Value | M3: Monthly Total | N3: Annual Total | O3: Cost per Mile
A4: Toyota Camry | B4: Family | C4: 420 | D4: 85 | E4: 130 | F4: 60 | G4: 45 | H4: 120 | I4: 90 | J4: 30 | K4: 12000 | L4: 13500 | M4: =IF(C4="","",SUM(C4:G4,J4)+IF(H4="",0,H4/12)+IF(I4="",0,I4/12)) | N4: =IF(M4="","",M4*12) | O4: =IF(OR(K4="",K4=0),"",N4/K4)
A5: Honda CR-V | B5: Parent 2 | C5: 0 | D5: 75 | E5: 90 | F5: 50 | G5: 30 | H5: 100 | I5: 80 | J5: 20 | K5: 9000 | L5: 21000 | M5: =IF(C5="","",SUM(C5:G5,J5)+IF(H5="",0,H5/12)+IF(I5="",0,I5/12)) | N5: =IF(M5="","",M5*12) | O5: =IF(OR(K5="",K5=0),"",N5/K5)
M6: =IF(C6="","",SUM(C6:G6,J6)+IF(H6="",0,H6/12)+IF(I6="",0,I6/12)) | N6: =IF(M6="","",M6*12) | O6: =IF(OR(K6="",K6=0),"",N6/K6)
M7: =IF(C7="","",SUM(C7:G7,J7)+IF(H7="",0,H7/12)+IF(I7="",0,I7/12)) | N7: =IF(M7="","",M7*12) | O7: =IF(OR(K7="",K7=0),"",N7/K7)
M8: =IF(C8="","",SUM(C8:G8,J8)+IF(H8="",0,H8/12)+IF(I8="",0,I8/12)) | N8: =IF(M8="","",M8*12) | O8: =IF(OR(K8="",K8=0),"",N8/K8)
M9: =IF(C9="","",SUM(C9:G9,J9)+IF(H9="",0,H9/12)+IF(I9="",0,I9/12)) | N9: =IF(M9="","",M9*12) | O9: =IF(OR(K9="",K9=0),"",N9/K9)
M10: =IF(C10="","",SUM(C10:G10,J10)+IF(H10="",0,H10/12)+IF(I10="",0,I10/12)) | N10: =IF(M10="","",M10*12) | O10: =IF(OR(K10="",K10=0),"",N10/K10)
M11: =IF(C11="","",SUM(C11:G11,J11)+IF(H11="",0,H11/12)+IF(I11="",0,I11/12)) | N11: =IF(M11="","",M11*12) | O11: =IF(OR(K11="",K11=0),"",N11/K11)
M12: =IF(C12="","",SUM(C12:G12,J12)+IF(H12="",0,H12/12)+IF(I12="",0,I12/12)) | N12: =IF(M12="","",M12*12) | O12: =IF(OR(K12="",K12=0),"",N12/K12)
M13: =IF(C13="","",SUM(C13:G13,J13)+IF(H13="",0,H13/12)+IF(I13="",0,I13/12)) | N13: =IF(M13="","",M13*12) | O13: =IF(OR(K13="",K13=0),"",N13/K13)
M14: =IF(C14="","",SUM(C14:G14,J14)+IF(H14="",0,H14/12)+IF(I14="",0,I14/12)) | N14: =IF(M14="","",M14*12) | O14: =IF(OR(K14="",K14=0),"",N14/K14)
M15: =IF(C15="","",SUM(C15:G15,J15)+IF(H15="",0,H15/12)+IF(I15="",0,I15/12)) | N15: =IF(M15="","",M15*12) | O15: =IF(OR(K15="",K15=0),"",N15/K15)
M16: =IF(C16="","",SUM(C16:G16,J16)+IF(H16="",0,H16/12)+IF(I16="",0,I16/12)) | N16: =IF(M16="","",M16*12) | O16: =IF(OR(K16="",K16=0),"",N16/K16)
M17: =IF(C17="","",SUM(C17:G17,J17)+IF(H17="",0,H17/12)+IF(I17="",0,I17/12)) | N17: =IF(M17="","",M17*12) | O17: =IF(OR(K17="",K17=0),"",N17/K17)
... M33: =IF(C33="","",SUM(C33:G33,J33)+IF(H33="",0,H33/12)+IF(I33="",0,I33/12)) | N33: =IF(M33="","",M33*12) | O33: =IF(OR(K33="",K33=0),"",N33/K33)

Sheet 👨‍👩‍👧‍👦 Family & Kids
A1: 👨‍👩‍👧‍👦 Family & Kids
A2: Family-related spending at a glance, plus spending broken down by family member.
A3: Category | B3: Subcategory | C3: Monthly Budget | D3: Actual This Month | E3: Actual YTD | F3: Variance | G3: Notes
A4: Family | B4: Childcare | C4: 585 | D4: =SUMIFS('💳 Transactions'!$F$4:$F$403,'💳 Transactions'!$C$4:$C$403,"Family",'💳 Transactions'!$D$4:$D$403,B4,'💳 Transactions'!$B$4:$B$403,"Expense",'💳 Transactions'!$O$4:$O$403,C_Month,'💳 Transactions'!$P$4:$P$403,C_Year) | E4: =SUMIFS('💳 Transactions'!$F$4:$F$403,'💳 Transactions'!$C$4:$C$403,"Family",'💳 Transactions'!$D$4:$D$403,B4,'💳 Transactions'!$B$4:$B$403,"Expense",'💳 Transactions'!$P$4:$P$403,C_Year) | F4: =IF(C4="","",C4-D4)
A5: Family | B5: School | C5: 60 | D5: =SUMIFS('💳 Transactions'!$F$4:$F$403,'💳 Transactions'!$C$4:$C$403,"Family",'💳 Transactions'!$D$4:$D$403,B5,'💳 Transactions'!$B$4:$B$403,"Expense",'💳 Transactions'!$O$4:$O$403,C_Month,'💳 Transactions'!$P$4:$P$403,C_Year) | E5: =SUMIFS('💳 Transactions'!$F$4:$F$403,'💳 Transactions'!$C$4:$C$403,"Family",'💳 Transactions'!$D$4:$D$403,B5,'💳 Transactions'!$B$4:$B$403,"Expense",'💳 Transactions'!$P$4:$P$403,C_Year) | F5: =IF(C5="","",C5-D5)
A6: Family | B6: Activities/Sports | C6: 75 | D6: =SUMIFS('💳 Transactions'!$F$4:$F$403,'💳 Transactions'!$C$4:$C$403,"Family",'💳 Transactions'!$D$4:$D$403,B6,'💳 Transactions'!$B$4:$B$403,"Expense",'💳 Transactions'!$O$4:$O$403,C_Month,'💳 Transactions'!$P$4:$P$403,C_Year) | E6: =SUMIFS('💳 Transactions'!$F$4:$F$403,'💳 Transactions'!$C$4:$C$403,"Family",'💳 Transactions'!$D$4:$D$403,B6,'💳 Transactions'!$B$4:$B$403,"Expense",'💳 Transactions'!$P$4:$P$403,C_Year) | F6: =IF(C6="","",C6-D6)
A7: Family | B7: Clothing | C7: 65 | D7: =SUMIFS('💳 Transactions'!$F$4:$F$403,'💳 Transactions'!$C$4:$C$403,"Family",'💳 Transactions'!$D$4:$D$403,B7,'💳 Transactions'!$B$4:$B$403,"Expense",'💳 Transactions'!$O$4:$O$403,C_Month,'💳 Transactions'!$P$4:$P$403,C_Year) | E7: =SUMIFS('💳 Transactions'!$F$4:$F$403,'💳 Transactions'!$C$4:$C$403,"Family",'💳 Transactions'!$D$4:$D$403,B7,'💳 Transactions'!$B$4:$B$403,"Expense",'💳 Transactions'!$P$4:$P$403,C_Year) | F7: =IF(C7="","",C7-D7)
A8: Family | B8: Allowances | C8: 25 | D8: =SUMIFS('💳 Transactions'!$F$4:$F$403,'💳 Transactions'!$C$4:$C$403,"Family",'💳 Transactions'!$D$4:$D$403,B8,'💳 Transactions'!$B$4:$B$403,"Expense",'💳 Transactions'!$O$4:$O$403,C_Month,'💳 Transactions'!$P$4:$P$403,C_Year) | E8: =SUMIFS('💳 Transactions'!$F$4:$F$403,'💳 Transactions'!$C$4:$C$403,"Family",'💳 Transactions'!$D$4:$D$403,B8,'💳 Transactions'!$B$4:$B$403,"Expense",'💳 Transactions'!$P$4:$P$403,C_Year) | F8: =IF(C8="","",C8-D8)
A9: Family | B9: Baby Expenses | C9: 40 | D9: =SUMIFS('💳 Transactions'!$F$4:$F$403,'💳 Transactions'!$C$4:$C$403,"Family",'💳 Transactions'!$D$4:$D$403,B9,'💳 Transactions'!$B$4:$B$403,"Expense",'💳 Transactions'!$O$4:$O$403,C_Month,'💳 Transactions'!$P$4:$P$403,C_Year) | E9: =SUMIFS('💳 Transactions'!$F$4:$F$403,'💳 Transactions'!$C$4:$C$403,"Family",'💳 Transactions'!$D$4:$D$403,B9,'💳 Transactions'!$B$4:$B$403,"Expense",'💳 Transactions'!$P$4:$P$403,C_Year) | F9: =IF(C9="","",C9-D9)
A10: Family | B10: College Savings | C10: 125 | D10: =SUMIFS('💳 Transactions'!$F$4:$F$403,'💳 Transactions'!$C$4:$C$403,"Family",'💳 Transactions'!$D$4:$D$403,B10,'💳 Transactions'!$B$4:$B$403,"Expense",'💳 Transactions'!$O$4:$O$403,C_Month,'💳 Transactions'!$P$4:$P$403,C_Year) | E10: =SUMIFS('💳 Transactions'!$F$4:$F$403,'💳 Transactions'!$C$4:$C$403,"Family",'💳 Transactions'!$D$4:$D$403,B10,'💳 Transactions'!$B$4:$B$403,"Expense",'💳 Transactions'!$P$4:$P$403,C_Year) | F10: =IF(C10="","",C10-D10)
A11: Family | B11: Other Family | D11: =SUMIFS('💳 Transactions'!$F$4:$F$403,'💳 Transactions'!$C$4:$C$403,"Family",'💳 Transactions'!$D$4:$D$403,B11,'💳 Transactions'!$B$4:$B$403,"Expense",'💳 Transactions'!$O$4:$O$403,C_Month,'💳 Transactions'!$P$4:$P$403,C_Year) | E11: =SUMIFS('💳 Transactions'!$F$4:$F$403,'💳 Transactions'!$C$4:$C$403,"Family",'💳 Transactions'!$D$4:$D$403,B11,'💳 Transactions'!$B$4:$B$403,"Expense",'💳 Transactions'!$P$4:$P$403,C_Year) | F11: =IF(C11="","",C11-D11)
A13: TOTAL | B13: Family Total | C13: =SUM(C4:C11) | D13: =SUM(D4:D11) | E13: =SUM(E4:E11)
A16: SPENDING BY FAMILY MEMBER (THIS MONTH)
A17: Family Member | B17: This Month | C17: YTD
A18: Parent 1 | B18: =SUMIFS('💳 Transactions'!$F$4:$F$403,'💳 Transactions'!$B$4:$B$403,"Expense",'💳 Transactions'!$I$4:$I$403,A18,'💳 Transactions'!$O$4:$O$403,C_Month,'💳 Transactions'!$P$4:$P$403,C_Year) | C18: =SUMIFS('💳 Transactions'!$F$4:$F$403,'💳 Transactions'!$B$4:$B$403,"Expense",'💳 Transactions'!$I$4:$I$403,A18,'💳 Transactions'!$P$4:$P$403,C_Year)
A19: Parent 2 | B19: =SUMIFS('💳 Transactions'!$F$4:$F$403,'💳 Transactions'!$B$4:$B$403,"Expense",'💳 Transactions'!$I$4:$I$403,A19,'💳 Transactions'!$O$4:$O$403,C_Month,'💳 Transactions'!$P$4:$P$403,C_Year) | C19: =SUMIFS('💳 Transactions'!$F$4:$F$403,'💳 Transactions'!$B$4:$B$403,"Expense",'💳 Transactions'!$I$4:$I$403,A19,'💳 Transactions'!$P$4:$P$403,C_Year)
A20: Child 1 | B20: =SUMIFS('💳 Transactions'!$F$4:$F$403,'💳 Transactions'!$B$4:$B$403,"Expense",'💳 Transactions'!$I$4:$I$403,A20,'💳 Transactions'!$O$4:$O$403,C_Month,'💳 Transactions'!$P$4:$P$403,C_Year) | C20: =SUMIFS('💳 Transactions'!$F$4:$F$403,'💳 Transactions'!$B$4:$B$403,"Expense",'💳 Transactions'!$I$4:$I$403,A20,'💳 Transactions'!$P$4:$P$403,C_Year)
A21: Child 2 | B21: =SUMIFS('💳 Transactions'!$F$4:$F$403,'💳 Transactions'!$B$4:$B$403,"Expense",'💳 Transactions'!$I$4:$I$403,A21,'💳 Transactions'!$O$4:$O$403,C_Month,'💳 Transactions'!$P$4:$P$403,C_Year) | C21: =SUMIFS('💳 Transactions'!$F$4:$F$403,'💳 Transactions'!$B$4:$B$403,"Expense",'💳 Transactions'!$I$4:$I$403,A21,'💳 Transactions'!$P$4:$P$403,C_Year)
A22: Household | B22: =SUMIFS('💳 Transactions'!$F$4:$F$403,'💳 Transactions'!$B$4:$B$403,"Expense",'💳 Transactions'!$I$4:$I$403,A22,'💳 Transactions'!$O$4:$O$403,C_Month,'💳 Transactions'!$P$4:$P$403,C_Year) | C22: =SUMIFS('💳 Transactions'!$F$4:$F$403,'💳 Transactions'!$B$4:$B$403,"Expense",'💳 Transactions'!$I$4:$I$403,A22,'💳 Transactions'!$P$4:$P$403,C_Year)
A23: Other | B23: =SUMIFS('💳 Transactions'!$F$4:$F$403,'💳 Transactions'!$B$4:$B$403,"Expense",'💳 Transactions'!$I$4:$I$403,A23,'💳 Transactions'!$O$4:$O$403,C_Month,'💳 Transactions'!$P$4:$P$403,C_Year) | C23: =SUMIFS('💳 Transactions'!$F$4:$F$403,'💳 Transactions'!$B$4:$B$403,"Expense",'💳 Transactions'!$I$4:$I$403,A23,'💳 Transactions'!$P$4:$P$403,C_Year)

Sheet 🏥 Healthcare
A1: 🏥 Healthcare & Insurance
A2: Healthcare spending vs budget, plus every insurance premium in one place.
A3: Category | B3: Subcategory | C3: Monthly Budget | D3: Actual This Month | E3: Actual YTD | F3: Variance | G3: Notes
A4: Healthcare | B4: Health Insurance | C4: 290 | D4: =SUMIFS('💳 Transactions'!$F$4:$F$403,'💳 Transactions'!$C$4:$C$403,"Healthcare",'💳 Transactions'!$D$4:$D$403,B4,'💳 Transactions'!$B$4:$B$403,"Expense",'💳 Transactions'!$O$4:$O$403,C_Month,'💳 Transactions'!$P$4:$P$403,C_Year) | E4: =SUMIFS('💳 Transactions'!$F$4:$F$403,'💳 Transactions'!$C$4:$C$403,"Healthcare",'💳 Transactions'!$D$4:$D$403,B4,'💳 Transactions'!$B$4:$B$403,"Expense",'💳 Transactions'!$P$4:$P$403,C_Year) | F4: =IF(C4="","",C4-D4)
A5: Healthcare | B5: Dental | C5: 20 | D5: =SUMIFS('💳 Transactions'!$F$4:$F$403,'💳 Transactions'!$C$4:$C$403,"Healthcare",'💳 Transactions'!$D$4:$D$403,B5,'💳 Transactions'!$B$4:$B$403,"Expense",'💳 Transactions'!$O$4:$O$403,C_Month,'💳 Transactions'!$P$4:$P$403,C_Year) | E5: =SUMIFS('💳 Transactions'!$F$4:$F$403,'💳 Transactions'!$C$4:$C$403,"Healthcare",'💳 Transactions'!$D$4:$D$403,B5,'💳 Transactions'!$B$4:$B$403,"Expense",'💳 Transactions'!$P$4:$P$403,C_Year) | F5: =IF(C5="","",C5-D5)
A6: Healthcare | B6: Vision | C6: 15 | D6: =SUMIFS('💳 Transactions'!$F$4:$F$403,'💳 Transactions'!$C$4:$C$403,"Healthcare",'💳 Transactions'!$D$4:$D$403,B6,'💳 Transactions'!$B$4:$B$403,"Expense",'💳 Transactions'!$O$4:$O$403,C_Month,'💳 Transactions'!$P$4:$P$403,C_Year) | E6: =SUMIFS('💳 Transactions'!$F$4:$F$403,'💳 Transactions'!$C$4:$C$403,"Healthcare",'💳 Transactions'!$D$4:$D$403,B6,'💳 Transactions'!$B$4:$B$403,"Expense",'💳 Transactions'!$P$4:$P$403,C_Year) | F6: =IF(C6="","",C6-D6)
A7: Healthcare | B7: Prescriptions | C7: 35 | D7: =SUMIFS('💳 Transactions'!$F$4:$F$403,'💳 Transactions'!$C$4:$C$403,"Healthcare",'💳 Transactions'!$D$4:$D$403,B7,'💳 Transactions'!$B$4:$B$403,"Expense",'💳 Transactions'!$O$4:$O$403,C_Month,'💳 Transactions'!$P$4:$P$403,C_Year) | E7: =SUMIFS('💳 Transactions'!$F$4:$F$403,'💳 Transactions'!$C$4:$C$403,"Healthcare",'💳 Transactions'!$D$4:$D$403,B7,'💳 Transactions'!$B$4:$B$403,"Expense",'💳 Transactions'!$P$4:$P$403,C_Year) | F7: =IF(C7="","",C7-D7)
A8: Healthcare | B8: Medical Expenses | C8: 65 | D8: =SUMIFS('💳 Transactions'!$F$4:$F$403,'💳 Transactions'!$C$4:$C$403,"Healthcare",'💳 Transactions'!$D$4:$D$403,B8,'💳 Transactions'!$B$4:$B$403,"Expense",'💳 Transactions'!$O$4:$O$403,C_Month,'💳 Transactions'!$P$4:$P$403,C_Year) | E8: =SUMIFS('💳 Transactions'!$F$4:$F$403,'💳 Transactions'!$C$4:$C$403,"Healthcare",'💳 Transactions'!$D$4:$D$403,B8,'💳 Transactions'!$B$4:$B$403,"Expense",'💳 Transactions'!$P$4:$P$403,C_Year) | F8: =IF(C8="","",C8-D8)
A9: Healthcare | B9: Other Healthcare | D9: =SUMIFS('💳 Transactions'!$F$4:$F$403,'💳 Transactions'!$C$4:$C$403,"Healthcare",'💳 Transactions'!$D$4:$D$403,B9,'💳 Transactions'!$B$4:$B$403,"Expense",'💳 Transactions'!$O$4:$O$403,C_Month,'💳 Transactions'!$P$4:$P$403,C_Year) | E9: =SUMIFS('💳 Transactions'!$F$4:$F$403,'💳 Transactions'!$C$4:$C$403,"Healthcare",'💳 Transactions'!$D$4:$D$403,B9,'💳 Transactions'!$B$4:$B$403,"Expense",'💳 Transactions'!$P$4:$P$403,C_Year) | F9: =IF(C9="","",C9-D9)
A11: TOTAL | B11: Healthcare Total | C11: =SUM(C4:C9) | D11: =SUM(D4:D9) | E11: =SUM(E4:E9)
A14: INSURANCE PREMIUMS & HEALTH DETAILS
A15: Policy | B15: Monthly Premium | C15: Annual Cost | D15: Deductible | E15: OOP Max | F15: HSA/FSA | G15: Notes
A16: Health Insurance | B16: 420 | C16: =IF(B16="","",B16*12) | E16: 3000 | F16: 9200
A17: Dental | B17: 30 | C17: =IF(B17="","",B17*12) | E17: 150 | F17: 1500
A18: Vision | B18: 20 | C18: =IF(B18="","",B18*12) | E18: 25 | F18: 500
A19: Life Insurance | B19: 55 | C19: =IF(B19="","",B19*12)
A20: Disability | B20: 40 | C20: =IF(B20="","",B20*12)
A21: Auto Insurance | B21: 130 | C21: =IF(B21="","",B21*12) | E21: 500
A22: Home / Renters | B22: 120 | C22: =IF(B22="","",B22*12) | E22: 1000
A24: TOTAL PREMIUMS | B24: =SUM(B16:B22) | C24: =SUM(C16:C22)

Sheet 🇺🇸 Tax Center
A1: 🇺🇸 U.S. Tax Center
A2: ESTIMATE ONLY — simplified federal + FICA estimate. Update brackets & deductions when tax rules change.
A4: INPUTS
A5: Filing Status
A6: Gross Income (YTD) | B6: =SUMIFS('💰 Income'!$E$4:$E$203,'💰 Income'!$P$4:$P$203,C_Year)
A7: 401(k)/403(b) pre-tax (YTD) | B7: =SUMIFS('💰 Income'!$J$4:$J$203,'💰 Income'!$P$4:$P$203,C_Year)
A8: HSA pre-tax (YTD) | B8: =SUMIFS('💰 Income'!$K$4:$K$203,'💰 Income'!$P$4:$P$203,C_Year)
A9: Federal Withheld (YTD) | B9: =SUMIFS('💰 Income'!$F$4:$F$203,'💰 Income'!$P$4:$P$203,C_Year)
A10: State/Local Withheld (YTD) | B10: =SUMIFS('💰 Income'!$G$4:$G$203,'💰 Income'!$P$4:$P$203,C_Year)
A11: FICA Withheld (YTD) | B11: =SUMIFS('💰 Income'!$H$4:$H$203,'💰 Income'!$P$4:$P$203,C_Year)+SUMIFS('💰 Income'!$I$4:$I$203,'💰 Income'!$P$4:$P$203,C_Year)
A12: Other Taxable Income (YTD)
A13: Dependents (count)
A14: Charitable Donations
A15: Mortgage Interest
A16: Property Taxes Paid
A17: State & Local Taxes (SALT) | B17: =B10
A20: STANDARD DEDUCTION | B20: =IF(B5="Married Filing Jointly",30000,IF(B5="Qualifying Surviving Spouse",30000,IF(B5="Head of Household",22500,15000)))
A21: ITEMIZED ESTIMATE | B21: =B14+B15+B16+MIN(10000,B17)
A22: DEDUCTION USED | B22: =MAX(B20,B21)
A25: ESTIMATED TAX POSITION
A26: Adjusted Gross Income (AGI) | B26: =B6-B7-B8
A27: Taxable Income | B27: =MAX(0,B26-$B$22)
A28: Estimated Federal Tax | B28: =IF($B$5="Married Filing Jointly",IF(B27<=23850,0+(B27-0)*0.1,IF(B27<=96950,2385.0+(B27-23850)*0.12,IF(B27<=206700,11157.0+(B27-96950)*0.22,IF(B27<=394600,35302.0+(B27-206700)*0.24,IF(B27<=501050,80398.0+(B27-394600)*0.32,IF(B27<=751600,114462.0+(B27-501050)*0.35,202154.5+(B27-751600)*0.37)))))),IF($B$5="Qualifying Surviving Spouse",IF(B27<=23850,0+(B27-0)*0.1,IF(B27<=96950,2385.0+(B27-23850)*0.12,IF(B27<=206700,11157.0+(B27-96950)*0.22,IF(B27<=394600,35302.0+(B27-206700)*0.24,IF(B27<=501050,80398.0+(B27-394600)*0.32,IF(B27<=751600,114462.0+(B27-501050)*0.35,202154.5+(B27-751600)*0.37)))))),IF($B$5="Head of Household",IF(B27<=17000,0+(B27-0)*0.1,IF(B27<=64850,1700.0+(B27-17000)*0.12,IF(B27<=103350,7442.0+(B27-64850)*0.22,IF(B27<=197300,15912.0+(B27-103350)*0.24,IF(B27<=250525,38460.0+(B27-197300)*0.32,IF(B27<=626350,55492.0+(B27-250525)*0.35,187030.75+(B27-626350)*0.37)))))),IF(B27<=11925,0+(B27-0)*0.1,IF(B27<=48475,1192.5+(B27-11925)*0.12,IF(B27<=103350,5578.5+(B27-48475)*0.22,IF(B27<=197300,17651.0+(B27-103350)*0.24,IF(B27<=250525,40199.0+(B27-197300)*0.32,IF(B27<=626350,57231.0+(B27-250525)*0.35,188769.75+(B27-626350)*0.37)))))))))
A29: Estimated FICA (employee) | B29: =IF(B6="","",MIN(B6,176100)*0.062+B6*0.0145)
A30: Total Estimated Tax | B30: =B28+B29
A31: Total Withheld (Fed + State + FICA) | B31: =B9+B10+B11
A32: EST. REFUND / (AMOUNT OWED) | B32: =B31-B30 | D32: Positive = refund. Negative = you may owe.
A34: ⚠️ This is a simplified ESTIMATE only. It ignores many credits, deductions, and phaseouts, and represents old tax rules. Update the brackets, standard deduction and formulas when tax law changes, or consult a professional.

Sheet 📊 Analytics
A1: 📊 Financial Analytics
A2: Automatic answers — where the money went, trends, needs vs wants, savings rate, debt, and per-person spend.
A4: YEAR-TO-DATE SUMMARY
A5: Total Income | B5: Total Spending | C5: Net Savings | D5: Savings Rate | E5: This Month Spending | F5: This Month Net | G5: Total Debt | H5: Avg Monthly Spend
A6: =SUMIFS('💰 Income'!$M$4:$M$203,'💰 Income'!$P$4:$P$203,C_Year) | B6: =SUMIFS('💳 Transactions'!$F$4:$F$403,'💳 Transactions'!$B$4:$B$403,"Expense",'💳 Transactions'!$P$4:$P$403,C_Year) | C6: =A6-B6 | D6: =IF(A6=0,"",C6/A6) | E6: =SUMIFS('💳 Transactions'!$F$4:$F$403,'💳 Transactions'!$B$4:$B$403,"Expense",'💳 Transactions'!$O$4:$O$403,C_Month,'💳 Transactions'!$P$4:$P$403,C_Year) | F6: =SUMIFS('💰 Income'!$M$4:$M$203,'💰 Income'!$O$4:$O$203,C_Month,'💰 Income'!$P$4:$P$203,C_Year)-E6 | G6: =SUM('💸 Debt Manager'!$D$8:$D$107) | H6: =IFERROR(AVERAGEIF($C$24:$C$35,">0"),0)
A8: SPENDING BY CATEGORY (YTD)
A9: Category | B9: Monthly Budget | C9: Actual YTD | D9: Actual This Month | E9: Variance | F9: % of Total | G9: Rank
A10: Housing | B10: ='📋 Budget'!$C$11 | C10: =SUMIFS('💳 Transactions'!$F$4:$F$403,'💳 Transactions'!$C$4:$C$403,A10,'💳 Transactions'!$B$4:$B$403,"Expense",'💳 Transactions'!$P$4:$P$403,C_Year) | D10: =SUMIFS('💳 Transactions'!$F$4:$F$403,'💳 Transactions'!$C$4:$C$403,A10,'💳 Transactions'!$B$4:$B$403,"Expense",'💳 Transactions'!$O$4:$O$403,C_Month,'💳 Transactions'!$P$4:$P$403,C_Year) | E10: =B10-C10 | F10: =IF($B$6=0,"",C10/$B$6) | G10: =IF(C10="","",RANK(C10,$C$10:$C$20,0))
A11: Transportation | B11: ='📋 Budget'!$C$19 | C11: =SUMIFS('💳 Transactions'!$F$4:$F$403,'💳 Transactions'!$C$4:$C$403,A11,'💳 Transactions'!$B$4:$B$403,"Expense",'💳 Transactions'!$P$4:$P$403,C_Year) | D11: =SUMIFS('💳 Transactions'!$F$4:$F$403,'💳 Transactions'!$C$4:$C$403,A11,'💳 Transactions'!$B$4:$B$403,"Expense",'💳 Transactions'!$O$4:$O$403,C_Month,'💳 Transactions'!$P$4:$P$403,C_Year) | E11: =B11-C11 | F11: =IF($B$6=0,"",C11/$B$6) | G11: =IF(C11="","",RANK(C11,$C$10:$C$20,0))
A12: Food | B12: ='📋 Budget'!$C$25 | C12: =SUMIFS('💳 Transactions'!$F$4:$F$403,'💳 Transactions'!$C$4:$C$403,A12,'💳 Transactions'!$B$4:$B$403,"Expense",'💳 Transactions'!$P$4:$P$403,C_Year) | D12: =SUMIFS('💳 Transactions'!$F$4:$F$403,'💳 Transactions'!$C$4:$C$403,A12,'💳 Transactions'!$B$4:$B$403,"Expense",'💳 Transactions'!$O$4:$O$403,C_Month,'💳 Transactions'!$P$4:$P$403,C_Year) | E12: =B12-C12 | F12: =IF($B$6=0,"",C12/$B$6) | G12: =IF(C12="","",RANK(C12,$C$10:$C$20,0))
A13: Family | B13: ='📋 Budget'!$C$34 | C13: =SUMIFS('💳 Transactions'!$F$4:$F$403,'💳 Transactions'!$C$4:$C$403,A13,'💳 Transactions'!$B$4:$B$403,"Expense",'💳 Transactions'!$P$4:$P$403,C_Year) | D13: =SUMIFS('💳 Transactions'!$F$4:$F$403,'💳 Transactions'!$C$4:$C$403,A13,'💳 Transactions'!$B$4:$B$403,"Expense",'💳 Transactions'!$O$4:$O$403,C_Month,'💳 Transactions'!$P$4:$P$403,C_Year) | E13: =B13-C13 | F13: =IF($B$6=0,"",C13/$B$6) | G13: =IF(C13="","",RANK(C13,$C$10:$C$20,0))
A14: Healthcare | B14: ='📋 Budget'!$C$41 | C14: =SUMIFS('💳 Transactions'!$F$4:$F$403,'💳 Transactions'!$C$4:$C$403,A14,'💳 Transactions'!$B$4:$B$403,"Expense",'💳 Transactions'!$P$4:$P$403,C_Year) | D14: =SUMIFS('💳 Transactions'!$F$4:$F$403,'💳 Transactions'!$C$4:$C$403,A14,'💳 Transactions'!$B$4:$B$403,"Expense",'💳 Transactions'!$O$4:$O$403,C_Month,'💳 Transactions'!$P$4:$P$403,C_Year) | E14: =B14-C14 | F14: =IF($B$6=0,"",C14/$B$6) | G14: =IF(C14="","",RANK(C14,$C$10:$C$20,0))
A15: Lifestyle | B15: ='📋 Budget'!$C$49 | C15: =SUMIFS('💳 Transactions'!$F$4:$F$403,'💳 Transactions'!$C$4:$C$403,A15,'💳 Transactions'!$B$4:$B$403,"Expense",'💳 Transactions'!$P$4:$P$403,C_Year) | D15: =SUMIFS('💳 Transactions'!$F$4:$F$403,'💳 Transactions'!$C$4:$C$403,A15,'💳 Transactions'!$B$4:$B$403,"Expense",'💳 Transactions'!$O$4:$O$403,C_Month,'💳 Transactions'!$P$4:$P$403,C_Year) | E15: =B15-C15 | F15: =IF($B$6=0,"",C15/$B$6) | G15: =IF(C15="","",RANK(C15,$C$10:$C$20,0))
A16: Financial | B16: ='📋 Budget'!$C$58 | C16: =SUMIFS('💳 Transactions'!$F$4:$F$403,'💳 Transactions'!$C$4:$C$403,A16,'💳 Transactions'!$B$4:$B$403,"Expense",'💳 Transactions'!$P$4:$P$403,C_Year) | D16: =SUMIFS('💳 Transactions'!$F$4:$F$403,'💳 Transactions'!$C$4:$C$403,A16,'💳 Transactions'!$B$4:$B$403,"Expense",'💳 Transactions'!$O$4:$O$403,C_Month,'💳 Transactions'!$P$4:$P$403,C_Year) | E16: =B16-C16 | F16: =IF($B$6=0,"",C16/$B$6) | G16: =IF(C16="","",RANK(C16,$C$10:$C$20,0))
A17: Giving | B17: ='📋 Budget'!$C$63 | C17: =SUMIFS('💳 Transactions'!$F$4:$F$403,'💳 Transactions'!$C$4:$C$403,A17,'💳 Transactions'!$B$4:$B$403,"Expense",'💳 Transactions'!$P$4:$P$403,C_Year) | D17: =SUMIFS('💳 Transactions'!$F$4:$F$403,'💳 Transactions'!$C$4:$C$403,A17,'💳 Transactions'!$B$4:$B$403,"Expense",'💳 Transactions'!$O$4:$O$403,C_Month,'💳 Transactions'!$P$4:$P$403,C_Year) | E17: =B17-C17 | F17: =IF($B$6=0,"",C17/$B$6) | G17: =IF(C17="","",RANK(C17,$C$10:$C$20,0))
A18: Pets | B18: ='📋 Budget'!$C$69 | C18: =SUMIFS('💳 Transactions'!$F$4:$F$403,'💳 Transactions'!$C$4:$C$403,A18,'💳 Transactions'!$B$4:$B$403,"Expense",'💳 Transactions'!$P$4:$P$403,C_Year) | D18: =SUMIFS('💳 Transactions'!$F$4:$F$403,'💳 Transactions'!$C$4:$C$403,A18,'💳 Transactions'!$B$4:$B$403,"Expense",'💳 Transactions'!$O$4:$O$403,C_Month,'💳 Transactions'!$P$4:$P$403,C_Year) | E18: =B18-C18 | F18: =IF($B$6=0,"",C18/$B$6) | G18: =IF(C18="","",RANK(C18,$C$10:$C$20,0))
A19: Travel | B19: ='📋 Budget'!$C$75 | C19: =SUMIFS('💳 Transactions'!$F$4:$F$403,'💳 Transactions'!$C$4:$C$403,A19,'💳 Transactions'!$B$4:$B$403,"Expense",'💳 Transactions'!$P$4:$P$403,C_Year) | D19: =SUMIFS('💳 Transactions'!$F$4:$F$403,'💳 Transactions'!$C$4:$C$403,A19,'💳 Transactions'!$B$4:$B$403,"Expense",'💳 Transactions'!$O$4:$O$403,C_Month,'💳 Transactions'!$P$4:$P$403,C_Year) | E19: =B19-C19 | F19: =IF($B$6=0,"",C19/$B$6) | G19: =IF(C19="","",RANK(C19,$C$10:$C$20,0))
A20: Miscellaneous | B20: ='📋 Budget'!$C$79 | C20: =SUMIFS('💳 Transactions'!$F$4:$F$403,'💳 Transactions'!$C$4:$C$403,A20,'💳 Transactions'!$B$4:$B$403,"Expense",'💳 Transactions'!$P$4:$P$403,C_Year) | D20: =SUMIFS('💳 Transactions'!$F$4:$F$403,'💳 Transactions'!$C$4:$C$403,A20,'💳 Transactions'!$B$4:$B$403,"Expense",'💳 Transactions'!$O$4:$O$403,C_Month,'💳 Transactions'!$P$4:$P$403,C_Year) | E20: =B20-C20 | F20: =IF($B$6=0,"",C20/$B$6) | G20: =IF(C20="","",RANK(C20,$C$10:$C$20,0))
A22: MONTHLY CASH FLOW TREND
A23: Month | B23: Income | C23: Spending | D23: Net
A24: January | B24: =SUMIFS('💰 Income'!$M$4:$M$203,'💰 Income'!$O$4:$O$203,1,'💰 Income'!$P$4:$P$203,C_Year) | C24: =SUMIFS('💳 Transactions'!$F$4:$F$403,'💳 Transactions'!$B$4:$B$403,"Expense",'💳 Transactions'!$O$4:$O$403,1,'💳 Transactions'!$P$4:$P$403,C_Year) | D24: =B24-C24
A25: February | B25: =SUMIFS('💰 Income'!$M$4:$M$203,'💰 Income'!$O$4:$O$203,2,'💰 Income'!$P$4:$P$203,C_Year) | C25: =SUMIFS('💳 Transactions'!$F$4:$F$403,'💳 Transactions'!$B$4:$B$403,"Expense",'💳 Transactions'!$O$4:$O$403,2,'💳 Transactions'!$P$4:$P$403,C_Year) | D25: =B25-C25
A26: March | B26: =SUMIFS('💰 Income'!$M$4:$M$203,'💰 Income'!$O$4:$O$203,3,'💰 Income'!$P$4:$P$203,C_Year) | C26: =SUMIFS('💳 Transactions'!$F$4:$F$403,'💳 Transactions'!$B$4:$B$403,"Expense",'💳 Transactions'!$O$4:$O$403,3,'💳 Transactions'!$P$4:$P$403,C_Year) | D26: =B26-C26
A27: April | B27: =SUMIFS('💰 Income'!$M$4:$M$203,'💰 Income'!$O$4:$O$203,4,'💰 Income'!$P$4:$P$203,C_Year) | C27: =SUMIFS('💳 Transactions'!$F$4:$F$403,'💳 Transactions'!$B$4:$B$403,"Expense",'💳 Transactions'!$O$4:$O$403,4,'💳 Transactions'!$P$4:$P$403,C_Year) | D27: =B27-C27
A28: May | B28: =SUMIFS('💰 Income'!$M$4:$M$203,'💰 Income'!$O$4:$O$203,5,'💰 Income'!$P$4:$P$203,C_Year) | C28: =SUMIFS('💳 Transactions'!$F$4:$F$403,'💳 Transactions'!$B$4:$B$403,"Expense",'💳 Transactions'!$O$4:$O$403,5,'💳 Transactions'!$P$4:$P$403,C_Year) | D28: =B28-C28
A29: June | B29: =SUMIFS('💰 Income'!$M$4:$M$203,'💰 Income'!$O$4:$O$203,6,'💰 Income'!$P$4:$P$203,C_Year) | C29: =SUMIFS('💳 Transactions'!$F$4:$F$403,'💳 Transactions'!$B$4:$B$403,"Expense",'💳 Transactions'!$O$4:$O$403,6,'💳 Transactions'!$P$4:$P$403,C_Year) | D29: =B29-C29
A30: July | B30: =SUMIFS('💰 Income'!$M$4:$M$203,'💰 Income'!$O$4:$O$203,7,'💰 Income'!$P$4:$P$203,C_Year) | C30: =SUMIFS('💳 Transactions'!$F$4:$F$403,'💳 Transactions'!$B$4:$B$403,"Expense",'💳 Transactions'!$O$4:$O$403,7,'💳 Transactions'!$P$4:$P$403,C_Year) | D30: =B30-C30
A31: August | B31: =SUMIFS('💰 Income'!$M$4:$M$203,'💰 Income'!$O$4:$O$203,8,'💰 Income'!$P$4:$P$203,C_Year) | C31: =SUMIFS('💳 Transactions'!$F$4:$F$403,'💳 Transactions'!$B$4:$B$403,"Expense",'💳 Transactions'!$O$4:$O$403,8,'💳 Transactions'!$P$4:$P$403,C_Year) | D31: =B31-C31
A32: September | B32: =SUMIFS('💰 Income'!$M$4:$M$203,'💰 Income'!$O$4:$O$203,9,'💰 Income'!$P$4:$P$203,C_Year) | C32: =SUMIFS('💳 Transactions'!$F$4:$F$403,'💳 Transactions'!$B$4:$B$403,"Expense",'💳 Transactions'!$O$4:$O$403,9,'💳 Transactions'!$P$4:$P$403,C_Year) | D32: =B32-C32
A33: October | B33: =SUMIFS('💰 Income'!$M$4:$M$203,'💰 Income'!$O$4:$O$203,10,'💰 Income'!$P$4:$P$203,C_Year) | C33: =SUMIFS('💳 Transactions'!$F$4:$F$403,'💳 Transactions'!$B$4:$B$403,"Expense",'💳 Transactions'!$O$4:$O$403,10,'💳 Transactions'!$P$4:$P$403,C_Year) | D33: =B33-C33
A34: November | B34: =SUMIFS('💰 Income'!$M$4:$M$203,'💰 Income'!$O$4:$O$203,11,'💰 Income'!$P$4:$P$203,C_Year) | C34: =SUMIFS('💳 Transactions'!$F$4:$F$403,'💳 Transactions'!$B$4:$B$403,"Expense",'💳 Transactions'!$O$4:$O$403,11,'💳 Transactions'!$P$4:$P$403,C_Year) | D34: =B34-C34
A35: December | B35: =SUMIFS('💰 Income'!$M$4:$M$203,'💰 Income'!$O$4:$O$203,12,'💰 Income'!$P$4:$P$203,C_Year) | C35: =SUMIFS('💳 Transactions'!$F$4:$F$403,'💳 Transactions'!$B$4:$B$403,"Expense",'💳 Transactions'!$O$4:$O$403,12,'💳 Transactions'!$P$4:$P$403,C_Year) | D35: =B35-C35
A38: NEEDS vs WANTS (YTD)
A39: Type | B39: Actual | C39: % of Total
A40: Essential | B40: =SUMIFS('💳 Transactions'!$F$4:$F$403,'💳 Transactions'!$B$4:$B$403,"Expense",'💳 Transactions'!$K$4:$K$403,"Essential",'💳 Transactions'!$P$4:$P$403,C_Year) | C40: =IF($B$6=0,"",B40/$B$6)
A41: Discretionary | B41: =SUMIFS('💳 Transactions'!$F$4:$F$403,'💳 Transactions'!$B$4:$B$403,"Expense",'💳 Transactions'!$K$4:$K$403,"Discretionary",'💳 Transactions'!$P$4:$P$403,C_Year) | C41: =IF($B$6=0,"",B41/$B$6)
A42: TOTAL | B42: =SUM(B40:B41) | C42: =IF($B$6=0,"",B42/$B$6)
A45: SPENDING BY FAMILY MEMBER (THIS MONTH)
A46: Family Member | B46: This Month | C46: YTD
A47: Parent 1 | B47: =SUMIFS('💳 Transactions'!$F$4:$F$403,'💳 Transactions'!$B$4:$B$403,"Expense",'💳 Transactions'!$I$4:$I$403,A47,'💳 Transactions'!$O$4:$O$403,C_Month,'💳 Transactions'!$P$4:$P$403,C_Year) | C47: =SUMIFS('💳 Transactions'!$F$4:$F$403,'💳 Transactions'!$B$4:$B$403,"Expense",'💳 Transactions'!$I$4:$I$403,A47,'💳 Transactions'!$P$4:$P$403,C_Year)
A48: Parent 2 | B48: =SUMIFS('💳 Transactions'!$F$4:$F$403,'💳 Transactions'!$B$4:$B$403,"Expense",'💳 Transactions'!$I$4:$I$403,A48,'💳 Transactions'!$O$4:$O$403,C_Month,'💳 Transactions'!$P$4:$P$403,C_Year) | C48: =SUMIFS('💳 Transactions'!$F$4:$F$403,'💳 Transactions'!$B$4:$B$403,"Expense",'💳 Transactions'!$I$4:$I$403,A48,'💳 Transactions'!$P$4:$P$403,C_Year)
A49: Child 1 | B49: =SUMIFS('💳 Transactions'!$F$4:$F$403,'💳 Transactions'!$B$4:$B$403,"Expense",'💳 Transactions'!$I$4:$I$403,A49,'💳 Transactions'!$O$4:$O$403,C_Month,'💳 Transactions'!$P$4:$P$403,C_Year) | C49: =SUMIFS('💳 Transactions'!$F$4:$F$403,'💳 Transactions'!$B$4:$B$403,"Expense",'💳 Transactions'!$I$4:$I$403,A49,'💳 Transactions'!$P$4:$P$403,C_Year)
A50: Child 2 | B50: =SUMIFS('💳 Transactions'!$F$4:$F$403,'💳 Transactions'!$B$4:$B$403,"Expense",'💳 Transactions'!$I$4:$I$403,A50,'💳 Transactions'!$O$4:$O$403,C_Month,'💳 Transactions'!$P$4:$P$403,C_Year) | C50: =SUMIFS('💳 Transactions'!$F$4:$F$403,'💳 Transactions'!$B$4:$B$403,"Expense",'💳 Transactions'!$I$4:$I$403,A50,'💳 Transactions'!$P$4:$P$403,C_Year)
A51: Household | B51: =SUMIFS('💳 Transactions'!$F$4:$F$403,'💳 Transactions'!$B$4:$B$403,"Expense",'💳 Transactions'!$I$4:$I$403,A51,'💳 Transactions'!$O$4:$O$403,C_Month,'💳 Transactions'!$P$4:$P$403,C_Year) | C51: =SUMIFS('💳 Transactions'!$F$4:$F$403,'💳 Transactions'!$B$4:$B$403,"Expense",'💳 Transactions'!$I$4:$I$403,A51,'💳 Transactions'!$P$4:$P$403,C_Year)
A52: Other | B52: =SUMIFS('💳 Transactions'!$F$4:$F$403,'💳 Transactions'!$B$4:$B$403,"Expense",'💳 Transactions'!$I$4:$I$403,A52,'💳 Transactions'!$O$4:$O$403,C_Month,'💳 Transactions'!$P$4:$P$403,C_Year) | C52: =SUMIFS('💳 Transactions'!$F$4:$F$403,'💳 Transactions'!$B$4:$B$403,"Expense",'💳 Transactions'!$I$4:$I$403,A52,'💳 Transactions'!$P$4:$P$403,C_Year)
A55: QUICK ANSWERS (YTD)
A56: Subscriptions | B56: =SUMIFS('💳 Transactions'!$F$4:$F$403,'💳 Transactions'!$D$4:$D$403,"Subscriptions",'💳 Transactions'!$P$4:$P$403,C_Year)
A57: Restaurants | B57: =SUMIFS('💳 Transactions'!$F$4:$F$403,'💳 Transactions'!$D$4:$D$403,"Restaurants",'💳 Transactions'!$P$4:$P$403,C_Year)
A58: Groceries | B58: =SUMIFS('💳 Transactions'!$F$4:$F$403,'💳 Transactions'!$D$4:$D$403,"Groceries",'💳 Transactions'!$P$4:$P$403,C_Year)
A59: Gas / Fuel | B59: =SUMIFS('💳 Transactions'!$F$4:$F$403,'💳 Transactions'!$D$4:$D$403,"Gas",'💳 Transactions'!$P$4:$P$403,C_Year)
A60: Top Category | B60: =INDEX(A10:A20,MATCH(MAX(C10:C20),C10:C20,0))

Sheet 📅 Calendar
A1: 📅 Financial Calendar
A2: Everything due on each day of the C_Year / C_Month — bills, paydays, debt payments and subscriptions.
A3: Day | B3: Bills Due | C3: Paydays / Income | D3: Debt Minimums | E3: Subscriptions | F3: Notes
A4: 1 | B4: =SUMIFS('🧾 Bills & Subs'!$B$4:$B$303,'🧾 Bills & Subs'!$K$4:$K$303,C_Month,'🧾 Bills & Subs'!$L$4:$L$303,C_Year,'🧾 Bills & Subs'!$M$4:$M$303,A4) | C4: =SUMIFS('💰 Income'!$M$4:$M$203,'💰 Income'!$O$4:$O$203,C_Month,'💰 Income'!$P$4:$P$203,C_Year,'💰 Income'!$Q$4:$Q$203,A4) | D4: =SUMIFS('💸 Debt Manager'!$G$8:$G$107,'💸 Debt Manager'!$J$8:$J$107,C_Month,'💸 Debt Manager'!$K$8:$K$107,C_Year,'💸 Debt Manager'!$L$8:$L$107,A4) | E4: =SUMIFS('💳 Transactions'!$F$4:$F$403,'💳 Transactions'!$D$4:$D$403,"Subscriptions",'💳 Transactions'!$O$4:$O$403,C_Month,'💳 Transactions'!$P$4:$P$403,C_Year,'💳 Transactions'!$Q$4:$Q$403,A4)
A5: 2 | B5: =SUMIFS('🧾 Bills & Subs'!$B$4:$B$303,'🧾 Bills & Subs'!$K$4:$K$303,C_Month,'🧾 Bills & Subs'!$L$4:$L$303,C_Year,'🧾 Bills & Subs'!$M$4:$M$303,A5) | C5: =SUMIFS('💰 Income'!$M$4:$M$203,'💰 Income'!$O$4:$O$203,C_Month,'💰 Income'!$P$4:$P$203,C_Year,'💰 Income'!$Q$4:$Q$203,A5) | D5: =SUMIFS('💸 Debt Manager'!$G$8:$G$107,'💸 Debt Manager'!$J$8:$J$107,C_Month,'💸 Debt Manager'!$K$8:$K$107,C_Year,'💸 Debt Manager'!$L$8:$L$107,A5) | E5: =SUMIFS('💳 Transactions'!$F$4:$F$403,'💳 Transactions'!$D$4:$D$403,"Subscriptions",'💳 Transactions'!$O$4:$O$403,C_Month,'💳 Transactions'!$P$4:$P$403,C_Year,'💳 Transactions'!$Q$4:$Q$403,A5)
A6: 3 | B6: =SUMIFS('🧾 Bills & Subs'!$B$4:$B$303,'🧾 Bills & Subs'!$K$4:$K$303,C_Month,'🧾 Bills & Subs'!$L$4:$L$303,C_Year,'🧾 Bills & Subs'!$M$4:$M$303,A6) | C6: =SUMIFS('💰 Income'!$M$4:$M$203,'💰 Income'!$O$4:$O$203,C_Month,'💰 Income'!$P$4:$P$203,C_Year,'💰 Income'!$Q$4:$Q$203,A6) | D6: =SUMIFS('💸 Debt Manager'!$G$8:$G$107,'💸 Debt Manager'!$J$8:$J$107,C_Month,'💸 Debt Manager'!$K$8:$K$107,C_Year,'💸 Debt Manager'!$L$8:$L$107,A6) | E6: =SUMIFS('💳 Transactions'!$F$4:$F$403,'💳 Transactions'!$D$4:$D$403,"Subscriptions",'💳 Transactions'!$O$4:$O$403,C_Month,'💳 Transactions'!$P$4:$P$403,C_Year,'💳 Transactions'!$Q$4:$Q$403,A6)
A7: 4 | B7: =SUMIFS('🧾 Bills & Subs'!$B$4:$B$303,'🧾 Bills & Subs'!$K$4:$K$303,C_Month,'🧾 Bills & Subs'!$L$4:$L$303,C_Year,'🧾 Bills & Subs'!$M$4:$M$303,A7) | C7: =SUMIFS('💰 Income'!$M$4:$M$203,'💰 Income'!$O$4:$O$203,C_Month,'💰 Income'!$P$4:$P$203,C_Year,'💰 Income'!$Q$4:$Q$203,A7) | D7: =SUMIFS('💸 Debt Manager'!$G$8:$G$107,'💸 Debt Manager'!$J$8:$J$107,C_Month,'💸 Debt Manager'!$K$8:$K$107,C_Year,'💸 Debt Manager'!$L$8:$L$107,A7) | E7: =SUMIFS('💳 Transactions'!$F$4:$F$403,'💳 Transactions'!$D$4:$D$403,"Subscriptions",'💳 Transactions'!$O$4:$O$403,C_Month,'💳 Transactions'!$P$4:$P$403,C_Year,'💳 Transactions'!$Q$4:$Q$403,A7)
A8: 5 | B8: =SUMIFS('🧾 Bills & Subs'!$B$4:$B$303,'🧾 Bills & Subs'!$K$4:$K$303,C_Month,'🧾 Bills & Subs'!$L$4:$L$303,C_Year,'🧾 Bills & Subs'!$M$4:$M$303,A8) | C8: =SUMIFS('💰 Income'!$M$4:$M$203,'💰 Income'!$O$4:$O$203,C_Month,'💰 Income'!$P$4:$P$203,C_Year,'💰 Income'!$Q$4:$Q$203,A8) | D8: =SUMIFS('💸 Debt Manager'!$G$8:$G$107,'💸 Debt Manager'!$J$8:$J$107,C_Month,'💸 Debt Manager'!$K$8:$K$107,C_Year,'💸 Debt Manager'!$L$8:$L$107,A8) | E8: =SUMIFS('💳 Transactions'!$F$4:$F$403,'💳 Transactions'!$D$4:$D$403,"Subscriptions",'💳 Transactions'!$O$4:$O$403,C_Month,'💳 Transactions'!$P$4:$P$403,C_Year,'💳 Transactions'!$Q$4:$Q$403,A8)
A9: 6 | B9: =SUMIFS('🧾 Bills & Subs'!$B$4:$B$303,'🧾 Bills & Subs'!$K$4:$K$303,C_Month,'🧾 Bills & Subs'!$L$4:$L$303,C_Year,'🧾 Bills & Subs'!$M$4:$M$303,A9) | C9: =SUMIFS('💰 Income'!$M$4:$M$203,'💰 Income'!$O$4:$O$203,C_Month,'💰 Income'!$P$4:$P$203,C_Year,'💰 Income'!$Q$4:$Q$203,A9) | D9: =SUMIFS('💸 Debt Manager'!$G$8:$G$107,'💸 Debt Manager'!$J$8:$J$107,C_Month,'💸 Debt Manager'!$K$8:$K$107,C_Year,'💸 Debt Manager'!$L$8:$L$107,A9) | E9: =SUMIFS('💳 Transactions'!$F$4:$F$403,'💳 Transactions'!$D$4:$D$403,"Subscriptions",'💳 Transactions'!$O$4:$O$403,C_Month,'💳 Transactions'!$P$4:$P$403,C_Year,'💳 Transactions'!$Q$4:$Q$403,A9)
A10: 7 | B10: =SUMIFS('🧾 Bills & Subs'!$B$4:$B$303,'🧾 Bills & Subs'!$K$4:$K$303,C_Month,'🧾 Bills & Subs'!$L$4:$L$303,C_Year,'🧾 Bills & Subs'!$M$4:$M$303,A10) | C10: =SUMIFS('💰 Income'!$M$4:$M$203,'💰 Income'!$O$4:$O$203,C_Month,'💰 Income'!$P$4:$P$203,C_Year,'💰 Income'!$Q$4:$Q$203,A10) | D10: =SUMIFS('💸 Debt Manager'!$G$8:$G$107,'💸 Debt Manager'!$J$8:$J$107,C_Month,'💸 Debt Manager'!$K$8:$K$107,C_Year,'💸 Debt Manager'!$L$8:$L$107,A10) | E10: =SUMIFS('💳 Transactions'!$F$4:$F$403,'💳 Transactions'!$D$4:$D$403,"Subscriptions",'💳 Transactions'!$O$4:$O$403,C_Month,'💳 Transactions'!$P$4:$P$403,C_Year,'💳 Transactions'!$Q$4:$Q$403,A10)
A11: 8 | B11: =SUMIFS('🧾 Bills & Subs'!$B$4:$B$303,'🧾 Bills & Subs'!$K$4:$K$303,C_Month,'🧾 Bills & Subs'!$L$4:$L$303,C_Year,'🧾 Bills & Subs'!$M$4:$M$303,A11) | C11: =SUMIFS('💰 Income'!$M$4:$M$203,'💰 Income'!$O$4:$O$203,C_Month,'💰 Income'!$P$4:$P$203,C_Year,'💰 Income'!$Q$4:$Q$203,A11) | D11: =SUMIFS('💸 Debt Manager'!$G$8:$G$107,'💸 Debt Manager'!$J$8:$J$107,C_Month,'💸 Debt Manager'!$K$8:$K$107,C_Year,'💸 Debt Manager'!$L$8:$L$107,A11) | E11: =SUMIFS('💳 Transactions'!$F$4:$F$403,'💳 Transactions'!$D$4:$D$403,"Subscriptions",'💳 Transactions'!$O$4:$O$403,C_Month,'💳 Transactions'!$P$4:$P$403,C_Year,'💳 Transactions'!$Q$4:$Q$403,A11)
A12: 9 | B12: =SUMIFS('🧾 Bills & Subs'!$B$4:$B$303,'🧾 Bills & Subs'!$K$4:$K$303,C_Month,'🧾 Bills & Subs'!$L$4:$L$303,C_Year,'🧾 Bills & Subs'!$M$4:$M$303,A12) | C12: =SUMIFS('💰 Income'!$M$4:$M$203,'💰 Income'!$O$4:$O$203,C_Month,'💰 Income'!$P$4:$P$203,C_Year,'💰 Income'!$Q$4:$Q$203,A12) | D12: =SUMIFS('💸 Debt Manager'!$G$8:$G$107,'💸 Debt Manager'!$J$8:$J$107,C_Month,'💸 Debt Manager'!$K$8:$K$107,C_Year,'💸 Debt Manager'!$L$8:$L$107,A12) | E12: =SUMIFS('💳 Transactions'!$F$4:$F$403,'💳 Transactions'!$D$4:$D$403,"Subscriptions",'💳 Transactions'!$O$4:$O$403,C_Month,'💳 Transactions'!$P$4:$P$403,C_Year,'💳 Transactions'!$Q$4:$Q$403,A12)
A13: 10 | B13: =SUMIFS('🧾 Bills & Subs'!$B$4:$B$303,'🧾 Bills & Subs'!$K$4:$K$303,C_Month,'🧾 Bills & Subs'!$L$4:$L$303,C_Year,'🧾 Bills & Subs'!$M$4:$M$303,A13) | C13: =SUMIFS('💰 Income'!$M$4:$M$203,'💰 Income'!$O$4:$O$203,C_Month,'💰 Income'!$P$4:$P$203,C_Year,'💰 Income'!$Q$4:$Q$203,A13) | D13: =SUMIFS('💸 Debt Manager'!$G$8:$G$107,'💸 Debt Manager'!$J$8:$J$107,C_Month,'💸 Debt Manager'!$K$8:$K$107,C_Year,'💸 Debt Manager'!$L$8:$L$107,A13) | E13: =SUMIFS('💳 Transactions'!$F$4:$F$403,'💳 Transactions'!$D$4:$D$403,"Subscriptions",'💳 Transactions'!$O$4:$O$403,C_Month,'💳 Transactions'!$P$4:$P$403,C_Year,'💳 Transactions'!$Q$4:$Q$403,A13)
A14: 11 | B14: =SUMIFS('🧾 Bills & Subs'!$B$4:$B$303,'🧾 Bills & Subs'!$K$4:$K$303,C_Month,'🧾 Bills & Subs'!$L$4:$L$303,C_Year,'🧾 Bills & Subs'!$M$4:$M$303,A14) | C14: =SUMIFS('💰 Income'!$M$4:$M$203,'💰 Income'!$O$4:$O$203,C_Month,'💰 Income'!$P$4:$P$203,C_Year,'💰 Income'!$Q$4:$Q$203,A14) | D14: =SUMIFS('💸 Debt Manager'!$G$8:$G$107,'💸 Debt Manager'!$J$8:$J$107,C_Month,'💸 Debt Manager'!$K$8:$K$107,C_Year,'💸 Debt Manager'!$L$8:$L$107,A14) | E14: =SUMIFS('💳 Transactions'!$F$4:$F$403,'💳 Transactions'!$D$4:$D$403,"Subscriptions",'💳 Transactions'!$O$4:$O$403,C_Month,'💳 Transactions'!$P$4:$P$403,C_Year,'💳 Transactions'!$Q$4:$Q$403,A14)
A15: 12 | B15: =SUMIFS('🧾 Bills & Subs'!$B$4:$B$303,'🧾 Bills & Subs'!$K$4:$K$303,C_Month,'🧾 Bills & Subs'!$L$4:$L$303,C_Year,'🧾 Bills & Subs'!$M$4:$M$303,A15) | C15: =SUMIFS('💰 Income'!$M$4:$M$203,'💰 Income'!$O$4:$O$203,C_Month,'💰 Income'!$P$4:$P$203,C_Year,'💰 Income'!$Q$4:$Q$203,A15) | D15: =SUMIFS('💸 Debt Manager'!$G$8:$G$107,'💸 Debt Manager'!$J$8:$J$107,C_Month,'💸 Debt Manager'!$K$8:$K$107,C_Year,'💸 Debt Manager'!$L$8:$L$107,A15) | E15: =SUMIFS('💳 Transactions'!$F$4:$F$403,'💳 Transactions'!$D$4:$D$403,"Subscriptions",'💳 Transactions'!$O$4:$O$403,C_Month,'💳 Transactions'!$P$4:$P$403,C_Year,'💳 Transactions'!$Q$4:$Q$403,A15)
... A34: 31 | B34: =SUMIFS('🧾 Bills & Subs'!$B$4:$B$303,'🧾 Bills & Subs'!$K$4:$K$303,C_Month,'🧾 Bills & Subs'!$L$4:$L$303,C_Year,'🧾 Bills & Subs'!$M$4:$M$303,A34) | C34: =SUMIFS('💰 Income'!$M$4:$M$203,'💰 Income'!$O$4:$O$203,C_Month,'💰 Income'!$P$4:$P$203,C_Year,'💰 Income'!$Q$4:$Q$203,A34) | D34: =SUMIFS('💸 Debt Manager'!$G$8:$G$107,'💸 Debt Manager'!$J$8:$J$107,C_Month,'💸 Debt Manager'!$K$8:$K$107,C_Year,'💸 Debt Manager'!$L$8:$L$107,A34) | E34: =SUMIFS('💳 Transactions'!$F$4:$F$403,'💳 Transactions'!$D$4:$D$403,"Subscriptions",'💳 Transactions'!$O$4:$O$403,C_Month,'💳 Transactions'!$P$4:$P$403,C_Year,'💳 Transactions'!$Q$4:$Q$403,A34)

Sheet ⚙️ Settings
A1: ⚙️ Settings / Setup
A2: Set once — every dropdown, formula and chart reads from here. Only the cream cells are editable.
A4: REPORTING CONTROL
A5: Current Date | B5: =TODAY()
A6: Current Month | B6: =MONTH(B5)
A7: Current Year | B7: =YEAR(B5)
A8: Tip: the Dashboard uses 'Current Month' & 'Current Year' to pick the
A9: reporting period automatically. Change the date to re-baseline it.
A12: Family Members | C12: Account Master | E12: Categories | G12: Subcategories | I12: Income Sources | K12: Pay Frequencies | M12: Account Types | O12: Payment Methods | Q12: Transaction Types | S12: Bill Frequencies | U12: Yes / No | W12: Essential / Discretionary | Y12: Months | AA12: Filing Status | AC12: Debt Types | AE12: Goal Types | AG12: Investment Types
A13: Parent 1 | C13: Checking | E13: Housing | G13: Mortgage/Rent | I13: Salary | K13: Weekly | M13: Checking | O13: Checking | Q13: Expense | S13: Weekly | U13: Yes | W13: Essential | Y13: January | AA13: Single | AC13: Credit Card | AE13: Emergency Fund | AG13: 401(k)
A14: Parent 2 | C14: Savings | E14: Transportation | G14: Property Tax | I14: Hourly | K14: Biweekly | M14: Savings | O14: Savings | Q14: Income | S14: Biweekly | U14: No | W14: Discretionary | Y14: February | AA14: Married Filing Jointly | AC14: Student Loan | AE14: Vacation | AG14: 403(b)
A15: Child 1 | C15: HYSA | E15: Food | G15: HOA | I15: Bonus | K15: Twice Monthly | M15: HYSA | O15: Credit Card | Q15: Transfer | S15: Twice Monthly | Y15: March | AA15: Married Filing Separately | AC15: Auto Loan | AE15: Christmas | AG15: IRA
A16: Child 2 | C16: Cash | E16: Family | G16: Home Insurance | I16: Overtime | K16: Monthly | M16: Cash | O16: Cash | S16: Monthly | Y16: April | AA16: Head of Household | AC16: Personal Loan | AE16: Birthdays | AG16: Roth IRA
A17: Household | C17: Credit Card | E17: Healthcare | G17: Repairs/Maintenance | I17: Commission | K17: Irregular | M17: Credit Card | O17: Autopay | S17: Quarterly | Y17: May | AA17: Qualifying Surviving Spouse | AC17: Mortgage | AE17: Car Repairs | AG17: Brokerage
A18: Other | C18: 401(k) | E18: Lifestyle | G18: Utilities | I18: Freelance/Side Hustle | M18: 401(k) | O18: Debit Card | S18: Annually | Y18: June | AC18: Other | AE18: Home Repairs | AG18: HSA
C19: 403(b) | E19: Financial | G19: Other Housing | I19: Child Support | M19: 403(b) | O19: Other | S19: One-time | Y19: July | AE19: Insurance | AG19: 529
C20: IRA | E20: Giving | G20: Car Payments | I20: Social Security | M20: IRA | Y20: August | AE20: Property Taxes | AG20: CD
C21: Roth IRA | E21: Pets | G21: Gas | I21: Retirement | M21: Roth IRA | Y21: September | AE21: College | AG21: HYSA
C22: Brokerage | E22: Travel | G22: Auto Insurance | I22: Government Benefits | M22: Brokerage | Y22: October | AE22: Major Purchase | AG22: Cash
C23: 529 | E23: Miscellaneous | G23: Maintenance/Repairs | I23: Other | M23: 529 | Y23: November | AE23: Custom | AG23: Emergency Fund
C24: HSA | G24: Registration | M24: HSA | Y24: December
C25: FSA | G25: Parking/Tolls | M25: FSA
C26: CD | G26: Public Transportation | M26: CD
C27: Other Investment | G27: Groceries | M27: Other Investment
C28: Other | G28: Restaurants | M28: Other
G29: Takeout/Delivery
G30: Coffee
G31: Other Food
G32: Childcare
G33: School
G34: Activities/Sports
G35: Clothing
G36: Allowances
G37: Baby Expenses
G38: College Savings
G39: Other Family
G40: Health Insurance
... G77: Other Misc

Sheet 📖 Instructions
A1: 📖 Instructions & Help
A2: How to use the Novality Premium Family Budget. Green cells are formulas; cream cells are where you type.
A4: HOW IT WORKS | B4: You only enter information ONCE. The Transaction Ledger, Income and Bills tabs feed every else automatically.
A6: 1. ⚙️ Settings | B6: List your Family Members, Accounts, Categories, Income Sources, Pay Frequencies, Goal Types etc. here once. These fill every dropdown.
A7: 2. 💳 Transactions | B7: This is the master ledger. Pick the Type, Category, Subcategory, Account, Family Member from dropdowns. Month / Year / Day are automatic. Enter each expense/income once.
A8: 3. 💰 Income | B8: Enter each paycheck with gross, federal/state/FICA withholding, 401k/HSA. Net take-home is automatic. Date drives Month/Year/Day.
A9: 4. 🧾 Bills & Subs | B9: List recurring bills with due date & frequency. Annual cost is computed. The 📅 Calendar shows what is due each day.
A10: 5. 🏦 Accounts | B10: Enter every account's current balance. Available credit and Month tracking are automatic.
A11: 6. 💸 Debt Manager | B11: Enter balances, APR, min & extra payments. Snowball & avalanche order, payoff date and interest saved are automatic.
A12: 7. 🎯 Goals & Funds | B12: Set a target, current saved and monthly contribution. % complete, per-paycheck amount and projected completion are automatic.
A13: 8. 📋 Budget | B13: Set a monthly limit per subcategory. Actuals pull from the ledger automatically; over-budget turns red.
A15: ONLY EDIT THE CREAM CELLS | B15: Formula cells (green) are locked and protected. To change formulas or add more rows: Review → Unprotect Sheet → password: premium.
A16: 🧪 Sample data | B16: Sample data is pre-loaded so you can see everything working. Delete it and add your own, or keep adding rows in the cream areas.
A17: 📊 Analytics & 🏠 Dashboard | B17: All charts and KPI cards read the ledgers automatically. No manual totals needed.
... A21: 🔐 Protection settings | B21: Password: premium · Select unlocked cells = ON · Filtering/Sorting = ON
