Workbook
Name BusinessName: '⚙️ Setup'!$C$6
Name CalMonth: '⚙️ Setup'!$C$18
Name CalYear: '⚙️ Setup'!$C$19
Name ClientsList: OFFSET('👥 Clients'!$C$8,0,0,MAX(1,COUNTA('👥 Clients'!$C$8:$C$47)),1)
Name Currency: '⚙️ Setup'!$C$10
Name DefaultMargin: '⚙️ Setup'!$C$12
Name DepositPct: '⚙️ Setup'!$C$13
Name DueSoonDays: '⚙️ Setup'!$C$14
Name EventList: OFFSET('📅 Events'!$C$8,0,0,MAX(1,COUNTA('📅 Events'!$C$8:$C$47)),1)
Name EventStatuses: '⚙️ Setup'!$C$47:$C$52
Name EventTypes: OFFSET('⚙️ Setup'!$B$23,0,0,MAX(1,COUNTA('⚙️ Setup'!$B$23:$B$42)),1)
Name ExpenseCategories: OFFSET('⚙️ Setup'!$C$23,0,0,MAX(1,COUNTA('⚙️ Setup'!$C$23:$C$42)),1)
Name IngredientCategories: OFFSET('⚙️ Setup'!$G$23,0,0,MAX(1,COUNTA('⚙️ Setup'!$G$23:$G$42)),1)
Name MenuCategories: OFFSET('⚙️ Setup'!$F$23,0,0,MAX(1,COUNTA('⚙️ Setup'!$F$23:$F$42)),1)
Name MenuItems: OFFSET('🍽️ Menu Costing'!$C$8,0,0,MAX(1,COUNTA('🍽️ Menu Costing'!$C$8:$C$37)),1)
Name PaymentMethods: OFFSET('⚙️ Setup'!$D$23,0,0,MAX(1,COUNTA('⚙️ Setup'!$D$23:$D$42)),1)
Name PaymentStatuses: '⚙️ Setup'!$D$47:$D$49
Name ReportYear: '⚙️ Setup'!$C$15
Name StaffRoles: OFFSET('⚙️ Setup'!$E$23,0,0,MAX(1,COUNTA('⚙️ Setup'!$E$23:$E$42)),1)
Name SuppliersList: OFFSET('🚚 Suppliers'!$C$8,0,0,MAX(1,COUNTA('🚚 Suppliers'!$C$8:$C$37)),1)
Name TaxRate: '⚙️ Setup'!$C$11
Name Tick: '⚙️ Setup'!$E$47:$E$48

Sheet _Data
A1: Ultimate Catering Business Spreadsheet - calculation engine (hidden). Every number on the Dashboard and the reports is computed here. | H1: Month | I1: Cash in | J1: Cash out | K1: Net | L1: Events | N1: Expense category | O1: Spend | AA1: Upcoming date | AB1: Upcoming event | AC1: Status | AE1: KPI | AF1: Value
H2: Jan | I2: =SUMPRODUCT(--(('💰 Payments'!$E$8:$E$67<>"")*(MONTH('💰 Payments'!$E$8:$E$67)=1)),'💰 Payments'!$J$8:$J$67) -> 0 | J2: =SUMPRODUCT(--(('💸 Expenses'!$C$8:$C$67<>"")*(MONTH('💸 Expenses'!$C$8:$C$67)=1)),'💸 Expenses'!$G$8:$G$67) -> 0 | K2: =I2-J2 -> 0 | L2: =SUMPRODUCT(('📅 Events'!$E$8:$E$47<>"")*(MONTH('📅 Events'!$E$8:$E$47)=1)*1) -> 0 | N2: Ingredients | O2: =SUMIF('💸 Expenses'!$E$8:$E$67,$N2,'💸 Expenses'!$G$8:$G$67) -> 0 | AA2: =IFERROR(AGGREGATE(15,6,'📅 Events'!$E$8:$E$47/('📅 Events'!$E$8:$E$47>=TODAY())*('📅 Events'!$Q$8:$Q$47<>"❌ Cancelled")*('📅 Events'!$Q$8:$Q$47<>"🎉 Completed"),1),"") | AB2: =IF($AA2="","",INDEX('📅 Events'!$D$8:$D$47,MATCH($AA2,'📅 Events'!$E$8:$E$47,0))&" - "&INDEX('📅 Events'!$F$8:$F$47,MATCH($AA2,'📅 Events'!$E$8:$E$47,0))) | AC2: =IF($AA2="","",INDEX('📅 Events'!$Q$8:$Q$47,MATCH($AA2,'📅 Events'!$E$8:$E$47,0))) | AE2: Cash received (deposits + payments) | AF2: =SUM('💰 Payments'!$J$8:$J$67) -> 0
H3: Feb | I3: =SUMPRODUCT(--(('💰 Payments'!$E$8:$E$67<>"")*(MONTH('💰 Payments'!$E$8:$E$67)=2)),'💰 Payments'!$J$8:$J$67) -> 0 | J3: =SUMPRODUCT(--(('💸 Expenses'!$C$8:$C$67<>"")*(MONTH('💸 Expenses'!$C$8:$C$67)=2)),'💸 Expenses'!$G$8:$G$67) -> 0 | K3: =I3-J3 -> 0 | L3: =SUMPRODUCT(('📅 Events'!$E$8:$E$47<>"")*(MONTH('📅 Events'!$E$8:$E$47)=2)*1) -> 0 | N3: Packaging | O3: =SUMIF('💸 Expenses'!$E$8:$E$67,$N3,'💸 Expenses'!$G$8:$G$67) -> 0 | AA3: =IFERROR(AGGREGATE(15,6,'📅 Events'!$E$8:$E$47/('📅 Events'!$E$8:$E$47>=TODAY())*('📅 Events'!$Q$8:$Q$47<>"❌ Cancelled")*('📅 Events'!$Q$8:$Q$47<>"🎉 Completed"),2),"") | AB3: =IF($AA3="","",INDEX('📅 Events'!$D$8:$D$47,MATCH($AA3,'📅 Events'!$E$8:$E$47,0))&" - "&INDEX('📅 Events'!$F$8:$F$47,MATCH($AA3,'📅 Events'!$E$8:$E$47,0))) | AC3: =IF($AA3="","",INDEX('📅 Events'!$Q$8:$Q$47,MATCH($AA3,'📅 Events'!$E$8:$E$47,0))) | AE3: Total expenses | AF3: =SUM('💸 Expenses'!$G$8:$G$67) -> 0
H4: Mar | I4: =SUMPRODUCT(--(('💰 Payments'!$E$8:$E$67<>"")*(MONTH('💰 Payments'!$E$8:$E$67)=3)),'💰 Payments'!$J$8:$J$67) -> 0 | J4: =SUMPRODUCT(--(('💸 Expenses'!$C$8:$C$67<>"")*(MONTH('💸 Expenses'!$C$8:$C$67)=3)),'💸 Expenses'!$G$8:$G$67) -> 0 | K4: =I4-J4 -> 0 | L4: =SUMPRODUCT(('📅 Events'!$E$8:$E$47<>"")*(MONTH('📅 Events'!$E$8:$E$47)=3)*1) -> 0 | N4: Staff / Labor | O4: =SUMIF('💸 Expenses'!$E$8:$E$67,$N4,'💸 Expenses'!$G$8:$G$67) -> 0 | AA4: =IFERROR(AGGREGATE(15,6,'📅 Events'!$E$8:$E$47/('📅 Events'!$E$8:$E$47>=TODAY())*('📅 Events'!$Q$8:$Q$47<>"❌ Cancelled")*('📅 Events'!$Q$8:$Q$47<>"🎉 Completed"),3),"") | AB4: =IF($AA4="","",INDEX('📅 Events'!$D$8:$D$47,MATCH($AA4,'📅 Events'!$E$8:$E$47,0))&" - "&INDEX('📅 Events'!$F$8:$F$47,MATCH($AA4,'📅 Events'!$E$8:$E$47,0))) | AC4: =IF($AA4="","",INDEX('📅 Events'!$Q$8:$Q$47,MATCH($AA4,'📅 Events'!$E$8:$E$47,0))) | AE4: Net profit | AF4: =$AF$2-$AF$3 -> 0
H5: Apr | I5: =SUMPRODUCT(--(('💰 Payments'!$E$8:$E$67<>"")*(MONTH('💰 Payments'!$E$8:$E$67)=4)),'💰 Payments'!$J$8:$J$67) -> 0 | J5: =SUMPRODUCT(--(('💸 Expenses'!$C$8:$C$67<>"")*(MONTH('💸 Expenses'!$C$8:$C$67)=4)),'💸 Expenses'!$G$8:$G$67) -> 0 | K5: =I5-J5 -> 0 | L5: =SUMPRODUCT(('📅 Events'!$E$8:$E$47<>"")*(MONTH('📅 Events'!$E$8:$E$47)=4)*1) -> 0 | N5: Transportation | O5: =SUMIF('💸 Expenses'!$E$8:$E$67,$N5,'💸 Expenses'!$G$8:$G$67) -> 0 | AA5: =IFERROR(AGGREGATE(15,6,'📅 Events'!$E$8:$E$47/('📅 Events'!$E$8:$E$47>=TODAY())*('📅 Events'!$Q$8:$Q$47<>"❌ Cancelled")*('📅 Events'!$Q$8:$Q$47<>"🎉 Completed"),4),"") | AB5: =IF($AA5="","",INDEX('📅 Events'!$D$8:$D$47,MATCH($AA5,'📅 Events'!$E$8:$E$47,0))&" - "&INDEX('📅 Events'!$F$8:$F$47,MATCH($AA5,'📅 Events'!$E$8:$E$47,0))) | AC5: =IF($AA5="","",INDEX('📅 Events'!$Q$8:$Q$47,MATCH($AA5,'📅 Events'!$E$8:$E$47,0))) | AE5: Net profit margin | AF5: =IFERROR($AF$4/$AF$2,0) -> 0
H6: May | I6: =SUMPRODUCT(--(('💰 Payments'!$E$8:$E$67<>"")*(MONTH('💰 Payments'!$E$8:$E$67)=5)),'💰 Payments'!$J$8:$J$67) -> 0 | J6: =SUMPRODUCT(--(('💸 Expenses'!$C$8:$C$67<>"")*(MONTH('💸 Expenses'!$C$8:$C$67)=5)),'💸 Expenses'!$G$8:$G$67) -> 0 | K6: =I6-J6 -> 0 | L6: =SUMPRODUCT(('📅 Events'!$E$8:$E$47<>"")*(MONTH('📅 Events'!$E$8:$E$47)=5)*1) -> 0 | N6: Equipment | O6: =SUMIF('💸 Expenses'!$E$8:$E$67,$N6,'💸 Expenses'!$G$8:$G$67) -> 0 | AA6: =IFERROR(AGGREGATE(15,6,'📅 Events'!$E$8:$E$47/('📅 Events'!$E$8:$E$47>=TODAY())*('📅 Events'!$Q$8:$Q$47<>"❌ Cancelled")*('📅 Events'!$Q$8:$Q$47<>"🎉 Completed"),5),"") | AB6: =IF($AA6="","",INDEX('📅 Events'!$D$8:$D$47,MATCH($AA6,'📅 Events'!$E$8:$E$47,0))&" - "&INDEX('📅 Events'!$F$8:$F$47,MATCH($AA6,'📅 Events'!$E$8:$E$47,0))) | AC6: =IF($AA6="","",INDEX('📅 Events'!$Q$8:$Q$47,MATCH($AA6,'📅 Events'!$E$8:$E$47,0))) | AE6: Events on the books | AF6: =COUNTA('📅 Events'!$C$8:$C$47) -> 0
H7: Jun | I7: =SUMPRODUCT(--(('💰 Payments'!$E$8:$E$67<>"")*(MONTH('💰 Payments'!$E$8:$E$67)=6)),'💰 Payments'!$J$8:$J$67) -> 0 | J7: =SUMPRODUCT(--(('💸 Expenses'!$C$8:$C$67<>"")*(MONTH('💸 Expenses'!$C$8:$C$67)=6)),'💸 Expenses'!$G$8:$G$67) -> 0 | K7: =I7-J7 -> 0 | L7: =SUMPRODUCT(('📅 Events'!$E$8:$E$47<>"")*(MONTH('📅 Events'!$E$8:$E$47)=6)*1) -> 0 | N7: Kitchen Rental | O7: =SUMIF('💸 Expenses'!$E$8:$E$67,$N7,'💸 Expenses'!$G$8:$G$67) -> 0 | AA7: =IFERROR(AGGREGATE(15,6,'📅 Events'!$E$8:$E$47/('📅 Events'!$E$8:$E$47>=TODAY())*('📅 Events'!$Q$8:$Q$47<>"❌ Cancelled")*('📅 Events'!$Q$8:$Q$47<>"🎉 Completed"),6),"") | AB7: =IF($AA7="","",INDEX('📅 Events'!$D$8:$D$47,MATCH($AA7,'📅 Events'!$E$8:$E$47,0))&" - "&INDEX('📅 Events'!$F$8:$F$47,MATCH($AA7,'📅 Events'!$E$8:$E$47,0))) | AC7: =IF($AA7="","",INDEX('📅 Events'!$Q$8:$Q$47,MATCH($AA7,'📅 Events'!$E$8:$E$47,0))) | AE7: Events completed | AF7: =COUNTIF('📅 Events'!$Q$8:$Q$47,"🎉 Completed") -> 0
H8: Jul | I8: =SUMPRODUCT(--(('💰 Payments'!$E$8:$E$67<>"")*(MONTH('💰 Payments'!$E$8:$E$67)=7)),'💰 Payments'!$J$8:$J$67) -> 0 | J8: =SUMPRODUCT(--(('💸 Expenses'!$C$8:$C$67<>"")*(MONTH('💸 Expenses'!$C$8:$C$67)=7)),'💸 Expenses'!$G$8:$G$67) -> 0 | K8: =I8-J8 -> 0 | L8: =SUMPRODUCT(('📅 Events'!$E$8:$E$47<>"")*(MONTH('📅 Events'!$E$8:$E$47)=7)*1) -> 0 | N8: Marketing | O8: =SUMIF('💸 Expenses'!$E$8:$E$67,$N8,'💸 Expenses'!$G$8:$G$67) -> 0 | AA8: =IFERROR(AGGREGATE(15,6,'📅 Events'!$E$8:$E$47/('📅 Events'!$E$8:$E$47>=TODAY())*('📅 Events'!$Q$8:$Q$47<>"❌ Cancelled")*('📅 Events'!$Q$8:$Q$47<>"🎉 Completed"),7),"") | AB8: =IF($AA8="","",INDEX('📅 Events'!$D$8:$D$47,MATCH($AA8,'📅 Events'!$E$8:$E$47,0))&" - "&INDEX('📅 Events'!$F$8:$F$47,MATCH($AA8,'📅 Events'!$E$8:$E$47,0))) | AC8: =IF($AA8="","",INDEX('📅 Events'!$Q$8:$Q$47,MATCH($AA8,'📅 Events'!$E$8:$E$47,0))) | AE8: Events confirmed (upcoming) | AF8: =COUNTIF('📅 Events'!$Q$8:$Q$47,"💰 Deposit Paid")+COUNTIF('📅 Events'!$Q$8:$Q$47,"✅ Confirmed") -> 0
H9: Aug | I9: =SUMPRODUCT(--(('💰 Payments'!$E$8:$E$67<>"")*(MONTH('💰 Payments'!$E$8:$E$67)=8)),'💰 Payments'!$J$8:$J$67) -> 0 | J9: =SUMPRODUCT(--(('💸 Expenses'!$C$8:$C$67<>"")*(MONTH('💸 Expenses'!$C$8:$C$67)=8)),'💸 Expenses'!$G$8:$G$67) -> 0 | K9: =I9-J9 -> 0 | L9: =SUMPRODUCT(('📅 Events'!$E$8:$E$47<>"")*(MONTH('📅 Events'!$E$8:$E$47)=8)*1) -> 0 | N9: Insurance | O9: =SUMIF('💸 Expenses'!$E$8:$E$67,$N9,'💸 Expenses'!$G$8:$G$67) -> 0 | AA9: =IFERROR(AGGREGATE(15,6,'📅 Events'!$E$8:$E$47/('📅 Events'!$E$8:$E$47>=TODAY())*('📅 Events'!$Q$8:$Q$47<>"❌ Cancelled")*('📅 Events'!$Q$8:$Q$47<>"🎉 Completed"),8),"") | AB9: =IF($AA9="","",INDEX('📅 Events'!$D$8:$D$47,MATCH($AA9,'📅 Events'!$E$8:$E$47,0))&" - "&INDEX('📅 Events'!$F$8:$F$47,MATCH($AA9,'📅 Events'!$E$8:$E$47,0))) | AC9: =IF($AA9="","",INDEX('📅 Events'!$Q$8:$Q$47,MATCH($AA9,'📅 Events'!$E$8:$E$47,0))) | AE9: Events cancelled | AF9: =COUNTIF('📅 Events'!$Q$8:$Q$47,"❌ Cancelled") -> 0
H10: Sep | I10: =SUMPRODUCT(--(('💰 Payments'!$E$8:$E$67<>"")*(MONTH('💰 Payments'!$E$8:$E$67)=9)),'💰 Payments'!$J$8:$J$67) -> 0 | J10: =SUMPRODUCT(--(('💸 Expenses'!$C$8:$C$67<>"")*(MONTH('💸 Expenses'!$C$8:$C$67)=9)),'💸 Expenses'!$G$8:$G$67) -> 0 | K10: =I10-J10 -> 0 | L10: =SUMPRODUCT(('📅 Events'!$E$8:$E$47<>"")*(MONTH('📅 Events'!$E$8:$E$47)=9)*1) -> 0 | N10: Utilities | O10: =SUMIF('💸 Expenses'!$E$8:$E$67,$N10,'💸 Expenses'!$G$8:$G$67) -> 0 | AA10: =IFERROR(AGGREGATE(15,6,'📅 Events'!$E$8:$E$47/('📅 Events'!$E$8:$E$47>=TODAY())*('📅 Events'!$Q$8:$Q$47<>"❌ Cancelled")*('📅 Events'!$Q$8:$Q$47<>"🎉 Completed"),9),"") | AB10: =IF($AA10="","",INDEX('📅 Events'!$D$8:$D$47,MATCH($AA10,'📅 Events'!$E$8:$E$47,0))&" - "&INDEX('📅 Events'!$F$8:$F$47,MATCH($AA10,'📅 Events'!$E$8:$E$47,0))) | AC10: =IF($AA10="","",INDEX('📅 Events'!$Q$8:$Q$47,MATCH($AA10,'📅 Events'!$E$8:$E$47,0))) | AE10: Average order value | AF10: =IFERROR(AVERAGEIF('📅 Events'!$Q$8:$Q$47,"<>❌ Cancelled",'📅 Events'!$L$8:$L$47),0) -> 0
H11: Oct | I11: =SUMPRODUCT(--(('💰 Payments'!$E$8:$E$67<>"")*(MONTH('💰 Payments'!$E$8:$E$67)=10)),'💰 Payments'!$J$8:$J$67) -> 0 | J11: =SUMPRODUCT(--(('💸 Expenses'!$C$8:$C$67<>"")*(MONTH('💸 Expenses'!$C$8:$C$67)=10)),'💸 Expenses'!$G$8:$G$67) -> 0 | K11: =I11-J11 -> 0 | L11: =SUMPRODUCT(('📅 Events'!$E$8:$E$47<>"")*(MONTH('📅 Events'!$E$8:$E$47)=10)*1) -> 0 | N11: Software | O11: =SUMIF('💸 Expenses'!$E$8:$E$67,$N11,'💸 Expenses'!$G$8:$G$67) -> 0 | AA11: =IFERROR(AGGREGATE(15,6,'📅 Events'!$E$8:$E$47/('📅 Events'!$E$8:$E$47>=TODAY())*('📅 Events'!$Q$8:$Q$47<>"❌ Cancelled")*('📅 Events'!$Q$8:$Q$47<>"🎉 Completed"),10),"") | AB11: =IF($AA11="","",INDEX('📅 Events'!$D$8:$D$47,MATCH($AA11,'📅 Events'!$E$8:$E$47,0))&" - "&INDEX('📅 Events'!$F$8:$F$47,MATCH($AA11,'📅 Events'!$E$8:$E$47,0))) | AC11: =IF($AA11="","",INDEX('📅 Events'!$Q$8:$Q$47,MATCH($AA11,'📅 Events'!$E$8:$E$47,0))) | AE11: Average guests per event | AF11: =IFERROR(AVERAGEIF('📅 Events'!$Q$8:$Q$47,"<>❌ Cancelled",'📅 Events'!$G$8:$G$47),0) -> 0
H12: Nov | I12: =SUMPRODUCT(--(('💰 Payments'!$E$8:$E$67<>"")*(MONTH('💰 Payments'!$E$8:$E$67)=11)),'💰 Payments'!$J$8:$J$67) -> 0 | J12: =SUMPRODUCT(--(('💸 Expenses'!$C$8:$C$67<>"")*(MONTH('💸 Expenses'!$C$8:$C$67)=11)),'💸 Expenses'!$G$8:$G$67) -> 0 | K12: =I12-J12 -> 0 | L12: =SUMPRODUCT(('📅 Events'!$E$8:$E$47<>"")*(MONTH('📅 Events'!$E$8:$E$47)=11)*1) -> 0 | N12: Miscellaneous | O12: =SUMIF('💸 Expenses'!$E$8:$E$67,$N12,'💸 Expenses'!$G$8:$G$67) -> 0 | AA12: =IFERROR(AGGREGATE(15,6,'📅 Events'!$E$8:$E$47/('📅 Events'!$E$8:$E$47>=TODAY())*('📅 Events'!$Q$8:$Q$47<>"❌ Cancelled")*('📅 Events'!$Q$8:$Q$47<>"🎉 Completed"),11),"") | AB12: =IF($AA12="","",INDEX('📅 Events'!$D$8:$D$47,MATCH($AA12,'📅 Events'!$E$8:$E$47,0))&" - "&INDEX('📅 Events'!$F$8:$F$47,MATCH($AA12,'📅 Events'!$E$8:$E$47,0))) | AC12: =IF($AA12="","",INDEX('📅 Events'!$Q$8:$Q$47,MATCH($AA12,'📅 Events'!$E$8:$E$47,0))) | AE12: Average profit per event | AF12: =IFERROR(AVERAGEIF('📅 Events'!$Q$8:$Q$47,"<>❌ Cancelled",'📅 Events'!$M$8:$M$47),0) -> 0
H13: Dec | I13: =SUMPRODUCT(--(('💰 Payments'!$E$8:$E$67<>"")*(MONTH('💰 Payments'!$E$8:$E$67)=12)),'💰 Payments'!$J$8:$J$67) -> 0 | J13: =SUMPRODUCT(--(('💸 Expenses'!$C$8:$C$67<>"")*(MONTH('💸 Expenses'!$C$8:$C$67)=12)),'💸 Expenses'!$G$8:$G$67) -> 0 | K13: =I13-J13 -> 0 | L13: =SUMPRODUCT(('📅 Events'!$E$8:$E$47<>"")*(MONTH('📅 Events'!$E$8:$E$47)=12)*1) -> 0 | AA13: =IFERROR(AGGREGATE(15,6,'📅 Events'!$E$8:$E$47/('📅 Events'!$E$8:$E$47>=TODAY())*('📅 Events'!$Q$8:$Q$47<>"❌ Cancelled")*('📅 Events'!$Q$8:$Q$47<>"🎉 Completed"),12),"") | AB13: =IF($AA13="","",INDEX('📅 Events'!$D$8:$D$47,MATCH($AA13,'📅 Events'!$E$8:$E$47,0))&" - "&INDEX('📅 Events'!$F$8:$F$47,MATCH($AA13,'📅 Events'!$E$8:$E$47,0))) | AC13: =IF($AA13="","",INDEX('📅 Events'!$Q$8:$Q$47,MATCH($AA13,'📅 Events'!$E$8:$E$47,0))) | AE13: Guests catered (completed) | AF13: =SUMIF('📅 Events'!$Q$8:$Q$47,"🎉 Completed",'📅 Events'!$G$8:$G$47) -> 0
AA14: =IFERROR(AGGREGATE(15,6,'📅 Events'!$E$8:$E$47/('📅 Events'!$E$8:$E$47>=TODAY())*('📅 Events'!$Q$8:$Q$47<>"❌ Cancelled")*('📅 Events'!$Q$8:$Q$47<>"🎉 Completed"),13),"") | AB14: =IF($AA14="","",INDEX('📅 Events'!$D$8:$D$47,MATCH($AA14,'📅 Events'!$E$8:$E$47,0))&" - "&INDEX('📅 Events'!$F$8:$F$47,MATCH($AA14,'📅 Events'!$E$8:$E$47,0))) | AC14: =IF($AA14="","",INDEX('📅 Events'!$Q$8:$Q$47,MATCH($AA14,'📅 Events'!$E$8:$E$47,0))) | AE14: Outstanding receivables | AF14: =SUM('💰 Payments'!$K$8:$K$67) -> 0
N15: Event type | O15: Revenue | AA15: =IFERROR(AGGREGATE(15,6,'📅 Events'!$E$8:$E$47/('📅 Events'!$E$8:$E$47>=TODAY())*('📅 Events'!$Q$8:$Q$47<>"❌ Cancelled")*('📅 Events'!$Q$8:$Q$47<>"🎉 Completed"),14),"") | AB15: =IF($AA15="","",INDEX('📅 Events'!$D$8:$D$47,MATCH($AA15,'📅 Events'!$E$8:$E$47,0))&" - "&INDEX('📅 Events'!$F$8:$F$47,MATCH($AA15,'📅 Events'!$E$8:$E$47,0))) | AC15: =IF($AA15="","",INDEX('📅 Events'!$Q$8:$Q$47,MATCH($AA15,'📅 Events'!$E$8:$E$47,0))) | AE15: Overdue invoices | AF15: =SUMPRODUCT(('💰 Payments'!$K$8:$K$67>0)*('💰 Payments'!$L$8:$L$67<>"")*('💰 Payments'!$L$8:$L$67<TODAY())) -> 0
N16: Wedding | O16: =SUMIFS('📅 Events'!$L$8:$L$47,'📅 Events'!$F$8:$F$47,$N16,'📅 Events'!$Q$8:$Q$47,"<>❌ Cancelled") -> 0 | AA16: =IFERROR(AGGREGATE(15,6,'📅 Events'!$E$8:$E$47/('📅 Events'!$E$8:$E$47>=TODAY())*('📅 Events'!$Q$8:$Q$47<>"❌ Cancelled")*('📅 Events'!$Q$8:$Q$47<>"🎉 Completed"),15),"") | AB16: =IF($AA16="","",INDEX('📅 Events'!$D$8:$D$47,MATCH($AA16,'📅 Events'!$E$8:$E$47,0))&" - "&INDEX('📅 Events'!$F$8:$F$47,MATCH($AA16,'📅 Events'!$E$8:$E$47,0))) | AC16: =IF($AA16="","",INDEX('📅 Events'!$Q$8:$Q$47,MATCH($AA16,'📅 Events'!$E$8:$E$47,0))) | AE16: Invoices still open | AF16: =COUNTIF('💰 Payments'!$K$8:$K$67,">0") -> 0
N17: Corporate | O17: =SUMIFS('📅 Events'!$L$8:$L$47,'📅 Events'!$F$8:$F$47,$N17,'📅 Events'!$Q$8:$Q$47,"<>❌ Cancelled") -> 0 | AA17: =IFERROR(AGGREGATE(15,6,'📅 Events'!$E$8:$E$47/('📅 Events'!$E$8:$E$47>=TODAY())*('📅 Events'!$Q$8:$Q$47<>"❌ Cancelled")*('📅 Events'!$Q$8:$Q$47<>"🎉 Completed"),16),"") | AB17: =IF($AA17="","",INDEX('📅 Events'!$D$8:$D$47,MATCH($AA17,'📅 Events'!$E$8:$E$47,0))&" - "&INDEX('📅 Events'!$F$8:$F$47,MATCH($AA17,'📅 Events'!$E$8:$E$47,0))) | AC17: =IF($AA17="","",INDEX('📅 Events'!$Q$8:$Q$47,MATCH($AA17,'📅 Events'!$E$8:$E$47,0))) | AE17: Ingredient & packaging spend | AF17: =SUMIF('💸 Expenses'!$E$8:$E$67,"Ingredients",'💸 Expenses'!$G$8:$G$67)+SUMIF('💸 Expenses'!$E$8:$E$67,"Packaging",'💸 Expenses'!$G$8:$G$67) -> 0
N18: Birthday | O18: =SUMIFS('📅 Events'!$L$8:$L$47,'📅 Events'!$F$8:$F$47,$N18,'📅 Events'!$Q$8:$Q$47,"<>❌ Cancelled") -> 0 | AA18: =IFERROR(AGGREGATE(15,6,'📅 Events'!$E$8:$E$47/('📅 Events'!$E$8:$E$47>=TODAY())*('📅 Events'!$Q$8:$Q$47<>"❌ Cancelled")*('📅 Events'!$Q$8:$Q$47<>"🎉 Completed"),17),"") | AB18: =IF($AA18="","",INDEX('📅 Events'!$D$8:$D$47,MATCH($AA18,'📅 Events'!$E$8:$E$47,0))&" - "&INDEX('📅 Events'!$F$8:$F$47,MATCH($AA18,'📅 Events'!$E$8:$E$47,0))) | AC18: =IF($AA18="","",INDEX('📅 Events'!$Q$8:$Q$47,MATCH($AA18,'📅 Events'!$E$8:$E$47,0))) | AE18: Staff / labor spend | AF18: =SUMIF('💸 Expenses'!$E$8:$E$67,"Staff / Labor",'💸 Expenses'!$G$8:$G$67) -> 0
N19: Private Party | O19: =SUMIFS('📅 Events'!$L$8:$L$47,'📅 Events'!$F$8:$F$47,$N19,'📅 Events'!$Q$8:$Q$47,"<>❌ Cancelled") -> 0 | AA19: =IFERROR(AGGREGATE(15,6,'📅 Events'!$E$8:$E$47/('📅 Events'!$E$8:$E$47>=TODAY())*('📅 Events'!$Q$8:$Q$47<>"❌ Cancelled")*('📅 Events'!$Q$8:$Q$47<>"🎉 Completed"),18),"") | AB19: =IF($AA19="","",INDEX('📅 Events'!$D$8:$D$47,MATCH($AA19,'📅 Events'!$E$8:$E$47,0))&" - "&INDEX('📅 Events'!$F$8:$F$47,MATCH($AA19,'📅 Events'!$E$8:$E$47,0))) | AC19: =IF($AA19="","",INDEX('📅 Events'!$Q$8:$Q$47,MATCH($AA19,'📅 Events'!$E$8:$E$47,0))) | AE19: Food cost % of revenue | AF19: =IFERROR($AF$17/$AF$2,0) -> 0
N20: Buffet | O20: =SUMIFS('📅 Events'!$L$8:$L$47,'📅 Events'!$F$8:$F$47,$N20,'📅 Events'!$Q$8:$Q$47,"<>❌ Cancelled") -> 0 | AA20: =IFERROR(AGGREGATE(15,6,'📅 Events'!$E$8:$E$47/('📅 Events'!$E$8:$E$47>=TODAY())*('📅 Events'!$Q$8:$Q$47<>"❌ Cancelled")*('📅 Events'!$Q$8:$Q$47<>"🎉 Completed"),19),"") | AB20: =IF($AA20="","",INDEX('📅 Events'!$D$8:$D$47,MATCH($AA20,'📅 Events'!$E$8:$E$47,0))&" - "&INDEX('📅 Events'!$F$8:$F$47,MATCH($AA20,'📅 Events'!$E$8:$E$47,0))) | AC20: =IF($AA20="","",INDEX('📅 Events'!$Q$8:$Q$47,MATCH($AA20,'📅 Events'!$E$8:$E$47,0))) | AE20: Labor cost % of revenue | AF20: =IFERROR($AF$18/$AF$2,0) -> 0
N21: Cocktail | O21: =SUMIFS('📅 Events'!$L$8:$L$47,'📅 Events'!$F$8:$F$47,$N21,'📅 Events'!$Q$8:$Q$47,"<>❌ Cancelled") -> 0 | AA21: =IFERROR(AGGREGATE(15,6,'📅 Events'!$E$8:$E$47/('📅 Events'!$E$8:$E$47>=TODAY())*('📅 Events'!$Q$8:$Q$47<>"❌ Cancelled")*('📅 Events'!$Q$8:$Q$47<>"🎉 Completed"),20),"") | AB21: =IF($AA21="","",INDEX('📅 Events'!$D$8:$D$47,MATCH($AA21,'📅 Events'!$E$8:$E$47,0))&" - "&INDEX('📅 Events'!$F$8:$F$47,MATCH($AA21,'📅 Events'!$E$8:$E$47,0))) | AC21: =IF($AA21="","",INDEX('📅 Events'!$Q$8:$Q$47,MATCH($AA21,'📅 Events'!$E$8:$E$47,0))) | AE21: Repeat customer % | AF21: =IFERROR(SUMPRODUCT((COUNTIF('👥 Clients'!$C$8:$C$47,'👥 Clients'!$C$8:$C$47&"")>1)*(('👥 Clients'!$C$8:$C$47&"")<>"")*1)/COUNTA('👥 Clients'!$C$8:$C$47),0) -> 0
N22: Conference | O22: =SUMIFS('📅 Events'!$L$8:$L$47,'📅 Events'!$F$8:$F$47,$N22,'📅 Events'!$Q$8:$Q$47,"<>❌ Cancelled") -> 0 | AA22: =IFERROR(AGGREGATE(15,6,'📅 Events'!$E$8:$E$47/('📅 Events'!$E$8:$E$47>=TODAY())*('📅 Events'!$Q$8:$Q$47<>"❌ Cancelled")*('📅 Events'!$Q$8:$Q$47<>"🎉 Completed"),21),"") | AB22: =IF($AA22="","",INDEX('📅 Events'!$D$8:$D$47,MATCH($AA22,'📅 Events'!$E$8:$E$47,0))&" - "&INDEX('📅 Events'!$F$8:$F$47,MATCH($AA22,'📅 Events'!$E$8:$E$47,0))) | AC22: =IF($AA22="","",INDEX('📅 Events'!$Q$8:$Q$47,MATCH($AA22,'📅 Events'!$E$8:$E$47,0))) | AE22: Inventory value | AF22: =SUM('📦 Inventory'!$I$8:$I$47) -> 0
N23: Festival | O23: =SUMIFS('📅 Events'!$L$8:$L$47,'📅 Events'!$F$8:$F$47,$N23,'📅 Events'!$Q$8:$Q$47,"<>❌ Cancelled") -> 0 | AA23: =IFERROR(AGGREGATE(15,6,'📅 Events'!$E$8:$E$47/('📅 Events'!$E$8:$E$47>=TODAY())*('📅 Events'!$Q$8:$Q$47<>"❌ Cancelled")*('📅 Events'!$Q$8:$Q$47<>"🎉 Completed"),22),"") | AB23: =IF($AA23="","",INDEX('📅 Events'!$D$8:$D$47,MATCH($AA23,'📅 Events'!$E$8:$E$47,0))&" - "&INDEX('📅 Events'!$F$8:$F$47,MATCH($AA23,'📅 Events'!$E$8:$E$47,0))) | AC23: =IF($AA23="","",INDEX('📅 Events'!$Q$8:$Q$47,MATCH($AA23,'📅 Events'!$E$8:$E$47,0))) | AE23: Ingredients below minimum | AF23: =COUNTIF('📦 Inventory'!$K$8:$K$47,"🔴 Reorder") -> 0
N24: Other | O24: =SUMIFS('📅 Events'!$L$8:$L$47,'📅 Events'!$F$8:$F$47,$N24,'📅 Events'!$Q$8:$Q$47,"<>❌ Cancelled") -> 0 | AA24: =IFERROR(AGGREGATE(15,6,'📅 Events'!$E$8:$E$47/('📅 Events'!$E$8:$E$47>=TODAY())*('📅 Events'!$Q$8:$Q$47<>"❌ Cancelled")*('📅 Events'!$Q$8:$Q$47<>"🎉 Completed"),23),"") | AB24: =IF($AA24="","",INDEX('📅 Events'!$D$8:$D$47,MATCH($AA24,'📅 Events'!$E$8:$E$47,0))&" - "&INDEX('📅 Events'!$F$8:$F$47,MATCH($AA24,'📅 Events'!$E$8:$E$47,0))) | AC24: =IF($AA24="","",INDEX('📅 Events'!$Q$8:$Q$47,MATCH($AA24,'📅 Events'!$E$8:$E$47,0))) | AE24: Shopping lines open | AF24: =SUMPRODUCT(ISNUMBER('🛒 Shopping List'!$G$8:$G$47)*('🛒 Shopping List'!$G$8:$G$47>0)*('🛒 Shopping List'!$J$8:$J$47<>"✓")) -> 0
Q25: Client | R25: Received | T25: Menu item | U25: Booked | AA25: =IFERROR(AGGREGATE(15,6,'📅 Events'!$E$8:$E$47/('📅 Events'!$E$8:$E$47>=TODAY())*('📅 Events'!$Q$8:$Q$47<>"❌ Cancelled")*('📅 Events'!$Q$8:$Q$47<>"🎉 Completed"),24),"") | AB25: =IF($AA25="","",INDEX('📅 Events'!$D$8:$D$47,MATCH($AA25,'📅 Events'!$E$8:$E$47,0))&" - "&INDEX('📅 Events'!$F$8:$F$47,MATCH($AA25,'📅 Events'!$E$8:$E$47,0))) | AC25: =IF($AA25="","",INDEX('📅 Events'!$Q$8:$Q$47,MATCH($AA25,'📅 Events'!$E$8:$E$47,0))) | AE25: Shopping list estimated cost | AF25: =SUMPRODUCT(ISNUMBER('🛒 Shopping List'!$G$8:$G$47)*('🛒 Shopping List'!$G$8:$G$47>0)*('🛒 Shopping List'!$J$8:$J$47<>"✓"),'🛒 Shopping List'!$I$8:$I$47) -> 0
Q26: =IF('👥 Clients'!$C$8="","",'👥 Clients'!$C$8) | R26: =IF($Q26="","",SUMIF('💰 Payments'!$D$8:$D$67,$Q26,'💰 Payments'!$J$8:$J$67)) | T26: =IF('🍽️ Menu Costing'!$C$8="","",'🍽️ Menu Costing'!$C$8) | U26: =IF($T26="","",SUMPRODUCT(('📅 Events'!$H$8:$H$47<>"")*IFERROR(--ISNUMBER(SEARCH($T26,'📅 Events'!$H$8:$H$47)),0))) | AA26: =IFERROR(AGGREGATE(15,6,'📅 Events'!$E$8:$E$47/('📅 Events'!$E$8:$E$47>=TODAY())*('📅 Events'!$Q$8:$Q$47<>"❌ Cancelled")*('📅 Events'!$Q$8:$Q$47<>"🎉 Completed"),25),"") | AB26: =IF($AA26="","",INDEX('📅 Events'!$D$8:$D$47,MATCH($AA26,'📅 Events'!$E$8:$E$47,0))&" - "&INDEX('📅 Events'!$F$8:$F$47,MATCH($AA26,'📅 Events'!$E$8:$E$47,0))) | AC26: =IF($AA26="","",INDEX('📅 Events'!$Q$8:$Q$47,MATCH($AA26,'📅 Events'!$E$8:$E$47,0))) | AE26: Unpaid staff shifts | AF26: =SUMPRODUCT(('👷 Staff & Labor'!$C$8:$C$57<>"")*('👷 Staff & Labor'!$J$8:$J$57<>"✓")) -> 0
N27: Status | O27: Events | Q27: =IF('👥 Clients'!$C$9="","",'👥 Clients'!$C$9) | R27: =IF($Q27="","",SUMIF('💰 Payments'!$D$8:$D$67,$Q27,'💰 Payments'!$J$8:$J$67)) | T27: =IF('🍽️ Menu Costing'!$C$9="","",'🍽️ Menu Costing'!$C$9) | U27: =IF($T27="","",SUMPRODUCT(('📅 Events'!$H$8:$H$47<>"")*IFERROR(--ISNUMBER(SEARCH($T27,'📅 Events'!$H$8:$H$47)),0))) | AA27: =IFERROR(AGGREGATE(15,6,'📅 Events'!$E$8:$E$47/('📅 Events'!$E$8:$E$47>=TODAY())*('📅 Events'!$Q$8:$Q$47<>"❌ Cancelled")*('📅 Events'!$Q$8:$Q$47<>"🎉 Completed"),26),"") | AB27: =IF($AA27="","",INDEX('📅 Events'!$D$8:$D$47,MATCH($AA27,'📅 Events'!$E$8:$E$47,0))&" - "&INDEX('📅 Events'!$F$8:$F$47,MATCH($AA27,'📅 Events'!$E$8:$E$47,0))) | AC27: =IF($AA27="","",INDEX('📅 Events'!$Q$8:$Q$47,MATCH($AA27,'📅 Events'!$E$8:$E$47,0))) | AE27: Equipment value | AF27: =SUM('🍳 Equipment'!$J$8:$J$42) -> 0
N28: 💬 Inquiry | O28: =COUNTIF('📅 Events'!$Q$8:$Q$47,$N28) -> 0 | Q28: =IF('👥 Clients'!$C$10="","",'👥 Clients'!$C$10) | R28: =IF($Q28="","",SUMIF('💰 Payments'!$D$8:$D$67,$Q28,'💰 Payments'!$J$8:$J$67)) | T28: =IF('🍽️ Menu Costing'!$C$10="","",'🍽️ Menu Costing'!$C$10) | U28: =IF($T28="","",SUMPRODUCT(('📅 Events'!$H$8:$H$47<>"")*IFERROR(--ISNUMBER(SEARCH($T28,'📅 Events'!$H$8:$H$47)),0))) | AA28: =IFERROR(AGGREGATE(15,6,'📅 Events'!$E$8:$E$47/('📅 Events'!$E$8:$E$47>=TODAY())*('📅 Events'!$Q$8:$Q$47<>"❌ Cancelled")*('📅 Events'!$Q$8:$Q$47<>"🎉 Completed"),27),"") | AB28: =IF($AA28="","",INDEX('📅 Events'!$D$8:$D$47,MATCH($AA28,'📅 Events'!$E$8:$E$47,0))&" - "&INDEX('📅 Events'!$F$8:$F$47,MATCH($AA28,'📅 Events'!$E$8:$E$47,0))) | AC28: =IF($AA28="","",INDEX('📅 Events'!$Q$8:$Q$47,MATCH($AA28,'📅 Events'!$E$8:$E$47,0))) | AE28: Equipment needing service | AF28: =COUNTIF('🍳 Equipment'!$L$8:$L$42,"🔧 Service")+COUNTIF('🍳 Equipment'!$L$8:$L$42,"🟡 Soon") -> 0
N29: 📝 Quote Sent | O29: =COUNTIF('📅 Events'!$Q$8:$Q$47,$N29) -> 0 | Q29: =IF('👥 Clients'!$C$11="","",'👥 Clients'!$C$11) | R29: =IF($Q29="","",SUMIF('💰 Payments'!$D$8:$D$67,$Q29,'💰 Payments'!$J$8:$J$67)) | T29: =IF('🍽️ Menu Costing'!$C$11="","",'🍽️ Menu Costing'!$C$11) | U29: =IF($T29="","",SUMPRODUCT(('📅 Events'!$H$8:$H$47<>"")*IFERROR(--ISNUMBER(SEARCH($T29,'📅 Events'!$H$8:$H$47)),0))) | AA29: =IFERROR(AGGREGATE(15,6,'📅 Events'!$E$8:$E$47/('📅 Events'!$E$8:$E$47>=TODAY())*('📅 Events'!$Q$8:$Q$47<>"❌ Cancelled")*('📅 Events'!$Q$8:$Q$47<>"🎉 Completed"),28),"") | AB29: =IF($AA29="","",INDEX('📅 Events'!$D$8:$D$47,MATCH($AA29,'📅 Events'!$E$8:$E$47,0))&" - "&INDEX('📅 Events'!$F$8:$F$47,MATCH($AA29,'📅 Events'!$E$8:$E$47,0))) | AC29: =IF($AA29="","",INDEX('📅 Events'!$Q$8:$Q$47,MATCH($AA29,'📅 Events'!$E$8:$E$47,0))) | AE29: Tax collected on sales | AF29: ='🧾 Tax Tracker'!$C$11 -> 0
N30: 💰 Deposit Paid | O30: =COUNTIF('📅 Events'!$Q$8:$Q$47,$N30) -> 0 | Q30: =IF('👥 Clients'!$C$12="","",'👥 Clients'!$C$12) | R30: =IF($Q30="","",SUMIF('💰 Payments'!$D$8:$D$67,$Q30,'💰 Payments'!$J$8:$J$67)) | T30: =IF('🍽️ Menu Costing'!$C$12="","",'🍽️ Menu Costing'!$C$12) | U30: =IF($T30="","",SUMPRODUCT(('📅 Events'!$H$8:$H$47<>"")*IFERROR(--ISNUMBER(SEARCH($T30,'📅 Events'!$H$8:$H$47)),0))) | AA30: =IFERROR(AGGREGATE(15,6,'📅 Events'!$E$8:$E$47/('📅 Events'!$E$8:$E$47>=TODAY())*('📅 Events'!$Q$8:$Q$47<>"❌ Cancelled")*('📅 Events'!$Q$8:$Q$47<>"🎉 Completed"),29),"") | AB30: =IF($AA30="","",INDEX('📅 Events'!$D$8:$D$47,MATCH($AA30,'📅 Events'!$E$8:$E$47,0))&" - "&INDEX('📅 Events'!$F$8:$F$47,MATCH($AA30,'📅 Events'!$E$8:$E$47,0))) | AC30: =IF($AA30="","",INDEX('📅 Events'!$Q$8:$Q$47,MATCH($AA30,'📅 Events'!$E$8:$E$47,0))) | AE30: Estimated tax still due | AF30: ='🧾 Tax Tracker'!$C$13 -> 0
N31: ✅ Confirmed | O31: =COUNTIF('📅 Events'!$Q$8:$Q$47,$N31) -> 0 | Q31: =IF('👥 Clients'!$C$13="","",'👥 Clients'!$C$13) | R31: =IF($Q31="","",SUMIF('💰 Payments'!$D$8:$D$67,$Q31,'💰 Payments'!$J$8:$J$67)) | T31: =IF('🍽️ Menu Costing'!$C$13="","",'🍽️ Menu Costing'!$C$13) | U31: =IF($T31="","",SUMPRODUCT(('📅 Events'!$H$8:$H$47<>"")*IFERROR(--ISNUMBER(SEARCH($T31,'📅 Events'!$H$8:$H$47)),0))) | AA31: =IFERROR(AGGREGATE(15,6,'📅 Events'!$E$8:$E$47/('📅 Events'!$E$8:$E$47>=TODAY())*('📅 Events'!$Q$8:$Q$47<>"❌ Cancelled")*('📅 Events'!$Q$8:$Q$47<>"🎉 Completed"),30),"") | AB31: =IF($AA31="","",INDEX('📅 Events'!$D$8:$D$47,MATCH($AA31,'📅 Events'!$E$8:$E$47,0))&" - "&INDEX('📅 Events'!$F$8:$F$47,MATCH($AA31,'📅 Events'!$E$8:$E$47,0))) | AC31: =IF($AA31="","",INDEX('📅 Events'!$Q$8:$Q$47,MATCH($AA31,'📅 Events'!$E$8:$E$47,0))) | AE31: Quote calculator: recommended price | AF31: ='🧮 Quote Calculator'!$E$16 -> 0
N32: 🎉 Completed | O32: =COUNTIF('📅 Events'!$Q$8:$Q$47,$N32) -> 0 | Q32: =IF('👥 Clients'!$C$14="","",'👥 Clients'!$C$14) | R32: =IF($Q32="","",SUMIF('💰 Payments'!$D$8:$D$67,$Q32,'💰 Payments'!$J$8:$J$67)) | T32: =IF('🍽️ Menu Costing'!$C$14="","",'🍽️ Menu Costing'!$C$14) | U32: =IF($T32="","",SUMPRODUCT(('📅 Events'!$H$8:$H$47<>"")*IFERROR(--ISNUMBER(SEARCH($T32,'📅 Events'!$H$8:$H$47)),0))) | AA32: =IFERROR(AGGREGATE(15,6,'📅 Events'!$E$8:$E$47/('📅 Events'!$E$8:$E$47>=TODAY())*('📅 Events'!$Q$8:$Q$47<>"❌ Cancelled")*('📅 Events'!$Q$8:$Q$47<>"🎉 Completed"),31),"") | AB32: =IF($AA32="","",INDEX('📅 Events'!$D$8:$D$47,MATCH($AA32,'📅 Events'!$E$8:$E$47,0))&" - "&INDEX('📅 Events'!$F$8:$F$47,MATCH($AA32,'📅 Events'!$E$8:$E$47,0))) | AC32: =IF($AA32="","",INDEX('📅 Events'!$Q$8:$Q$47,MATCH($AA32,'📅 Events'!$E$8:$E$47,0))) | AE32: Quote calculator: price per guest | AF32: ='🧮 Quote Calculator'!$E$17 -> 0
N33: ❌ Cancelled | O33: =COUNTIF('📅 Events'!$Q$8:$Q$47,$N33) -> 0 | Q33: =IF('👥 Clients'!$C$15="","",'👥 Clients'!$C$15) | R33: =IF($Q33="","",SUMIF('💰 Payments'!$D$8:$D$67,$Q33,'💰 Payments'!$J$8:$J$67)) | T33: =IF('🍽️ Menu Costing'!$C$15="","",'🍽️ Menu Costing'!$C$15) | U33: =IF($T33="","",SUMPRODUCT(('📅 Events'!$H$8:$H$47<>"")*IFERROR(--ISNUMBER(SEARCH($T33,'📅 Events'!$H$8:$H$47)),0))) | AA33: =IFERROR(AGGREGATE(15,6,'📅 Events'!$E$8:$E$47/('📅 Events'!$E$8:$E$47>=TODAY())*('📅 Events'!$Q$8:$Q$47<>"❌ Cancelled")*('📅 Events'!$Q$8:$Q$47<>"🎉 Completed"),32),"") | AB33: =IF($AA33="","",INDEX('📅 Events'!$D$8:$D$47,MATCH($AA33,'📅 Events'!$E$8:$E$47,0))&" - "&INDEX('📅 Events'!$F$8:$F$47,MATCH($AA33,'📅 Events'!$E$8:$E$47,0))) | AC33: =IF($AA33="","",INDEX('📅 Events'!$Q$8:$Q$47,MATCH($AA33,'📅 Events'!$E$8:$E$47,0))) | AE33: Menu items priced | AF33: =COUNTA('🍽️ Menu Costing'!$C$8:$C$37) -> 0
Q34: =IF('👥 Clients'!$C$16="","",'👥 Clients'!$C$16) | R34: =IF($Q34="","",SUMIF('💰 Payments'!$D$8:$D$67,$Q34,'💰 Payments'!$J$8:$J$67)) | T34: =IF('🍽️ Menu Costing'!$C$16="","",'🍽️ Menu Costing'!$C$16) | U34: =IF($T34="","",SUMPRODUCT(('📅 Events'!$H$8:$H$47<>"")*IFERROR(--ISNUMBER(SEARCH($T34,'📅 Events'!$H$8:$H$47)),0))) | AA34: =IFERROR(AGGREGATE(15,6,'📅 Events'!$E$8:$E$47/('📅 Events'!$E$8:$E$47>=TODAY())*('📅 Events'!$Q$8:$Q$47<>"❌ Cancelled")*('📅 Events'!$Q$8:$Q$47<>"🎉 Completed"),33),"") | AB34: =IF($AA34="","",INDEX('📅 Events'!$D$8:$D$47,MATCH($AA34,'📅 Events'!$E$8:$E$47,0))&" - "&INDEX('📅 Events'!$F$8:$F$47,MATCH($AA34,'📅 Events'!$E$8:$E$47,0))) | AC34: =IF($AA34="","",INDEX('📅 Events'!$Q$8:$Q$47,MATCH($AA34,'📅 Events'!$E$8:$E$47,0))) | AE34: Average menu margin | AF34: =IFERROR(AVERAGE('🍽️ Menu Costing'!$J$8:$J$37),0) -> 0
Q35: =IF('👥 Clients'!$C$17="","",'👥 Clients'!$C$17) | R35: =IF($Q35="","",SUMIF('💰 Payments'!$D$8:$D$67,$Q35,'💰 Payments'!$J$8:$J$67)) | T35: =IF('🍽️ Menu Costing'!$C$17="","",'🍽️ Menu Costing'!$C$17) | U35: =IF($T35="","",SUMPRODUCT(('📅 Events'!$H$8:$H$47<>"")*IFERROR(--ISNUMBER(SEARCH($T35,'📅 Events'!$H$8:$H$47)),0))) | AA35: =IFERROR(AGGREGATE(15,6,'📅 Events'!$E$8:$E$47/('📅 Events'!$E$8:$E$47>=TODAY())*('📅 Events'!$Q$8:$Q$47<>"❌ Cancelled")*('📅 Events'!$Q$8:$Q$47<>"🎉 Completed"),34),"") | AB35: =IF($AA35="","",INDEX('📅 Events'!$D$8:$D$47,MATCH($AA35,'📅 Events'!$E$8:$E$47,0))&" - "&INDEX('📅 Events'!$F$8:$F$47,MATCH($AA35,'📅 Events'!$E$8:$E$47,0))) | AC35: =IF($AA35="","",INDEX('📅 Events'!$Q$8:$Q$47,MATCH($AA35,'📅 Events'!$E$8:$E$47,0))) | AE35: Best earning event type | AF35: =IF(MAX($O$16:$O$24)=0,"-",INDEX($N$16:$N$24,MATCH(MAX($O$16:$O$24),$O$16:$O$24,0))) -> 0
Q36: =IF('👥 Clients'!$C$18="","",'👥 Clients'!$C$18) | R36: =IF($Q36="","",SUMIF('💰 Payments'!$D$8:$D$67,$Q36,'💰 Payments'!$J$8:$J$67)) | T36: =IF('🍽️ Menu Costing'!$C$18="","",'🍽️ Menu Costing'!$C$18) | U36: =IF($T36="","",SUMPRODUCT(('📅 Events'!$H$8:$H$47<>"")*IFERROR(--ISNUMBER(SEARCH($T36,'📅 Events'!$H$8:$H$47)),0))) | AA36: =IFERROR(AGGREGATE(15,6,'📅 Events'!$E$8:$E$47/('📅 Events'!$E$8:$E$47>=TODAY())*('📅 Events'!$Q$8:$Q$47<>"❌ Cancelled")*('📅 Events'!$Q$8:$Q$47<>"🎉 Completed"),35),"") | AB36: =IF($AA36="","",INDEX('📅 Events'!$D$8:$D$47,MATCH($AA36,'📅 Events'!$E$8:$E$47,0))&" - "&INDEX('📅 Events'!$F$8:$F$47,MATCH($AA36,'📅 Events'!$E$8:$E$47,0))) | AC36: =IF($AA36="","",INDEX('📅 Events'!$Q$8:$Q$47,MATCH($AA36,'📅 Events'!$E$8:$E$47,0))) | AE36: Highest value client | AF36: =IF(MAX($R$26:$R$40)=0,"-",INDEX($Q$26:$Q$40,MATCH(MAX($R$26:$R$40),$R$26:$R$40,0))) -> 0
Q37: =IF('👥 Clients'!$C$19="","",'👥 Clients'!$C$19) | R37: =IF($Q37="","",SUMIF('💰 Payments'!$D$8:$D$67,$Q37,'💰 Payments'!$J$8:$J$67)) | T37: =IF('🍽️ Menu Costing'!$C$19="","",'🍽️ Menu Costing'!$C$19) | U37: =IF($T37="","",SUMPRODUCT(('📅 Events'!$H$8:$H$47<>"")*IFERROR(--ISNUMBER(SEARCH($T37,'📅 Events'!$H$8:$H$47)),0))) | AA37: =IFERROR(AGGREGATE(15,6,'📅 Events'!$E$8:$E$47/('📅 Events'!$E$8:$E$47>=TODAY())*('📅 Events'!$Q$8:$Q$47<>"❌ Cancelled")*('📅 Events'!$Q$8:$Q$47<>"🎉 Completed"),36),"") | AB37: =IF($AA37="","",INDEX('📅 Events'!$D$8:$D$47,MATCH($AA37,'📅 Events'!$E$8:$E$47,0))&" - "&INDEX('📅 Events'!$F$8:$F$47,MATCH($AA37,'📅 Events'!$E$8:$E$47,0))) | AC37: =IF($AA37="","",INDEX('📅 Events'!$Q$8:$Q$47,MATCH($AA37,'📅 Events'!$E$8:$E$47,0)))
Q38: =IF('👥 Clients'!$C$20="","",'👥 Clients'!$C$20) | R38: =IF($Q38="","",SUMIF('💰 Payments'!$D$8:$D$67,$Q38,'💰 Payments'!$J$8:$J$67)) | T38: =IF('🍽️ Menu Costing'!$C$20="","",'🍽️ Menu Costing'!$C$20) | U38: =IF($T38="","",SUMPRODUCT(('📅 Events'!$H$8:$H$47<>"")*IFERROR(--ISNUMBER(SEARCH($T38,'📅 Events'!$H$8:$H$47)),0))) | AA38: =IFERROR(AGGREGATE(15,6,'📅 Events'!$E$8:$E$47/('📅 Events'!$E$8:$E$47>=TODAY())*('📅 Events'!$Q$8:$Q$47<>"❌ Cancelled")*('📅 Events'!$Q$8:$Q$47<>"🎉 Completed"),37),"") | AB38: =IF($AA38="","",INDEX('📅 Events'!$D$8:$D$47,MATCH($AA38,'📅 Events'!$E$8:$E$47,0))&" - "&INDEX('📅 Events'!$F$8:$F$47,MATCH($AA38,'📅 Events'!$E$8:$E$47,0))) | AC38: =IF($AA38="","",INDEX('📅 Events'!$Q$8:$Q$47,MATCH($AA38,'📅 Events'!$E$8:$E$47,0)))
Q39: =IF('👥 Clients'!$C$21="","",'👥 Clients'!$C$21) | R39: =IF($Q39="","",SUMIF('💰 Payments'!$D$8:$D$67,$Q39,'💰 Payments'!$J$8:$J$67)) | T39: =IF('🍽️ Menu Costing'!$C$21="","",'🍽️ Menu Costing'!$C$21) | U39: =IF($T39="","",SUMPRODUCT(('📅 Events'!$H$8:$H$47<>"")*IFERROR(--ISNUMBER(SEARCH($T39,'📅 Events'!$H$8:$H$47)),0))) | AA39: =IFERROR(AGGREGATE(15,6,'📅 Events'!$E$8:$E$47/('📅 Events'!$E$8:$E$47>=TODAY())*('📅 Events'!$Q$8:$Q$47<>"❌ Cancelled")*('📅 Events'!$Q$8:$Q$47<>"🎉 Completed"),38),"") | AB39: =IF($AA39="","",INDEX('📅 Events'!$D$8:$D$47,MATCH($AA39,'📅 Events'!$E$8:$E$47,0))&" - "&INDEX('📅 Events'!$F$8:$F$47,MATCH($AA39,'📅 Events'!$E$8:$E$47,0))) | AC39: =IF($AA39="","",INDEX('📅 Events'!$Q$8:$Q$47,MATCH($AA39,'📅 Events'!$E$8:$E$47,0)))
Q40: =IF('👥 Clients'!$C$22="","",'👥 Clients'!$C$22) | R40: =IF($Q40="","",SUMIF('💰 Payments'!$D$8:$D$67,$Q40,'💰 Payments'!$J$8:$J$67)) | T40: =IF('🍽️ Menu Costing'!$C$22="","",'🍽️ Menu Costing'!$C$22) | U40: =IF($T40="","",SUMPRODUCT(('📅 Events'!$H$8:$H$47<>"")*IFERROR(--ISNUMBER(SEARCH($T40,'📅 Events'!$H$8:$H$47)),0))) | AA40: =IFERROR(AGGREGATE(15,6,'📅 Events'!$E$8:$E$47/('📅 Events'!$E$8:$E$47>=TODAY())*('📅 Events'!$Q$8:$Q$47<>"❌ Cancelled")*('📅 Events'!$Q$8:$Q$47<>"🎉 Completed"),39),"") | AB40: =IF($AA40="","",INDEX('📅 Events'!$D$8:$D$47,MATCH($AA40,'📅 Events'!$E$8:$E$47,0))&" - "&INDEX('📅 Events'!$F$8:$F$47,MATCH($AA40,'📅 Events'!$E$8:$E$47,0))) | AC40: =IF($AA40="","",INDEX('📅 Events'!$Q$8:$Q$47,MATCH($AA40,'📅 Events'!$E$8:$E$47,0)))
AA41: Payment due | AB41: Owes | AC41: Balance
AA42: =IFERROR(AGGREGATE(15,6,'💰 Payments'!$L$8:$L$67/(('💰 Payments'!$L$8:$L$67<>"")*('💰 Payments'!$K$8:$K$67>0)),1),"") | AB42: =IF($AA42="","",INDEX('💰 Payments'!$D$8:$D$67,MATCH($AA42,'💰 Payments'!$L$8:$L$67,0))&" ("&INDEX('💰 Payments'!$C$8:$C$67,MATCH($AA42,'💰 Payments'!$L$8:$L$67,0))&")") | AC42: =IF($AA42="","",INDEX('💰 Payments'!$K$8:$K$67,MATCH($AA42,'💰 Payments'!$L$8:$L$67,0)))
AA43: =IFERROR(AGGREGATE(15,6,'💰 Payments'!$L$8:$L$67/(('💰 Payments'!$L$8:$L$67<>"")*('💰 Payments'!$K$8:$K$67>0)),2),"") | AB43: =IF($AA43="","",INDEX('💰 Payments'!$D$8:$D$67,MATCH($AA43,'💰 Payments'!$L$8:$L$67,0))&" ("&INDEX('💰 Payments'!$C$8:$C$67,MATCH($AA43,'💰 Payments'!$L$8:$L$67,0))&")") | AC43: =IF($AA43="","",INDEX('💰 Payments'!$K$8:$K$67,MATCH($AA43,'💰 Payments'!$L$8:$L$67,0)))
AA44: =IFERROR(AGGREGATE(15,6,'💰 Payments'!$L$8:$L$67/(('💰 Payments'!$L$8:$L$67<>"")*('💰 Payments'!$K$8:$K$67>0)),3),"") | AB44: =IF($AA44="","",INDEX('💰 Payments'!$D$8:$D$67,MATCH($AA44,'💰 Payments'!$L$8:$L$67,0))&" ("&INDEX('💰 Payments'!$C$8:$C$67,MATCH($AA44,'💰 Payments'!$L$8:$L$67,0))&")") | AC44: =IF($AA44="","",INDEX('💰 Payments'!$K$8:$K$67,MATCH($AA44,'💰 Payments'!$L$8:$L$67,0)))
AA45: =IFERROR(AGGREGATE(15,6,'💰 Payments'!$L$8:$L$67/(('💰 Payments'!$L$8:$L$67<>"")*('💰 Payments'!$K$8:$K$67>0)),4),"") | AB45: =IF($AA45="","",INDEX('💰 Payments'!$D$8:$D$67,MATCH($AA45,'💰 Payments'!$L$8:$L$67,0))&" ("&INDEX('💰 Payments'!$C$8:$C$67,MATCH($AA45,'💰 Payments'!$L$8:$L$67,0))&")") | AC45: =IF($AA45="","",INDEX('💰 Payments'!$K$8:$K$67,MATCH($AA45,'💰 Payments'!$L$8:$L$67,0)))
AA46: =IFERROR(AGGREGATE(15,6,'💰 Payments'!$L$8:$L$67/(('💰 Payments'!$L$8:$L$67<>"")*('💰 Payments'!$K$8:$K$67>0)),5),"") | AB46: =IF($AA46="","",INDEX('💰 Payments'!$D$8:$D$67,MATCH($AA46,'💰 Payments'!$L$8:$L$67,0))&" ("&INDEX('💰 Payments'!$C$8:$C$67,MATCH($AA46,'💰 Payments'!$L$8:$L$67,0))&")") | AC46: =IF($AA46="","",INDEX('💰 Payments'!$K$8:$K$67,MATCH($AA46,'💰 Payments'!$L$8:$L$67,0)))
AA47: =IFERROR(AGGREGATE(15,6,'💰 Payments'!$L$8:$L$67/(('💰 Payments'!$L$8:$L$67<>"")*('💰 Payments'!$K$8:$K$67>0)),6),"") | AB47: =IF($AA47="","",INDEX('💰 Payments'!$D$8:$D$67,MATCH($AA47,'💰 Payments'!$L$8:$L$67,0))&" ("&INDEX('💰 Payments'!$C$8:$C$67,MATCH($AA47,'💰 Payments'!$L$8:$L$67,0))&")") | AC47: =IF($AA47="","",INDEX('💰 Payments'!$K$8:$K$67,MATCH($AA47,'💰 Payments'!$L$8:$L$67,0)))
AA48: =IFERROR(AGGREGATE(15,6,'💰 Payments'!$L$8:$L$67/(('💰 Payments'!$L$8:$L$67<>"")*('💰 Payments'!$K$8:$K$67>0)),7),"") | AB48: =IF($AA48="","",INDEX('💰 Payments'!$D$8:$D$67,MATCH($AA48,'💰 Payments'!$L$8:$L$67,0))&" ("&INDEX('💰 Payments'!$C$8:$C$67,MATCH($AA48,'💰 Payments'!$L$8:$L$67,0))&")") | AC48: =IF($AA48="","",INDEX('💰 Payments'!$K$8:$K$67,MATCH($AA48,'💰 Payments'!$L$8:$L$67,0)))
AA49: =IFERROR(AGGREGATE(15,6,'💰 Payments'!$L$8:$L$67/(('💰 Payments'!$L$8:$L$67<>"")*('💰 Payments'!$K$8:$K$67>0)),8),"") | AB49: =IF($AA49="","",INDEX('💰 Payments'!$D$8:$D$67,MATCH($AA49,'💰 Payments'!$L$8:$L$67,0))&" ("&INDEX('💰 Payments'!$C$8:$C$67,MATCH($AA49,'💰 Payments'!$L$8:$L$67,0))&")") | AC49: =IF($AA49="","",INDEX('💰 Payments'!$K$8:$K$67,MATCH($AA49,'💰 Payments'!$L$8:$L$67,0)))
AA50: =IFERROR(AGGREGATE(15,6,'💰 Payments'!$L$8:$L$67/(('💰 Payments'!$L$8:$L$67<>"")*('💰 Payments'!$K$8:$K$67>0)),9),"") | AB50: =IF($AA50="","",INDEX('💰 Payments'!$D$8:$D$67,MATCH($AA50,'💰 Payments'!$L$8:$L$67,0))&" ("&INDEX('💰 Payments'!$C$8:$C$67,MATCH($AA50,'💰 Payments'!$L$8:$L$67,0))&")") | AC50: =IF($AA50="","",INDEX('💰 Payments'!$K$8:$K$67,MATCH($AA50,'💰 Payments'!$L$8:$L$67,0)))
AA51: =IFERROR(AGGREGATE(15,6,'💰 Payments'!$L$8:$L$67/(('💰 Payments'!$L$8:$L$67<>"")*('💰 Payments'!$K$8:$K$67>0)),10),"") | AB51: =IF($AA51="","",INDEX('💰 Payments'!$D$8:$D$67,MATCH($AA51,'💰 Payments'!$L$8:$L$67,0))&" ("&INDEX('💰 Payments'!$C$8:$C$67,MATCH($AA51,'💰 Payments'!$L$8:$L$67,0))&")") | AC51: =IF($AA51="","",INDEX('💰 Payments'!$K$8:$K$67,MATCH($AA51,'💰 Payments'!$L$8:$L$67,0)))
AA52: =IFERROR(AGGREGATE(15,6,'💰 Payments'!$L$8:$L$67/(('💰 Payments'!$L$8:$L$67<>"")*('💰 Payments'!$K$8:$K$67>0)),11),"") | AB52: =IF($AA52="","",INDEX('💰 Payments'!$D$8:$D$67,MATCH($AA52,'💰 Payments'!$L$8:$L$67,0))&" ("&INDEX('💰 Payments'!$C$8:$C$67,MATCH($AA52,'💰 Payments'!$L$8:$L$67,0))&")") | AC52: =IF($AA52="","",INDEX('💰 Payments'!$K$8:$K$67,MATCH($AA52,'💰 Payments'!$L$8:$L$67,0)))
AA53: =IFERROR(AGGREGATE(15,6,'💰 Payments'!$L$8:$L$67/(('💰 Payments'!$L$8:$L$67<>"")*('💰 Payments'!$K$8:$K$67>0)),12),"") | AB53: =IF($AA53="","",INDEX('💰 Payments'!$D$8:$D$67,MATCH($AA53,'💰 Payments'!$L$8:$L$67,0))&" ("&INDEX('💰 Payments'!$C$8:$C$67,MATCH($AA53,'💰 Payments'!$L$8:$L$67,0))&")") | AC53: =IF($AA53="","",INDEX('💰 Payments'!$K$8:$K$67,MATCH($AA53,'💰 Payments'!$L$8:$L$67,0)))
AA54: =IFERROR(AGGREGATE(15,6,'💰 Payments'!$L$8:$L$67/(('💰 Payments'!$L$8:$L$67<>"")*('💰 Payments'!$K$8:$K$67>0)),13),"") | AB54: =IF($AA54="","",INDEX('💰 Payments'!$D$8:$D$67,MATCH($AA54,'💰 Payments'!$L$8:$L$67,0))&" ("&INDEX('💰 Payments'!$C$8:$C$67,MATCH($AA54,'💰 Payments'!$L$8:$L$67,0))&")") | AC54: =IF($AA54="","",INDEX('💰 Payments'!$K$8:$K$67,MATCH($AA54,'💰 Payments'!$L$8:$L$67,0)))
AA55: =IFERROR(AGGREGATE(15,6,'💰 Payments'!$L$8:$L$67/(('💰 Payments'!$L$8:$L$67<>"")*('💰 Payments'!$K$8:$K$67>0)),14),"") | AB55: =IF($AA55="","",INDEX('💰 Payments'!$D$8:$D$67,MATCH($AA55,'💰 Payments'!$L$8:$L$67,0))&" ("&INDEX('💰 Payments'!$C$8:$C$67,MATCH($AA55,'💰 Payments'!$L$8:$L$67,0))&")") | AC55: =IF($AA55="","",INDEX('💰 Payments'!$K$8:$K$67,MATCH($AA55,'💰 Payments'!$L$8:$L$67,0)))
AA56: =IFERROR(AGGREGATE(15,6,'💰 Payments'!$L$8:$L$67/(('💰 Payments'!$L$8:$L$67<>"")*('💰 Payments'!$K$8:$K$67>0)),15),"") | AB56: =IF($AA56="","",INDEX('💰 Payments'!$D$8:$D$67,MATCH($AA56,'💰 Payments'!$L$8:$L$67,0))&" ("&INDEX('💰 Payments'!$C$8:$C$67,MATCH($AA56,'💰 Payments'!$L$8:$L$67,0))&")") | AC56: =IF($AA56="","",INDEX('💰 Payments'!$K$8:$K$67,MATCH($AA56,'💰 Payments'!$L$8:$L$67,0)))
AA57: =IFERROR(AGGREGATE(15,6,'💰 Payments'!$L$8:$L$67/(('💰 Payments'!$L$8:$L$67<>"")*('💰 Payments'!$K$8:$K$67>0)),16),"") | AB57: =IF($AA57="","",INDEX('💰 Payments'!$D$8:$D$67,MATCH($AA57,'💰 Payments'!$L$8:$L$67,0))&" ("&INDEX('💰 Payments'!$C$8:$C$67,MATCH($AA57,'💰 Payments'!$L$8:$L$67,0))&")") | AC57: =IF($AA57="","",INDEX('💰 Payments'!$K$8:$K$67,MATCH($AA57,'💰 Payments'!$L$8:$L$67,0)))
AA58: =IFERROR(AGGREGATE(15,6,'💰 Payments'!$L$8:$L$67/(('💰 Payments'!$L$8:$L$67<>"")*('💰 Payments'!$K$8:$K$67>0)),17),"") | AB58: =IF($AA58="","",INDEX('💰 Payments'!$D$8:$D$67,MATCH($AA58,'💰 Payments'!$L$8:$L$67,0))&" ("&INDEX('💰 Payments'!$C$8:$C$67,MATCH($AA58,'💰 Payments'!$L$8:$L$67,0))&")") | AC58: =IF($AA58="","",INDEX('💰 Payments'!$K$8:$K$67,MATCH($AA58,'💰 Payments'!$L$8:$L$67,0)))
AA59: =IFERROR(AGGREGATE(15,6,'💰 Payments'!$L$8:$L$67/(('💰 Payments'!$L$8:$L$67<>"")*('💰 Payments'!$K$8:$K$67>0)),18),"") | AB59: =IF($AA59="","",INDEX('💰 Payments'!$D$8:$D$67,MATCH($AA59,'💰 Payments'!$L$8:$L$67,0))&" ("&INDEX('💰 Payments'!$C$8:$C$67,MATCH($AA59,'💰 Payments'!$L$8:$L$67,0))&")") | AC59: =IF($AA59="","",INDEX('💰 Payments'!$K$8:$K$67,MATCH($AA59,'💰 Payments'!$L$8:$L$67,0)))
AA60: =IFERROR(AGGREGATE(15,6,'💰 Payments'!$L$8:$L$67/(('💰 Payments'!$L$8:$L$67<>"")*('💰 Payments'!$K$8:$K$67>0)),19),"") | AB60: =IF($AA60="","",INDEX('💰 Payments'!$D$8:$D$67,MATCH($AA60,'💰 Payments'!$L$8:$L$67,0))&" ("&INDEX('💰 Payments'!$C$8:$C$67,MATCH($AA60,'💰 Payments'!$L$8:$L$67,0))&")") | AC60: =IF($AA60="","",INDEX('💰 Payments'!$K$8:$K$67,MATCH($AA60,'💰 Payments'!$L$8:$L$67,0)))
AA61: =IFERROR(AGGREGATE(15,6,'💰 Payments'!$L$8:$L$67/(('💰 Payments'!$L$8:$L$67<>"")*('💰 Payments'!$K$8:$K$67>0)),20),"") | AB61: =IF($AA61="","",INDEX('💰 Payments'!$D$8:$D$67,MATCH($AA61,'💰 Payments'!$L$8:$L$67,0))&" ("&INDEX('💰 Payments'!$C$8:$C$67,MATCH($AA61,'💰 Payments'!$L$8:$L$67,0))&")") | AC61: =IF($AA61="","",INDEX('💰 Payments'!$K$8:$K$67,MATCH($AA61,'💰 Payments'!$L$8:$L$67,0)))
AA62: =IFERROR(AGGREGATE(15,6,'💰 Payments'!$L$8:$L$67/(('💰 Payments'!$L$8:$L$67<>"")*('💰 Payments'!$K$8:$K$67>0)),21),"") | AB62: =IF($AA62="","",INDEX('💰 Payments'!$D$8:$D$67,MATCH($AA62,'💰 Payments'!$L$8:$L$67,0))&" ("&INDEX('💰 Payments'!$C$8:$C$67,MATCH($AA62,'💰 Payments'!$L$8:$L$67,0))&")") | AC62: =IF($AA62="","",INDEX('💰 Payments'!$K$8:$K$67,MATCH($AA62,'💰 Payments'!$L$8:$L$67,0)))
AA63: =IFERROR(AGGREGATE(15,6,'💰 Payments'!$L$8:$L$67/(('💰 Payments'!$L$8:$L$67<>"")*('💰 Payments'!$K$8:$K$67>0)),22),"") | AB63: =IF($AA63="","",INDEX('💰 Payments'!$D$8:$D$67,MATCH($AA63,'💰 Payments'!$L$8:$L$67,0))&" ("&INDEX('💰 Payments'!$C$8:$C$67,MATCH($AA63,'💰 Payments'!$L$8:$L$67,0))&")") | AC63: =IF($AA63="","",INDEX('💰 Payments'!$K$8:$K$67,MATCH($AA63,'💰 Payments'!$L$8:$L$67,0)))
AA64: =IFERROR(AGGREGATE(15,6,'💰 Payments'!$L$8:$L$67/(('💰 Payments'!$L$8:$L$67<>"")*('💰 Payments'!$K$8:$K$67>0)),23),"") | AB64: =IF($AA64="","",INDEX('💰 Payments'!$D$8:$D$67,MATCH($AA64,'💰 Payments'!$L$8:$L$67,0))&" ("&INDEX('💰 Payments'!$C$8:$C$67,MATCH($AA64,'💰 Payments'!$L$8:$L$67,0))&")") | AC64: =IF($AA64="","",INDEX('💰 Payments'!$K$8:$K$67,MATCH($AA64,'💰 Payments'!$L$8:$L$67,0)))
AA65: =IFERROR(AGGREGATE(15,6,'💰 Payments'!$L$8:$L$67/(('💰 Payments'!$L$8:$L$67<>"")*('💰 Payments'!$K$8:$K$67>0)),24),"") | AB65: =IF($AA65="","",INDEX('💰 Payments'!$D$8:$D$67,MATCH($AA65,'💰 Payments'!$L$8:$L$67,0))&" ("&INDEX('💰 Payments'!$C$8:$C$67,MATCH($AA65,'💰 Payments'!$L$8:$L$67,0))&")") | AC65: =IF($AA65="","",INDEX('💰 Payments'!$K$8:$K$67,MATCH($AA65,'💰 Payments'!$L$8:$L$67,0)))
AA66: =IFERROR(AGGREGATE(15,6,'💰 Payments'!$L$8:$L$67/(('💰 Payments'!$L$8:$L$67<>"")*('💰 Payments'!$K$8:$K$67>0)),25),"") | AB66: =IF($AA66="","",INDEX('💰 Payments'!$D$8:$D$67,MATCH($AA66,'💰 Payments'!$L$8:$L$67,0))&" ("&INDEX('💰 Payments'!$C$8:$C$67,MATCH($AA66,'💰 Payments'!$L$8:$L$67,0))&")") | AC66: =IF($AA66="","",INDEX('💰 Payments'!$K$8:$K$67,MATCH($AA66,'💰 Payments'!$L$8:$L$67,0)))
AA67: =IFERROR(AGGREGATE(15,6,'💰 Payments'!$L$8:$L$67/(('💰 Payments'!$L$8:$L$67<>"")*('💰 Payments'!$K$8:$K$67>0)),26),"") | AB67: =IF($AA67="","",INDEX('💰 Payments'!$D$8:$D$67,MATCH($AA67,'💰 Payments'!$L$8:$L$67,0))&" ("&INDEX('💰 Payments'!$C$8:$C$67,MATCH($AA67,'💰 Payments'!$L$8:$L$67,0))&")") | AC67: =IF($AA67="","",INDEX('💰 Payments'!$K$8:$K$67,MATCH($AA67,'💰 Payments'!$L$8:$L$67,0)))
AA68: =IFERROR(AGGREGATE(15,6,'💰 Payments'!$L$8:$L$67/(('💰 Payments'!$L$8:$L$67<>"")*('💰 Payments'!$K$8:$K$67>0)),27),"") | AB68: =IF($AA68="","",INDEX('💰 Payments'!$D$8:$D$67,MATCH($AA68,'💰 Payments'!$L$8:$L$67,0))&" ("&INDEX('💰 Payments'!$C$8:$C$67,MATCH($AA68,'💰 Payments'!$L$8:$L$67,0))&")") | AC68: =IF($AA68="","",INDEX('💰 Payments'!$K$8:$K$67,MATCH($AA68,'💰 Payments'!$L$8:$L$67,0)))
AA69: =IFERROR(AGGREGATE(15,6,'💰 Payments'!$L$8:$L$67/(('💰 Payments'!$L$8:$L$67<>"")*('💰 Payments'!$K$8:$K$67>0)),28),"") | AB69: =IF($AA69="","",INDEX('💰 Payments'!$D$8:$D$67,MATCH($AA69,'💰 Payments'!$L$8:$L$67,0))&" ("&INDEX('💰 Payments'!$C$8:$C$67,MATCH($AA69,'💰 Payments'!$L$8:$L$67,0))&")") | AC69: =IF($AA69="","",INDEX('💰 Payments'!$K$8:$K$67,MATCH($AA69,'💰 Payments'!$L$8:$L$67,0)))
AA70: =IFERROR(AGGREGATE(15,6,'💰 Payments'!$L$8:$L$67/(('💰 Payments'!$L$8:$L$67<>"")*('💰 Payments'!$K$8:$K$67>0)),29),"") | AB70: =IF($AA70="","",INDEX('💰 Payments'!$D$8:$D$67,MATCH($AA70,'💰 Payments'!$L$8:$L$67,0))&" ("&INDEX('💰 Payments'!$C$8:$C$67,MATCH($AA70,'💰 Payments'!$L$8:$L$67,0))&")") | AC70: =IF($AA70="","",INDEX('💰 Payments'!$K$8:$K$67,MATCH($AA70,'💰 Payments'!$L$8:$L$67,0)))
AA71: =IFERROR(AGGREGATE(15,6,'💰 Payments'!$L$8:$L$67/(('💰 Payments'!$L$8:$L$67<>"")*('💰 Payments'!$K$8:$K$67>0)),30),"") | AB71: =IF($AA71="","",INDEX('💰 Payments'!$D$8:$D$67,MATCH($AA71,'💰 Payments'!$L$8:$L$67,0))&" ("&INDEX('💰 Payments'!$C$8:$C$67,MATCH($AA71,'💰 Payments'!$L$8:$L$67,0))&")") | AC71: =IF($AA71="","",INDEX('💰 Payments'!$K$8:$K$67,MATCH($AA71,'💰 Payments'!$L$8:$L$67,0)))
AA72: =IFERROR(AGGREGATE(15,6,'💰 Payments'!$L$8:$L$67/(('💰 Payments'!$L$8:$L$67<>"")*('💰 Payments'!$K$8:$K$67>0)),31),"") | AB72: =IF($AA72="","",INDEX('💰 Payments'!$D$8:$D$67,MATCH($AA72,'💰 Payments'!$L$8:$L$67,0))&" ("&INDEX('💰 Payments'!$C$8:$C$67,MATCH($AA72,'💰 Payments'!$L$8:$L$67,0))&")") | AC72: =IF($AA72="","",INDEX('💰 Payments'!$K$8:$K$67,MATCH($AA72,'💰 Payments'!$L$8:$L$67,0)))
AA73: =IFERROR(AGGREGATE(15,6,'💰 Payments'!$L$8:$L$67/(('💰 Payments'!$L$8:$L$67<>"")*('💰 Payments'!$K$8:$K$67>0)),32),"") | AB73: =IF($AA73="","",INDEX('💰 Payments'!$D$8:$D$67,MATCH($AA73,'💰 Payments'!$L$8:$L$67,0))&" ("&INDEX('💰 Payments'!$C$8:$C$67,MATCH($AA73,'💰 Payments'!$L$8:$L$67,0))&")") | AC73: =IF($AA73="","",INDEX('💰 Payments'!$K$8:$K$67,MATCH($AA73,'💰 Payments'!$L$8:$L$67,0)))
AA74: =IFERROR(AGGREGATE(15,6,'💰 Payments'!$L$8:$L$67/(('💰 Payments'!$L$8:$L$67<>"")*('💰 Payments'!$K$8:$K$67>0)),33),"") | AB74: =IF($AA74="","",INDEX('💰 Payments'!$D$8:$D$67,MATCH($AA74,'💰 Payments'!$L$8:$L$67,0))&" ("&INDEX('💰 Payments'!$C$8:$C$67,MATCH($AA74,'💰 Payments'!$L$8:$L$67,0))&")") | AC74: =IF($AA74="","",INDEX('💰 Payments'!$K$8:$K$67,MATCH($AA74,'💰 Payments'!$L$8:$L$67,0)))
AA75: =IFERROR(AGGREGATE(15,6,'💰 Payments'!$L$8:$L$67/(('💰 Payments'!$L$8:$L$67<>"")*('💰 Payments'!$K$8:$K$67>0)),34),"") | AB75: =IF($AA75="","",INDEX('💰 Payments'!$D$8:$D$67,MATCH($AA75,'💰 Payments'!$L$8:$L$67,0))&" ("&INDEX('💰 Payments'!$C$8:$C$67,MATCH($AA75,'💰 Payments'!$L$8:$L$67,0))&")") | AC75: =IF($AA75="","",INDEX('💰 Payments'!$K$8:$K$67,MATCH($AA75,'💰 Payments'!$L$8:$L$67,0)))
AA76: =IFERROR(AGGREGATE(15,6,'💰 Payments'!$L$8:$L$67/(('💰 Payments'!$L$8:$L$67<>"")*('💰 Payments'!$K$8:$K$67>0)),35),"") | AB76: =IF($AA76="","",INDEX('💰 Payments'!$D$8:$D$67,MATCH($AA76,'💰 Payments'!$L$8:$L$67,0))&" ("&INDEX('💰 Payments'!$C$8:$C$67,MATCH($AA76,'💰 Payments'!$L$8:$L$67,0))&")") | AC76: =IF($AA76="","",INDEX('💰 Payments'!$K$8:$K$67,MATCH($AA76,'💰 Payments'!$L$8:$L$67,0)))
AA77: =IFERROR(AGGREGATE(15,6,'💰 Payments'!$L$8:$L$67/(('💰 Payments'!$L$8:$L$67<>"")*('💰 Payments'!$K$8:$K$67>0)),36),"") | AB77: =IF($AA77="","",INDEX('💰 Payments'!$D$8:$D$67,MATCH($AA77,'💰 Payments'!$L$8:$L$67,0))&" ("&INDEX('💰 Payments'!$C$8:$C$67,MATCH($AA77,'💰 Payments'!$L$8:$L$67,0))&")") | AC77: =IF($AA77="","",INDEX('💰 Payments'!$K$8:$K$67,MATCH($AA77,'💰 Payments'!$L$8:$L$67,0)))
AA78: =IFERROR(AGGREGATE(15,6,'💰 Payments'!$L$8:$L$67/(('💰 Payments'!$L$8:$L$67<>"")*('💰 Payments'!$K$8:$K$67>0)),37),"") | AB78: =IF($AA78="","",INDEX('💰 Payments'!$D$8:$D$67,MATCH($AA78,'💰 Payments'!$L$8:$L$67,0))&" ("&INDEX('💰 Payments'!$C$8:$C$67,MATCH($AA78,'💰 Payments'!$L$8:$L$67,0))&")") | AC78: =IF($AA78="","",INDEX('💰 Payments'!$K$8:$K$67,MATCH($AA78,'💰 Payments'!$L$8:$L$67,0)))
AA79: =IFERROR(AGGREGATE(15,6,'💰 Payments'!$L$8:$L$67/(('💰 Payments'!$L$8:$L$67<>"")*('💰 Payments'!$K$8:$K$67>0)),38),"") | AB79: =IF($AA79="","",INDEX('💰 Payments'!$D$8:$D$67,MATCH($AA79,'💰 Payments'!$L$8:$L$67,0))&" ("&INDEX('💰 Payments'!$C$8:$C$67,MATCH($AA79,'💰 Payments'!$L$8:$L$67,0))&")") | AC79: =IF($AA79="","",INDEX('💰 Payments'!$K$8:$K$67,MATCH($AA79,'💰 Payments'!$L$8:$L$67,0)))
AA80: =IFERROR(AGGREGATE(15,6,'💰 Payments'!$L$8:$L$67/(('💰 Payments'!$L$8:$L$67<>"")*('💰 Payments'!$K$8:$K$67>0)),39),"") | AB80: =IF($AA80="","",INDEX('💰 Payments'!$D$8:$D$67,MATCH($AA80,'💰 Payments'!$L$8:$L$67,0))&" ("&INDEX('💰 Payments'!$C$8:$C$67,MATCH($AA80,'💰 Payments'!$L$8:$L$67,0))&")") | AC80: =IF($AA80="","",INDEX('💰 Payments'!$K$8:$K$67,MATCH($AA80,'💰 Payments'!$L$8:$L$67,0)))
AA81: =IFERROR(AGGREGATE(15,6,'💰 Payments'!$L$8:$L$67/(('💰 Payments'!$L$8:$L$67<>"")*('💰 Payments'!$K$8:$K$67>0)),40),"") | AB81: =IF($AA81="","",INDEX('💰 Payments'!$D$8:$D$67,MATCH($AA81,'💰 Payments'!$L$8:$L$67,0))&" ("&INDEX('💰 Payments'!$C$8:$C$67,MATCH($AA81,'💰 Payments'!$L$8:$L$67,0))&")") | AC81: =IF($AA81="","",INDEX('💰 Payments'!$K$8:$K$67,MATCH($AA81,'💰 Payments'!$L$8:$L$67,0)))
AA82: =IFERROR(AGGREGATE(15,6,'💰 Payments'!$L$8:$L$67/(('💰 Payments'!$L$8:$L$67<>"")*('💰 Payments'!$K$8:$K$67>0)),41),"") | AB82: =IF($AA82="","",INDEX('💰 Payments'!$D$8:$D$67,MATCH($AA82,'💰 Payments'!$L$8:$L$67,0))&" ("&INDEX('💰 Payments'!$C$8:$C$67,MATCH($AA82,'💰 Payments'!$L$8:$L$67,0))&")") | AC82: =IF($AA82="","",INDEX('💰 Payments'!$K$8:$K$67,MATCH($AA82,'💰 Payments'!$L$8:$L$67,0)))
AA83: =IFERROR(AGGREGATE(15,6,'💰 Payments'!$L$8:$L$67/(('💰 Payments'!$L$8:$L$67<>"")*('💰 Payments'!$K$8:$K$67>0)),42),"") | AB83: =IF($AA83="","",INDEX('💰 Payments'!$D$8:$D$67,MATCH($AA83,'💰 Payments'!$L$8:$L$67,0))&" ("&INDEX('💰 Payments'!$C$8:$C$67,MATCH($AA83,'💰 Payments'!$L$8:$L$67,0))&")") | AC83: =IF($AA83="","",INDEX('💰 Payments'!$K$8:$K$67,MATCH($AA83,'💰 Payments'!$L$8:$L$67,0)))
AA84: =IFERROR(AGGREGATE(15,6,'💰 Payments'!$L$8:$L$67/(('💰 Payments'!$L$8:$L$67<>"")*('💰 Payments'!$K$8:$K$67>0)),43),"") | AB84: =IF($AA84="","",INDEX('💰 Payments'!$D$8:$D$67,MATCH($AA84,'💰 Payments'!$L$8:$L$67,0))&" ("&INDEX('💰 Payments'!$C$8:$C$67,MATCH($AA84,'💰 Payments'!$L$8:$L$67,0))&")") | AC84: =IF($AA84="","",INDEX('💰 Payments'!$K$8:$K$67,MATCH($AA84,'💰 Payments'!$L$8:$L$67,0)))
AA85: =IFERROR(AGGREGATE(15,6,'💰 Payments'!$L$8:$L$67/(('💰 Payments'!$L$8:$L$67<>"")*('💰 Payments'!$K$8:$K$67>0)),44),"") | AB85: =IF($AA85="","",INDEX('💰 Payments'!$D$8:$D$67,MATCH($AA85,'💰 Payments'!$L$8:$L$67,0))&" ("&INDEX('💰 Payments'!$C$8:$C$67,MATCH($AA85,'💰 Payments'!$L$8:$L$67,0))&")") | AC85: =IF($AA85="","",INDEX('💰 Payments'!$K$8:$K$67,MATCH($AA85,'💰 Payments'!$L$8:$L$67,0)))
AA86: =IFERROR(AGGREGATE(15,6,'💰 Payments'!$L$8:$L$67/(('💰 Payments'!$L$8:$L$67<>"")*('💰 Payments'!$K$8:$K$67>0)),45),"") | AB86: =IF($AA86="","",INDEX('💰 Payments'!$D$8:$D$67,MATCH($AA86,'💰 Payments'!$L$8:$L$67,0))&" ("&INDEX('💰 Payments'!$C$8:$C$67,MATCH($AA86,'💰 Payments'!$L$8:$L$67,0))&")") | AC86: =IF($AA86="","",INDEX('💰 Payments'!$K$8:$K$67,MATCH($AA86,'💰 Payments'!$L$8:$L$67,0)))
AA87: =IFERROR(AGGREGATE(15,6,'💰 Payments'!$L$8:$L$67/(('💰 Payments'!$L$8:$L$67<>"")*('💰 Payments'!$K$8:$K$67>0)),46),"") | AB87: =IF($AA87="","",INDEX('💰 Payments'!$D$8:$D$67,MATCH($AA87,'💰 Payments'!$L$8:$L$67,0))&" ("&INDEX('💰 Payments'!$C$8:$C$67,MATCH($AA87,'💰 Payments'!$L$8:$L$67,0))&")") | AC87: =IF($AA87="","",INDEX('💰 Payments'!$K$8:$K$67,MATCH($AA87,'💰 Payments'!$L$8:$L$67,0)))
AA88: =IFERROR(AGGREGATE(15,6,'💰 Payments'!$L$8:$L$67/(('💰 Payments'!$L$8:$L$67<>"")*('💰 Payments'!$K$8:$K$67>0)),47),"") | AB88: =IF($AA88="","",INDEX('💰 Payments'!$D$8:$D$67,MATCH($AA88,'💰 Payments'!$L$8:$L$67,0))&" ("&INDEX('💰 Payments'!$C$8:$C$67,MATCH($AA88,'💰 Payments'!$L$8:$L$67,0))&")") | AC88: =IF($AA88="","",INDEX('💰 Payments'!$K$8:$K$67,MATCH($AA88,'💰 Payments'!$L$8:$L$67,0)))
AA89: =IFERROR(AGGREGATE(15,6,'💰 Payments'!$L$8:$L$67/(('💰 Payments'!$L$8:$L$67<>"")*('💰 Payments'!$K$8:$K$67>0)),48),"") | AB89: =IF($AA89="","",INDEX('💰 Payments'!$D$8:$D$67,MATCH($AA89,'💰 Payments'!$L$8:$L$67,0))&" ("&INDEX('💰 Payments'!$C$8:$C$67,MATCH($AA89,'💰 Payments'!$L$8:$L$67,0))&")") | AC89: =IF($AA89="","",INDEX('💰 Payments'!$K$8:$K$67,MATCH($AA89,'💰 Payments'!$L$8:$L$67,0)))
AA90: =IFERROR(AGGREGATE(15,6,'💰 Payments'!$L$8:$L$67/(('💰 Payments'!$L$8:$L$67<>"")*('💰 Payments'!$K$8:$K$67>0)),49),"") | AB90: =IF($AA90="","",INDEX('💰 Payments'!$D$8:$D$67,MATCH($AA90,'💰 Payments'!$L$8:$L$67,0))&" ("&INDEX('💰 Payments'!$C$8:$C$67,MATCH($AA90,'💰 Payments'!$L$8:$L$67,0))&")") | AC90: =IF($AA90="","",INDEX('💰 Payments'!$K$8:$K$67,MATCH($AA90,'💰 Payments'!$L$8:$L$67,0)))
AA91: =IFERROR(AGGREGATE(15,6,'💰 Payments'!$L$8:$L$67/(('💰 Payments'!$L$8:$L$67<>"")*('💰 Payments'!$K$8:$K$67>0)),50),"") | AB91: =IF($AA91="","",INDEX('💰 Payments'!$D$8:$D$67,MATCH($AA91,'💰 Payments'!$L$8:$L$67,0))&" ("&INDEX('💰 Payments'!$C$8:$C$67,MATCH($AA91,'💰 Payments'!$L$8:$L$67,0))&")") | AC91: =IF($AA91="","",INDEX('💰 Payments'!$K$8:$K$67,MATCH($AA91,'💰 Payments'!$L$8:$L$67,0)))
AA92: =IFERROR(AGGREGATE(15,6,'💰 Payments'!$L$8:$L$67/(('💰 Payments'!$L$8:$L$67<>"")*('💰 Payments'!$K$8:$K$67>0)),51),"") | AB92: =IF($AA92="","",INDEX('💰 Payments'!$D$8:$D$67,MATCH($AA92,'💰 Payments'!$L$8:$L$67,0))&" ("&INDEX('💰 Payments'!$C$8:$C$67,MATCH($AA92,'💰 Payments'!$L$8:$L$67,0))&")") | AC92: =IF($AA92="","",INDEX('💰 Payments'!$K$8:$K$67,MATCH($AA92,'💰 Payments'!$L$8:$L$67,0)))
AA93: =IFERROR(AGGREGATE(15,6,'💰 Payments'!$L$8:$L$67/(('💰 Payments'!$L$8:$L$67<>"")*('💰 Payments'!$K$8:$K$67>0)),52),"") | AB93: =IF($AA93="","",INDEX('💰 Payments'!$D$8:$D$67,MATCH($AA93,'💰 Payments'!$L$8:$L$67,0))&" ("&INDEX('💰 Payments'!$C$8:$C$67,MATCH($AA93,'💰 Payments'!$L$8:$L$67,0))&")") | AC93: =IF($AA93="","",INDEX('💰 Payments'!$K$8:$K$67,MATCH($AA93,'💰 Payments'!$L$8:$L$67,0)))
AA94: =IFERROR(AGGREGATE(15,6,'💰 Payments'!$L$8:$L$67/(('💰 Payments'!$L$8:$L$67<>"")*('💰 Payments'!$K$8:$K$67>0)),53),"") | AB94: =IF($AA94="","",INDEX('💰 Payments'!$D$8:$D$67,MATCH($AA94,'💰 Payments'!$L$8:$L$67,0))&" ("&INDEX('💰 Payments'!$C$8:$C$67,MATCH($AA94,'💰 Payments'!$L$8:$L$67,0))&")") | AC94: =IF($AA94="","",INDEX('💰 Payments'!$K$8:$K$67,MATCH($AA94,'💰 Payments'!$L$8:$L$67,0)))
AA95: =IFERROR(AGGREGATE(15,6,'💰 Payments'!$L$8:$L$67/(('💰 Payments'!$L$8:$L$67<>"")*('💰 Payments'!$K$8:$K$67>0)),54),"") | AB95: =IF($AA95="","",INDEX('💰 Payments'!$D$8:$D$67,MATCH($AA95,'💰 Payments'!$L$8:$L$67,0))&" ("&INDEX('💰 Payments'!$C$8:$C$67,MATCH($AA95,'💰 Payments'!$L$8:$L$67,0))&")") | AC95: =IF($AA95="","",INDEX('💰 Payments'!$K$8:$K$67,MATCH($AA95,'💰 Payments'!$L$8:$L$67,0)))
AA96: =IFERROR(AGGREGATE(15,6,'💰 Payments'!$L$8:$L$67/(('💰 Payments'!$L$8:$L$67<>"")*('💰 Payments'!$K$8:$K$67>0)),55),"") | AB96: =IF($AA96="","",INDEX('💰 Payments'!$D$8:$D$67,MATCH($AA96,'💰 Payments'!$L$8:$L$67,0))&" ("&INDEX('💰 Payments'!$C$8:$C$67,MATCH($AA96,'💰 Payments'!$L$8:$L$67,0))&")") | AC96: =IF($AA96="","",INDEX('💰 Payments'!$K$8:$K$67,MATCH($AA96,'💰 Payments'!$L$8:$L$67,0)))
AA97: =IFERROR(AGGREGATE(15,6,'💰 Payments'!$L$8:$L$67/(('💰 Payments'!$L$8:$L$67<>"")*('💰 Payments'!$K$8:$K$67>0)),56),"") | AB97: =IF($AA97="","",INDEX('💰 Payments'!$D$8:$D$67,MATCH($AA97,'💰 Payments'!$L$8:$L$67,0))&" ("&INDEX('💰 Payments'!$C$8:$C$67,MATCH($AA97,'💰 Payments'!$L$8:$L$67,0))&")") | AC97: =IF($AA97="","",INDEX('💰 Payments'!$K$8:$K$67,MATCH($AA97,'💰 Payments'!$L$8:$L$67,0)))
AA98: =IFERROR(AGGREGATE(15,6,'💰 Payments'!$L$8:$L$67/(('💰 Payments'!$L$8:$L$67<>"")*('💰 Payments'!$K$8:$K$67>0)),57),"") | AB98: =IF($AA98="","",INDEX('💰 Payments'!$D$8:$D$67,MATCH($AA98,'💰 Payments'!$L$8:$L$67,0))&" ("&INDEX('💰 Payments'!$C$8:$C$67,MATCH($AA98,'💰 Payments'!$L$8:$L$67,0))&")") | AC98: =IF($AA98="","",INDEX('💰 Payments'!$K$8:$K$67,MATCH($AA98,'💰 Payments'!$L$8:$L$67,0)))
AA99: =IFERROR(AGGREGATE(15,6,'💰 Payments'!$L$8:$L$67/(('💰 Payments'!$L$8:$L$67<>"")*('💰 Payments'!$K$8:$K$67>0)),58),"") | AB99: =IF($AA99="","",INDEX('💰 Payments'!$D$8:$D$67,MATCH($AA99,'💰 Payments'!$L$8:$L$67,0))&" ("&INDEX('💰 Payments'!$C$8:$C$67,MATCH($AA99,'💰 Payments'!$L$8:$L$67,0))&")") | AC99: =IF($AA99="","",INDEX('💰 Payments'!$K$8:$K$67,MATCH($AA99,'💰 Payments'!$L$8:$L$67,0)))
AA100: =IFERROR(AGGREGATE(15,6,'💰 Payments'!$L$8:$L$67/(('💰 Payments'!$L$8:$L$67<>"")*('💰 Payments'!$K$8:$K$67>0)),59),"") | AB100: =IF($AA100="","",INDEX('💰 Payments'!$D$8:$D$67,MATCH($AA100,'💰 Payments'!$L$8:$L$67,0))&" ("&INDEX('💰 Payments'!$C$8:$C$67,MATCH($AA100,'💰 Payments'!$L$8:$L$67,0))&")") | AC100: =IF($AA100="","",INDEX('💰 Payments'!$K$8:$K$67,MATCH($AA100,'💰 Payments'!$L$8:$L$67,0)))
...

Sheet ⚙️ Setup
B2: Settings & lists
B3: Set up once - every tab reads from here | G3: 🏠 Back to Dashboard
B5: 1 · Your business
B6: Business name | H6: Shown on the Dashboard and the Invoice tab.
B7: Dashboard note | H7: A little reminder for the team - shown under the Dashboard title.
B9: 2 · Money settings
B10: Currency symbol | C10: $ | H10: Pick from the dropdown, or type your own symbol.
B11: Sales tax / VAT rate | C11: 0 | H11: Applied on the Invoice tab and in the Tax Tracker.
B12: Target profit margin | C12: 0.35 | H12: The Quote Calculator prices events to hit this.
B13: Deposit to confirm | C13: 0.4 | H13: Suggested deposit share of the total price.
B14: “Due soon” window (days) | C14: 7 | H14: Dates inside this window glow amber on every tab.
B15: Report year | C15: 2026 | H15: Drives the P&L and the Tax Tracker.
B17: 3 · Calendar
B18: Month to show | C18: 9 | H18: The Event Calendar tab shows this month (1 = January ... 12 = December).
B19: Year to show | C19: 2026
B21: 4 · Your dropdown lists (edit freely)
A22: Event types | B22: Expense categories | C22: Payment methods | D22: Staff roles | E22: Menu categories | F22: Ingredient categories
A23: Wedding | B23: Ingredients | C23: Cash | D23: Head Chef | E23: Starter | F23: Produce
A24: Corporate | B24: Packaging | C24: Bank Transfer | D24: Chef | E24: Main | F24: Meat & Fish
A25: Birthday | B25: Staff / Labor | C25: Card | D25: Sous Chef | E25: Dessert | F25: Dairy
A26: Private Party | B26: Transportation | C26: Cheque | D26: Server | E26: Sides | F26: Pantry
A27: Buffet | B27: Equipment | C27: Mobile Wallet | D27: Bartender | E27: Beverage | F27: Bakery
A28: Cocktail | B28: Kitchen Rental | C28: Other | D28: Driver | E28: Canapé | F28: Beverages
A29: Conference | B29: Marketing | D29: Setup Crew | E29: Other | F29: Packaging
A30: Festival | B30: Insurance | D30: Cleaner | F30: Other
A31: Other | B31: Utilities | D31: Manager
B32: Software | D32: Other
B33: Miscellaneous
B44: 5 · Fixed lists (the status formulas depend on these exact texts - locked)
B46: Event statuses | C46: Payment statuses | D46: Tick
B47: 💬 Inquiry | C47: 🔴 Unpaid | D47: ✓
B48: 📝 Quote Sent | C48: 🟠 Partial
B49: 💰 Deposit Paid | C49: 🟢 Paid in full
B50: ✅ Confirmed
B51: 🎉 Completed
B52: ❌ Cancelled
B56: Tip: empty rows in a list simply don't appear in the dropdowns. Add options at the bottom of a column and they show up everywhere, instantly.
B58: ▶ Setup | C58: 🏠 Home | D58: Clients | E58: Events | F58: Quote | G58: Menu | H58: Stock
B59: Shop | C59: Expenses | D59: Payments | E59: Staff | F59: Equip | G59: Suppliers | H59: Calendar
B60: P&L | C60: Tax | D60: Checks | E60: Invoice | F60: Help

Sheet 📊 Dashboard
B2: =IF(BusinessName="","Your Catering Business",BusinessName) -> Your Catering Business | K2: ="Cash in "&Currency&TEXT('_Data'!$AF$2,"#,##0") -> Cash in 0
B3: =IF('⚙️ Setup'!$C$7="","Events • Clients • Quotes • Food Cost • Profit",'⚙️ Setup'!$C$7) -> Events • Clients • Quotes • Food Cost • Profit
B5: CASH IN | F5: CASH OUT | J5: NET PROFIT | N5: NET MARGIN
B6: ='_Data'!$AF$2 -> 0 | F6: ='_Data'!$AF$3 -> 0 | J6: ='_Data'!$AF$4 -> 0 | N6: ='_Data'!$AF$5 -> 0
B8: EVENTS ON THE BOOKS | F8: CONFIRMED & COMING UP | J8: OUTSTANDING | N8: OVERDUE INVOICES
B9: =SUMPRODUCT(('📅 Events'!$Q$8:$Q$47<>"")*('📅 Events'!$Q$8:$Q$47<>"❌ Cancelled")) -> 0 | F9: ='_Data'!$AF$8 -> 0 | J9: ='_Data'!$AF$14 -> 0 | N9: ='_Data'!$AF$15 -> 0
B11: FOOD COST % | F11: LABOR % | J11: AVG ORDER VALUE | N11: GUESTS SERVED
B12: ='_Data'!$AF$19 -> 0 | F12: ='_Data'!$AF$20 -> 0 | J12: ='_Data'!$AF$10 -> 0 | N12: ='_Data'!$AF$13 -> 0
B14: INVENTORY VALUE | F14: LOW STOCK | J14: SHOPPING TO BUY | N14: UNPAID SHIFTS
B15: ='_Data'!$AF$22 -> 0 | F15: ='_Data'!$AF$23 -> 0 | J15: ='_Data'!$AF$24&" lines · "&Currency&TEXT('_Data'!$AF$25,"#,##0") -> 0 lines | N15: ='_Data'!$AF$26 -> 0
B18: How the season is going
B19: Collected vs invoiced | E19: =IFERROR(REPT("█",ROUND(MIN(1,IFERROR(('_Data'!$AF$2)/(SUM('💰 Payments'!$F$8:$F$67)),0))*18,0))&REPT("░",18-ROUND(MIN(1,IFERROR(('_Data'!$AF$2)/(SUM('💰 Payments'!$F$8:$F$67)),0))*18,0)),"░░░░░░░░░░░░░░░░░░") -> ░░░░░░░░░░░░░░░░░░ | M19: =IFERROR(TEXT(MIN(1,'_Data'!$AF$2/(SUM('💰 Payments'!$F$8:$F$67))),"0%"),"0%") -> 0%
B20: Costs vs cash in | E20: =IFERROR(REPT("█",ROUND(MIN(1,IFERROR((SUM('💸 Expenses'!$G$8:$G$67))/('_Data'!$AF$2),0))*18,0))&REPT("░",18-ROUND(MIN(1,IFERROR((SUM('💸 Expenses'!$G$8:$G$67))/('_Data'!$AF$2),0))*18,0)),"░░░░░░░░░░░░░░░░░░") -> ░░░░░░░░░░░░░░░░░░ | M20: =IFERROR(TEXT(MIN(1,SUM('💸 Expenses'!$G$8:$G$67)/('_Data'!$AF$2)),"0%"),"0%") -> 0%
B23: The picture
B67: Every number on this page updates itself from the other tabs - nothing here is typed by hand.
B69: Setup | E69: ▶ 🏠 Home | H69: Clients | K69: Events | N69: Quote
B70: Menu | E70: Stock | H70: Shop | K70: Expenses | N70: Payments
B71: Staff | E71: Equip | H71: Suppliers | K71: Calendar | N71: P&L
B72: Tax | E72: Checks | H72: Invoice | K72: Help

Sheet 👥 Clients
B2: Clients
B3: Everyone you cook for - balances and history in one place | M3: 🏠 Back to Dashboard
B5: ="Clients: "&COUNTA('👥 Clients'!$C$8:$C$47) -> Clients: 0 | D5: ="Repeat rate: "&TEXT('_Data'!$AF$21,"0%") -> Repeat rate: 0% | F5: ="Quotes out: "&Currency&TEXT(SUM('👥 Clients'!$K$8:$K$47),"#,##0") -> Quotes out: $0 | H5: ="Still owed: "&Currency&TEXT('_Data'!$AF$14,"#,##0") -> Still owed: $0
B7: # | C7: Client / company | D7: Phone | E7: Email | F7: Next event | G7: Event type | H7: Guests | I7: Venue / address | J7: Package | K7: Quoted | L7: Deposit | M7: Balance due | N7: Payment status | O7: Notes
B8: =IF($C8="","",ROW()-7) | M8: =IF(OR($K8="",$L8=""),"",ROUND($K8-$L8,2))
B9: =IF($C9="","",ROW()-7) | M9: =IF(OR($K9="",$L9=""),"",ROUND($K9-$L9,2))
B10: =IF($C10="","",ROW()-7) | M10: =IF(OR($K10="",$L10=""),"",ROUND($K10-$L10,2))
B11: =IF($C11="","",ROW()-7) | M11: =IF(OR($K11="",$L11=""),"",ROUND($K11-$L11,2))
B12: =IF($C12="","",ROW()-7) | M12: =IF(OR($K12="",$L12=""),"",ROUND($K12-$L12,2))
B13: =IF($C13="","",ROW()-7) | M13: =IF(OR($K13="",$L13=""),"",ROUND($K13-$L13,2))
B14: =IF($C14="","",ROW()-7) | M14: =IF(OR($K14="",$L14=""),"",ROUND($K14-$L14,2))
B15: =IF($C15="","",ROW()-7) | M15: =IF(OR($K15="",$L15=""),"",ROUND($K15-$L15,2))
B16: =IF($C16="","",ROW()-7) | M16: =IF(OR($K16="",$L16=""),"",ROUND($K16-$L16,2))
B17: =IF($C17="","",ROW()-7) | M17: =IF(OR($K17="",$L17=""),"",ROUND($K17-$L17,2))
B18: =IF($C18="","",ROW()-7) | M18: =IF(OR($K18="",$L18=""),"",ROUND($K18-$L18,2))
B19: =IF($C19="","",ROW()-7) | M19: =IF(OR($K19="",$L19=""),"",ROUND($K19-$L19,2))
... B47: =IF($C47="","",ROW()-7) | M47: =IF(OR($K47="",$L47=""),"",ROUND($K47-$L47,2))
B48: TOTALS | H48: =SUM('👥 Clients'!$H$8:$H$47) -> 0 | K48: =SUM('👥 Clients'!$K$8:$K$47) -> 0 | L48: =SUM('👥 Clients'!$L$8:$L$47) -> 0 | M48: =SUM('👥 Clients'!$K$8:$K$47)-SUM('👥 Clients'!$L$8:$L$47) -> 0
B50: How this tab works
B51: The Balance due column calculates itself (quote minus deposit) - type over the white cells only. Payment status drives the colours here and the receivables cards on the Dashboard.
B55: Setup | D55: 🏠 Home | F55: ▶ Clients | H55: Events | J55: Quote | L55: Menu | N55: Stock
B56: Shop | D56: Expenses | F56: Payments | H56: Staff | J56: Equip | L56: Suppliers | N56: Calendar
B57: P&L | D57: Tax | F57: Checks | H57: Invoice | J57: Help

Sheet 📅 Events
B2: Events
B3: Every booking - costs, pricing and profit per event | P3: 🏠 Back to Dashboard
B5: ="Bookings: "&SUMPRODUCT(('📅 Events'!$Q$8:$Q$47<>"")*('📅 Events'!$Q$8:$Q$47<>"❌ Cancelled")) -> Bookings: 0 | D5: ="In the pipeline: "&COUNTIF('📅 Events'!$Q$8:$Q$47,"📝 Quote Sent") + COUNTIF('📅 Events'!$Q$8:$Q$47,"💰 Deposit Paid") + COUNTIF('📅 Events'!$Q$8:$Q$47,"✅ Confirmed") + COUNTIF('📅 Events'!$Q$8:$Q$47,"🎉 Completed") -> In the pipeline: 0 | F5: ="Booked value: "&Currency&TEXT(SUMPRODUCT(('📅 Events'!$Q$8:$Q$47<>"❌ Cancelled")*'📅 Events'!$L$8:$L$47),"#,##0") -> Booked value: $0 | H5: ="Expected profit: "&Currency&TEXT(SUMPRODUCT(('📅 Events'!$Q$8:$Q$47<>"❌ Cancelled")*'📅 Events'!$L$8:$L$47)-SUMPRODUCT(('📅 Events'!$Q$8:$Q$47<>"❌ Cancelled")*'📅 Events'!$K$8:$K$47),"#,##0") -> Expected profit: $0
B7: # | C7: Event ID | D7: Client | E7: Date | F7: Type | G7: Guests | H7: Menu / dishes | I7: Crew | J7: Equipment needed | K7: Cost | L7: Price | M7: Profit | N7: Margin | O7: Deposit | P7: Balance | Q7: Status | R7: Notes
B8: =IF($C8="","",ROW()-7) | M8: =IF(OR($K8="",$L8=""),"",ROUND($L8-$K8,2)) | N8: =IFERROR(IF($M8="","",$M8/$L8),"") | P8: =IF($L8="","",ROUND($L8-$O8,2))
B9: =IF($C9="","",ROW()-7) | M9: =IF(OR($K9="",$L9=""),"",ROUND($L9-$K9,2)) | N9: =IFERROR(IF($M9="","",$M9/$L9),"") | P9: =IF($L9="","",ROUND($L9-$O9,2))
B10: =IF($C10="","",ROW()-7) | M10: =IF(OR($K10="",$L10=""),"",ROUND($L10-$K10,2)) | N10: =IFERROR(IF($M10="","",$M10/$L10),"") | P10: =IF($L10="","",ROUND($L10-$O10,2))
B11: =IF($C11="","",ROW()-7) | M11: =IF(OR($K11="",$L11=""),"",ROUND($L11-$K11,2)) | N11: =IFERROR(IF($M11="","",$M11/$L11),"") | P11: =IF($L11="","",ROUND($L11-$O11,2))
B12: =IF($C12="","",ROW()-7) | M12: =IF(OR($K12="",$L12=""),"",ROUND($L12-$K12,2)) | N12: =IFERROR(IF($M12="","",$M12/$L12),"") | P12: =IF($L12="","",ROUND($L12-$O12,2))
B13: =IF($C13="","",ROW()-7) | M13: =IF(OR($K13="",$L13=""),"",ROUND($L13-$K13,2)) | N13: =IFERROR(IF($M13="","",$M13/$L13),"") | P13: =IF($L13="","",ROUND($L13-$O13,2))
B14: =IF($C14="","",ROW()-7) | M14: =IF(OR($K14="",$L14=""),"",ROUND($L14-$K14,2)) | N14: =IFERROR(IF($M14="","",$M14/$L14),"") | P14: =IF($L14="","",ROUND($L14-$O14,2))
B15: =IF($C15="","",ROW()-7) | M15: =IF(OR($K15="",$L15=""),"",ROUND($L15-$K15,2)) | N15: =IFERROR(IF($M15="","",$M15/$L15),"") | P15: =IF($L15="","",ROUND($L15-$O15,2))
B16: =IF($C16="","",ROW()-7) | M16: =IF(OR($K16="",$L16=""),"",ROUND($L16-$K16,2)) | N16: =IFERROR(IF($M16="","",$M16/$L16),"") | P16: =IF($L16="","",ROUND($L16-$O16,2))
B17: =IF($C17="","",ROW()-7) | M17: =IF(OR($K17="",$L17=""),"",ROUND($L17-$K17,2)) | N17: =IFERROR(IF($M17="","",$M17/$L17),"") | P17: =IF($L17="","",ROUND($L17-$O17,2))
B18: =IF($C18="","",ROW()-7) | M18: =IF(OR($K18="",$L18=""),"",ROUND($L18-$K18,2)) | N18: =IFERROR(IF($M18="","",$M18/$L18),"") | P18: =IF($L18="","",ROUND($L18-$O18,2))
B19: =IF($C19="","",ROW()-7) | M19: =IF(OR($K19="",$L19=""),"",ROUND($L19-$K19,2)) | N19: =IFERROR(IF($M19="","",$M19/$L19),"") | P19: =IF($L19="","",ROUND($L19-$O19,2))
... B47: =IF($C47="","",ROW()-7) | M47: =IF(OR($K47="",$L47=""),"",ROUND($L47-$K47,2)) | N47: =IFERROR(IF($M47="","",$M47/$L47),"") | P47: =IF($L47="","",ROUND($L47-$O47,2))
B48: TOTALS | G48: =SUMPRODUCT(--('📅 Events'!$E$8:$E$47<>""),'📅 Events'!$G$8:$G$47) -> 0 | I48: =SUMPRODUCT(--('📅 Events'!$E$8:$E$47<>""),'📅 Events'!$I$8:$I$47) -> 0 | K48: =SUMPRODUCT(--('📅 Events'!$E$8:$E$47<>""),'📅 Events'!$K$8:$K$47) -> 0 | L48: =SUMPRODUCT(--('📅 Events'!$E$8:$E$47<>""),'📅 Events'!$L$8:$L$47) -> 0 | M48: =SUMPRODUCT(--('📅 Events'!$E$8:$E$47<>""),'📅 Events'!$M$8:$M$47) -> 0 | O48: =SUMPRODUCT(--('📅 Events'!$E$8:$E$47<>""),'📅 Events'!$O$8:$O$47) -> 0 | P48: =SUM('📅 Events'!$L$8:$L$47)-SUM('📅 Events'!$O$8:$O$47) -> 0
B50: How this tab works
B51: Profit, Margin and Balance calculate themselves - never type in the tinted columns. The Status pipeline feeds the Pipeline doughnut on the Dashboard; dates go amber inside your due-soon window and red once a live event has passed.
B55: Setup | D55: 🏠 Home | F55: Clients | H55: ▶ Events | J55: Quote | L55: Menu | N55: Stock | P55: Shop
B56: Expenses | D56: Payments | F56: Staff | H56: Equip | J56: Suppliers | L56: Calendar | N56: P&L | P56: Tax
B57: Checks | D57: Invoice | F57: Help

Sheet 🧮 Quote Calculator
B2: Quote Calculator
B3: Price an event in 30 seconds - margin, deposit and per-guest numbers included | D3: 🏠 Back to Dashboard
B8: 1 · Your inputs | D8: 2 · The quote (automatic)
B10: Client / enquiry
B11: Event date
B12: Guests
B14: Food cost per guest | D14: Food total | E14: =IF($C$12="","",ROUND($C$12*$C$14,2))
B15: Kitchen & service crew | D15: Total cost | E15: =IF($C$12="","",ROUND($C$12*$C$14+$C$15+$C$16+$C$17+$C$18,2))
B16: Equipment & rentals | D16: RECOMMENDED PRICE | E16: =IF($E$15="","",ROUND($E$15/(1-$C$20),2))
B17: Transport & fuel | D17: Price per guest | E17: =IF($E$16="","",ROUND($E$16/$C$12,2))
B18: Other costs | D18: Profit on the job | E18: =IF($E$16="","",ROUND($E$16-$E$15,2))
D19: Margin | E19: =IFERROR(IF($E$18="","",$E$18/$E$16),"")
B20: Target margin | C20: =DefaultMargin -> 0.35 | D20: Deposit to confirm | E20: =IF($E$16="","",ROUND($E$16*$C$21,2))
B21: Deposit % | C21: =DepositPct -> 0.4 | D21: Balance after deposit | E21: =IF($E$16="","",ROUND($E$16*(1-$C$21),2))
D22: Cost per guest | E22: =IF($E$15="","",ROUND($E$15/$C$12,2))
B24: =IF($E$16="","",Currency&TEXT($E$16,"#,##0.00")&" for the event · "&Currency&TEXT($E$17,"#,##0.00")&" per guest")
B27: How the math works
B28: • Price = Total cost ÷ (1 - margin). At a 35% target margin, $1,000 of costs prices at $1,538 - you keep $538.
B29: • The margin and deposit start from your Setup defaults; type over them here for a one-off quote without changing the defaults.
B30: • When they say yes: add the event on the Events tab, the deposit on the Payments tab, and the ingredients on the Shopping List.
B32: Setup | D32: 🏠 Home
B33: Clients | D33: Events
B34: ▶ Quote | D34: Menu
B35: Stock | D35: Shop
B36: Expenses | D36: Payments
B37: Staff | D37: Equip
B38: Suppliers | D38: Calendar
B39: P&L | D39: Tax
B40: Checks | D40: Invoice
B41: Help

Sheet 🍽️ Menu Costing
B2: Menu Costing
B3: Cost every dish - margins that make the quotes honest | I3: 🏠 Back to Dashboard
B5: ="Dishes priced: "&COUNTA('🍽️ Menu Costing'!$C$8:$C$37) -> Dishes priced: 0 | D5: ="Avg cost: "&Currency&TEXT(IFERROR(AVERAGE('🍽️ Menu Costing'!$G$8:$G$37),0),"0.00") -> Avg cost: $0.00 | F5: ="Avg price: "&Currency&TEXT(IFERROR(AVERAGE('🍽️ Menu Costing'!$H$8:$H$37),0),"0.00") -> Avg price: $0.00 | H5: ="Avg margin: "&TEXT('_Data'!$AF$34,"0%") -> Avg margin: 0%
B7: # | C7: Menu item | D7: Category | E7: Key ingredients | F7: Portion | G7: Cost / portion | H7: Menu price | I7: Profit | J7: Margin | K7: Notes
B8: =IF($C8="","",ROW()-7) | I8: =IF(OR($G8="",$H8=""),"",ROUND($H8-$G8,2)) | J8: =IFERROR(IF($I8="","",$I8/$H8),"")
B9: =IF($C9="","",ROW()-7) | I9: =IF(OR($G9="",$H9=""),"",ROUND($H9-$G9,2)) | J9: =IFERROR(IF($I9="","",$I9/$H9),"")
B10: =IF($C10="","",ROW()-7) | I10: =IF(OR($G10="",$H10=""),"",ROUND($H10-$G10,2)) | J10: =IFERROR(IF($I10="","",$I10/$H10),"")
B11: =IF($C11="","",ROW()-7) | I11: =IF(OR($G11="",$H11=""),"",ROUND($H11-$G11,2)) | J11: =IFERROR(IF($I11="","",$I11/$H11),"")
B12: =IF($C12="","",ROW()-7) | I12: =IF(OR($G12="",$H12=""),"",ROUND($H12-$G12,2)) | J12: =IFERROR(IF($I12="","",$I12/$H12),"")
B13: =IF($C13="","",ROW()-7) | I13: =IF(OR($G13="",$H13=""),"",ROUND($H13-$G13,2)) | J13: =IFERROR(IF($I13="","",$I13/$H13),"")
B14: =IF($C14="","",ROW()-7) | I14: =IF(OR($G14="",$H14=""),"",ROUND($H14-$G14,2)) | J14: =IFERROR(IF($I14="","",$I14/$H14),"")
B15: =IF($C15="","",ROW()-7) | I15: =IF(OR($G15="",$H15=""),"",ROUND($H15-$G15,2)) | J15: =IFERROR(IF($I15="","",$I15/$H15),"")
B16: =IF($C16="","",ROW()-7) | I16: =IF(OR($G16="",$H16=""),"",ROUND($H16-$G16,2)) | J16: =IFERROR(IF($I16="","",$I16/$H16),"")
B17: =IF($C17="","",ROW()-7) | I17: =IF(OR($G17="",$H17=""),"",ROUND($H17-$G17,2)) | J17: =IFERROR(IF($I17="","",$I17/$H17),"")
B18: =IF($C18="","",ROW()-7) | I18: =IF(OR($G18="",$H18=""),"",ROUND($H18-$G18,2)) | J18: =IFERROR(IF($I18="","",$I18/$H18),"")
B19: =IF($C19="","",ROW()-7) | I19: =IF(OR($G19="",$H19=""),"",ROUND($H19-$G19,2)) | J19: =IFERROR(IF($I19="","",$I19/$H19),"")
... B37: =IF($C37="","",ROW()-7) | I37: =IF(OR($G37="",$H37=""),"",ROUND($H37-$G37,2)) | J37: =IFERROR(IF($I37="","",$I37/$H37),"")
B38: MENU TOTALS | G38: =SUM('🍽️ Menu Costing'!$G$8:$G$37) -> 0 | H38: =SUM('🍽️ Menu Costing'!$H$8:$H$37) -> 0 | I38: =SUM('🍽️ Menu Costing'!$H$8:$H$37)-SUM('🍽️ Menu Costing'!$G$8:$G$37) -> 0
B58: How this tab works
B59: Cost per portion = everything on the plate: ingredients plus a share of packaging. If the margin bar glows amber the dish is under your Setup target. Use these numbers in the Quote Calculator (food cost per guest) so every quote is backed by real food costs.
B65: Setup | D65: 🏠 Home | F65: Clients | H65: Events | J65: Quote
B66: ▶ Menu | D66: Stock | F66: Shop | H66: Expenses | J66: Payments
B67: Staff | D67: Equip | F67: Suppliers | H67: Calendar | J67: P&L
B68: Tax | D68: Checks | F68: Invoice | H68: Help

Sheet 📦 Inventory
B2: Inventory
B3: Know what's on the shelf - and what to reorder this week | J3: 🏠 Back to Dashboard
B5: ="Items tracked: "&COUNTA('📦 Inventory'!$C$8:$C$47) -> Items tracked: 0 | D5: ="Stock value: "&Currency&TEXT(SUMPRODUCT(('📦 Inventory'!$C$8:$C$47<>"")*'📦 Inventory'!$F$8:$F$47*'📦 Inventory'!$H$8:$H$47),"#,##0.00") -> Stock value: $0.00 | F5: ="Below minimum: "&'_Data'!$AF$23 -> Below minimum: 0 | H5: ="Reorder spend: "&Currency&TEXT(SUMPRODUCT(('📦 Inventory'!$C$8:$C$47<>"")*('📦 Inventory'!$F$8:$F$47<'📦 Inventory'!$G$8:$G$47)*('📦 Inventory'!$G$8:$G$47-'📦 Inventory'!$F$8:$F$47)*'📦 Inventory'!$H$8:$H$47),"#,##0.00") -> Reorder spend: $0.00
B7: # | C7: Ingredient | D7: Category | E7: Unit | F7: In stock | G7: Min level | H7: Unit cost | I7: Stock value | J7: Supplier | K7: Status | L7: Notes
B8: =IF($C8="","",ROW()-7) | I8: =IF(OR($F8="",$H8=""),"",ROUND($F8*$H8,2)) | K8: =IF($C8="","",IF($F8<$G8,"🔴 Reorder",IF($F8<$G8*1.5,"🟡 Low","🟢 OK")))
B9: =IF($C9="","",ROW()-7) | I9: =IF(OR($F9="",$H9=""),"",ROUND($F9*$H9,2)) | K9: =IF($C9="","",IF($F9<$G9,"🔴 Reorder",IF($F9<$G9*1.5,"🟡 Low","🟢 OK")))
B10: =IF($C10="","",ROW()-7) | I10: =IF(OR($F10="",$H10=""),"",ROUND($F10*$H10,2)) | K10: =IF($C10="","",IF($F10<$G10,"🔴 Reorder",IF($F10<$G10*1.5,"🟡 Low","🟢 OK")))
B11: =IF($C11="","",ROW()-7) | I11: =IF(OR($F11="",$H11=""),"",ROUND($F11*$H11,2)) | K11: =IF($C11="","",IF($F11<$G11,"🔴 Reorder",IF($F11<$G11*1.5,"🟡 Low","🟢 OK")))
B12: =IF($C12="","",ROW()-7) | I12: =IF(OR($F12="",$H12=""),"",ROUND($F12*$H12,2)) | K12: =IF($C12="","",IF($F12<$G12,"🔴 Reorder",IF($F12<$G12*1.5,"🟡 Low","🟢 OK")))
B13: =IF($C13="","",ROW()-7) | I13: =IF(OR($F13="",$H13=""),"",ROUND($F13*$H13,2)) | K13: =IF($C13="","",IF($F13<$G13,"🔴 Reorder",IF($F13<$G13*1.5,"🟡 Low","🟢 OK")))
B14: =IF($C14="","",ROW()-7) | I14: =IF(OR($F14="",$H14=""),"",ROUND($F14*$H14,2)) | K14: =IF($C14="","",IF($F14<$G14,"🔴 Reorder",IF($F14<$G14*1.5,"🟡 Low","🟢 OK")))
B15: =IF($C15="","",ROW()-7) | I15: =IF(OR($F15="",$H15=""),"",ROUND($F15*$H15,2)) | K15: =IF($C15="","",IF($F15<$G15,"🔴 Reorder",IF($F15<$G15*1.5,"🟡 Low","🟢 OK")))
B16: =IF($C16="","",ROW()-7) | I16: =IF(OR($F16="",$H16=""),"",ROUND($F16*$H16,2)) | K16: =IF($C16="","",IF($F16<$G16,"🔴 Reorder",IF($F16<$G16*1.5,"🟡 Low","🟢 OK")))
B17: =IF($C17="","",ROW()-7) | I17: =IF(OR($F17="",$H17=""),"",ROUND($F17*$H17,2)) | K17: =IF($C17="","",IF($F17<$G17,"🔴 Reorder",IF($F17<$G17*1.5,"🟡 Low","🟢 OK")))
B18: =IF($C18="","",ROW()-7) | I18: =IF(OR($F18="",$H18=""),"",ROUND($F18*$H18,2)) | K18: =IF($C18="","",IF($F18<$G18,"🔴 Reorder",IF($F18<$G18*1.5,"🟡 Low","🟢 OK")))
B19: =IF($C19="","",ROW()-7) | I19: =IF(OR($F19="",$H19=""),"",ROUND($F19*$H19,2)) | K19: =IF($C19="","",IF($F19<$G19,"🔴 Reorder",IF($F19<$G19*1.5,"🟡 Low","🟢 OK")))
... B47: =IF($C47="","",ROW()-7) | I47: =IF(OR($F47="",$H47=""),"",ROUND($F47*$H47,2)) | K47: =IF($C47="","",IF($F47<$G47,"🔴 Reorder",IF($F47<$G47*1.5,"🟡 Low","🟢 OK")))
B48: TOTAL STOCK VALUE | I48: =SUMPRODUCT(('📦 Inventory'!$C$8:$C$47<>"")*'📦 Inventory'!$F$8:$F$47*'📦 Inventory'!$H$8:$H$47) -> 0
B50: How this tab works
B51: Status is automatic: below your minimum it turns red (Reorder), under 1.5x the minimum it glows amber (Low), otherwise green (OK). The Shopping List checks these quantities before telling you what to buy - keep them honest after every shop.
B55: Setup | D55: 🏠 Home | F55: Clients | H55: Events | J55: Quote
B56: Menu | D56: ▶ Stock | F56: Shop | H56: Expenses | J56: Payments
B57: Staff | D57: Equip | F57: Suppliers | H57: Calendar | J57: P&L
B58: Tax | D58: Checks | F58: Invoice | H58: Help

Sheet 🛒 Shopping List
B2: Shopping List
B3: Buy exactly what each event needs - nothing more, nothing less | J3: 🏠 Back to Dashboard
B5: ="Lines to buy: "&'_Data'!$AF$24 -> Lines to buy: 0 | D5: ="Estimated cost: "&Currency&TEXT('_Data'!$AF$25,"#,##0.00") -> Estimated cost: $0.00 | F5: ="Bought: "&COUNTIF('🛒 Shopping List'!$J$8:$J$47,"✓")&" of "&COUNTA('🛒 Shopping List'!$D$8:$D$47) -> Bought: 0 of 0
B7: # | C7: Event | D7: Ingredient | E7: Needed | F7: In stock | G7: To buy | H7: Supplier | I7: Est. cost | J7: Bought | K7: Bought on | L7: Notes
B8: =IF($D8="","",ROW()-7) | F8: =IF($D8="","",IFERROR(SUMIF('📦 Inventory'!$C$8:$C$47,$D8,'📦 Inventory'!$F$8:$F$47),0)) | G8: =IF($E8="","",MAX(0,ROUND($E8-$F8,1))) | I8: =IF(OR($G8="",NOT(ISNUMBER($G8))),"",ROUND($G8*IFERROR(SUMIF('📦 Inventory'!$C$8:$C$47,$D8,'📦 Inventory'!$H$8:$H$47),0),2))
B9: =IF($D9="","",ROW()-7) | F9: =IF($D9="","",IFERROR(SUMIF('📦 Inventory'!$C$8:$C$47,$D9,'📦 Inventory'!$F$8:$F$47),0)) | G9: =IF($E9="","",MAX(0,ROUND($E9-$F9,1))) | I9: =IF(OR($G9="",NOT(ISNUMBER($G9))),"",ROUND($G9*IFERROR(SUMIF('📦 Inventory'!$C$8:$C$47,$D9,'📦 Inventory'!$H$8:$H$47),0),2))
B10: =IF($D10="","",ROW()-7) | F10: =IF($D10="","",IFERROR(SUMIF('📦 Inventory'!$C$8:$C$47,$D10,'📦 Inventory'!$F$8:$F$47),0)) | G10: =IF($E10="","",MAX(0,ROUND($E10-$F10,1))) | I10: =IF(OR($G10="",NOT(ISNUMBER($G10))),"",ROUND($G10*IFERROR(SUMIF('📦 Inventory'!$C$8:$C$47,$D10,'📦 Inventory'!$H$8:$H$47),0),2))
B11: =IF($D11="","",ROW()-7) | F11: =IF($D11="","",IFERROR(SUMIF('📦 Inventory'!$C$8:$C$47,$D11,'📦 Inventory'!$F$8:$F$47),0)) | G11: =IF($E11="","",MAX(0,ROUND($E11-$F11,1))) | I11: =IF(OR($G11="",NOT(ISNUMBER($G11))),"",ROUND($G11*IFERROR(SUMIF('📦 Inventory'!$C$8:$C$47,$D11,'📦 Inventory'!$H$8:$H$47),0),2))
B12: =IF($D12="","",ROW()-7) | F12: =IF($D12="","",IFERROR(SUMIF('📦 Inventory'!$C$8:$C$47,$D12,'📦 Inventory'!$F$8:$F$47),0)) | G12: =IF($E12="","",MAX(0,ROUND($E12-$F12,1))) | I12: =IF(OR($G12="",NOT(ISNUMBER($G12))),"",ROUND($G12*IFERROR(SUMIF('📦 Inventory'!$C$8:$C$47,$D12,'📦 Inventory'!$H$8:$H$47),0),2))
B13: =IF($D13="","",ROW()-7) | F13: =IF($D13="","",IFERROR(SUMIF('📦 Inventory'!$C$8:$C$47,$D13,'📦 Inventory'!$F$8:$F$47),0)) | G13: =IF($E13="","",MAX(0,ROUND($E13-$F13,1))) | I13: =IF(OR($G13="",NOT(ISNUMBER($G13))),"",ROUND($G13*IFERROR(SUMIF('📦 Inventory'!$C$8:$C$47,$D13,'📦 Inventory'!$H$8:$H$47),0),2))
B14: =IF($D14="","",ROW()-7) | F14: =IF($D14="","",IFERROR(SUMIF('📦 Inventory'!$C$8:$C$47,$D14,'📦 Inventory'!$F$8:$F$47),0)) | G14: =IF($E14="","",MAX(0,ROUND($E14-$F14,1))) | I14: =IF(OR($G14="",NOT(ISNUMBER($G14))),"",ROUND($G14*IFERROR(SUMIF('📦 Inventory'!$C$8:$C$47,$D14,'📦 Inventory'!$H$8:$H$47),0),2))
B15: =IF($D15="","",ROW()-7) | F15: =IF($D15="","",IFERROR(SUMIF('📦 Inventory'!$C$8:$C$47,$D15,'📦 Inventory'!$F$8:$F$47),0)) | G15: =IF($E15="","",MAX(0,ROUND($E15-$F15,1))) | I15: =IF(OR($G15="",NOT(ISNUMBER($G15))),"",ROUND($G15*IFERROR(SUMIF('📦 Inventory'!$C$8:$C$47,$D15,'📦 Inventory'!$H$8:$H$47),0),2))
B16: =IF($D16="","",ROW()-7) | F16: =IF($D16="","",IFERROR(SUMIF('📦 Inventory'!$C$8:$C$47,$D16,'📦 Inventory'!$F$8:$F$47),0)) | G16: =IF($E16="","",MAX(0,ROUND($E16-$F16,1))) | I16: =IF(OR($G16="",NOT(ISNUMBER($G16))),"",ROUND($G16*IFERROR(SUMIF('📦 Inventory'!$C$8:$C$47,$D16,'📦 Inventory'!$H$8:$H$47),0),2))
B17: =IF($D17="","",ROW()-7) | F17: =IF($D17="","",IFERROR(SUMIF('📦 Inventory'!$C$8:$C$47,$D17,'📦 Inventory'!$F$8:$F$47),0)) | G17: =IF($E17="","",MAX(0,ROUND($E17-$F17,1))) | I17: =IF(OR($G17="",NOT(ISNUMBER($G17))),"",ROUND($G17*IFERROR(SUMIF('📦 Inventory'!$C$8:$C$47,$D17,'📦 Inventory'!$H$8:$H$47),0),2))
B18: =IF($D18="","",ROW()-7) | F18: =IF($D18="","",IFERROR(SUMIF('📦 Inventory'!$C$8:$C$47,$D18,'📦 Inventory'!$F$8:$F$47),0)) | G18: =IF($E18="","",MAX(0,ROUND($E18-$F18,1))) | I18: =IF(OR($G18="",NOT(ISNUMBER($G18))),"",ROUND($G18*IFERROR(SUMIF('📦 Inventory'!$C$8:$C$47,$D18,'📦 Inventory'!$H$8:$H$47),0),2))
B19: =IF($D19="","",ROW()-7) | F19: =IF($D19="","",IFERROR(SUMIF('📦 Inventory'!$C$8:$C$47,$D19,'📦 Inventory'!$F$8:$F$47),0)) | G19: =IF($E19="","",MAX(0,ROUND($E19-$F19,1))) | I19: =IF(OR($G19="",NOT(ISNUMBER($G19))),"",ROUND($G19*IFERROR(SUMIF('📦 Inventory'!$C$8:$C$47,$D19,'📦 Inventory'!$H$8:$H$47),0),2))
... B47: =IF($D47="","",ROW()-7) | F47: =IF($D47="","",IFERROR(SUMIF('📦 Inventory'!$C$8:$C$47,$D47,'📦 Inventory'!$F$8:$F$47),0)) | G47: =IF($E47="","",MAX(0,ROUND($E47-$F47,1))) | I47: =IF(OR($G47="",NOT(ISNUMBER($G47))),"",ROUND($G47*IFERROR(SUMIF('📦 Inventory'!$C$8:$C$47,$D47,'📦 Inventory'!$H$8:$H$47),0),2))
B48: STILL TO BUY | I48: =SUMPRODUCT(--(('🛒 Shopping List'!$J$8:$J$47<>"✓")*('🛒 Shopping List'!$D$8:$D$47<>"")),'🛒 Shopping List'!$I$8:$I$47) -> 0
B50: How this tab works
B51: In stock and To buy are looked up from the Inventory tab automatically - type the event, ingredient and how much you need. Estimated cost uses the unit cost on the Inventory tab; the total only counts lines you haven't ticked off yet.
B55: Setup | D55: 🏠 Home | F55: Clients | H55: Events | J55: Quote
B56: Menu | D56: Stock | F56: ▶ Shop | H56: Expenses | J56: Payments
B57: Staff | D57: Equip | F57: Suppliers | H57: Calendar | J57: P&L
B58: Tax | D58: Checks | F58: Invoice | H58: Help

Sheet 💸 Expenses
B2: Expenses
B3: Every cost, categorised - the P&L builds itself from here | H3: 🏠 Back to Dashboard
B5: ="Total spend: "&Currency&TEXT(SUM('💸 Expenses'!$G$8:$G$67),"#,##0") -> Total spend: $0 | D5: ="This month: "&Currency&TEXT(SUMPRODUCT(('💸 Expenses'!$C$8:$C$67<>"")*(MONTH('💸 Expenses'!$C$8:$C$67)=MONTH(TODAY()))*(YEAR('💸 Expenses'!$C$8:$C$67)=YEAR(TODAY()))*'💸 Expenses'!$G$8:$G$67),"#,##0") -> This month: $0 | F5: ="Food & packaging: "&Currency&TEXT('_Data'!$AF$17,"#,##0") -> Food & packaging: $0 | H5: ="No receipt: "&COUNTA('💸 Expenses'!$C$8:$C$67)-COUNTIF('💸 Expenses'!$J$8:$J$67,"✓") -> No receipt: 0
B7: # | C7: Date | D7: Vendor | E7: Category | F7: What / description | G7: Amount | H7: Paid by | I7: Event | J7: Receipt
B8: =IF($C8="","",ROW()-7)
B9: =IF($C9="","",ROW()-7)
B10: =IF($C10="","",ROW()-7)
B11: =IF($C11="","",ROW()-7)
B12: =IF($C12="","",ROW()-7)
B13: =IF($C13="","",ROW()-7)
B14: =IF($C14="","",ROW()-7)
B15: =IF($C15="","",ROW()-7)
B16: =IF($C16="","",ROW()-7)
B17: =IF($C17="","",ROW()-7)
B18: =IF($C18="","",ROW()-7)
B19: =IF($C19="","",ROW()-7)
... B67: =IF($C67="","",ROW()-7)
B68: TOTAL SPEND | G68: =SUM('💸 Expenses'!$G$8:$G$67) -> 0
B70: How this tab works
B71: Categorising is what makes the Dashboard doughnut, the food cost % and the P&L work - pick from the dropdown rather than typing. Ingredients + Packaging count as food cost; everything else is operating cost in the P&L.
B75: Setup | D75: 🏠 Home | F75: Clients | H75: Events
B76: Quote | D76: Menu | F76: Stock | H76: Shop
B77: ▶ Expenses | D77: Payments | F77: Staff | H77: Equip
B78: Suppliers | D78: Calendar | F78: P&L | H78: Tax
B79: Checks | D79: Invoice | F79: Help

Sheet 💰 Payments
B2: Payments
B3: Deposits, installments and final balances - who owes what | K3: 🏠 Back to Dashboard
B5: ="Invoiced: "&Currency&TEXT(SUM('💰 Payments'!$F$8:$F$67),"#,##0") -> Invoiced: $0 | D5: ="Received: "&Currency&TEXT('_Data'!$AF$2,"#,##0") -> Received: $0 | F5: ="Outstanding: "&Currency&TEXT('_Data'!$AF$14,"#,##0") -> Outstanding: $0 | H5: ="Overdue: "&'_Data'!$AF$15&IF('_Data'!$AF$15=1," invoice"," invoices") -> Overdue: 0 invoices
B7: # | C7: Invoice # | D7: Client | E7: Event date | F7: Invoice total | G7: Deposit | H7: Payment 2 | I7: Final payment | J7: Received | K7: Balance | L7: Due date | M7: Status
B8: =IF($C8="","",ROW()-7) | J8: =IF($F8="","",ROUND($G8+$H8+$I8,2)) | K8: =IF($F8="","",$F8-$J8) | M8: =IF($F8="","",IF($K8<=0,"🟢 Paid in full",IF($J8>0,"🟠 Partial","🔴 Unpaid")))
B9: =IF($C9="","",ROW()-7) | J9: =IF($F9="","",ROUND($G9+$H9+$I9,2)) | K9: =IF($F9="","",$F9-$J9) | M9: =IF($F9="","",IF($K9<=0,"🟢 Paid in full",IF($J9>0,"🟠 Partial","🔴 Unpaid")))
B10: =IF($C10="","",ROW()-7) | J10: =IF($F10="","",ROUND($G10+$H10+$I10,2)) | K10: =IF($F10="","",$F10-$J10) | M10: =IF($F10="","",IF($K10<=0,"🟢 Paid in full",IF($J10>0,"🟠 Partial","🔴 Unpaid")))
B11: =IF($C11="","",ROW()-7) | J11: =IF($F11="","",ROUND($G11+$H11+$I11,2)) | K11: =IF($F11="","",$F11-$J11) | M11: =IF($F11="","",IF($K11<=0,"🟢 Paid in full",IF($J11>0,"🟠 Partial","🔴 Unpaid")))
B12: =IF($C12="","",ROW()-7) | J12: =IF($F12="","",ROUND($G12+$H12+$I12,2)) | K12: =IF($F12="","",$F12-$J12) | M12: =IF($F12="","",IF($K12<=0,"🟢 Paid in full",IF($J12>0,"🟠 Partial","🔴 Unpaid")))
B13: =IF($C13="","",ROW()-7) | J13: =IF($F13="","",ROUND($G13+$H13+$I13,2)) | K13: =IF($F13="","",$F13-$J13) | M13: =IF($F13="","",IF($K13<=0,"🟢 Paid in full",IF($J13>0,"🟠 Partial","🔴 Unpaid")))
B14: =IF($C14="","",ROW()-7) | J14: =IF($F14="","",ROUND($G14+$H14+$I14,2)) | K14: =IF($F14="","",$F14-$J14) | M14: =IF($F14="","",IF($K14<=0,"🟢 Paid in full",IF($J14>0,"🟠 Partial","🔴 Unpaid")))
B15: =IF($C15="","",ROW()-7) | J15: =IF($F15="","",ROUND($G15+$H15+$I15,2)) | K15: =IF($F15="","",$F15-$J15) | M15: =IF($F15="","",IF($K15<=0,"🟢 Paid in full",IF($J15>0,"🟠 Partial","🔴 Unpaid")))
B16: =IF($C16="","",ROW()-7) | J16: =IF($F16="","",ROUND($G16+$H16+$I16,2)) | K16: =IF($F16="","",$F16-$J16) | M16: =IF($F16="","",IF($K16<=0,"🟢 Paid in full",IF($J16>0,"🟠 Partial","🔴 Unpaid")))
B17: =IF($C17="","",ROW()-7) | J17: =IF($F17="","",ROUND($G17+$H17+$I17,2)) | K17: =IF($F17="","",$F17-$J17) | M17: =IF($F17="","",IF($K17<=0,"🟢 Paid in full",IF($J17>0,"🟠 Partial","🔴 Unpaid")))
B18: =IF($C18="","",ROW()-7) | J18: =IF($F18="","",ROUND($G18+$H18+$I18,2)) | K18: =IF($F18="","",$F18-$J18) | M18: =IF($F18="","",IF($K18<=0,"🟢 Paid in full",IF($J18>0,"🟠 Partial","🔴 Unpaid")))
B19: =IF($C19="","",ROW()-7) | J19: =IF($F19="","",ROUND($G19+$H19+$I19,2)) | K19: =IF($F19="","",$F19-$J19) | M19: =IF($F19="","",IF($K19<=0,"🟢 Paid in full",IF($J19>0,"🟠 Partial","🔴 Unpaid")))
... B67: =IF($C67="","",ROW()-7) | J67: =IF($F67="","",ROUND($G67+$H67+$I67,2)) | K67: =IF($F67="","",$F67-$J67) | M67: =IF($F67="","",IF($K67<=0,"🟢 Paid in full",IF($J67>0,"🟠 Partial","🔴 Unpaid")))
B68: TOTALS | F68: =SUM('💰 Payments'!$F$8:$F$67) -> 0 | J68: =SUM('💰 Payments'!$G$8:$G$67)+SUM('💰 Payments'!$H$8:$H$67)+SUM('💰 Payments'!$I$8:$I$67) -> 0 | K68: =SUM('💰 Payments'!$F$8:$F$67)-SUM('💰 Payments'!$G$8:$G$67)-SUM('💰 Payments'!$H$8:$H$67)-SUM('💰 Payments'!$I$8:$I$67) -> 0
B88: How this tab works
B89: Received and Balance calculate themselves from the deposit and payment columns - only type in the white cells. Due dates go amber inside your due-soon window and red once they pass with a balance left; the Dashboard overdue card counts them.
B95: Setup | D95: 🏠 Home | F95: Clients | H95: Events | J95: Quote | L95: Menu
B96: Stock | D96: Shop | F96: Expenses | H96: ▶ Payments | J96: Staff | L96: Equip
B97: Suppliers | D97: Calendar | F97: P&L | H97: Tax | J97: Checks | L97: Invoice
B98: Help

Sheet 👷 Staff & Labor
B2: Staff & Labor
B3: Crew, shifts and the wage bill - overtime at 1.5x | I3: 🏠 Back to Dashboard
B5: ="Shifts logged: "&COUNTA('👷 Staff & Labor'!$C$8:$C$57) -> Shifts logged: 0 | D5: ="Wage bill: "&Currency&TEXT(SUMPRODUCT(('👷 Staff & Labor'!$C$8:$C$57<>"")*'👷 Staff & Labor'!$F$8:$F$57*'👷 Staff & Labor'!$G$8:$G$57)+SUMPRODUCT(('👷 Staff & Labor'!$C$8:$C$57<>"")*'👷 Staff & Labor'!$H$8:$H$57*'👷 Staff & Labor'!$G$8:$G$57*1.5),"#,##0") -> Wage bill: $0 | F5: ="Unpaid shifts: "&'_Data'!$AF$26 -> Unpaid shifts: 0
B7: # | C7: Team member | D7: Role | E7: Event | F7: Hours | G7: Rate | H7: OT hrs | I7: Shift cost | J7: Paid | K7: Notes
B8: =IF($C8="","",ROW()-7) | I8: =IF(OR($F8="",$G8=""),"",ROUND($F8*$G8+$H8*$G8*1.5,2))
B9: =IF($C9="","",ROW()-7) | I9: =IF(OR($F9="",$G9=""),"",ROUND($F9*$G9+$H9*$G9*1.5,2))
B10: =IF($C10="","",ROW()-7) | I10: =IF(OR($F10="",$G10=""),"",ROUND($F10*$G10+$H10*$G10*1.5,2))
B11: =IF($C11="","",ROW()-7) | I11: =IF(OR($F11="",$G11=""),"",ROUND($F11*$G11+$H11*$G11*1.5,2))
B12: =IF($C12="","",ROW()-7) | I12: =IF(OR($F12="",$G12=""),"",ROUND($F12*$G12+$H12*$G12*1.5,2))
B13: =IF($C13="","",ROW()-7) | I13: =IF(OR($F13="",$G13=""),"",ROUND($F13*$G13+$H13*$G13*1.5,2))
B14: =IF($C14="","",ROW()-7) | I14: =IF(OR($F14="",$G14=""),"",ROUND($F14*$G14+$H14*$G14*1.5,2))
B15: =IF($C15="","",ROW()-7) | I15: =IF(OR($F15="",$G15=""),"",ROUND($F15*$G15+$H15*$G15*1.5,2))
B16: =IF($C16="","",ROW()-7) | I16: =IF(OR($F16="",$G16=""),"",ROUND($F16*$G16+$H16*$G16*1.5,2))
B17: =IF($C17="","",ROW()-7) | I17: =IF(OR($F17="",$G17=""),"",ROUND($F17*$G17+$H17*$G17*1.5,2))
B18: =IF($C18="","",ROW()-7) | I18: =IF(OR($F18="",$G18=""),"",ROUND($F18*$G18+$H18*$G18*1.5,2))
B19: =IF($C19="","",ROW()-7) | I19: =IF(OR($F19="",$G19=""),"",ROUND($F19*$G19+$H19*$G19*1.5,2))
... B57: =IF($C57="","",ROW()-7) | I57: =IF(OR($F57="",$G57=""),"",ROUND($F57*$G57+$H57*$G57*1.5,2))
B58: TOTAL WAGE BILL | I58: =SUMPRODUCT(('👷 Staff & Labor'!$C$8:$C$57<>"")*'👷 Staff & Labor'!$F$8:$F$57*'👷 Staff & Labor'!$G$8:$G$57)+SUMPRODUCT(('👷 Staff & Labor'!$C$8:$C$57<>"")*'👷 Staff & Labor'!$H$8:$H$57*'👷 Staff & Labor'!$G$8:$G$57*1.5) -> 0
B60: How this tab works
B61: Shift cost = hours x rate + overtime x rate x 1.5. It calculates itself; the totals feed the labor % on the Dashboard when you log wages on the Expenses tab. Tick the Paid box when the shift is settled - unpaid shifts stay amber until you do.
B65: Setup | D65: 🏠 Home | F65: Clients | H65: Events | J65: Quote
B66: Menu | D66: Stock | F66: Shop | H66: Expenses | J66: Payments
B67: ▶ Staff | D67: Equip | F67: Suppliers | H67: Calendar | J67: P&L
B68: Tax | D68: Checks | F68: Invoice | H68: Help

Sheet 🍳 Equipment
B2: Equipment
B3: Chafers to trailers - availability, value and service dates | J3: 🏠 Back to Dashboard
B5: ="Items owned: "&COUNTA('🍳 Equipment'!$C$8:$C$42) -> Items owned: 0 | D5: ="Equipment value: "&Currency&TEXT(SUMPRODUCT(('🍳 Equipment'!$C$8:$C$42<>"")*'🍳 Equipment'!$E$8:$E$42*'🍳 Equipment'!$I$8:$I$42),"#,##0") -> Equipment value: $0 | F5: ="Reserved now: "&SUMPRODUCT(('🍳 Equipment'!$C$8:$C$42<>"")*'🍳 Equipment'!$F$8:$F$42) -> Reserved now: 0 | H5: ="Needs attention: "&'_Data'!$AF$28 -> Needs attention: 0
B7: # | C7: Item | D7: Category | E7: Owned | F7: Reserved | G7: Damaged | H7: Available | I7: Value / unit | J7: Total value | K7: Next service | L7: Status
B8: =IF($C8="","",ROW()-7) | H8: =IF($C8="","",$E8-$F8-$G8) | J8: =IF(OR($E8="",$I8=""),"",ROUND($E8*$I8,2)) | L8: =IF($C8="","",IF($G8>0,"🔧 Service",IF($K8-TODAY()<=30,"🟡 Soon","🟢 Ready")))
B9: =IF($C9="","",ROW()-7) | H9: =IF($C9="","",$E9-$F9-$G9) | J9: =IF(OR($E9="",$I9=""),"",ROUND($E9*$I9,2)) | L9: =IF($C9="","",IF($G9>0,"🔧 Service",IF($K9-TODAY()<=30,"🟡 Soon","🟢 Ready")))
B10: =IF($C10="","",ROW()-7) | H10: =IF($C10="","",$E10-$F10-$G10) | J10: =IF(OR($E10="",$I10=""),"",ROUND($E10*$I10,2)) | L10: =IF($C10="","",IF($G10>0,"🔧 Service",IF($K10-TODAY()<=30,"🟡 Soon","🟢 Ready")))
B11: =IF($C11="","",ROW()-7) | H11: =IF($C11="","",$E11-$F11-$G11) | J11: =IF(OR($E11="",$I11=""),"",ROUND($E11*$I11,2)) | L11: =IF($C11="","",IF($G11>0,"🔧 Service",IF($K11-TODAY()<=30,"🟡 Soon","🟢 Ready")))
B12: =IF($C12="","",ROW()-7) | H12: =IF($C12="","",$E12-$F12-$G12) | J12: =IF(OR($E12="",$I12=""),"",ROUND($E12*$I12,2)) | L12: =IF($C12="","",IF($G12>0,"🔧 Service",IF($K12-TODAY()<=30,"🟡 Soon","🟢 Ready")))
B13: =IF($C13="","",ROW()-7) | H13: =IF($C13="","",$E13-$F13-$G13) | J13: =IF(OR($E13="",$I13=""),"",ROUND($E13*$I13,2)) | L13: =IF($C13="","",IF($G13>0,"🔧 Service",IF($K13-TODAY()<=30,"🟡 Soon","🟢 Ready")))
B14: =IF($C14="","",ROW()-7) | H14: =IF($C14="","",$E14-$F14-$G14) | J14: =IF(OR($E14="",$I14=""),"",ROUND($E14*$I14,2)) | L14: =IF($C14="","",IF($G14>0,"🔧 Service",IF($K14-TODAY()<=30,"🟡 Soon","🟢 Ready")))
B15: =IF($C15="","",ROW()-7) | H15: =IF($C15="","",$E15-$F15-$G15) | J15: =IF(OR($E15="",$I15=""),"",ROUND($E15*$I15,2)) | L15: =IF($C15="","",IF($G15>0,"🔧 Service",IF($K15-TODAY()<=30,"🟡 Soon","🟢 Ready")))
B16: =IF($C16="","",ROW()-7) | H16: =IF($C16="","",$E16-$F16-$G16) | J16: =IF(OR($E16="",$I16=""),"",ROUND($E16*$I16,2)) | L16: =IF($C16="","",IF($G16>0,"🔧 Service",IF($K16-TODAY()<=30,"🟡 Soon","🟢 Ready")))
B17: =IF($C17="","",ROW()-7) | H17: =IF($C17="","",$E17-$F17-$G17) | J17: =IF(OR($E17="",$I17=""),"",ROUND($E17*$I17,2)) | L17: =IF($C17="","",IF($G17>0,"🔧 Service",IF($K17-TODAY()<=30,"🟡 Soon","🟢 Ready")))
B18: =IF($C18="","",ROW()-7) | H18: =IF($C18="","",$E18-$F18-$G18) | J18: =IF(OR($E18="",$I18=""),"",ROUND($E18*$I18,2)) | L18: =IF($C18="","",IF($G18>0,"🔧 Service",IF($K18-TODAY()<=30,"🟡 Soon","🟢 Ready")))
B19: =IF($C19="","",ROW()-7) | H19: =IF($C19="","",$E19-$F19-$G19) | J19: =IF(OR($E19="",$I19=""),"",ROUND($E19*$I19,2)) | L19: =IF($C19="","",IF($G19>0,"🔧 Service",IF($K19-TODAY()<=30,"🟡 Soon","🟢 Ready")))
... B42: =IF($C42="","",ROW()-7) | H42: =IF($C42="","",$E42-$F42-$G42) | J42: =IF(OR($E42="",$I42=""),"",ROUND($E42*$I42,2)) | L42: =IF($C42="","",IF($G42>0,"🔧 Service",IF($K42-TODAY()<=30,"🟡 Soon","🟢 Ready")))
B43: FLEET TOTALS | E43: =SUM('🍳 Equipment'!$E$8:$E$42) -> 0 | J43: =SUMPRODUCT(('🍳 Equipment'!$C$8:$C$42<>"")*'🍳 Equipment'!$E$8:$E$42*'🍳 Equipment'!$I$8:$I$42) -> 0
B45: How this tab works
B46: Available = owned - reserved - damaged. Status turns 🔧 Service when something is damaged and 🟡 Soon within 30 days of the service date. Use Reserved for what's already promised to upcoming events so you never double-book the trailer.
B50: Setup | D50: 🏠 Home | F50: Clients | H50: Events | J50: Quote
B51: Menu | D51: Stock | F51: Shop | H51: Expenses | J51: Payments
B52: Staff | D52: ▶ Equip | F52: Suppliers | H52: Calendar | J52: P&L
B53: Tax | D53: Checks | F53: Invoice | H53: Help

Sheet 🚚 Suppliers
B2: Suppliers
B3: Who sells what, at what price, on what terms | K3: 🏠 Back to Dashboard
B5: ="Suppliers: "&COUNTA('🚚 Suppliers'!$C$8:$C$37) -> Suppliers: 0 | D5: ="Categories: "&SUMPRODUCT(('🚚 Suppliers'!$G$8:$G$37<>"")/COUNTIF('🚚 Suppliers'!$G$8:$G$37,'🚚 Suppliers'!$G$8:$G$37&"")) -> Categories: 0
B7: # | C7: Supplier | D7: Contact | E7: Phone | F7: Email | G7: Category | H7: What they supply | I7: From price | J7: Min order | K7: Delivery | L7: Terms | M7: Notes
B8: =IF($C8="","",ROW()-7)
B9: =IF($C9="","",ROW()-7)
B10: =IF($C10="","",ROW()-7)
B11: =IF($C11="","",ROW()-7)
B12: =IF($C12="","",ROW()-7)
B13: =IF($C13="","",ROW()-7)
B14: =IF($C14="","",ROW()-7)
B15: =IF($C15="","",ROW()-7)
B16: =IF($C16="","",ROW()-7)
B17: =IF($C17="","",ROW()-7)
B18: =IF($C18="","",ROW()-7)
B19: =IF($C19="","",ROW()-7)
... B37: =IF($C37="","",ROW()-7)
B40: How this tab works
B41: Adding a supplier here makes them selectable on the Inventory and Shopping List tabs. From price is your reference price for comparisons - the actual cost per unit lives on the Inventory tab, where the shopping estimates read it.
B45: Setup | D45: 🏠 Home | F45: Clients | H45: Events | J45: Quote | L45: Menu
B46: Stock | D46: Shop | F46: Expenses | H46: Payments | J46: Staff | L46: Equip
B47: ▶ Suppliers | D47: Calendar | F47: P&L | H47: Tax | J47: Checks | L47: Invoice
B48: Help

Sheet 📆 Event Calendar
B2: =TEXT(DATE(CalYear,CalMonth,1),"mmmm yyyy") -> September 2026
B3: One glance at the month - events, deliveries and payment deadlines | J3: 🏠 Back to Dashboard
B5: ="Events this month: "&COUNTIFS('_Data'!$AA$2:$AA$41,">="&DATE(CalYear,CalMonth,1),'_Data'!$AA$2:$AA$41,"<="&EOMONTH(DATE(CalYear,CalMonth,1),0)) -> Events this month: 0 | D5: ="Payments due: "&COUNTIFS('_Data'!$AA$42:$AA$101,">="&DATE(CalYear,CalMonth,1),'_Data'!$AA$42:$AA$101,"<="&EOMONTH(DATE(CalYear,CalMonth,1),0)) -> Payments due: 0 | F5: ="Next up: "&IF('_Data'!$AA$2="","-",'_Data'!$AB$2) -> Next up: -
N8: calendar helpers
N9: =IFERROR(MATCH(DATE(CalYear,CalMonth,1)-0.5,'_Data'!$AA$2:$AA$41,1)+1,1) -> 1
N10: =IFERROR(MATCH(DATE(CalYear,CalMonth,1)-0.5,'_Data'!$AA$42:$AA$101,1)+1,1) -> 1
B11: Mon | C11: Tue | D11: Wed | E11: Thu | F11: Fri | G11: Sat | H11: Sun | J11: This month's events
B12: =IF(MONTH(DATE(CalYear,CalMonth,1)-WEEKDAY(DATE(CalYear,CalMonth,1),2)+1+0)=CalMonth,DATE(CalYear,CalMonth,1)-WEEKDAY(DATE(CalYear,CalMonth,1),2)+1+0,"") | C12: =IF(MONTH(DATE(CalYear,CalMonth,1)-WEEKDAY(DATE(CalYear,CalMonth,1),2)+1+1)=CalMonth,DATE(CalYear,CalMonth,1)-WEEKDAY(DATE(CalYear,CalMonth,1),2)+1+1,"") | D12: =IF(MONTH(DATE(CalYear,CalMonth,1)-WEEKDAY(DATE(CalYear,CalMonth,1),2)+1+2)=CalMonth,DATE(CalYear,CalMonth,1)-WEEKDAY(DATE(CalYear,CalMonth,1),2)+1+2,"") | E12: =IF(MONTH(DATE(CalYear,CalMonth,1)-WEEKDAY(DATE(CalYear,CalMonth,1),2)+1+3)=CalMonth,DATE(CalYear,CalMonth,1)-WEEKDAY(DATE(CalYear,CalMonth,1),2)+1+3,"") | F12: =IF(MONTH(DATE(CalYear,CalMonth,1)-WEEKDAY(DATE(CalYear,CalMonth,1),2)+1+4)=CalMonth,DATE(CalYear,CalMonth,1)-WEEKDAY(DATE(CalYear,CalMonth,1),2)+1+4,"") | G12: =IF(MONTH(DATE(CalYear,CalMonth,1)-WEEKDAY(DATE(CalYear,CalMonth,1),2)+1+5)=CalMonth,DATE(CalYear,CalMonth,1)-WEEKDAY(DATE(CalYear,CalMonth,1),2)+1+5,"") | H12: =IF(MONTH(DATE(CalYear,CalMonth,1)-WEEKDAY(DATE(CalYear,CalMonth,1),2)+1+6)=CalMonth,DATE(CalYear,CalMonth,1)-WEEKDAY(DATE(CalYear,CalMonth,1),2)+1+6,"") | J12: =IFERROR(IF(INDEX('_Data'!$AA$2:$AA$41,$N$9+0)="","",IF(MONTH(INDEX('_Data'!$AA$2:$AA$41,$N$9+0))<>CalMonth,"",INDEX('_Data'!$AA$2:$AA$41,$N$9+0))),"") | K12: =IF($J12="","",INDEX('_Data'!$AB$2:$AB$41,$N$9+0)) | L12: =IF($J12="","",INDEX('_Data'!$AC$2:$AC$41,$N$9+0))
B13: =IF($B$12="","",TRIM(IF(COUNTIF('_Data'!$AA$2:$AA$41,$B$12)>0,"● "&COUNTIF('_Data'!$AA$2:$AA$41,$B$12)&IF(COUNTIF('_Data'!$AA$2:$AA$41,$B$12)>1," events"," event"),"")&IF(COUNTIF('_Data'!$AA$42:$AA$101,$B$12)>0," ▲ "&COUNTIF('_Data'!$AA$42:$AA$101,$B$12)&" due",""))) | C13: =IF($C$12="","",TRIM(IF(COUNTIF('_Data'!$AA$2:$AA$41,$C$12)>0,"● "&COUNTIF('_Data'!$AA$2:$AA$41,$C$12)&IF(COUNTIF('_Data'!$AA$2:$AA$41,$C$12)>1," events"," event"),"")&IF(COUNTIF('_Data'!$AA$42:$AA$101,$C$12)>0," ▲ "&COUNTIF('_Data'!$AA$42:$AA$101,$C$12)&" due",""))) | D13: =IF($D$12="","",TRIM(IF(COUNTIF('_Data'!$AA$2:$AA$41,$D$12)>0,"● "&COUNTIF('_Data'!$AA$2:$AA$41,$D$12)&IF(COUNTIF('_Data'!$AA$2:$AA$41,$D$12)>1," events"," event"),"")&IF(COUNTIF('_Data'!$AA$42:$AA$101,$D$12)>0," ▲ "&COUNTIF('_Data'!$AA$42:$AA$101,$D$12)&" due",""))) | E13: =IF($E$12="","",TRIM(IF(COUNTIF('_Data'!$AA$2:$AA$41,$E$12)>0,"● "&COUNTIF('_Data'!$AA$2:$AA$41,$E$12)&IF(COUNTIF('_Data'!$AA$2:$AA$41,$E$12)>1," events"," event"),"")&IF(COUNTIF('_Data'!$AA$42:$AA$101,$E$12)>0," ▲ "&COUNTIF('_Data'!$AA$42:$AA$101,$E$12)&" due",""))) | F13: =IF($F$12="","",TRIM(IF(COUNTIF('_Data'!$AA$2:$AA$41,$F$12)>0,"● "&COUNTIF('_Data'!$AA$2:$AA$41,$F$12)&IF(COUNTIF('_Data'!$AA$2:$AA$41,$F$12)>1," events"," event"),"")&IF(COUNTIF('_Data'!$AA$42:$AA$101,$F$12)>0," ▲ "&COUNTIF('_Data'!$AA$42:$AA$101,$F$12)&" due",""))) | G13: =IF($G$12="","",TRIM(IF(COUNTIF('_Data'!$AA$2:$AA$41,$G$12)>0,"● "&COUNTIF('_Data'!$AA$2:$AA$41,$G$12)&IF(COUNTIF('_Data'!$AA$2:$AA$41,$G$12)>1," events"," event"),"")&IF(COUNTIF('_Data'!$AA$42:$AA$101,$G$12)>0," ▲ "&COUNTIF('_Data'!$AA$42:$AA$101,$G$12)&" due",""))) | H13: =IF($H$12="","",TRIM(IF(COUNTIF('_Data'!$AA$2:$AA$41,$H$12)>0,"● "&COUNTIF('_Data'!$AA$2:$AA$41,$H$12)&IF(COUNTIF('_Data'!$AA$2:$AA$41,$H$12)>1," events"," event"),"")&IF(COUNTIF('_Data'!$AA$42:$AA$101,$H$12)>0," ▲ "&COUNTIF('_Data'!$AA$42:$AA$101,$H$12)&" due",""))) | J13: =IFERROR(IF(INDEX('_Data'!$AA$2:$AA$41,$N$9+1)="","",IF(MONTH(INDEX('_Data'!$AA$2:$AA$41,$N$9+1))<>CalMonth,"",INDEX('_Data'!$AA$2:$AA$41,$N$9+1))),"") | K13: =IF($J13="","",INDEX('_Data'!$AB$2:$AB$41,$N$9+1)) | L13: =IF($J13="","",INDEX('_Data'!$AC$2:$AC$41,$N$9+1))
B14: =IF(MONTH(DATE(CalYear,CalMonth,1)-WEEKDAY(DATE(CalYear,CalMonth,1),2)+1+7)=CalMonth,DATE(CalYear,CalMonth,1)-WEEKDAY(DATE(CalYear,CalMonth,1),2)+1+7,"") | C14: =IF(MONTH(DATE(CalYear,CalMonth,1)-WEEKDAY(DATE(CalYear,CalMonth,1),2)+1+8)=CalMonth,DATE(CalYear,CalMonth,1)-WEEKDAY(DATE(CalYear,CalMonth,1),2)+1+8,"") | D14: =IF(MONTH(DATE(CalYear,CalMonth,1)-WEEKDAY(DATE(CalYear,CalMonth,1),2)+1+9)=CalMonth,DATE(CalYear,CalMonth,1)-WEEKDAY(DATE(CalYear,CalMonth,1),2)+1+9,"") | E14: =IF(MONTH(DATE(CalYear,CalMonth,1)-WEEKDAY(DATE(CalYear,CalMonth,1),2)+1+10)=CalMonth,DATE(CalYear,CalMonth,1)-WEEKDAY(DATE(CalYear,CalMonth,1),2)+1+10,"") | F14: =IF(MONTH(DATE(CalYear,CalMonth,1)-WEEKDAY(DATE(CalYear,CalMonth,1),2)+1+11)=CalMonth,DATE(CalYear,CalMonth,1)-WEEKDAY(DATE(CalYear,CalMonth,1),2)+1+11,"") | G14: =IF(MONTH(DATE(CalYear,CalMonth,1)-WEEKDAY(DATE(CalYear,CalMonth,1),2)+1+12)=CalMonth,DATE(CalYear,CalMonth,1)-WEEKDAY(DATE(CalYear,CalMonth,1),2)+1+12,"") | H14: =IF(MONTH(DATE(CalYear,CalMonth,1)-WEEKDAY(DATE(CalYear,CalMonth,1),2)+1+13)=CalMonth,DATE(CalYear,CalMonth,1)-WEEKDAY(DATE(CalYear,CalMonth,1),2)+1+13,"") | J14: =IFERROR(IF(INDEX('_Data'!$AA$2:$AA$41,$N$9+2)="","",IF(MONTH(INDEX('_Data'!$AA$2:$AA$41,$N$9+2))<>CalMonth,"",INDEX('_Data'!$AA$2:$AA$41,$N$9+2))),"") | K14: =IF($J14="","",INDEX('_Data'!$AB$2:$AB$41,$N$9+2)) | L14: =IF($J14="","",INDEX('_Data'!$AC$2:$AC$41,$N$9+2))
B15: =IF($B$14="","",TRIM(IF(COUNTIF('_Data'!$AA$2:$AA$41,$B$14)>0,"● "&COUNTIF('_Data'!$AA$2:$AA$41,$B$14)&IF(COUNTIF('_Data'!$AA$2:$AA$41,$B$14)>1," events"," event"),"")&IF(COUNTIF('_Data'!$AA$42:$AA$101,$B$14)>0," ▲ "&COUNTIF('_Data'!$AA$42:$AA$101,$B$14)&" due",""))) | C15: =IF($C$14="","",TRIM(IF(COUNTIF('_Data'!$AA$2:$AA$41,$C$14)>0,"● "&COUNTIF('_Data'!$AA$2:$AA$41,$C$14)&IF(COUNTIF('_Data'!$AA$2:$AA$41,$C$14)>1," events"," event"),"")&IF(COUNTIF('_Data'!$AA$42:$AA$101,$C$14)>0," ▲ "&COUNTIF('_Data'!$AA$42:$AA$101,$C$14)&" due",""))) | D15: =IF($D$14="","",TRIM(IF(COUNTIF('_Data'!$AA$2:$AA$41,$D$14)>0,"● "&COUNTIF('_Data'!$AA$2:$AA$41,$D$14)&IF(COUNTIF('_Data'!$AA$2:$AA$41,$D$14)>1," events"," event"),"")&IF(COUNTIF('_Data'!$AA$42:$AA$101,$D$14)>0," ▲ "&COUNTIF('_Data'!$AA$42:$AA$101,$D$14)&" due",""))) | E15: =IF($E$14="","",TRIM(IF(COUNTIF('_Data'!$AA$2:$AA$41,$E$14)>0,"● "&COUNTIF('_Data'!$AA$2:$AA$41,$E$14)&IF(COUNTIF('_Data'!$AA$2:$AA$41,$E$14)>1," events"," event"),"")&IF(COUNTIF('_Data'!$AA$42:$AA$101,$E$14)>0," ▲ "&COUNTIF('_Data'!$AA$42:$AA$101,$E$14)&" due",""))) | F15: =IF($F$14="","",TRIM(IF(COUNTIF('_Data'!$AA$2:$AA$41,$F$14)>0,"● "&COUNTIF('_Data'!$AA$2:$AA$41,$F$14)&IF(COUNTIF('_Data'!$AA$2:$AA$41,$F$14)>1," events"," event"),"")&IF(COUNTIF('_Data'!$AA$42:$AA$101,$F$14)>0," ▲ "&COUNTIF('_Data'!$AA$42:$AA$101,$F$14)&" due",""))) | G15: =IF($G$14="","",TRIM(IF(COUNTIF('_Data'!$AA$2:$AA$41,$G$14)>0,"● "&COUNTIF('_Data'!$AA$2:$AA$41,$G$14)&IF(COUNTIF('_Data'!$AA$2:$AA$41,$G$14)>1," events"," event"),"")&IF(COUNTIF('_Data'!$AA$42:$AA$101,$G$14)>0," ▲ "&COUNTIF('_Data'!$AA$42:$AA$101,$G$14)&" due",""))) | H15: =IF($H$14="","",TRIM(IF(COUNTIF('_Data'!$AA$2:$AA$41,$H$14)>0,"● "&COUNTIF('_Data'!$AA$2:$AA$41,$H$14)&IF(COUNTIF('_Data'!$AA$2:$AA$41,$H$14)>1," events"," event"),"")&IF(COUNTIF('_Data'!$AA$42:$AA$101,$H$14)>0," ▲ "&COUNTIF('_Data'!$AA$42:$AA$101,$H$14)&" due",""))) | J15: =IFERROR(IF(INDEX('_Data'!$AA$2:$AA$41,$N$9+3)="","",IF(MONTH(INDEX('_Data'!$AA$2:$AA$41,$N$9+3))<>CalMonth,"",INDEX('_Data'!$AA$2:$AA$41,$N$9+3))),"") | K15: =IF($J15="","",INDEX('_Data'!$AB$2:$AB$41,$N$9+3)) | L15: =IF($J15="","",INDEX('_Data'!$AC$2:$AC$41,$N$9+3))
B16: =IF(MONTH(DATE(CalYear,CalMonth,1)-WEEKDAY(DATE(CalYear,CalMonth,1),2)+1+14)=CalMonth,DATE(CalYear,CalMonth,1)-WEEKDAY(DATE(CalYear,CalMonth,1),2)+1+14,"") | C16: =IF(MONTH(DATE(CalYear,CalMonth,1)-WEEKDAY(DATE(CalYear,CalMonth,1),2)+1+15)=CalMonth,DATE(CalYear,CalMonth,1)-WEEKDAY(DATE(CalYear,CalMonth,1),2)+1+15,"") | D16: =IF(MONTH(DATE(CalYear,CalMonth,1)-WEEKDAY(DATE(CalYear,CalMonth,1),2)+1+16)=CalMonth,DATE(CalYear,CalMonth,1)-WEEKDAY(DATE(CalYear,CalMonth,1),2)+1+16,"") | E16: =IF(MONTH(DATE(CalYear,CalMonth,1)-WEEKDAY(DATE(CalYear,CalMonth,1),2)+1+17)=CalMonth,DATE(CalYear,CalMonth,1)-WEEKDAY(DATE(CalYear,CalMonth,1),2)+1+17,"") | F16: =IF(MONTH(DATE(CalYear,CalMonth,1)-WEEKDAY(DATE(CalYear,CalMonth,1),2)+1+18)=CalMonth,DATE(CalYear,CalMonth,1)-WEEKDAY(DATE(CalYear,CalMonth,1),2)+1+18,"") | G16: =IF(MONTH(DATE(CalYear,CalMonth,1)-WEEKDAY(DATE(CalYear,CalMonth,1),2)+1+19)=CalMonth,DATE(CalYear,CalMonth,1)-WEEKDAY(DATE(CalYear,CalMonth,1),2)+1+19,"") | H16: =IF(MONTH(DATE(CalYear,CalMonth,1)-WEEKDAY(DATE(CalYear,CalMonth,1),2)+1+20)=CalMonth,DATE(CalYear,CalMonth,1)-WEEKDAY(DATE(CalYear,CalMonth,1),2)+1+20,"") | J16: =IFERROR(IF(INDEX('_Data'!$AA$2:$AA$41,$N$9+4)="","",IF(MONTH(INDEX('_Data'!$AA$2:$AA$41,$N$9+4))<>CalMonth,"",INDEX('_Data'!$AA$2:$AA$41,$N$9+4))),"") | K16: =IF($J16="","",INDEX('_Data'!$AB$2:$AB$41,$N$9+4)) | L16: =IF($J16="","",INDEX('_Data'!$AC$2:$AC$41,$N$9+4))
B17: =IF($B$16="","",TRIM(IF(COUNTIF('_Data'!$AA$2:$AA$41,$B$16)>0,"● "&COUNTIF('_Data'!$AA$2:$AA$41,$B$16)&IF(COUNTIF('_Data'!$AA$2:$AA$41,$B$16)>1," events"," event"),"")&IF(COUNTIF('_Data'!$AA$42:$AA$101,$B$16)>0," ▲ "&COUNTIF('_Data'!$AA$42:$AA$101,$B$16)&" due",""))) | C17: =IF($C$16="","",TRIM(IF(COUNTIF('_Data'!$AA$2:$AA$41,$C$16)>0,"● "&COUNTIF('_Data'!$AA$2:$AA$41,$C$16)&IF(COUNTIF('_Data'!$AA$2:$AA$41,$C$16)>1," events"," event"),"")&IF(COUNTIF('_Data'!$AA$42:$AA$101,$C$16)>0," ▲ "&COUNTIF('_Data'!$AA$42:$AA$101,$C$16)&" due",""))) | D17: =IF($D$16="","",TRIM(IF(COUNTIF('_Data'!$AA$2:$AA$41,$D$16)>0,"● "&COUNTIF('_Data'!$AA$2:$AA$41,$D$16)&IF(COUNTIF('_Data'!$AA$2:$AA$41,$D$16)>1," events"," event"),"")&IF(COUNTIF('_Data'!$AA$42:$AA$101,$D$16)>0," ▲ "&COUNTIF('_Data'!$AA$42:$AA$101,$D$16)&" due",""))) | E17: =IF($E$16="","",TRIM(IF(COUNTIF('_Data'!$AA$2:$AA$41,$E$16)>0,"● "&COUNTIF('_Data'!$AA$2:$AA$41,$E$16)&IF(COUNTIF('_Data'!$AA$2:$AA$41,$E$16)>1," events"," event"),"")&IF(COUNTIF('_Data'!$AA$42:$AA$101,$E$16)>0," ▲ "&COUNTIF('_Data'!$AA$42:$AA$101,$E$16)&" due",""))) | F17: =IF($F$16="","",TRIM(IF(COUNTIF('_Data'!$AA$2:$AA$41,$F$16)>0,"● "&COUNTIF('_Data'!$AA$2:$AA$41,$F$16)&IF(COUNTIF('_Data'!$AA$2:$AA$41,$F$16)>1," events"," event"),"")&IF(COUNTIF('_Data'!$AA$42:$AA$101,$F$16)>0," ▲ "&COUNTIF('_Data'!$AA$42:$AA$101,$F$16)&" due",""))) | G17: =IF($G$16="","",TRIM(IF(COUNTIF('_Data'!$AA$2:$AA$41,$G$16)>0,"● "&COUNTIF('_Data'!$AA$2:$AA$41,$G$16)&IF(COUNTIF('_Data'!$AA$2:$AA$41,$G$16)>1," events"," event"),"")&IF(COUNTIF('_Data'!$AA$42:$AA$101,$G$16)>0," ▲ "&COUNTIF('_Data'!$AA$42:$AA$101,$G$16)&" due",""))) | H17: =IF($H$16="","",TRIM(IF(COUNTIF('_Data'!$AA$2:$AA$41,$H$16)>0,"● "&COUNTIF('_Data'!$AA$2:$AA$41,$H$16)&IF(COUNTIF('_Data'!$AA$2:$AA$41,$H$16)>1," events"," event"),"")&IF(COUNTIF('_Data'!$AA$42:$AA$101,$H$16)>0," ▲ "&COUNTIF('_Data'!$AA$42:$AA$101,$H$16)&" due",""))) | J17: =IFERROR(IF(INDEX('_Data'!$AA$2:$AA$41,$N$9+5)="","",IF(MONTH(INDEX('_Data'!$AA$2:$AA$41,$N$9+5))<>CalMonth,"",INDEX('_Data'!$AA$2:$AA$41,$N$9+5))),"") | K17: =IF($J17="","",INDEX('_Data'!$AB$2:$AB$41,$N$9+5)) | L17: =IF($J17="","",INDEX('_Data'!$AC$2:$AC$41,$N$9+5))
B18: =IF(MONTH(DATE(CalYear,CalMonth,1)-WEEKDAY(DATE(CalYear,CalMonth,1),2)+1+21)=CalMonth,DATE(CalYear,CalMonth,1)-WEEKDAY(DATE(CalYear,CalMonth,1),2)+1+21,"") | C18: =IF(MONTH(DATE(CalYear,CalMonth,1)-WEEKDAY(DATE(CalYear,CalMonth,1),2)+1+22)=CalMonth,DATE(CalYear,CalMonth,1)-WEEKDAY(DATE(CalYear,CalMonth,1),2)+1+22,"") | D18: =IF(MONTH(DATE(CalYear,CalMonth,1)-WEEKDAY(DATE(CalYear,CalMonth,1),2)+1+23)=CalMonth,DATE(CalYear,CalMonth,1)-WEEKDAY(DATE(CalYear,CalMonth,1),2)+1+23,"") | E18: =IF(MONTH(DATE(CalYear,CalMonth,1)-WEEKDAY(DATE(CalYear,CalMonth,1),2)+1+24)=CalMonth,DATE(CalYear,CalMonth,1)-WEEKDAY(DATE(CalYear,CalMonth,1),2)+1+24,"") | F18: =IF(MONTH(DATE(CalYear,CalMonth,1)-WEEKDAY(DATE(CalYear,CalMonth,1),2)+1+25)=CalMonth,DATE(CalYear,CalMonth,1)-WEEKDAY(DATE(CalYear,CalMonth,1),2)+1+25,"") | G18: =IF(MONTH(DATE(CalYear,CalMonth,1)-WEEKDAY(DATE(CalYear,CalMonth,1),2)+1+26)=CalMonth,DATE(CalYear,CalMonth,1)-WEEKDAY(DATE(CalYear,CalMonth,1),2)+1+26,"") | H18: =IF(MONTH(DATE(CalYear,CalMonth,1)-WEEKDAY(DATE(CalYear,CalMonth,1),2)+1+27)=CalMonth,DATE(CalYear,CalMonth,1)-WEEKDAY(DATE(CalYear,CalMonth,1),2)+1+27,"") | J18: =IFERROR(IF(INDEX('_Data'!$AA$2:$AA$41,$N$9+6)="","",IF(MONTH(INDEX('_Data'!$AA$2:$AA$41,$N$9+6))<>CalMonth,"",INDEX('_Data'!$AA$2:$AA$41,$N$9+6))),"") | K18: =IF($J18="","",INDEX('_Data'!$AB$2:$AB$41,$N$9+6)) | L18: =IF($J18="","",INDEX('_Data'!$AC$2:$AC$41,$N$9+6))
B19: =IF($B$18="","",TRIM(IF(COUNTIF('_Data'!$AA$2:$AA$41,$B$18)>0,"● "&COUNTIF('_Data'!$AA$2:$AA$41,$B$18)&IF(COUNTIF('_Data'!$AA$2:$AA$41,$B$18)>1," events"," event"),"")&IF(COUNTIF('_Data'!$AA$42:$AA$101,$B$18)>0," ▲ "&COUNTIF('_Data'!$AA$42:$AA$101,$B$18)&" due",""))) | C19: =IF($C$18="","",TRIM(IF(COUNTIF('_Data'!$AA$2:$AA$41,$C$18)>0,"● "&COUNTIF('_Data'!$AA$2:$AA$41,$C$18)&IF(COUNTIF('_Data'!$AA$2:$AA$41,$C$18)>1," events"," event"),"")&IF(COUNTIF('_Data'!$AA$42:$AA$101,$C$18)>0," ▲ "&COUNTIF('_Data'!$AA$42:$AA$101,$C$18)&" due",""))) | D19: =IF($D$18="","",TRIM(IF(COUNTIF('_Data'!$AA$2:$AA$41,$D$18)>0,"● "&COUNTIF('_Data'!$AA$2:$AA$41,$D$18)&IF(COUNTIF('_Data'!$AA$2:$AA$41,$D$18)>1," events"," event"),"")&IF(COUNTIF('_Data'!$AA$42:$AA$101,$D$18)>0," ▲ "&COUNTIF('_Data'!$AA$42:$AA$101,$D$18)&" due",""))) | E19: =IF($E$18="","",TRIM(IF(COUNTIF('_Data'!$AA$2:$AA$41,$E$18)>0,"● "&COUNTIF('_Data'!$AA$2:$AA$41,$E$18)&IF(COUNTIF('_Data'!$AA$2:$AA$41,$E$18)>1," events"," event"),"")&IF(COUNTIF('_Data'!$AA$42:$AA$101,$E$18)>0," ▲ "&COUNTIF('_Data'!$AA$42:$AA$101,$E$18)&" due",""))) | F19: =IF($F$18="","",TRIM(IF(COUNTIF('_Data'!$AA$2:$AA$41,$F$18)>0,"● "&COUNTIF('_Data'!$AA$2:$AA$41,$F$18)&IF(COUNTIF('_Data'!$AA$2:$AA$41,$F$18)>1," events"," event"),"")&IF(COUNTIF('_Data'!$AA$42:$AA$101,$F$18)>0," ▲ "&COUNTIF('_Data'!$AA$42:$AA$101,$F$18)&" due",""))) | G19: =IF($G$18="","",TRIM(IF(COUNTIF('_Data'!$AA$2:$AA$41,$G$18)>0,"● "&COUNTIF('_Data'!$AA$2:$AA$41,$G$18)&IF(COUNTIF('_Data'!$AA$2:$AA$41,$G$18)>1," events"," event"),"")&IF(COUNTIF('_Data'!$AA$42:$AA$101,$G$18)>0," ▲ "&COUNTIF('_Data'!$AA$42:$AA$101,$G$18)&" due",""))) | H19: =IF($H$18="","",TRIM(IF(COUNTIF('_Data'!$AA$2:$AA$41,$H$18)>0,"● "&COUNTIF('_Data'!$AA$2:$AA$41,$H$18)&IF(COUNTIF('_Data'!$AA$2:$AA$41,$H$18)>1," events"," event"),"")&IF(COUNTIF('_Data'!$AA$42:$AA$101,$H$18)>0," ▲ "&COUNTIF('_Data'!$AA$42:$AA$101,$H$18)&" due",""))) | J19: =IFERROR(IF(INDEX('_Data'!$AA$2:$AA$41,$N$9+7)="","",IF(MONTH(INDEX('_Data'!$AA$2:$AA$41,$N$9+7))<>CalMonth,"",INDEX('_Data'!$AA$2:$AA$41,$N$9+7))),"") | K19: =IF($J19="","",INDEX('_Data'!$AB$2:$AB$41,$N$9+7)) | L19: =IF($J19="","",INDEX('_Data'!$AC$2:$AC$41,$N$9+7))
B20: =IF(MONTH(DATE(CalYear,CalMonth,1)-WEEKDAY(DATE(CalYear,CalMonth,1),2)+1+28)=CalMonth,DATE(CalYear,CalMonth,1)-WEEKDAY(DATE(CalYear,CalMonth,1),2)+1+28,"") | C20: =IF(MONTH(DATE(CalYear,CalMonth,1)-WEEKDAY(DATE(CalYear,CalMonth,1),2)+1+29)=CalMonth,DATE(CalYear,CalMonth,1)-WEEKDAY(DATE(CalYear,CalMonth,1),2)+1+29,"") | D20: =IF(MONTH(DATE(CalYear,CalMonth,1)-WEEKDAY(DATE(CalYear,CalMonth,1),2)+1+30)=CalMonth,DATE(CalYear,CalMonth,1)-WEEKDAY(DATE(CalYear,CalMonth,1),2)+1+30,"") | E20: =IF(MONTH(DATE(CalYear,CalMonth,1)-WEEKDAY(DATE(CalYear,CalMonth,1),2)+1+31)=CalMonth,DATE(CalYear,CalMonth,1)-WEEKDAY(DATE(CalYear,CalMonth,1),2)+1+31,"") | F20: =IF(MONTH(DATE(CalYear,CalMonth,1)-WEEKDAY(DATE(CalYear,CalMonth,1),2)+1+32)=CalMonth,DATE(CalYear,CalMonth,1)-WEEKDAY(DATE(CalYear,CalMonth,1),2)+1+32,"") | G20: =IF(MONTH(DATE(CalYear,CalMonth,1)-WEEKDAY(DATE(CalYear,CalMonth,1),2)+1+33)=CalMonth,DATE(CalYear,CalMonth,1)-WEEKDAY(DATE(CalYear,CalMonth,1),2)+1+33,"") | H20: =IF(MONTH(DATE(CalYear,CalMonth,1)-WEEKDAY(DATE(CalYear,CalMonth,1),2)+1+34)=CalMonth,DATE(CalYear,CalMonth,1)-WEEKDAY(DATE(CalYear,CalMonth,1),2)+1+34,"") | J20: =IFERROR(IF(INDEX('_Data'!$AA$2:$AA$41,$N$9+8)="","",IF(MONTH(INDEX('_Data'!$AA$2:$AA$41,$N$9+8))<>CalMonth,"",INDEX('_Data'!$AA$2:$AA$41,$N$9+8))),"") | K20: =IF($J20="","",INDEX('_Data'!$AB$2:$AB$41,$N$9+8)) | L20: =IF($J20="","",INDEX('_Data'!$AC$2:$AC$41,$N$9+8))
B21: =IF($B$20="","",TRIM(IF(COUNTIF('_Data'!$AA$2:$AA$41,$B$20)>0,"● "&COUNTIF('_Data'!$AA$2:$AA$41,$B$20)&IF(COUNTIF('_Data'!$AA$2:$AA$41,$B$20)>1," events"," event"),"")&IF(COUNTIF('_Data'!$AA$42:$AA$101,$B$20)>0," ▲ "&COUNTIF('_Data'!$AA$42:$AA$101,$B$20)&" due",""))) | C21: =IF($C$20="","",TRIM(IF(COUNTIF('_Data'!$AA$2:$AA$41,$C$20)>0,"● "&COUNTIF('_Data'!$AA$2:$AA$41,$C$20)&IF(COUNTIF('_Data'!$AA$2:$AA$41,$C$20)>1," events"," event"),"")&IF(COUNTIF('_Data'!$AA$42:$AA$101,$C$20)>0," ▲ "&COUNTIF('_Data'!$AA$42:$AA$101,$C$20)&" due",""))) | D21: =IF($D$20="","",TRIM(IF(COUNTIF('_Data'!$AA$2:$AA$41,$D$20)>0,"● "&COUNTIF('_Data'!$AA$2:$AA$41,$D$20)&IF(COUNTIF('_Data'!$AA$2:$AA$41,$D$20)>1," events"," event"),"")&IF(COUNTIF('_Data'!$AA$42:$AA$101,$D$20)>0," ▲ "&COUNTIF('_Data'!$AA$42:$AA$101,$D$20)&" due",""))) | E21: =IF($E$20="","",TRIM(IF(COUNTIF('_Data'!$AA$2:$AA$41,$E$20)>0,"● "&COUNTIF('_Data'!$AA$2:$AA$41,$E$20)&IF(COUNTIF('_Data'!$AA$2:$AA$41,$E$20)>1," events"," event"),"")&IF(COUNTIF('_Data'!$AA$42:$AA$101,$E$20)>0," ▲ "&COUNTIF('_Data'!$AA$42:$AA$101,$E$20)&" due",""))) | F21: =IF($F$20="","",TRIM(IF(COUNTIF('_Data'!$AA$2:$AA$41,$F$20)>0,"● "&COUNTIF('_Data'!$AA$2:$AA$41,$F$20)&IF(COUNTIF('_Data'!$AA$2:$AA$41,$F$20)>1," events"," event"),"")&IF(COUNTIF('_Data'!$AA$42:$AA$101,$F$20)>0," ▲ "&COUNTIF('_Data'!$AA$42:$AA$101,$F$20)&" due",""))) | G21: =IF($G$20="","",TRIM(IF(COUNTIF('_Data'!$AA$2:$AA$41,$G$20)>0,"● "&COUNTIF('_Data'!$AA$2:$AA$41,$G$20)&IF(COUNTIF('_Data'!$AA$2:$AA$41,$G$20)>1," events"," event"),"")&IF(COUNTIF('_Data'!$AA$42:$AA$101,$G$20)>0," ▲ "&COUNTIF('_Data'!$AA$42:$AA$101,$G$20)&" due",""))) | H21: =IF($H$20="","",TRIM(IF(COUNTIF('_Data'!$AA$2:$AA$41,$H$20)>0,"● "&COUNTIF('_Data'!$AA$2:$AA$41,$H$20)&IF(COUNTIF('_Data'!$AA$2:$AA$41,$H$20)>1," events"," event"),"")&IF(COUNTIF('_Data'!$AA$42:$AA$101,$H$20)>0," ▲ "&COUNTIF('_Data'!$AA$42:$AA$101,$H$20)&" due",""))) | J21: =IFERROR(IF(INDEX('_Data'!$AA$2:$AA$41,$N$9+9)="","",IF(MONTH(INDEX('_Data'!$AA$2:$AA$41,$N$9+9))<>CalMonth,"",INDEX('_Data'!$AA$2:$AA$41,$N$9+9))),"") | K21: =IF($J21="","",INDEX('_Data'!$AB$2:$AB$41,$N$9+9)) | L21: =IF($J21="","",INDEX('_Data'!$AC$2:$AC$41,$N$9+9))
B22: =IF(MONTH(DATE(CalYear,CalMonth,1)-WEEKDAY(DATE(CalYear,CalMonth,1),2)+1+35)=CalMonth,DATE(CalYear,CalMonth,1)-WEEKDAY(DATE(CalYear,CalMonth,1),2)+1+35,"") | C22: =IF(MONTH(DATE(CalYear,CalMonth,1)-WEEKDAY(DATE(CalYear,CalMonth,1),2)+1+36)=CalMonth,DATE(CalYear,CalMonth,1)-WEEKDAY(DATE(CalYear,CalMonth,1),2)+1+36,"") | D22: =IF(MONTH(DATE(CalYear,CalMonth,1)-WEEKDAY(DATE(CalYear,CalMonth,1),2)+1+37)=CalMonth,DATE(CalYear,CalMonth,1)-WEEKDAY(DATE(CalYear,CalMonth,1),2)+1+37,"") | E22: =IF(MONTH(DATE(CalYear,CalMonth,1)-WEEKDAY(DATE(CalYear,CalMonth,1),2)+1+38)=CalMonth,DATE(CalYear,CalMonth,1)-WEEKDAY(DATE(CalYear,CalMonth,1),2)+1+38,"") | F22: =IF(MONTH(DATE(CalYear,CalMonth,1)-WEEKDAY(DATE(CalYear,CalMonth,1),2)+1+39)=CalMonth,DATE(CalYear,CalMonth,1)-WEEKDAY(DATE(CalYear,CalMonth,1),2)+1+39,"") | G22: =IF(MONTH(DATE(CalYear,CalMonth,1)-WEEKDAY(DATE(CalYear,CalMonth,1),2)+1+40)=CalMonth,DATE(CalYear,CalMonth,1)-WEEKDAY(DATE(CalYear,CalMonth,1),2)+1+40,"") | H22: =IF(MONTH(DATE(CalYear,CalMonth,1)-WEEKDAY(DATE(CalYear,CalMonth,1),2)+1+41)=CalMonth,DATE(CalYear,CalMonth,1)-WEEKDAY(DATE(CalYear,CalMonth,1),2)+1+41,"") | J22: =IFERROR(IF(INDEX('_Data'!$AA$2:$AA$41,$N$9+10)="","",IF(MONTH(INDEX('_Data'!$AA$2:$AA$41,$N$9+10))<>CalMonth,"",INDEX('_Data'!$AA$2:$AA$41,$N$9+10))),"") | K22: =IF($J22="","",INDEX('_Data'!$AB$2:$AB$41,$N$9+10)) | L22: =IF($J22="","",INDEX('_Data'!$AC$2:$AC$41,$N$9+10))
B23: =IF($B$22="","",TRIM(IF(COUNTIF('_Data'!$AA$2:$AA$41,$B$22)>0,"● "&COUNTIF('_Data'!$AA$2:$AA$41,$B$22)&IF(COUNTIF('_Data'!$AA$2:$AA$41,$B$22)>1," events"," event"),"")&IF(COUNTIF('_Data'!$AA$42:$AA$101,$B$22)>0," ▲ "&COUNTIF('_Data'!$AA$42:$AA$101,$B$22)&" due",""))) | C23: =IF($C$22="","",TRIM(IF(COUNTIF('_Data'!$AA$2:$AA$41,$C$22)>0,"● "&COUNTIF('_Data'!$AA$2:$AA$41,$C$22)&IF(COUNTIF('_Data'!$AA$2:$AA$41,$C$22)>1," events"," event"),"")&IF(COUNTIF('_Data'!$AA$42:$AA$101,$C$22)>0," ▲ "&COUNTIF('_Data'!$AA$42:$AA$101,$C$22)&" due",""))) | D23: =IF($D$22="","",TRIM(IF(COUNTIF('_Data'!$AA$2:$AA$41,$D$22)>0,"● "&COUNTIF('_Data'!$AA$2:$AA$41,$D$22)&IF(COUNTIF('_Data'!$AA$2:$AA$41,$D$22)>1," events"," event"),"")&IF(COUNTIF('_Data'!$AA$42:$AA$101,$D$22)>0," ▲ "&COUNTIF('_Data'!$AA$42:$AA$101,$D$22)&" due",""))) | E23: =IF($E$22="","",TRIM(IF(COUNTIF('_Data'!$AA$2:$AA$41,$E$22)>0,"● "&COUNTIF('_Data'!$AA$2:$AA$41,$E$22)&IF(COUNTIF('_Data'!$AA$2:$AA$41,$E$22)>1," events"," event"),"")&IF(COUNTIF('_Data'!$AA$42:$AA$101,$E$22)>0," ▲ "&COUNTIF('_Data'!$AA$42:$AA$101,$E$22)&" due",""))) | F23: =IF($F$22="","",TRIM(IF(COUNTIF('_Data'!$AA$2:$AA$41,$F$22)>0,"● "&COUNTIF('_Data'!$AA$2:$AA$41,$F$22)&IF(COUNTIF('_Data'!$AA$2:$AA$41,$F$22)>1," events"," event"),"")&IF(COUNTIF('_Data'!$AA$42:$AA$101,$F$22)>0," ▲ "&COUNTIF('_Data'!$AA$42:$AA$101,$F$22)&" due",""))) | G23: =IF($G$22="","",TRIM(IF(COUNTIF('_Data'!$AA$2:$AA$41,$G$22)>0,"● "&COUNTIF('_Data'!$AA$2:$AA$41,$G$22)&IF(COUNTIF('_Data'!$AA$2:$AA$41,$G$22)>1," events"," event"),"")&IF(COUNTIF('_Data'!$AA$42:$AA$101,$G$22)>0," ▲ "&COUNTIF('_Data'!$AA$42:$AA$101,$G$22)&" due",""))) | H23: =IF($H$22="","",TRIM(IF(COUNTIF('_Data'!$AA$2:$AA$41,$H$22)>0,"● "&COUNTIF('_Data'!$AA$2:$AA$41,$H$22)&IF(COUNTIF('_Data'!$AA$2:$AA$41,$H$22)>1," events"," event"),"")&IF(COUNTIF('_Data'!$AA$42:$AA$101,$H$22)>0," ▲ "&COUNTIF('_Data'!$AA$42:$AA$101,$H$22)&" due",""))) | J23: =IFERROR(IF(INDEX('_Data'!$AA$2:$AA$41,$N$9+11)="","",IF(MONTH(INDEX('_Data'!$AA$2:$AA$41,$N$9+11))<>CalMonth,"",INDEX('_Data'!$AA$2:$AA$41,$N$9+11))),"") | K23: =IF($J23="","",INDEX('_Data'!$AB$2:$AB$41,$N$9+11)) | L23: =IF($J23="","",INDEX('_Data'!$AC$2:$AC$41,$N$9+11))
J25: Payments due
J26: =IFERROR(IF(INDEX('_Data'!$AA$42:$AA$101,$N$10+0)="","",IF(MONTH(INDEX('_Data'!$AA$42:$AA$101,$N$10+0))<>CalMonth,"",INDEX('_Data'!$AA$42:$AA$101,$N$10+0))),"") | K26: =IF($J26="","",INDEX('_Data'!$AB$42:$AB$101,$N$10+0)) | L26: =IF($J26="","",INDEX('_Data'!$AC$42:$AC$101,$N$10+0))
J27: =IFERROR(IF(INDEX('_Data'!$AA$42:$AA$101,$N$10+1)="","",IF(MONTH(INDEX('_Data'!$AA$42:$AA$101,$N$10+1))<>CalMonth,"",INDEX('_Data'!$AA$42:$AA$101,$N$10+1))),"") | K27: =IF($J27="","",INDEX('_Data'!$AB$42:$AB$101,$N$10+1)) | L27: =IF($J27="","",INDEX('_Data'!$AC$42:$AC$101,$N$10+1))
J28: =IFERROR(IF(INDEX('_Data'!$AA$42:$AA$101,$N$10+2)="","",IF(MONTH(INDEX('_Data'!$AA$42:$AA$101,$N$10+2))<>CalMonth,"",INDEX('_Data'!$AA$42:$AA$101,$N$10+2))),"") | K28: =IF($J28="","",INDEX('_Data'!$AB$42:$AB$101,$N$10+2)) | L28: =IF($J28="","",INDEX('_Data'!$AC$42:$AC$101,$N$10+2))
J29: =IFERROR(IF(INDEX('_Data'!$AA$42:$AA$101,$N$10+3)="","",IF(MONTH(INDEX('_Data'!$AA$42:$AA$101,$N$10+3))<>CalMonth,"",INDEX('_Data'!$AA$42:$AA$101,$N$10+3))),"") | K29: =IF($J29="","",INDEX('_Data'!$AB$42:$AB$101,$N$10+3)) | L29: =IF($J29="","",INDEX('_Data'!$AC$42:$AC$101,$N$10+3))
J30: =IFERROR(IF(INDEX('_Data'!$AA$42:$AA$101,$N$10+4)="","",IF(MONTH(INDEX('_Data'!$AA$42:$AA$101,$N$10+4))<>CalMonth,"",INDEX('_Data'!$AA$42:$AA$101,$N$10+4))),"") | K30: =IF($J30="","",INDEX('_Data'!$AB$42:$AB$101,$N$10+4)) | L30: =IF($J30="","",INDEX('_Data'!$AC$42:$AC$101,$N$10+4))
J31: =IFERROR(IF(INDEX('_Data'!$AA$42:$AA$101,$N$10+5)="","",IF(MONTH(INDEX('_Data'!$AA$42:$AA$101,$N$10+5))<>CalMonth,"",INDEX('_Data'!$AA$42:$AA$101,$N$10+5))),"") | K31: =IF($J31="","",INDEX('_Data'!$AB$42:$AB$101,$N$10+5)) | L31: =IF($J31="","",INDEX('_Data'!$AC$42:$AC$101,$N$10+5))
J32: =IFERROR(IF(INDEX('_Data'!$AA$42:$AA$101,$N$10+6)="","",IF(MONTH(INDEX('_Data'!$AA$42:$AA$101,$N$10+6))<>CalMonth,"",INDEX('_Data'!$AA$42:$AA$101,$N$10+6))),"") | K32: =IF($J32="","",INDEX('_Data'!$AB$42:$AB$101,$N$10+6)) | L32: =IF($J32="","",INDEX('_Data'!$AC$42:$AC$101,$N$10+6))
J33: =IFERROR(IF(INDEX('_Data'!$AA$42:$AA$101,$N$10+7)="","",IF(MONTH(INDEX('_Data'!$AA$42:$AA$101,$N$10+7))<>CalMonth,"",INDEX('_Data'!$AA$42:$AA$101,$N$10+7))),"") | K33: =IF($J33="","",INDEX('_Data'!$AB$42:$AB$101,$N$10+7)) | L33: =IF($J33="","",INDEX('_Data'!$AC$42:$AC$101,$N$10+7))
J34: =IFERROR(IF(INDEX('_Data'!$AA$42:$AA$101,$N$10+8)="","",IF(MONTH(INDEX('_Data'!$AA$42:$AA$101,$N$10+8))<>CalMonth,"",INDEX('_Data'!$AA$42:$AA$101,$N$10+8))),"") | K34: =IF($J34="","",INDEX('_Data'!$AB$42:$AB$101,$N$10+8)) | L34: =IF($J34="","",INDEX('_Data'!$AC$42:$AC$101,$N$10+8))
J35: =IFERROR(IF(INDEX('_Data'!$AA$42:$AA$101,$N$10+9)="","",IF(MONTH(INDEX('_Data'!$AA$42:$AA$101,$N$10+9))<>CalMonth,"",INDEX('_Data'!$AA$42:$AA$101,$N$10+9))),"") | K35: =IF($J35="","",INDEX('_Data'!$AB$42:$AB$101,$N$10+9)) | L35: =IF($J35="","",INDEX('_Data'!$AC$42:$AC$101,$N$10+9))
J36: =IFERROR(IF(INDEX('_Data'!$AA$42:$AA$101,$N$10+10)="","",IF(MONTH(INDEX('_Data'!$AA$42:$AA$101,$N$10+10))<>CalMonth,"",INDEX('_Data'!$AA$42:$AA$101,$N$10+10))),"") | K36: =IF($J36="","",INDEX('_Data'!$AB$42:$AB$101,$N$10+10)) | L36: =IF($J36="","",INDEX('_Data'!$AC$42:$AC$101,$N$10+10))
J37: =IFERROR(IF(INDEX('_Data'!$AA$42:$AA$101,$N$10+11)="","",IF(MONTH(INDEX('_Data'!$AA$42:$AA$101,$N$10+11))<>CalMonth,"",INDEX('_Data'!$AA$42:$AA$101,$N$10+11))),"") | K37: =IF($J37="","",INDEX('_Data'!$AB$42:$AB$101,$N$10+11)) | L37: =IF($J37="","",INDEX('_Data'!$AC$42:$AC$101,$N$10+11))
B40: Change the month and year in section 3 of the Setup tab - the grid, the marks and both lists follow. ● upcoming events ▲ payment deadlines
B42: Setup | D42: 🏠 Home | F42: Clients | H42: Events | J42: Quote
B43: Menu | D43: Stock | F43: Shop | H43: Expenses | J43: Payments
B44: Staff | D44: Equip | F44: Suppliers | H44: ▶ Calendar | J44: P&L
B45: Tax | D45: Checks | F45: Invoice | H45: Help

Sheet 📈 P&L & Reports
B2: P&L & Reports
B3: The year in numbers - profit, cash and where it all went | N3: 🏠 Back to Dashboard
B5: ="Report year: "&ReportYear -> Report year: 2026 | D5: ="Events completed: "&'_Data'!$AF$7 -> Events completed: 0 | F5: ="Cash profit: "&Currency&TEXT('_Data'!$AF$4,"#,##0") -> Cash profit: $0 | H5: ="Best client: "&'_Data'!$AF$36 -> Best client: -
B8: Profit & loss - booked basis | J8: The year in numbers
B9: Event revenue (booked, not cancelled) | D9: =SUMIFS('📅 Events'!$L$8:$L$47,'📅 Events'!$E$8:$E$47,">="&DATE(ReportYear,1,1),'📅 Events'!$E$8:$E$47,"<="&DATE(ReportYear,12,31),'📅 Events'!$Q$8:$Q$47,"<>❌ Cancelled") -> 0
B10: Cost of goods - food & packaging | D10: =SUMIFS('💸 Expenses'!$G$8:$G$67,'💸 Expenses'!$C$8:$C$67,">="&DATE(ReportYear,1,1),'💸 Expenses'!$C$8:$C$67,"<="&DATE(ReportYear,12,31),'💸 Expenses'!$E$8:$E$67,"Ingredients")+SUMIFS('💸 Expenses'!$G$8:$G$67,'💸 Expenses'!$C$8:$C$67,">="&DATE(ReportYear,1,1),'💸 Expenses'!$C$8:$C$67,"<="&DATE(ReportYear,12,31),'💸 Expenses'!$E$8:$E$67,"Packaging") -> 0 | J10: EVENTS COMPLETED | M10: GUESTS SERVED
B11: GROSS PROFIT | D11: =IF($D$9="","",ROUND($D$9-$D$10,2)) -> 0 | J11: ='_Data'!$AF$7 -> 0 | M11: ='_Data'!$AF$13 -> 0
B12: Operating expenses (everything else) | D12: =IF($D$9="","",ROUND(SUMIFS('💸 Expenses'!$G$8:$G$67,'💸 Expenses'!$C$8:$C$67,">="&DATE(ReportYear,1,1),'💸 Expenses'!$C$8:$C$67,"<="&DATE(ReportYear,12,31))-$D$10,2)) -> 0
B13: NET PROFIT | D13: =IF($D$12="","",$D$11-$D$12) -> 0 | J13: AVG ORDER VALUE | M13: AVG PROFIT / EVENT
B14: Gross margin | D14: =IFERROR($D$11/$D$9,"") -> 0 | J14: ='_Data'!$AF$10 -> 0 | M14: ='_Data'!$AF$12 -> 0
B15: Net margin | D15: =IFERROR($D$13/$D$9,"") -> 0
B16: Accrual view: bookings and spend inside the report year, regardless of when cash moved. | J16: BEST EARNING EVENT TYPE | M16: HIGHEST VALUE CLIENT
J17: ='_Data'!$AF$35 -> - | M17: ='_Data'!$AF$36 -> -
B19: Cash by month - what actually landed
B20: Month | C20: Cash in | D20: Cash out | E20: Net | F20: Events
B21: ='_Data'!$H$2 | C21: ='_Data'!$I$2 -> 0 | D21: ='_Data'!$J$2 -> 0 | E21: ='_Data'!$K$2 -> 0 | F21: ='_Data'!$L$2 -> 0
B22: ='_Data'!$H$3 | C22: ='_Data'!$I$3 -> 0 | D22: ='_Data'!$J$3 -> 0 | E22: ='_Data'!$K$3 -> 0 | F22: ='_Data'!$L$3 -> 0
B23: ='_Data'!$H$4 | C23: ='_Data'!$I$4 -> 0 | D23: ='_Data'!$J$4 -> 0 | E23: ='_Data'!$K$4 -> 0 | F23: ='_Data'!$L$4 -> 0
B24: ='_Data'!$H$5 | C24: ='_Data'!$I$5 -> 0 | D24: ='_Data'!$J$5 -> 0 | E24: ='_Data'!$K$5 -> 0 | F24: ='_Data'!$L$5 -> 0
B25: ='_Data'!$H$6 | C25: ='_Data'!$I$6 -> 0 | D25: ='_Data'!$J$6 -> 0 | E25: ='_Data'!$K$6 -> 0 | F25: ='_Data'!$L$6 -> 0
B26: ='_Data'!$H$7 | C26: ='_Data'!$I$7 -> 0 | D26: ='_Data'!$J$7 -> 0 | E26: ='_Data'!$K$7 -> 0 | F26: ='_Data'!$L$7 -> 0
B27: ='_Data'!$H$8 | C27: ='_Data'!$I$8 -> 0 | D27: ='_Data'!$J$8 -> 0 | E27: ='_Data'!$K$8 -> 0 | F27: ='_Data'!$L$8 -> 0
B28: ='_Data'!$H$9 | C28: ='_Data'!$I$9 -> 0 | D28: ='_Data'!$J$9 -> 0 | E28: ='_Data'!$K$9 -> 0 | F28: ='_Data'!$L$9 -> 0
B29: ='_Data'!$H$10 | C29: ='_Data'!$I$10 -> 0 | D29: ='_Data'!$J$10 -> 0 | E29: ='_Data'!$K$10 -> 0 | F29: ='_Data'!$L$10 -> 0
B30: ='_Data'!$H$11 | C30: ='_Data'!$I$11 -> 0 | D30: ='_Data'!$J$11 -> 0 | E30: ='_Data'!$K$11 -> 0 | F30: ='_Data'!$L$11 -> 0
B31: ='_Data'!$H$12 | C31: ='_Data'!$I$12 -> 0 | D31: ='_Data'!$J$12 -> 0 | E31: ='_Data'!$K$12 -> 0 | F31: ='_Data'!$L$12 -> 0
B32: ='_Data'!$H$13 | C32: ='_Data'!$I$13 -> 0 | D32: ='_Data'!$J$13 -> 0 | E32: ='_Data'!$K$13 -> 0 | F32: ='_Data'!$L$13 -> 0
B33: YEAR | C33: =SUM(C21:C32) -> 0 | D33: =SUM(D21:D32) -> 0 | E33: =SUM(E21:E32) -> 0 | F33: =SUM(F21:F32) -> 0
B80: Booked vs cash: the P&L counts bookings and spending in the report year; the monthly table counts money that actually moved. Healthy businesses watch both.
B82: Setup | E82: 🏠 Home | H82: Clients | K82: Events
B83: Quote | E83: Menu | H83: Stock | K83: Shop
B84: Expenses | E84: Payments | H84: Staff | K84: Equip
B85: Suppliers | E85: Calendar | H85: ▶ P&L | K85: Tax
B86: Checks | E86: Invoice | H86: Help

Sheet 🧾 Tax Tracker
B2: Tax Tracker
B3: Sales tax estimated, filed and still due - the honest picture | H3: 🏠 Back to Dashboard
B5: ="Report year: "&ReportYear -> Report year: 2026 | D5: ="Tax rate: "&TEXT(TaxRate,"0.0%") -> Tax rate: 0.0% | F5: ="Collected to date: "&Currency&TEXT('_Data'!$AF$29,"#,##0.00") -> Collected to date: $0.00 | H5: ="Still due: "&Currency&TEXT('_Data'!$AF$30,"#,##0.00") -> Still due: $0.00
B7: The estimate
C9: =SUMIFS('💰 Payments'!$F$8:$F$67,'💰 Payments'!$E$8:$E$67,">="&DATE(ReportYear,1,1),'💰 Payments'!$E$8:$E$67,"<="&DATE(ReportYear,12,31)) -> 0 | D9: Sales subject to tax (invoiced, year)
C10: =TaxRate -> 0 | D10: Your tax rate (from Setup)
C11: =ROUND($C$9*$C$10,2) -> 0 | D11: Tax collected on those sales
C12: =SUM($G$20:$G$39) -> 0 | D12: Tax already filed & paid
C13: =ROUND($C$11-$C$12,2) -> 0 | D13: ESTIMATED TAX STILL DUE
B15: Estimates only - rates and rules vary by country and state. Share this sheet with your accountant, keep the filings log below up to date, and you'll never dread a quarter-end again.
B18: Filings & payments log
A19: # | B19: Date | C19: What was filed / paid | D19: Reference | E19: Type | F19: Amount | G19: Paid by
B20: =IF($C20="","",ROW()-19)
B21: =IF($C21="","",ROW()-19)
B22: =IF($C22="","",ROW()-19)
B23: =IF($C23="","",ROW()-19)
B24: =IF($C24="","",ROW()-19)
B25: =IF($C25="","",ROW()-19)
B26: =IF($C26="","",ROW()-19)
B27: =IF($C27="","",ROW()-19)
B28: =IF($C28="","",ROW()-19)
B29: =IF($C29="","",ROW()-19)
B30: =IF($C30="","",ROW()-19)
B31: =IF($C31="","",ROW()-19)
... B39: =IF($C39="","",ROW()-19)
B40: FILED & PAID | G40: =SUM($G$20:$G$39) -> 0
B44: Setup | C44: 🏠 Home | D44: Clients | E44: Events | F44: Quote | G44: Menu | H44: Stock
B45: Shop | C45: Expenses | D45: Payments | E45: Staff | F45: Equip | G45: Suppliers | H45: Calendar
B46: P&L | C46: ▶ Tax | D46: Checks | E46: Invoice | F46: Help

Sheet ✅ Checklists
B2: Checklists
B3: From “yes” to packed up - the four lists that keep an event on the rails | I3: 🏠 Back to Dashboard
B8: =COUNTIF($B$11:$B$20,"✓")&"/"&10&" done" -> 0/10 done | D8: =IFERROR(REPT("█",ROUND(MIN(1,IFERROR((COUNTIF($B$11:$B$20,"✓"))/(10),0))*14,0))&REPT("░",14-ROUND(MIN(1,IFERROR((COUNTIF($B$11:$B$20,"✓"))/(10),0))*14,0)),"░░░░░░░░░░░░░░") -> ░░░░░░░░░░░░░░ | F8: =COUNTIF($B$23:$B$32,"✓")&"/"&10&" done" -> 0/10 done | H8: =IFERROR(REPT("█",ROUND(MIN(1,IFERROR((COUNTIF($B$23:$B$32,"✓"))/(10),0))*14,0))&REPT("░",14-ROUND(MIN(1,IFERROR((COUNTIF($B$23:$B$32,"✓"))/(10),0))*14,0)),"░░░░░░░░░░░░░░") -> ░░░░░░░░░░░░░░ | J8: =COUNTIF($B$35:$B$44,"✓")&"/"&10&" done" -> 0/10 done | L8: =IFERROR(REPT("█",ROUND(MIN(1,IFERROR((COUNTIF($B$35:$B$44,"✓"))/(10),0))*14,0))&REPT("░",14-ROUND(MIN(1,IFERROR((COUNTIF($B$35:$B$44,"✓"))/(10),0))*14,0)),"░░░░░░░░░░░░░░") -> ░░░░░░░░░░░░░░ | N8: =COUNTIF($B$47:$B$56,"✓")&"/"&10&" done" -> 0/10 done | P8: =IFERROR(REPT("█",ROUND(MIN(1,IFERROR((COUNTIF($B$47:$B$56,"✓"))/(10),0))*14,0))&REPT("░",14-ROUND(MIN(1,IFERROR((COUNTIF($B$47:$B$56,"✓"))/(10),0))*14,0)),"░░░░░░░░░░░░░░") -> ░░░░░░░░░░░░░░
B10: 1 · Event prep - the master list
C11: Confirm date, guest count and menu with the client
C12: Send the quote and get written approval
C13: Collect the deposit and log it on the Payments tab
C14: Book the venue walk-through and floor plan
C15: Finalise the menu and schedule a tasting if needed
C16: Confirm the crew and send the schedule (Staff tab)
C17: Reserve equipment and rentals (Equipment tab)
C18: Build the shopping list against inventory
C19: Order ingredients with long lead times
C20: Confirm delivery, setup and pack-down times
B22: 2 · Shopping & supplies
C23: Stock check against minimum levels (Inventory tab)
C24: Build the per-event shopping list
C25: Compare supplier prices before ordering
C26: Place bulk orders on account / net terms
C27: Buy dairy and proteins (2-3 days before)
C28: Buy fresh produce (1-2 days before)
C29: Confirm delivery slots with suppliers
C30: Receive, check, label and store everything
C31: Prepare anything that can be made ahead
C32: Stage crates per event so nothing walks off
B34: 3 · On the day - the timeline
C35: Load the van the night before (use the packing order)
C36: Team briefing, uniforms and food-safety check
C37: Arrive, set up kitchen and service stations
C38: Start cooking on schedule
C39: Set tables, linen and garnishes
C40: Brief the service team on the run of play
C41: Service begins - plates land on time
C42: Clear and refresh between courses
C43: Pack down equipment and leftovers
C44: Final walk-through with the client before leaving
B46: 4 · Wrap-up & follow-up
C47: Send the final invoice and log the balance
C48: Record actual costs on the Expenses tab
C49: Update inventory quantities after the event
C50: Pay the crew and tick the shifts off
C51: Log mileage, fuel and any parking costs
C52: Note what worked and what to change next time
C53: Ask for a review or a referral
C54: File receipts, photos and the signed quote
C55: Update the client's notes for next time
C56: Celebrate - you earned it
B59: Tweak these until they match how you work - then never improvise at 6am again.
B61: Setup | D61: 🏠 Home | F61: Clients | H61: Events | J61: Quote
B62: Menu | D62: Stock | F62: Shop | H62: Expenses | J62: Payments
B63: Staff | D63: Equip | F63: Suppliers | H63: Calendar | J63: P&L
B64: Tax | D64: ▶ Checks | F64: Invoice | H64: Help

Sheet 🖨️ Invoice & Proposal
B2: =IF(BusinessName="","Your Catering Business",BusinessName) -> Your Catering Business | F2: INVOICE
B4: Invoice # | E4: Date | F4: 46285
B5: Event date | E5: Valid until
B7: BILL TO | F7: PREPARED BY
B11: WHAT YOU'RE BUYING | F11: LINE TOTAL
F12: =IF(OR($C12="",$D12=""),"",ROUND($C12*$D12,2))
F13: =IF(OR($C13="",$D13=""),"",ROUND($C13*$D13,2))
F14: =IF(OR($C14="",$D14=""),"",ROUND($C14*$D14,2))
F15: =IF(OR($C15="",$D15=""),"",ROUND($C15*$D15,2))
F16: =IF(OR($C16="",$D16=""),"",ROUND($C16*$D16,2))
F17: =IF(OR($C17="",$D17=""),"",ROUND($C17*$D17,2))
F18: =IF(OR($C18="",$D18=""),"",ROUND($C18*$D18,2))
F19: =IF(OR($C19="",$D19=""),"",ROUND($C19*$D19,2))
D21: Subtotal | F21: =ROUND(SUM($F$12:$F$19),2)
D22: Discount
D23: Taxable subtotal | F23: =ROUND($F$21-IF($F$22="",0,$F$22),2)
D24: ="Tax ("&TEXT(TaxRate,"0.0%")&" - from Setup)" -> Tax (0.0% - from Setup) | F24: =ROUND($F$23*TaxRate,2)
D25: TOTAL DUE | F25: =ROUND($F$23+$F$24,2)
D26: ="Deposit to confirm ("&TEXT(DepositPct,"0%")&" - from Setup)" -> Deposit to confirm (40% - from Setup) | F26: =ROUND($F$25*DepositPct,2)
D27: Balance after deposit | F27: =ROUND($F$25-$F$26,2)
B29: Notes & terms | F29: Signatures
B30: Deposit due to confirm the date. Final balance due 3 days before the event. Prices valid for 14 days.
F32: Client signature | H32: For the business
F34: Date | H34: For the business
B37: Print this page (File > Print) - it is set up to fit one portrait page. Amounts use the currency symbol from your Setup tab.
B39: Setup | C39: 🏠 Home | D39: Clients | E39: Events | F39: Quote | G39: Menu | H39: Stock
B40: Shop | C40: Expenses | D40: Payments | E40: Staff | F40: Equip | G40: Suppliers | H40: Calendar
B41: P&L | C41: Tax | D41: Checks | E41: ▶ Invoice | F41: Help

Sheet 📖 Start Here
B5: Ultimate Catering Business Spreadsheet
B8: Events • Clients • Quotes • Food Cost • Profit · by Novality Store · v1.0
B11: Works in Microsoft Excel (2016 and newer) and Google Sheets - no macros, nothing to install.
B17: Welcome
B18: This is your whole catering operation in one file: clients, events, quotes, menu costs, inventory, shopping, staff, equipment, money and tax - with a dashboard that adds it all up for you.
B20: Start in three steps
B21: 1 | C21: Open the Setup tab: type your business name, pick your currency and set your target margin and deposit %.
B23: 2 | C23: Add your first event on the Events tab - cost, price, deposit, status. The Dashboard, Calendar and P&L update instantly.
B25: 3 | C25: Log the deposit on the Payments tab and the ingredients on the Shopping List. That's the whole loop - repeat and grow.
B28: What each tab does
B29: 📊 Dashboard | D29: Your live scorecards and charts - everything on this page updates itself.
B30: ⚙️ Setup | D30: Your business name, currency, margins and every dropdown list. Start here.
B31: 👥 Clients | D31: Who you cook for - quotes, deposits and balances.
B32: 📅 Events | D32: Every booking: costs, pricing, profit and the status pipeline.
B33: 🧮 Quote Calculator | D33: Price an event in 30 seconds - margin and deposit included.
B34: 🍽️ Menu Costing | D34: Cost each dish, set the price, watch the margin.
B35: 📦 Inventory | D35: Stock levels, values and automatic reorder alerts.
B36: 🛒 Shopping List | D36: What to buy per event, minus what you already have.
B37: 💸 Expenses | D37: Every cost, categorised - feeds the P&L and the doughnut chart.
B38: 💰 Payments | D38: Invoices, deposits and who still owes what.
B39: 👷 Staff & Labor | D39: Shifts, rates, overtime and the wage bill.
B40: 🍳 Equipment | D40: What you own, what's reserved, what needs a service.
... B47: 📖 Start Here | D47: This page.
B49: The house rules
C50: • Type only in the white cells. Tinted columns calculate themselves - if you type over one you'll get the number back on the next edit anyway.
C51: • Every formula is protected, so a stray keystroke can't break the file. All the input cells stay open; if you ever need to change a formula, use Review › Unprotect Sheet and it's yours.
C52: • Dropdowns: click a cell and pick. The lists live on the Setup tab - add your own options whenever you like and every dropdown updates.
C53: • Dates: type them in almost any format (“15 Oct 2026” works) or double-click and pick from the calendar.
C54: • Room to grow: Clients holds 40 rows, Events 40, Expenses 60, Payments 60, Menu 30. Need more? Right-click a row number inside a table and choose Insert.
C55: • Google Sheets: upload the file to Google Drive and open it with Google Sheets - formulas, dropdowns, colours and charts all carry over.
B57: Licence & support
B58: Personal licence: one purchase, use it for your own business forever, on as many of your own devices as you like. Please don't resell or share the file. Stuck, or spotted something odd? Message us through the shop - we read and answer everything. — Novality Store
B62: Setup | D62: 🏠 Home | F62: Clients
B63: Events | D63: Quote | F63: Menu
B64: Stock | D64: Shop | F64: Expenses
B65: Payments | D65: Staff | F65: Equip
B66: Suppliers | D66: Calendar | F66: P&L
B67: Tax | D67: Checks | F67: Invoice
B68: ▶ Help
