Workbook
Name BusinessName: '⚙️ Lists & Settings'!$C$6
Name Categories: OFFSET('⚙️ Lists & Settings'!$C$23,0,0,MAX(1,COUNTA('⚙️ Lists & Settings'!$C$23:$C$42)),1)
Name Currency: '⚙️ Lists & Settings'!$C$10
Name EventList: OFFSET('🏪 Craft Fairs'!$B$8,0,0,MAX(1,COUNTA('🏪 Craft Fairs'!$B$8:$B$31)),1)
Name HourlyWage: '⚙️ Lists & Settings'!$C$12
Name MaterialsList: OFFSET('🧵 Yarn & Materials'!$B$8,0,0,MAX(1,COUNTA('🧵 Yarn & Materials'!$B$8:$B$31)),1)
Name Message: '⚙️ Lists & Settings'!$C$7
Name OverheadPct: '⚙️ Lists & Settings'!$C$13
Name PaymentMethods: OFFSET('⚙️ Lists & Settings'!$D$23,0,0,MAX(1,COUNTA('⚙️ Lists & Settings'!$D$23:$D$42)),1)
Name ProductsList: OFFSET('🧶 Product Catalog'!$C$8,0,0,MAX(1,COUNTA('🧶 Product Catalog'!$C$8:$C$31)),1)
Name ReportYear: '⚙️ Lists & Settings'!$C$11
Name Suppliers: OFFSET('⚙️ Lists & Settings'!$G$23,0,0,MAX(1,COUNTA('⚙️ Lists & Settings'!$G$23:$G$42)),1)
Name TargetMargin: '⚙️ Lists & Settings'!$C$14
Name Tick: '⚙️ Lists & Settings'!$C$47:$C$48
Name Units: OFFSET('⚙️ Lists & Settings'!$F$23,0,0,MAX(1,COUNTA('⚙️ Lists & Settings'!$F$23:$F$42)),1)
Name YarnWeights: OFFSET('⚙️ Lists & Settings'!$E$23,0,0,MAX(1,COUNTA('⚙️ Lists & Settings'!$E$23:$E$42)),1)

Sheet _Data
A1: Ultimate Crochet Craft Fair Tracker v1.0 - calculation engine (hidden; do not edit) | H1: # | I1: Month | J1: Revenue | K1: COGS | L1: Fees | M1: Net | N1: Margin | P1: Method | Q1: Value | S1: Category | T1: Value | V1: # | W1: Product | X1: Units | Y1: Revenue | Z1: Stock | AA1: Margin | AB1: Profit | AC1: # | AD1: Event | AE1: Sales | AF1: Net | AK1: Ordered | AL1: Item | AN1: Ordered | AO1: Item
H2: 1 | I2: January | J2: =SUMIFS('💰 Sales Log'!$H$8:$H$67,'💰 Sales Log'!$B$8:$B$67,">="&DATE(ReportYear,1,1),'💰 Sales Log'!$B$8:$B$67,"<"&EDATE(DATE(ReportYear,1,1),1)) -> 0 | K2: =SUMIFS('💰 Sales Log'!$M$8:$M$67,'💰 Sales Log'!$B$8:$B$67,">="&DATE(ReportYear,1,1),'💰 Sales Log'!$B$8:$B$67,"<"&EDATE(DATE(ReportYear,1,1),1)) -> 0 | L2: =SUMIFS('🏪 Craft Fairs'!$K$8:$K$31,'🏪 Craft Fairs'!$C$8:$C$31,">="&DATE(ReportYear,1,1),'🏪 Craft Fairs'!$C$8:$C$31,"<"&EDATE(DATE(ReportYear,1,1),1)) -> 0 | M2: =J2-K2-L2 -> 0 | N2: =IFERROR(M2/J2,0) -> 0 | P2: Cash | Q2: =SUMIFS('💰 Sales Log'!$H$8:$H$67,'💰 Sales Log'!$I$8:$I$67,$P$2) -> 816 | S2: Booth fees | T2: =SUM('🏪 Craft Fairs'!$F$8:$F$31) -> 360 | V2: 1 | W2: =IF('🧶 Product Catalog'!$C$8="","",'🧶 Product Catalog'!$C$8) -> Amigurumi Bunny | X2: =IF($W2="","",SUMIFS('💰 Sales Log'!$E$8:$E$67,'💰 Sales Log'!$D$8:$D$67,$W2)) -> 6 | Y2: =IF($W2="","",SUMIFS('💰 Sales Log'!$H$8:$H$67,'💰 Sales Log'!$D$8:$D$67,$W2)) -> 168 | Z2: =IF($W2="","",INDEX('🧶 Product Catalog'!$M$8:$M$31,MATCH($W2,'🧶 Product Catalog'!$C$8:$C$31,0))) -> 5 | AA2: =IF(OR($W2="",$X2=0),"",INDEX('🧶 Product Catalog'!$K$8:$K$31,MATCH($W2,'🧶 Product Catalog'!$C$8:$C$31,0))) -> 0.82142857 | AB2: =IF($W2="","",$Y2-SUMIFS('💰 Sales Log'!$M$8:$M$67,'💰 Sales Log'!$D$8:$D$67,$W2)) -> 138 | AC2: 1 | AD2: =IF('🏪 Craft Fairs'!$B$8="","",'🏪 Craft Fairs'!$B$8) -> Spring Makers Market | AE2: =IF($AD2="","",SUMIFS('💰 Sales Log'!$H$8:$H$67,'💰 Sales Log'!$C$8:$C$67,$AD2)) -> 300 | AF2: =IF($AD2="","",$AE2-SUMIFS('🏪 Craft Fairs'!$K$8:$K$31,'💰 Sales Log'!$C$8:$C$67,$AD2)-SUMIFS('💰 Sales Log'!$M$8:$M$67,'💰 Sales Log'!$C$8:$C$67,$AD2)) -> 151.2 | AH2: Gross sales (all time) | AI2: =SUM('💰 Sales Log'!$H$8:$H$67) -> 1760 | AK2: =IF('🔄 Reorder List'!$B$10="","",'🔄 Reorder List'!$I$10) | AL2: =IF('🔄 Reorder List'!$B$10="","",'🔄 Reorder List'!$B$10) | AN2: =IF('🔄 Reorder List'!$B$25="","",'🔄 Reorder List'!$I$25) | AO2: =IF('🔄 Reorder List'!$B$25="","",'🔄 Reorder List'!$B$25)
H3: 2 | I3: February | J3: =SUMIFS('💰 Sales Log'!$H$8:$H$67,'💰 Sales Log'!$B$8:$B$67,">="&DATE(ReportYear,2,1),'💰 Sales Log'!$B$8:$B$67,"<"&EDATE(DATE(ReportYear,2,1),1)) -> 0 | K3: =SUMIFS('💰 Sales Log'!$M$8:$M$67,'💰 Sales Log'!$B$8:$B$67,">="&DATE(ReportYear,2,1),'💰 Sales Log'!$B$8:$B$67,"<"&EDATE(DATE(ReportYear,2,1),1)) -> 0 | L3: =SUMIFS('🏪 Craft Fairs'!$K$8:$K$31,'🏪 Craft Fairs'!$C$8:$C$31,">="&DATE(ReportYear,2,1),'🏪 Craft Fairs'!$C$8:$C$31,"<"&EDATE(DATE(ReportYear,2,1),1)) -> 0 | M3: =J3-K3-L3 -> 0 | N3: =IFERROR(M3/J3,0) -> 0 | P3: Card | Q3: =SUMIFS('💰 Sales Log'!$H$8:$H$67,'💰 Sales Log'!$I$8:$I$67,$P$3) -> 609 | S3: Travel | T3: =SUM('🏪 Craft Fairs'!$G$8:$G$31) -> 89 | V3: 2 | W3: =IF('🧶 Product Catalog'!$C$9="","",'🧶 Product Catalog'!$C$9) -> Chunky Beanie | X3: =IF($W3="","",SUMIFS('💰 Sales Log'!$E$8:$E$67,'💰 Sales Log'!$D$8:$D$67,$W3)) -> 5 | Y3: =IF($W3="","",SUMIFS('💰 Sales Log'!$H$8:$H$67,'💰 Sales Log'!$D$8:$D$67,$W3)) -> 120 | Z3: =IF($W3="","",INDEX('🧶 Product Catalog'!$M$8:$M$31,MATCH($W3,'🧶 Product Catalog'!$C$8:$C$31,0))) -> 10 | AA3: =IF(OR($W3="",$X3=0),"",INDEX('🧶 Product Catalog'!$K$8:$K$31,MATCH($W3,'🧶 Product Catalog'!$C$8:$C$31,0))) -> 0.7375 | AB3: =IF($W3="","",$Y3-SUMIFS('💰 Sales Log'!$M$8:$M$67,'💰 Sales Log'!$D$8:$D$67,$W3)) -> 88.5 | AC3: 2 | AD3: =IF('🏪 Craft Fairs'!$B$9="","",'🏪 Craft Fairs'!$B$9) -> Easter Craft Bazaar | AE3: =IF($AD3="","",SUMIFS('💰 Sales Log'!$H$8:$H$67,'💰 Sales Log'!$C$8:$C$67,$AD3)) -> 174 | AF3: =IF($AD3="","",$AE3-SUMIFS('🏪 Craft Fairs'!$K$8:$K$31,'💰 Sales Log'!$C$8:$C$67,$AD3)-SUMIFS('💰 Sales Log'!$M$8:$M$67,'💰 Sales Log'!$C$8:$C$67,$AD3)) -> 89.6 | AH3: Discounts given | AI3: =SUM('💰 Sales Log'!$G$8:$G$67) -> 2 | AK3: =IF('🔄 Reorder List'!$B$11="","",'🔄 Reorder List'!$I$11) | AL3: =IF('🔄 Reorder List'!$B$11="","",'🔄 Reorder List'!$B$11) | AN3: =IF('🔄 Reorder List'!$B$26="","",'🔄 Reorder List'!$I$26) | AO3: =IF('🔄 Reorder List'!$B$26="","",'🔄 Reorder List'!$B$26)
H4: 3 | I4: March | J4: =SUMIFS('💰 Sales Log'!$H$8:$H$67,'💰 Sales Log'!$B$8:$B$67,">="&DATE(ReportYear,3,1),'💰 Sales Log'!$B$8:$B$67,"<"&EDATE(DATE(ReportYear,3,1),1)) -> 300 | K4: =SUMIFS('💰 Sales Log'!$M$8:$M$67,'💰 Sales Log'!$B$8:$B$67,">="&DATE(ReportYear,3,1),'💰 Sales Log'!$B$8:$B$67,"<"&EDATE(DATE(ReportYear,3,1),1)) -> 58.8 | L4: =SUMIFS('🏪 Craft Fairs'!$K$8:$K$31,'🏪 Craft Fairs'!$C$8:$C$31,">="&DATE(ReportYear,3,1),'🏪 Craft Fairs'!$C$8:$C$31,"<"&EDATE(DATE(ReportYear,3,1),1)) -> 90 | M4: =J4-K4-L4 -> 151.2 | N4: =IFERROR(M4/J4,0) -> 0 | P4: Bank transfer | Q4: =SUMIFS('💰 Sales Log'!$H$8:$H$67,'💰 Sales Log'!$I$8:$I$67,$P$4) -> 170 | S4: Parking | T4: =SUM('🏪 Craft Fairs'!$H$8:$H$31) -> 31 | V4: 3 | W4: =IF('🧶 Product Catalog'!$C$10="","",'🧶 Product Catalog'!$C$10) -> Granny Square Cardigan | X4: =IF($W4="","",SUMIFS('💰 Sales Log'!$E$8:$E$67,'💰 Sales Log'!$D$8:$D$67,$W4)) -> 1 | Y4: =IF($W4="","",SUMIFS('💰 Sales Log'!$H$8:$H$67,'💰 Sales Log'!$D$8:$D$67,$W4)) -> 95 | Z4: =IF($W4="","",INDEX('🧶 Product Catalog'!$M$8:$M$31,MATCH($W4,'🧶 Product Catalog'!$C$8:$C$31,0))) -> 2 | AA4: =IF(OR($W4="",$X4=0),"",INDEX('🧶 Product Catalog'!$K$8:$K$31,MATCH($W4,'🧶 Product Catalog'!$C$8:$C$31,0))) -> 0.78315789 | AB4: =IF($W4="","",$Y4-SUMIFS('💰 Sales Log'!$M$8:$M$67,'💰 Sales Log'!$D$8:$D$67,$W4)) -> 74.4 | AC4: 3 | AD4: =IF('🏪 Craft Fairs'!$B$10="","",'🏪 Craft Fairs'!$B$10) -> School Fete Stall | AE4: =IF($AD4="","",SUMIFS('💰 Sales Log'!$H$8:$H$67,'💰 Sales Log'!$C$8:$C$67,$AD4)) -> 244 | AF4: =IF($AD4="","",$AE4-SUMIFS('🏪 Craft Fairs'!$K$8:$K$31,'💰 Sales Log'!$C$8:$C$67,$AD4)-SUMIFS('💰 Sales Log'!$M$8:$M$67,'💰 Sales Log'!$C$8:$C$67,$AD4)) -> 156.5 | AH4: Cost of products sold | AI4: =SUM('💰 Sales Log'!$M$8:$M$67) -> 363.5 | AK4: =IF('🔄 Reorder List'!$B$12="","",'🔄 Reorder List'!$I$12) | AL4: =IF('🔄 Reorder List'!$B$12="","",'🔄 Reorder List'!$B$12) | AN4: =IF('🔄 Reorder List'!$B$27="","",'🔄 Reorder List'!$I$27) | AO4: =IF('🔄 Reorder List'!$B$27="","",'🔄 Reorder List'!$B$27)
H5: 4 | I5: April | J5: =SUMIFS('💰 Sales Log'!$H$8:$H$67,'💰 Sales Log'!$B$8:$B$67,">="&DATE(ReportYear,4,1),'💰 Sales Log'!$B$8:$B$67,"<"&EDATE(DATE(ReportYear,4,1),1)) -> 174 | K5: =SUMIFS('💰 Sales Log'!$M$8:$M$67,'💰 Sales Log'!$B$8:$B$67,">="&DATE(ReportYear,4,1),'💰 Sales Log'!$B$8:$B$67,"<"&EDATE(DATE(ReportYear,4,1),1)) -> 30.4 | L5: =SUMIFS('🏪 Craft Fairs'!$K$8:$K$31,'🏪 Craft Fairs'!$C$8:$C$31,">="&DATE(ReportYear,4,1),'🏪 Craft Fairs'!$C$8:$C$31,"<"&EDATE(DATE(ReportYear,4,1),1)) -> 54 | M5: =J5-K5-L5 -> 89.6 | N5: =IFERROR(M5/J5,0) -> 0 | P5: Mobile wallet | Q5: =SUMIFS('💰 Sales Log'!$H$8:$H$67,'💰 Sales Log'!$I$8:$I$67,$P$5) -> 0 | S5: Food & drinks | T5: =SUM('🏪 Craft Fairs'!$I$8:$I$31) -> 60 | V5: 4 | W5: =IF('🧶 Product Catalog'!$C$11="","",'🧶 Product Catalog'!$C$11) -> Market Tote Bag | X5: =IF($W5="","",SUMIFS('💰 Sales Log'!$E$8:$E$67,'💰 Sales Log'!$D$8:$D$67,$W5)) -> 8 | Y5: =IF($W5="","",SUMIFS('💰 Sales Log'!$H$8:$H$67,'💰 Sales Log'!$D$8:$D$67,$W5)) -> 256 | Z5: =IF($W5="","",INDEX('🧶 Product Catalog'!$M$8:$M$31,MATCH($W5,'🧶 Product Catalog'!$C$8:$C$31,0))) -> 3 | AA5: =IF(OR($W5="",$X5=0),"",INDEX('🧶 Product Catalog'!$K$8:$K$31,MATCH($W5,'🧶 Product Catalog'!$C$8:$C$31,0))) -> 0.778125 | AB5: =IF($W5="","",$Y5-SUMIFS('💰 Sales Log'!$M$8:$M$67,'💰 Sales Log'!$D$8:$D$67,$W5)) -> 199.2 | AC5: 4 | AD5: =IF('🏪 Craft Fairs'!$B$11="","",'🏪 Craft Fairs'!$B$11) -> Summer Night Bazaar | AE5: =IF($AD5="","",SUMIFS('💰 Sales Log'!$H$8:$H$67,'💰 Sales Log'!$C$8:$C$67,$AD5)) -> 398 | AF5: =IF($AD5="","",$AE5-SUMIFS('🏪 Craft Fairs'!$K$8:$K$31,'💰 Sales Log'!$C$8:$C$67,$AD5)-SUMIFS('💰 Sales Log'!$M$8:$M$67,'💰 Sales Log'!$C$8:$C$67,$AD5)) -> 199.2 | AH5: Event expenses (all fairs) | AI5: =SUM('🏪 Craft Fairs'!$K$8:$K$31) -> 680 | AK5: =IF('🔄 Reorder List'!$B$13="","",'🔄 Reorder List'!$I$13) | AL5: =IF('🔄 Reorder List'!$B$13="","",'🔄 Reorder List'!$B$13) | AN5: =IF('🔄 Reorder List'!$B$28="","",'🔄 Reorder List'!$I$28) | AO5: =IF('🔄 Reorder List'!$B$28="","",'🔄 Reorder List'!$B$28)
H6: 5 | I6: May | J6: =SUMIFS('💰 Sales Log'!$H$8:$H$67,'💰 Sales Log'!$B$8:$B$67,">="&DATE(ReportYear,5,1),'💰 Sales Log'!$B$8:$B$67,"<"&EDATE(DATE(ReportYear,5,1),1)) -> 244 | K6: =SUMIFS('💰 Sales Log'!$M$8:$M$67,'💰 Sales Log'!$B$8:$B$67,">="&DATE(ReportYear,5,1),'💰 Sales Log'!$B$8:$B$67,"<"&EDATE(DATE(ReportYear,5,1),1)) -> 43.5 | L6: =SUMIFS('🏪 Craft Fairs'!$K$8:$K$31,'🏪 Craft Fairs'!$C$8:$C$31,">="&DATE(ReportYear,5,1),'🏪 Craft Fairs'!$C$8:$C$31,"<"&EDATE(DATE(ReportYear,5,1),1)) -> 44 | M6: =J6-K6-L6 -> 156.5 | N6: =IFERROR(M6/J6,0) -> 0 | P6: Online order | Q6: =SUMIFS('💰 Sales Log'!$H$8:$H$67,'💰 Sales Log'!$I$8:$I$67,$P$6) -> 165 | S6: Display & decor | T6: =SUM('🏪 Craft Fairs'!$J$8:$J$31) -> 140 | V6: 5 | W6: =IF('🧶 Product Catalog'!$C$12="","",'🧶 Product Catalog'!$C$12) -> Cozy Scarf | X6: =IF($W6="","",SUMIFS('💰 Sales Log'!$E$8:$E$67,'💰 Sales Log'!$D$8:$D$67,$W6)) -> 2 | Y6: =IF($W6="","",SUMIFS('💰 Sales Log'!$H$8:$H$67,'💰 Sales Log'!$D$8:$D$67,$W6)) -> 76 | Z6: =IF($W6="","",INDEX('🧶 Product Catalog'!$M$8:$M$31,MATCH($W6,'🧶 Product Catalog'!$C$8:$C$31,0))) -> 4 | AA6: =IF(OR($W6="",$X6=0),"",INDEX('🧶 Product Catalog'!$K$8:$K$31,MATCH($W6,'🧶 Product Catalog'!$C$8:$C$31,0))) -> 0.73684211 | AB6: =IF($W6="","",$Y6-SUMIFS('💰 Sales Log'!$M$8:$M$67,'💰 Sales Log'!$D$8:$D$67,$W6)) -> 56 | AC6: 5 | AD6: =IF('🏪 Craft Fairs'!$B$12="","",'🏪 Craft Fairs'!$B$12) -> Farmers Market Pop-up | AE6: =IF($AD6="","",SUMIFS('💰 Sales Log'!$H$8:$H$67,'💰 Sales Log'!$C$8:$C$67,$AD6)) -> 309 | AF6: =IF($AD6="","",$AE6-SUMIFS('🏪 Craft Fairs'!$K$8:$K$31,'💰 Sales Log'!$C$8:$C$67,$AD6)-SUMIFS('💰 Sales Log'!$M$8:$M$67,'💰 Sales Log'!$C$8:$C$67,$AD6)) -> 163.4 | AH6: Net profit | AI6: =AI2-AI4-AI5 -> 716.5 | AK6: =IF('🔄 Reorder List'!$B$14="","",'🔄 Reorder List'!$I$14) | AL6: =IF('🔄 Reorder List'!$B$14="","",'🔄 Reorder List'!$B$14) | AN6: =IF('🔄 Reorder List'!$B$29="","",'🔄 Reorder List'!$I$29) | AO6: =IF('🔄 Reorder List'!$B$29="","",'🔄 Reorder List'!$B$29)
H7: 6 | I7: June | J7: =SUMIFS('💰 Sales Log'!$H$8:$H$67,'💰 Sales Log'!$B$8:$B$67,">="&DATE(ReportYear,6,1),'💰 Sales Log'!$B$8:$B$67,"<"&EDATE(DATE(ReportYear,6,1),1)) -> 398 | K7: =SUMIFS('💰 Sales Log'!$M$8:$M$67,'💰 Sales Log'!$B$8:$B$67,">="&DATE(ReportYear,6,1),'💰 Sales Log'!$B$8:$B$67,"<"&EDATE(DATE(ReportYear,6,1),1)) -> 82.8 | L7: =SUMIFS('🏪 Craft Fairs'!$K$8:$K$31,'🏪 Craft Fairs'!$C$8:$C$31,">="&DATE(ReportYear,6,1),'🏪 Craft Fairs'!$C$8:$C$31,"<"&EDATE(DATE(ReportYear,6,1),1)) -> 116 | M7: =J7-K7-L7 -> 199.2 | N7: =IFERROR(M7/J7,0) -> 0 | P7: Other | Q7: =SUMIFS('💰 Sales Log'!$H$8:$H$67,'💰 Sales Log'!$I$8:$I$67,$P$7) -> 0 | V7: 6 | W7: =IF('🧶 Product Catalog'!$C$13="","",'🧶 Product Catalog'!$C$13) -> Baby Booties | X7: =IF($W7="","",SUMIFS('💰 Sales Log'!$E$8:$E$67,'💰 Sales Log'!$D$8:$D$67,$W7)) -> 5 | Y7: =IF($W7="","",SUMIFS('💰 Sales Log'!$H$8:$H$67,'💰 Sales Log'!$D$8:$D$67,$W7)) -> 90 | Z7: =IF($W7="","",INDEX('🧶 Product Catalog'!$M$8:$M$31,MATCH($W7,'🧶 Product Catalog'!$C$8:$C$31,0))) -> 3 | AA7: =IF(OR($W7="",$X7=0),"",INDEX('🧶 Product Catalog'!$K$8:$K$31,MATCH($W7,'🧶 Product Catalog'!$C$8:$C$31,0))) -> 0.82222222 | AB7: =IF($W7="","",$Y7-SUMIFS('💰 Sales Log'!$M$8:$M$67,'💰 Sales Log'!$D$8:$D$67,$W7)) -> 74 | AC7: 6 | AD7: =IF('🏪 Craft Fairs'!$B$13="","",'🏪 Craft Fairs'!$B$13) -> Online Order Batch | AE7: =IF($AD7="","",SUMIFS('💰 Sales Log'!$H$8:$H$67,'💰 Sales Log'!$C$8:$C$67,$AD7)) -> 335 | AF7: =IF($AD7="","",$AE7-SUMIFS('🏪 Craft Fairs'!$K$8:$K$31,'💰 Sales Log'!$C$8:$C$67,$AD7)-SUMIFS('💰 Sales Log'!$M$8:$M$67,'💰 Sales Log'!$C$8:$C$67,$AD7)) -> 259.6 | AH7: Profit margin | AI7: =IFERROR(AI6/AI2,0) -> 0.40710227 | AK7: =IF('🔄 Reorder List'!$B$15="","",'🔄 Reorder List'!$I$15) | AL7: =IF('🔄 Reorder List'!$B$15="","",'🔄 Reorder List'!$B$15) | AN7: =IF('🔄 Reorder List'!$B$30="","",'🔄 Reorder List'!$I$30) | AO7: =IF('🔄 Reorder List'!$B$30="","",'🔄 Reorder List'!$B$30)
H8: 7 | I8: July | J8: =SUMIFS('💰 Sales Log'!$H$8:$H$67,'💰 Sales Log'!$B$8:$B$67,">="&DATE(ReportYear,7,1),'💰 Sales Log'!$B$8:$B$67,"<"&EDATE(DATE(ReportYear,7,1),1)) -> 309 | K8: =SUMIFS('💰 Sales Log'!$M$8:$M$67,'💰 Sales Log'!$B$8:$B$67,">="&DATE(ReportYear,7,1),'💰 Sales Log'!$B$8:$B$67,"<"&EDATE(DATE(ReportYear,7,1),1)) -> 72.6 | L8: =SUMIFS('🏪 Craft Fairs'!$K$8:$K$31,'🏪 Craft Fairs'!$C$8:$C$31,">="&DATE(ReportYear,7,1),'🏪 Craft Fairs'!$C$8:$C$31,"<"&EDATE(DATE(ReportYear,7,1),1)) -> 73 | M8: =J8-K8-L8 -> 163.4 | N8: =IFERROR(M8/J8,0) -> 0 | V8: 7 | W8: =IF('🧶 Product Catalog'!$C$14="","",'🧶 Product Catalog'!$C$14) -> Flower Coaster Set | X8: =IF($W8="","",SUMIFS('💰 Sales Log'!$E$8:$E$67,'💰 Sales Log'!$D$8:$D$67,$W8)) -> 14 | Y8: =IF($W8="","",SUMIFS('💰 Sales Log'!$H$8:$H$67,'💰 Sales Log'!$D$8:$D$67,$W8)) -> 222 | Z8: =IF($W8="","",INDEX('🧶 Product Catalog'!$M$8:$M$31,MATCH($W8,'🧶 Product Catalog'!$C$8:$C$31,0))) -> 5 | AA8: =IF(OR($W8="",$X8=0),"",INDEX('🧶 Product Catalog'!$K$8:$K$31,MATCH($W8,'🧶 Product Catalog'!$C$8:$C$31,0))) -> 0.83125 | AB8: =IF($W8="","",$Y8-SUMIFS('💰 Sales Log'!$M$8:$M$67,'💰 Sales Log'!$D$8:$D$67,$W8)) -> 184.2 | AC8: 7 | AD8: =IF('🏪 Craft Fairs'!$B$14="","",'🏪 Craft Fairs'!$B$14) -> Autumn Craft Fair | AE8: =IF($AD8="","",SUMIFS('💰 Sales Log'!$H$8:$H$67,'💰 Sales Log'!$C$8:$C$67,$AD8)) -> 0 | AF8: =IF($AD8="","",$AE8-SUMIFS('🏪 Craft Fairs'!$K$8:$K$31,'💰 Sales Log'!$C$8:$C$67,$AD8)-SUMIFS('💰 Sales Log'!$M$8:$M$67,'💰 Sales Log'!$C$8:$C$67,$AD8)) -> -145 | AH8: Units sold | AI8: =SUM('💰 Sales Log'!$E$8:$E$67) -> 77 | AK8: =IF('🔄 Reorder List'!$B$16="","",'🔄 Reorder List'!$I$16) | AL8: =IF('🔄 Reorder List'!$B$16="","",'🔄 Reorder List'!$B$16) | AN8: =IF('🔄 Reorder List'!$B$31="","",'🔄 Reorder List'!$I$31) | AO8: =IF('🔄 Reorder List'!$B$31="","",'🔄 Reorder List'!$B$31)
H9: 8 | I9: August | J9: =SUMIFS('💰 Sales Log'!$H$8:$H$67,'💰 Sales Log'!$B$8:$B$67,">="&DATE(ReportYear,8,1),'💰 Sales Log'!$B$8:$B$67,"<"&EDATE(DATE(ReportYear,8,1),1)) -> 335 | K9: =SUMIFS('💰 Sales Log'!$M$8:$M$67,'💰 Sales Log'!$B$8:$B$67,">="&DATE(ReportYear,8,1),'💰 Sales Log'!$B$8:$B$67,"<"&EDATE(DATE(ReportYear,8,1),1)) -> 75.4 | L9: =SUMIFS('🏪 Craft Fairs'!$K$8:$K$31,'🏪 Craft Fairs'!$C$8:$C$31,">="&DATE(ReportYear,8,1),'🏪 Craft Fairs'!$C$8:$C$31,"<"&EDATE(DATE(ReportYear,8,1),1)) -> 0 | M9: =J9-K9-L9 -> 259.6 | N9: =IFERROR(M9/J9,0) -> 0 | V9: 8 | W9: =IF('🧶 Product Catalog'!$C$15="","",'🧶 Product Catalog'!$C$15) -> Lap Blanket | X9: =IF($W9="","",SUMIFS('💰 Sales Log'!$E$8:$E$67,'💰 Sales Log'!$D$8:$D$67,$W9)) -> 2 | Y9: =IF($W9="","",SUMIFS('💰 Sales Log'!$H$8:$H$67,'💰 Sales Log'!$D$8:$D$67,$W9)) -> 150 | Z9: =IF($W9="","",INDEX('🧶 Product Catalog'!$M$8:$M$31,MATCH($W9,'🧶 Product Catalog'!$C$8:$C$31,0))) -> 1 | AA9: =IF(OR($W9="",$X9=0),"",INDEX('🧶 Product Catalog'!$K$8:$K$31,MATCH($W9,'🧶 Product Catalog'!$C$8:$C$31,0))) -> 0.74933333 | AB9: =IF($W9="","",$Y9-SUMIFS('💰 Sales Log'!$M$8:$M$67,'💰 Sales Log'!$D$8:$D$67,$W9)) -> 112.4 | AC9: 8 | AD9: =IF('🏪 Craft Fairs'!$B$15="","",'🏪 Craft Fairs'!$B$15) -> Winter Holiday Market | AE9: =IF($AD9="","",SUMIFS('💰 Sales Log'!$H$8:$H$67,'💰 Sales Log'!$C$8:$C$67,$AD9)) -> 0 | AF9: =IF($AD9="","",$AE9-SUMIFS('🏪 Craft Fairs'!$K$8:$K$31,'💰 Sales Log'!$C$8:$C$67,$AD9)-SUMIFS('💰 Sales Log'!$M$8:$M$67,'💰 Sales Log'!$C$8:$C$67,$AD9)) -> -158 | AH9: Sales log entries | AI9: =COUNTA('💰 Sales Log'!$B$8:$B$67) -> 22 | AK9: =IF('🔄 Reorder List'!$B$17="","",'🔄 Reorder List'!$I$17) | AL9: =IF('🔄 Reorder List'!$B$17="","",'🔄 Reorder List'!$B$17) | AN9: =IF('🔄 Reorder List'!$B$32="","",'🔄 Reorder List'!$I$32) | AO9: =IF('🔄 Reorder List'!$B$32="","",'🔄 Reorder List'!$B$32)
H10: 9 | I10: September | J10: =SUMIFS('💰 Sales Log'!$H$8:$H$67,'💰 Sales Log'!$B$8:$B$67,">="&DATE(ReportYear,9,1),'💰 Sales Log'!$B$8:$B$67,"<"&EDATE(DATE(ReportYear,9,1),1)) -> 0 | K10: =SUMIFS('💰 Sales Log'!$M$8:$M$67,'💰 Sales Log'!$B$8:$B$67,">="&DATE(ReportYear,9,1),'💰 Sales Log'!$B$8:$B$67,"<"&EDATE(DATE(ReportYear,9,1),1)) -> 0 | L10: =SUMIFS('🏪 Craft Fairs'!$K$8:$K$31,'🏪 Craft Fairs'!$C$8:$C$31,">="&DATE(ReportYear,9,1),'🏪 Craft Fairs'!$C$8:$C$31,"<"&EDATE(DATE(ReportYear,9,1),1)) -> 145 | M10: =J10-K10-L10 -> -145 | N10: =IFERROR(M10/J10,0) -> 0 | V10: 9 | W10: =IF('🧶 Product Catalog'!$C$16="","",'🧶 Product Catalog'!$C$16) -> Ear Warmer Headband | X10: =IF($W10="","",SUMIFS('💰 Sales Log'!$E$8:$E$67,'💰 Sales Log'!$D$8:$D$67,$W10)) -> 10 | Y10: =IF($W10="","",SUMIFS('💰 Sales Log'!$H$8:$H$67,'💰 Sales Log'!$D$8:$D$67,$W10)) -> 160 | Z10: =IF($W10="","",INDEX('🧶 Product Catalog'!$M$8:$M$31,MATCH($W10,'🧶 Product Catalog'!$C$8:$C$31,0))) -> 0 | AA10: =IF(OR($W10="",$X10=0),"",INDEX('🧶 Product Catalog'!$K$8:$K$31,MATCH($W10,'🧶 Product Catalog'!$C$8:$C$31,0))) -> 0.7875 | AB10: =IF($W10="","",$Y10-SUMIFS('💰 Sales Log'!$M$8:$M$67,'💰 Sales Log'!$D$8:$D$67,$W10)) -> 126 | AC10: 9 | AD10: =IF('🏪 Craft Fairs'!$B$16="","",'🏪 Craft Fairs'!$B$16) | AE10: =IF($AD10="","",SUMIFS('💰 Sales Log'!$H$8:$H$67,'💰 Sales Log'!$C$8:$C$67,$AD10)) -> 0 | AF10: =IF($AD10="","",$AE10-SUMIFS('🏪 Craft Fairs'!$K$8:$K$31,'💰 Sales Log'!$C$8:$C$67,$AD10)-SUMIFS('💰 Sales Log'!$M$8:$M$67,'💰 Sales Log'!$C$8:$C$67,$AD10)) -> 0 | AH10: Average sale value | AI10: =IFERROR(AI2/AI9,0) -> 80 | AK10: =IF('🔄 Reorder List'!$B$18="","",'🔄 Reorder List'!$I$18) | AL10: =IF('🔄 Reorder List'!$B$18="","",'🔄 Reorder List'!$B$18) | AN10: =IF('🔄 Reorder List'!$B$33="","",'🔄 Reorder List'!$I$33) | AO10: =IF('🔄 Reorder List'!$B$33="","",'🔄 Reorder List'!$B$33)
H11: 10 | I11: October | J11: =SUMIFS('💰 Sales Log'!$H$8:$H$67,'💰 Sales Log'!$B$8:$B$67,">="&DATE(ReportYear,10,1),'💰 Sales Log'!$B$8:$B$67,"<"&EDATE(DATE(ReportYear,10,1),1)) -> 0 | K11: =SUMIFS('💰 Sales Log'!$M$8:$M$67,'💰 Sales Log'!$B$8:$B$67,">="&DATE(ReportYear,10,1),'💰 Sales Log'!$B$8:$B$67,"<"&EDATE(DATE(ReportYear,10,1),1)) -> 0 | L11: =SUMIFS('🏪 Craft Fairs'!$K$8:$K$31,'🏪 Craft Fairs'!$C$8:$C$31,">="&DATE(ReportYear,10,1),'🏪 Craft Fairs'!$C$8:$C$31,"<"&EDATE(DATE(ReportYear,10,1),1)) -> 0 | M11: =J11-K11-L11 -> 0 | N11: =IFERROR(M11/J11,0) -> 0 | V11: 10 | W11: =IF('🧶 Product Catalog'!$C$17="","",'🧶 Product Catalog'!$C$17) -> Stuffed Octopus | X11: =IF($W11="","",SUMIFS('💰 Sales Log'!$E$8:$E$67,'💰 Sales Log'!$D$8:$D$67,$W11)) -> 3 | Y11: =IF($W11="","",SUMIFS('💰 Sales Log'!$H$8:$H$67,'💰 Sales Log'!$D$8:$D$67,$W11)) -> 78 | Z11: =IF($W11="","",INDEX('🧶 Product Catalog'!$M$8:$M$31,MATCH($W11,'🧶 Product Catalog'!$C$8:$C$31,0))) -> 7 | AA11: =IF(OR($W11="",$X11=0),"",INDEX('🧶 Product Catalog'!$K$8:$K$31,MATCH($W11,'🧶 Product Catalog'!$C$8:$C$31,0))) -> 0.79230769 | AB11: =IF($W11="","",$Y11-SUMIFS('💰 Sales Log'!$M$8:$M$67,'💰 Sales Log'!$D$8:$D$67,$W11)) -> 61.8 | AC11: 10 | AD11: =IF('🏪 Craft Fairs'!$B$17="","",'🏪 Craft Fairs'!$B$17) | AE11: =IF($AD11="","",SUMIFS('💰 Sales Log'!$H$8:$H$67,'💰 Sales Log'!$C$8:$C$67,$AD11)) -> 0 | AF11: =IF($AD11="","",$AE11-SUMIFS('🏪 Craft Fairs'!$K$8:$K$31,'💰 Sales Log'!$C$8:$C$67,$AD11)-SUMIFS('💰 Sales Log'!$M$8:$M$67,'💰 Sales Log'!$C$8:$C$67,$AD11)) -> 0 | AH11: Average profit per item | AI11: =IFERROR(AI6/AI8,0) -> 9.3051948 | AK11: =IF('🔄 Reorder List'!$B$19="","",'🔄 Reorder List'!$I$19) | AL11: =IF('🔄 Reorder List'!$B$19="","",'🔄 Reorder List'!$B$19) | AN11: =IF('🔄 Reorder List'!$B$34="","",'🔄 Reorder List'!$I$34) | AO11: =IF('🔄 Reorder List'!$B$34="","",'🔄 Reorder List'!$B$34)
H12: 11 | I12: November | J12: =SUMIFS('💰 Sales Log'!$H$8:$H$67,'💰 Sales Log'!$B$8:$B$67,">="&DATE(ReportYear,11,1),'💰 Sales Log'!$B$8:$B$67,"<"&EDATE(DATE(ReportYear,11,1),1)) -> 0 | K12: =SUMIFS('💰 Sales Log'!$M$8:$M$67,'💰 Sales Log'!$B$8:$B$67,">="&DATE(ReportYear,11,1),'💰 Sales Log'!$B$8:$B$67,"<"&EDATE(DATE(ReportYear,11,1),1)) -> 0 | L12: =SUMIFS('🏪 Craft Fairs'!$K$8:$K$31,'🏪 Craft Fairs'!$C$8:$C$31,">="&DATE(ReportYear,11,1),'🏪 Craft Fairs'!$C$8:$C$31,"<"&EDATE(DATE(ReportYear,11,1),1)) -> 158 | M12: =J12-K12-L12 -> -158 | N12: =IFERROR(M12/J12,0) -> 0 | V12: 11 | W12: =IF('🧶 Product Catalog'!$C$18="","",'🧶 Product Catalog'!$C$18) -> Table Runner | X12: =IF($W12="","",SUMIFS('💰 Sales Log'!$E$8:$E$67,'💰 Sales Log'!$D$8:$D$67,$W12)) -> 3 | Y12: =IF($W12="","",SUMIFS('💰 Sales Log'!$H$8:$H$67,'💰 Sales Log'!$D$8:$D$67,$W12)) -> 165 | Z12: =IF($W12="","",INDEX('🧶 Product Catalog'!$M$8:$M$31,MATCH($W12,'🧶 Product Catalog'!$C$8:$C$31,0))) -> 0 | AA12: =IF(OR($W12="",$X12=0),"",INDEX('🧶 Product Catalog'!$K$8:$K$31,MATCH($W12,'🧶 Product Catalog'!$C$8:$C$31,0))) -> 0.78181818 | AB12: =IF($W12="","",$Y12-SUMIFS('💰 Sales Log'!$M$8:$M$67,'💰 Sales Log'!$D$8:$D$67,$W12)) -> 129 | AC12: 11 | AD12: =IF('🏪 Craft Fairs'!$B$18="","",'🏪 Craft Fairs'!$B$18) | AE12: =IF($AD12="","",SUMIFS('💰 Sales Log'!$H$8:$H$67,'💰 Sales Log'!$C$8:$C$67,$AD12)) -> 0 | AF12: =IF($AD12="","",$AE12-SUMIFS('🏪 Craft Fairs'!$K$8:$K$31,'💰 Sales Log'!$C$8:$C$67,$AD12)-SUMIFS('💰 Sales Log'!$M$8:$M$67,'💰 Sales Log'!$C$8:$C$67,$AD12)) -> 0 | AH12: Fairs on the books | AI12: =COUNTA('🏪 Craft Fairs'!$B$8:$B$31) -> 8 | AK12: =IF('🔄 Reorder List'!$B$20="","",'🔄 Reorder List'!$I$20) | AL12: =IF('🔄 Reorder List'!$B$20="","",'🔄 Reorder List'!$B$20)
H13: 12 | I13: December | J13: =SUMIFS('💰 Sales Log'!$H$8:$H$67,'💰 Sales Log'!$B$8:$B$67,">="&DATE(ReportYear,12,1),'💰 Sales Log'!$B$8:$B$67,"<"&EDATE(DATE(ReportYear,12,1),1)) -> 0 | K13: =SUMIFS('💰 Sales Log'!$M$8:$M$67,'💰 Sales Log'!$B$8:$B$67,">="&DATE(ReportYear,12,1),'💰 Sales Log'!$B$8:$B$67,"<"&EDATE(DATE(ReportYear,12,1),1)) -> 0 | L13: =SUMIFS('🏪 Craft Fairs'!$K$8:$K$31,'🏪 Craft Fairs'!$C$8:$C$31,">="&DATE(ReportYear,12,1),'🏪 Craft Fairs'!$C$8:$C$31,"<"&EDATE(DATE(ReportYear,12,1),1)) -> 0 | M13: =J13-K13-L13 -> 0 | N13: =IFERROR(M13/J13,0) -> 0 | V13: 12 | W13: =IF('🧶 Product Catalog'!$C$19="","",'🧶 Product Catalog'!$C$19) -> Keychain Charm | X13: =IF($W13="","",SUMIFS('💰 Sales Log'!$E$8:$E$67,'💰 Sales Log'!$D$8:$D$67,$W13)) -> 18 | Y13: =IF($W13="","",SUMIFS('💰 Sales Log'!$H$8:$H$67,'💰 Sales Log'!$D$8:$D$67,$W13)) -> 180 | Z13: =IF($W13="","",INDEX('🧶 Product Catalog'!$M$8:$M$31,MATCH($W13,'🧶 Product Catalog'!$C$8:$C$31,0))) -> 0 | AA13: =IF(OR($W13="",$X13=0),"",INDEX('🧶 Product Catalog'!$K$8:$K$31,MATCH($W13,'🧶 Product Catalog'!$C$8:$C$31,0))) -> 0.85 | AB13: =IF($W13="","",$Y13-SUMIFS('💰 Sales Log'!$M$8:$M$67,'💰 Sales Log'!$D$8:$D$67,$W13)) -> 153 | AC13: 12 | AD13: =IF('🏪 Craft Fairs'!$B$19="","",'🏪 Craft Fairs'!$B$19) | AE13: =IF($AD13="","",SUMIFS('💰 Sales Log'!$H$8:$H$67,'💰 Sales Log'!$C$8:$C$67,$AD13)) -> 0 | AF13: =IF($AD13="","",$AE13-SUMIFS('🏪 Craft Fairs'!$K$8:$K$31,'💰 Sales Log'!$C$8:$C$67,$AD13)-SUMIFS('💰 Sales Log'!$M$8:$M$67,'💰 Sales Log'!$C$8:$C$67,$AD13)) -> 0 | AH13: Fairs worked | AI13: =SUMPRODUCT(('💰 Sales Log'!$C$8:$C$67<>"")/COUNTIF('💰 Sales Log'!$C$8:$C$67,'💰 Sales Log'!$C$8:$C$67&"")) -> 6 | AK13: =IF('🔄 Reorder List'!$B$21="","",'🔄 Reorder List'!$I$21) | AL13: =IF('🔄 Reorder List'!$B$21="","",'🔄 Reorder List'!$B$21)
V14: 13 | W14: =IF('🧶 Product Catalog'!$C$20="","",'🧶 Product Catalog'!$C$20) | X14: =IF($W14="","",SUMIFS('💰 Sales Log'!$E$8:$E$67,'💰 Sales Log'!$D$8:$D$67,$W14)) -> 0 | Y14: =IF($W14="","",SUMIFS('💰 Sales Log'!$H$8:$H$67,'💰 Sales Log'!$D$8:$D$67,$W14)) -> 0 | Z14: =IF($W14="","",INDEX('🧶 Product Catalog'!$M$8:$M$31,MATCH($W14,'🧶 Product Catalog'!$C$8:$C$31,0))) -> 0 | AA14: =IF(OR($W14="",$X14=0),"",INDEX('🧶 Product Catalog'!$K$8:$K$31,MATCH($W14,'🧶 Product Catalog'!$C$8:$C$31,0))) -> 0 | AB14: =IF($W14="","",$Y14-SUMIFS('💰 Sales Log'!$M$8:$M$67,'💰 Sales Log'!$D$8:$D$67,$W14)) -> 0 | AC14: 13 | AD14: =IF('🏪 Craft Fairs'!$B$20="","",'🏪 Craft Fairs'!$B$20) | AE14: =IF($AD14="","",SUMIFS('💰 Sales Log'!$H$8:$H$67,'💰 Sales Log'!$C$8:$C$67,$AD14)) -> 0 | AF14: =IF($AD14="","",$AE14-SUMIFS('🏪 Craft Fairs'!$K$8:$K$31,'💰 Sales Log'!$C$8:$C$67,$AD14)-SUMIFS('💰 Sales Log'!$M$8:$M$67,'💰 Sales Log'!$C$8:$C$67,$AD14)) -> 0 | AH14: Inventory value (at unit cost) | AI14: =SUMPRODUCT('🧶 Product Catalog'!$M$8:$M$31*'🧶 Product Catalog'!$I$8:$I$31) -> 270.2
V15: 14 | W15: =IF('🧶 Product Catalog'!$C$21="","",'🧶 Product Catalog'!$C$21) | X15: =IF($W15="","",SUMIFS('💰 Sales Log'!$E$8:$E$67,'💰 Sales Log'!$D$8:$D$67,$W15)) -> 0 | Y15: =IF($W15="","",SUMIFS('💰 Sales Log'!$H$8:$H$67,'💰 Sales Log'!$D$8:$D$67,$W15)) -> 0 | Z15: =IF($W15="","",INDEX('🧶 Product Catalog'!$M$8:$M$31,MATCH($W15,'🧶 Product Catalog'!$C$8:$C$31,0))) -> 0 | AA15: =IF(OR($W15="",$X15=0),"",INDEX('🧶 Product Catalog'!$K$8:$K$31,MATCH($W15,'🧶 Product Catalog'!$C$8:$C$31,0))) -> 0 | AB15: =IF($W15="","",$Y15-SUMIFS('💰 Sales Log'!$M$8:$M$67,'💰 Sales Log'!$D$8:$D$67,$W15)) -> 0 | AC15: 14 | AD15: =IF('🏪 Craft Fairs'!$B$21="","",'🏪 Craft Fairs'!$B$21) | AE15: =IF($AD15="","",SUMIFS('💰 Sales Log'!$H$8:$H$67,'💰 Sales Log'!$C$8:$C$67,$AD15)) -> 0 | AF15: =IF($AD15="","",$AE15-SUMIFS('🏪 Craft Fairs'!$K$8:$K$31,'💰 Sales Log'!$C$8:$C$67,$AD15)-SUMIFS('💰 Sales Log'!$M$8:$M$67,'💰 Sales Log'!$C$8:$C$67,$AD15)) -> 0 | AH15: Products below minimum | AI15: =SUMPRODUCT(('🧶 Product Catalog'!$C$8:$C$31<>"")*('🧶 Product Catalog'!$M$8:$M$31<'🧶 Product Catalog'!$N$8:$N$31)) -> 7
V16: 15 | W16: =IF('🧶 Product Catalog'!$C$22="","",'🧶 Product Catalog'!$C$22) | X16: =IF($W16="","",SUMIFS('💰 Sales Log'!$E$8:$E$67,'💰 Sales Log'!$D$8:$D$67,$W16)) -> 0 | Y16: =IF($W16="","",SUMIFS('💰 Sales Log'!$H$8:$H$67,'💰 Sales Log'!$D$8:$D$67,$W16)) -> 0 | Z16: =IF($W16="","",INDEX('🧶 Product Catalog'!$M$8:$M$31,MATCH($W16,'🧶 Product Catalog'!$C$8:$C$31,0))) -> 0 | AA16: =IF(OR($W16="",$X16=0),"",INDEX('🧶 Product Catalog'!$K$8:$K$31,MATCH($W16,'🧶 Product Catalog'!$C$8:$C$31,0))) -> 0 | AB16: =IF($W16="","",$Y16-SUMIFS('💰 Sales Log'!$M$8:$M$67,'💰 Sales Log'!$D$8:$D$67,$W16)) -> 0 | AC16: 15 | AD16: =IF('🏪 Craft Fairs'!$B$22="","",'🏪 Craft Fairs'!$B$22) | AE16: =IF($AD16="","",SUMIFS('💰 Sales Log'!$H$8:$H$67,'💰 Sales Log'!$C$8:$C$67,$AD16)) -> 0 | AF16: =IF($AD16="","",$AE16-SUMIFS('🏪 Craft Fairs'!$K$8:$K$31,'💰 Sales Log'!$C$8:$C$67,$AD16)-SUMIFS('💰 Sales Log'!$M$8:$M$67,'💰 Sales Log'!$C$8:$C$67,$AD16)) -> 0 | AH16: Materials below threshold | AI16: =SUMPRODUCT(('🧵 Yarn & Materials'!$B$8:$B$31<>"")*('🧵 Yarn & Materials'!$K$8:$K$31<='🧵 Yarn & Materials'!$M$8:$M$31)) -> 5
V17: 16 | W17: =IF('🧶 Product Catalog'!$C$23="","",'🧶 Product Catalog'!$C$23) | X17: =IF($W17="","",SUMIFS('💰 Sales Log'!$E$8:$E$67,'💰 Sales Log'!$D$8:$D$67,$W17)) -> 0 | Y17: =IF($W17="","",SUMIFS('💰 Sales Log'!$H$8:$H$67,'💰 Sales Log'!$D$8:$D$67,$W17)) -> 0 | Z17: =IF($W17="","",INDEX('🧶 Product Catalog'!$M$8:$M$31,MATCH($W17,'🧶 Product Catalog'!$C$8:$C$31,0))) -> 0 | AA17: =IF(OR($W17="",$X17=0),"",INDEX('🧶 Product Catalog'!$K$8:$K$31,MATCH($W17,'🧶 Product Catalog'!$C$8:$C$31,0))) -> 0 | AB17: =IF($W17="","",$Y17-SUMIFS('💰 Sales Log'!$M$8:$M$67,'💰 Sales Log'!$D$8:$D$67,$W17)) -> 0 | AC17: 16 | AD17: =IF('🏪 Craft Fairs'!$B$23="","",'🏪 Craft Fairs'!$B$23) | AE17: =IF($AD17="","",SUMIFS('💰 Sales Log'!$H$8:$H$67,'💰 Sales Log'!$C$8:$C$67,$AD17)) -> 0 | AF17: =IF($AD17="","",$AE17-SUMIFS('🏪 Craft Fairs'!$K$8:$K$31,'💰 Sales Log'!$C$8:$C$67,$AD17)-SUMIFS('💰 Sales Log'!$M$8:$M$67,'💰 Sales Log'!$C$8:$C$67,$AD17)) -> 0 | AH17: Estimated reorder cost | AI17: =SUM('🔄 Reorder List'!$G$10:$G$34) -> 342.7
V18: 17 | W18: =IF('🧶 Product Catalog'!$C$24="","",'🧶 Product Catalog'!$C$24) | X18: =IF($W18="","",SUMIFS('💰 Sales Log'!$E$8:$E$67,'💰 Sales Log'!$D$8:$D$67,$W18)) -> 0 | Y18: =IF($W18="","",SUMIFS('💰 Sales Log'!$H$8:$H$67,'💰 Sales Log'!$D$8:$D$67,$W18)) -> 0 | Z18: =IF($W18="","",INDEX('🧶 Product Catalog'!$M$8:$M$31,MATCH($W18,'🧶 Product Catalog'!$C$8:$C$31,0))) -> 0 | AA18: =IF(OR($W18="",$X18=0),"",INDEX('🧶 Product Catalog'!$K$8:$K$31,MATCH($W18,'🧶 Product Catalog'!$C$8:$C$31,0))) -> 0 | AB18: =IF($W18="","",$Y18-SUMIFS('💰 Sales Log'!$M$8:$M$67,'💰 Sales Log'!$D$8:$D$67,$W18)) -> 0 | AC18: 17 | AD18: =IF('🏪 Craft Fairs'!$B$24="","",'🏪 Craft Fairs'!$B$24) | AE18: =IF($AD18="","",SUMIFS('💰 Sales Log'!$H$8:$H$67,'💰 Sales Log'!$C$8:$C$67,$AD18)) -> 0 | AF18: =IF($AD18="","",$AE18-SUMIFS('🏪 Craft Fairs'!$K$8:$K$31,'💰 Sales Log'!$C$8:$C$67,$AD18)-SUMIFS('💰 Sales Log'!$M$8:$M$67,'💰 Sales Log'!$C$8:$C$67,$AD18)) -> 0 | AH18: Sell-through rate | AI18: =IFERROR(AI8/AI19,0) -> 0.65254237
V19: 18 | W19: =IF('🧶 Product Catalog'!$C$25="","",'🧶 Product Catalog'!$C$25) | X19: =IF($W19="","",SUMIFS('💰 Sales Log'!$E$8:$E$67,'💰 Sales Log'!$D$8:$D$67,$W19)) -> 0 | Y19: =IF($W19="","",SUMIFS('💰 Sales Log'!$H$8:$H$67,'💰 Sales Log'!$D$8:$D$67,$W19)) -> 0 | Z19: =IF($W19="","",INDEX('🧶 Product Catalog'!$M$8:$M$31,MATCH($W19,'🧶 Product Catalog'!$C$8:$C$31,0))) -> 0 | AA19: =IF(OR($W19="",$X19=0),"",INDEX('🧶 Product Catalog'!$K$8:$K$31,MATCH($W19,'🧶 Product Catalog'!$C$8:$C$31,0))) -> 0 | AB19: =IF($W19="","",$Y19-SUMIFS('💰 Sales Log'!$M$8:$M$67,'💰 Sales Log'!$D$8:$D$67,$W19)) -> 0 | AC19: 18 | AD19: =IF('🏪 Craft Fairs'!$B$25="","",'🏪 Craft Fairs'!$B$25) | AE19: =IF($AD19="","",SUMIFS('💰 Sales Log'!$H$8:$H$67,'💰 Sales Log'!$C$8:$C$67,$AD19)) -> 0 | AF19: =IF($AD19="","",$AE19-SUMIFS('🏪 Craft Fairs'!$K$8:$K$31,'💰 Sales Log'!$C$8:$C$67,$AD19)-SUMIFS('💰 Sales Log'!$M$8:$M$67,'💰 Sales Log'!$C$8:$C$67,$AD19)) -> 0 | AH19: Units made (all batches) | AI19: =SUM('📦 Made & Stocked'!$D$8:$D$37) -> 118
V20: 19 | W20: =IF('🧶 Product Catalog'!$C$26="","",'🧶 Product Catalog'!$C$26) | X20: =IF($W20="","",SUMIFS('💰 Sales Log'!$E$8:$E$67,'💰 Sales Log'!$D$8:$D$67,$W20)) -> 0 | Y20: =IF($W20="","",SUMIFS('💰 Sales Log'!$H$8:$H$67,'💰 Sales Log'!$D$8:$D$67,$W20)) -> 0 | Z20: =IF($W20="","",INDEX('🧶 Product Catalog'!$M$8:$M$31,MATCH($W20,'🧶 Product Catalog'!$C$8:$C$31,0))) -> 0 | AA20: =IF(OR($W20="",$X20=0),"",INDEX('🧶 Product Catalog'!$K$8:$K$31,MATCH($W20,'🧶 Product Catalog'!$C$8:$C$31,0))) -> 0 | AB20: =IF($W20="","",$Y20-SUMIFS('💰 Sales Log'!$M$8:$M$67,'💰 Sales Log'!$D$8:$D$67,$W20)) -> 0 | AC20: 19 | AD20: =IF('🏪 Craft Fairs'!$B$26="","",'🏪 Craft Fairs'!$B$26) | AE20: =IF($AD20="","",SUMIFS('💰 Sales Log'!$H$8:$H$67,'💰 Sales Log'!$C$8:$C$67,$AD20)) -> 0 | AF20: =IF($AD20="","",$AE20-SUMIFS('🏪 Craft Fairs'!$K$8:$K$31,'💰 Sales Log'!$C$8:$C$67,$AD20)-SUMIFS('💰 Sales Log'!$M$8:$M$67,'💰 Sales Log'!$C$8:$C$67,$AD20)) -> 0 | AH20: Best-selling product | AI20: =IFERROR(INDEX($W$2:$W$25,MATCH(MAX($Y$2:$Y$25),$Y$2:$Y$25,0)),"") -> Market Tote Bag
V21: 20 | W21: =IF('🧶 Product Catalog'!$C$27="","",'🧶 Product Catalog'!$C$27) | X21: =IF($W21="","",SUMIFS('💰 Sales Log'!$E$8:$E$67,'💰 Sales Log'!$D$8:$D$67,$W21)) -> 0 | Y21: =IF($W21="","",SUMIFS('💰 Sales Log'!$H$8:$H$67,'💰 Sales Log'!$D$8:$D$67,$W21)) -> 0 | Z21: =IF($W21="","",INDEX('🧶 Product Catalog'!$M$8:$M$31,MATCH($W21,'🧶 Product Catalog'!$C$8:$C$31,0))) -> 0 | AA21: =IF(OR($W21="",$X21=0),"",INDEX('🧶 Product Catalog'!$K$8:$K$31,MATCH($W21,'🧶 Product Catalog'!$C$8:$C$31,0))) -> 0 | AB21: =IF($W21="","",$Y21-SUMIFS('💰 Sales Log'!$M$8:$M$67,'💰 Sales Log'!$D$8:$D$67,$W21)) -> 0 | AC21: 20 | AD21: =IF('🏪 Craft Fairs'!$B$27="","",'🏪 Craft Fairs'!$B$27) | AE21: =IF($AD21="","",SUMIFS('💰 Sales Log'!$H$8:$H$67,'💰 Sales Log'!$C$8:$C$67,$AD21)) -> 0 | AF21: =IF($AD21="","",$AE21-SUMIFS('🏪 Craft Fairs'!$K$8:$K$31,'💰 Sales Log'!$C$8:$C$67,$AD21)-SUMIFS('💰 Sales Log'!$M$8:$M$67,'💰 Sales Log'!$C$8:$C$67,$AD21)) -> 0 | AH21: Best craft fair | AI21: =IFERROR(INDEX($AD$2:$AD$25,MATCH(MAX($AF$2:$AF$25),$AF$2:$AF$25,0)),"") -> Online Order Batch
V22: 21 | W22: =IF('🧶 Product Catalog'!$C$28="","",'🧶 Product Catalog'!$C$28) | X22: =IF($W22="","",SUMIFS('💰 Sales Log'!$E$8:$E$67,'💰 Sales Log'!$D$8:$D$67,$W22)) -> 0 | Y22: =IF($W22="","",SUMIFS('💰 Sales Log'!$H$8:$H$67,'💰 Sales Log'!$D$8:$D$67,$W22)) -> 0 | Z22: =IF($W22="","",INDEX('🧶 Product Catalog'!$M$8:$M$31,MATCH($W22,'🧶 Product Catalog'!$C$8:$C$31,0))) -> 0 | AA22: =IF(OR($W22="",$X22=0),"",INDEX('🧶 Product Catalog'!$K$8:$K$31,MATCH($W22,'🧶 Product Catalog'!$C$8:$C$31,0))) -> 0 | AB22: =IF($W22="","",$Y22-SUMIFS('💰 Sales Log'!$M$8:$M$67,'💰 Sales Log'!$D$8:$D$67,$W22)) -> 0 | AC22: 21 | AD22: =IF('🏪 Craft Fairs'!$B$28="","",'🏪 Craft Fairs'!$B$28) | AE22: =IF($AD22="","",SUMIFS('💰 Sales Log'!$H$8:$H$67,'💰 Sales Log'!$C$8:$C$67,$AD22)) -> 0 | AF22: =IF($AD22="","",$AE22-SUMIFS('🏪 Craft Fairs'!$K$8:$K$31,'💰 Sales Log'!$C$8:$C$67,$AD22)-SUMIFS('💰 Sales Log'!$M$8:$M$67,'💰 Sales Log'!$C$8:$C$67,$AD22)) -> 0 | AH22: Most units sold | AI22: =IFERROR(INDEX($W$2:$W$25,MATCH(MAX($X$2:$X$25),$X$2:$X$25,0)),"") -> Keychain Charm
V23: 22 | W23: =IF('🧶 Product Catalog'!$C$29="","",'🧶 Product Catalog'!$C$29) | X23: =IF($W23="","",SUMIFS('💰 Sales Log'!$E$8:$E$67,'💰 Sales Log'!$D$8:$D$67,$W23)) -> 0 | Y23: =IF($W23="","",SUMIFS('💰 Sales Log'!$H$8:$H$67,'💰 Sales Log'!$D$8:$D$67,$W23)) -> 0 | Z23: =IF($W23="","",INDEX('🧶 Product Catalog'!$M$8:$M$31,MATCH($W23,'🧶 Product Catalog'!$C$8:$C$31,0))) -> 0 | AA23: =IF(OR($W23="",$X23=0),"",INDEX('🧶 Product Catalog'!$K$8:$K$31,MATCH($W23,'🧶 Product Catalog'!$C$8:$C$31,0))) -> 0 | AB23: =IF($W23="","",$Y23-SUMIFS('💰 Sales Log'!$M$8:$M$67,'💰 Sales Log'!$D$8:$D$67,$W23)) -> 0 | AC23: 22 | AD23: =IF('🏪 Craft Fairs'!$B$29="","",'🏪 Craft Fairs'!$B$29) | AE23: =IF($AD23="","",SUMIFS('💰 Sales Log'!$H$8:$H$67,'💰 Sales Log'!$C$8:$C$67,$AD23)) -> 0 | AF23: =IF($AD23="","",$AE23-SUMIFS('🏪 Craft Fairs'!$K$8:$K$31,'💰 Sales Log'!$C$8:$C$67,$AD23)-SUMIFS('💰 Sales Log'!$M$8:$M$67,'💰 Sales Log'!$C$8:$C$67,$AD23)) -> 0 | AH23: Highest revenue product | AI23: =IFERROR(INDEX($W$2:$W$25,MATCH(MAX($Y$2:$Y$25),$Y$2:$Y$25,0)),"") -> Market Tote Bag
V24: 23 | W24: =IF('🧶 Product Catalog'!$C$30="","",'🧶 Product Catalog'!$C$30) | X24: =IF($W24="","",SUMIFS('💰 Sales Log'!$E$8:$E$67,'💰 Sales Log'!$D$8:$D$67,$W24)) -> 0 | Y24: =IF($W24="","",SUMIFS('💰 Sales Log'!$H$8:$H$67,'💰 Sales Log'!$D$8:$D$67,$W24)) -> 0 | Z24: =IF($W24="","",INDEX('🧶 Product Catalog'!$M$8:$M$31,MATCH($W24,'🧶 Product Catalog'!$C$8:$C$31,0))) -> 0 | AA24: =IF(OR($W24="",$X24=0),"",INDEX('🧶 Product Catalog'!$K$8:$K$31,MATCH($W24,'🧶 Product Catalog'!$C$8:$C$31,0))) -> 0 | AB24: =IF($W24="","",$Y24-SUMIFS('💰 Sales Log'!$M$8:$M$67,'💰 Sales Log'!$D$8:$D$67,$W24)) -> 0 | AC24: 23 | AD24: =IF('🏪 Craft Fairs'!$B$30="","",'🏪 Craft Fairs'!$B$30) | AE24: =IF($AD24="","",SUMIFS('💰 Sales Log'!$H$8:$H$67,'💰 Sales Log'!$C$8:$C$67,$AD24)) -> 0 | AF24: =IF($AD24="","",$AE24-SUMIFS('🏪 Craft Fairs'!$K$8:$K$31,'💰 Sales Log'!$C$8:$C$67,$AD24)-SUMIFS('💰 Sales Log'!$M$8:$M$67,'💰 Sales Log'!$C$8:$C$67,$AD24)) -> 0 | AH24: Highest profit product | AI24: =IFERROR(INDEX($W$2:$W$25,MATCH(MAX($AB$2:$AB$25),$AB$2:$AB$25,0)),"") -> Market Tote Bag
V25: 24 | W25: =IF('🧶 Product Catalog'!$C$31="","",'🧶 Product Catalog'!$C$31) | X25: =IF($W25="","",SUMIFS('💰 Sales Log'!$E$8:$E$67,'💰 Sales Log'!$D$8:$D$67,$W25)) -> 0 | Y25: =IF($W25="","",SUMIFS('💰 Sales Log'!$H$8:$H$67,'💰 Sales Log'!$D$8:$D$67,$W25)) -> 0 | Z25: =IF($W25="","",INDEX('🧶 Product Catalog'!$M$8:$M$31,MATCH($W25,'🧶 Product Catalog'!$C$8:$C$31,0))) -> 0 | AA25: =IF(OR($W25="",$X25=0),"",INDEX('🧶 Product Catalog'!$K$8:$K$31,MATCH($W25,'🧶 Product Catalog'!$C$8:$C$31,0))) -> 0 | AB25: =IF($W25="","",$Y25-SUMIFS('💰 Sales Log'!$M$8:$M$67,'💰 Sales Log'!$D$8:$D$67,$W25)) -> 0 | AC25: 24 | AD25: =IF('🏪 Craft Fairs'!$B$31="","",'🏪 Craft Fairs'!$B$31) | AE25: =IF($AD25="","",SUMIFS('💰 Sales Log'!$H$8:$H$67,'💰 Sales Log'!$C$8:$C$67,$AD25)) -> 0 | AF25: =IF($AD25="","",$AE25-SUMIFS('🏪 Craft Fairs'!$K$8:$K$31,'💰 Sales Log'!$C$8:$C$67,$AD25)-SUMIFS('💰 Sales Log'!$M$8:$M$67,'💰 Sales Log'!$C$8:$C$67,$AD25)) -> 0 | AH25: Highest margin product | AI25: =IFERROR(INDEX($W$2:$W$25,MATCH(MAX($AA$2:$AA$25),$AA$2:$AA$25,0)),"") -> Keychain Charm
AH26: Slowest mover | AI26: =IFERROR(INDEX($W$2:$W$25,MATCH(MIN($X$2:$X$25),$X$2:$X$25,0)),"") -> Granny Square Cardigan
AH27: Pricing calculator: suggested price | AI27: ='💵 Pricing Calculator'!$J$17 -> 52

Sheet ⚙️ Lists & Settings
B2: ⚙️ Lists & Settings
B3: Your studio basics + every dropdown list in one place | H3: 🏠 Dashboard
B5: Your studio
B6: Business name | C6: Willow & Wren Crochet Studio | E6: Shown big on the Dashboard banner.
B7: Season note | C7: Autumn fair season - stock up on chunky yarn! | E7: A little reminder for yourself (optional).
B9: Money & targets
B10: Currency symbol | C10: $ | E10: Every money column shows this symbol.
B11: Report year | C11: 2026 | E11: The Dashboard's month chart follows this year.
B12: Your hourly wage | C12: 14 | E12: Used by the Pricing Calculator to pay yourself properly.
B13: Overhead % | C13: 0.1 | E13: Card fees, electricity, glue, parking... a little on top of everything.
B14: Target profit margin | C14: 0.45 | E14: The default margin the Pricing Calculator aims for.
B16: These five columns feed every dropdown in the workbook. Rename anything, add new rows or delete ones you don't use - the dropdowns update automatically. Keep each list inside its own column and leave no big gaps between entries.
C22: Product categories | D22: Payment methods | E22: Yarn weights | F22: Units | G22: Suppliers
C23: Toys & Amigurumi | D23: Cash | E23: Lace | F23: balls | G23: Local yarn shop
C24: Wearables | D24: Card | E24: Sock / 4-ply | F24: metres | G24: Online yarn store
C25: Home & Decor | D25: Bank transfer | E25: DK / light | F25: grams | G25: Wholesale craft
C26: Accessories | D26: Mobile wallet | E26: Worsted / aran | F26: skeins | G26: Market stall
C27: Baby & Kids | D27: Online order | E27: Chunky | F27: cones | G27: Second-hand / stash
C28: Seasonal | D28: Other | E28: Super chunky | F28: pieces | G28: Other
E29: Mixed / other
B44: Built-in marks (fixed)
B45: The tick marks below power every ✓ box in the workbook. They're fixed on purpose so the green tick highlights keep working - just pick them from the dropdowns.
C46: Tick marks
C47: ✓
C48: ✗ Skip
B52: 💡 Change a setting once and every sheet follows - currency, year, wage and dropdowns all live here.
B54: ▶ Settings | D54: 🏠 Home | F54: Products | H54: Yarn
B55: Stock | D55: Fairs | F55: Sales | H55: Event $
B56: Reorder | D56: Packing | F56: Pricing | H56: Monthly
B57: Help

Sheet 📊 Dashboard
B2: =IF(BusinessName="","My Crochet Studio",BusinessName) -> Willow & Wren Crochet Studio | H2: =IF(Message="","Plan it, make it, sell it.",Message) -> Autumn fair season - stock up on chunky yarn!
B3: 🧶 Your craft fair business at a glance | H3: PREMIUM EDITION • 14 tabs
B5: ="Sales logged: "&TEXT('_Data'!$AI$9,"0") -> Sales logged: 22 | E5: ="Units sold: "&TEXT('_Data'!$AI$8,"#,##0") -> Units sold: 77 | H5: ="Fairs booked: "&TEXT('_Data'!$AI$12,"0") -> Fairs booked: 8 | K5: =IF('_Data'!$AI$15+'_Data'!$AI$16>0,"! Restock needed - see Reorder List","Stock levels look healthy") -> Restock needed - see Reorder List
B7: GROSS SALES | D7: NET PROFIT | F7: PROFIT MARGIN | H7: UNITS SOLD | J7: AVERAGE SALE | L7: STOCK VALUE
B8: =Currency&TEXT('_Data'!$AI$2,"#,##0.00") -> $1,760.00 | D8: =Currency&TEXT('_Data'!$AI$6,"#,##0.00") -> $716.50 | F8: =TEXT('_Data'!$AI$7,"0.0%") -> 40.7% | H8: =TEXT('_Data'!$AI$8,"#,##0") -> 77 | J8: =Currency&TEXT('_Data'!$AI$10,"#,##0.00") -> $80.00 | L8: =Currency&TEXT('_Data'!$AI$14,"#,##0.00") -> $270.20
B11: FAIRS WORKED | D11: BEST CRAFT FAIR | F11: TOP SELLER | H11: TOP EARNER | J11: ITEMS MADE | L11: REORDER BILL
B12: =TEXT('_Data'!$AI$13,"0")&" of "&TEXT('_Data'!$AI$12,"0") -> 6 of 8 | D12: ='_Data'!$AI$21 -> Online Order Batch | F12: ='_Data'!$AI$22 -> Keychain Charm | H12: ='_Data'!$AI$23 -> Market Tote Bag | J12: =TEXT('_Data'!$AI$19,"#,##0") -> 118 | L12: =Currency&TEXT('_Data'!$AI$17,"#,##0.00") -> $342.70
B15: Your year at a glance
B67: Top products (by revenue)
B68: # | C68: Product | H68: Units | I68: Revenue | J68: Profit | K68: Margin
B69: 1 | C69: =IFERROR(INDEX($W$2:$W$25,MATCH(LARGE($Y$2:$Y$25,1),$Y$2:$Y$25,0)),"") -> Market Tote Bag | H69: =IFERROR(INDEX($X$2:$X$25,MATCH($C69,$W$2:$W$25,0)),"") -> 8 | I69: =IFERROR(LARGE($Y$2:$Y$25,1),0) -> 256 | J69: =IFERROR(INDEX($AB$2:$AB$25,MATCH($C69,$W$2:$W$25,0)),"") -> 199.2 | K69: =IFERROR(INDEX($AA$2:$AA$25,MATCH($C69,$W$2:$W$25,0)),"") -> 0.778125
B70: 2 | C70: =IFERROR(INDEX($W$2:$W$25,MATCH(LARGE($Y$2:$Y$25,2),$Y$2:$Y$25,0)),"") -> Flower Coaster Set | H70: =IFERROR(INDEX($X$2:$X$25,MATCH($C70,$W$2:$W$25,0)),"") -> 14 | I70: =IFERROR(LARGE($Y$2:$Y$25,2),0) -> 222 | J70: =IFERROR(INDEX($AB$2:$AB$25,MATCH($C70,$W$2:$W$25,0)),"") -> 186.2 | K70: =IFERROR(INDEX($AA$2:$AA$25,MATCH($C70,$W$2:$W$25,0)),"") -> 0.83125
B71: 3 | C71: =IFERROR(INDEX($W$2:$W$25,MATCH(LARGE($Y$2:$Y$25,3),$Y$2:$Y$25,0)),"") -> Keychain Charm | H71: =IFERROR(INDEX($X$2:$X$25,MATCH($C71,$W$2:$W$25,0)),"") -> 18 | I71: =IFERROR(LARGE($Y$2:$Y$25,3),0) -> 180 | J71: =IFERROR(INDEX($AB$2:$AB$25,MATCH($C71,$W$2:$W$25,0)),"") -> 153 | K71: =IFERROR(INDEX($AA$2:$AA$25,MATCH($C71,$W$2:$W$25,0)),"") -> 0.85
B72: 4 | C72: =IFERROR(INDEX($W$2:$W$25,MATCH(LARGE($Y$2:$Y$25,4),$Y$2:$Y$25,0)),"") -> Amigurumi Bunny | H72: =IFERROR(INDEX($X$2:$X$25,MATCH($C72,$W$2:$W$25,0)),"") -> 6 | I72: =IFERROR(LARGE($Y$2:$Y$25,4),0) -> 168 | J72: =IFERROR(INDEX($AB$2:$AB$25,MATCH($C72,$W$2:$W$25,0)),"") -> 138 | K72: =IFERROR(INDEX($AA$2:$AA$25,MATCH($C72,$W$2:$W$25,0)),"") -> 0.82142857
B73: 5 | C73: =IFERROR(INDEX($W$2:$W$25,MATCH(LARGE($Y$2:$Y$25,5),$Y$2:$Y$25,0)),"") -> Table Runner | H73: =IFERROR(INDEX($X$2:$X$25,MATCH($C73,$W$2:$W$25,0)),"") -> 3 | I73: =IFERROR(LARGE($Y$2:$Y$25,5),0) -> 165 | J73: =IFERROR(INDEX($AB$2:$AB$25,MATCH($C73,$W$2:$W$25,0)),"") -> 129 | K73: =IFERROR(INDEX($AA$2:$AA$25,MATCH($C73,$W$2:$W$25,0)),"") -> 0.78181818
B75: Restock radar
B77: ="Products below minimum: "&TEXT('_Data'!$AI$15,"0") -> Products below minimum: 7 | F77: ="Materials running low: "&TEXT('_Data'!$AI$16,"0") -> Materials running low: 5 | J77: ="Estimated shopping list: "&Currency&TEXT('_Data'!$AI$17,"#,##0.00") -> Estimated shopping list: $342.70
B79: The Reorder List tab turns these into a ready-to-buy shopping list with suppliers and costs - tick items off as you order.
B81: 💡 Every number on this page is live - log a sale on the Sales Log tab and watch it land here instantly.
B83: Settings | D83: ▶ 🏠 Home | F83: Products | H83: Yarn | J83: Stock | L83: Fairs
B84: Sales | D84: Event $ | F84: Reorder | H84: Packing | J84: Pricing | L84: Monthly
B85: Help

Sheet 🧶 Product Catalog
B2: 🧶 Product Catalog
B3: One row for everything you make - prices, costs and stock at a glance | N3: 🏠 Dashboard
B5: ="Products: "&TEXT(COUNTA('🧶 Product Catalog'!$C$8:$C$31),"0") -> 12 | E5: ="Avg price: "&Currency&TEXT(IFERROR(AVERAGE('🧶 Product Catalog'!$F$8:$F$31),0),"#,##0.00") -> 36.08 | H5: ="Stock value: "&Currency&TEXT('_Data'!$AI$14,"#,##0.00") -> $270.20 | K5: =IF('_Data'!$AI$15>0,"! "&TEXT('_Data'!$AI$15,"0")&" products low on stock","Stock levels OK") -> ! 7 products low on stock
A7: # | B7: SKU / code | C7: Product | D7: Category | E7: Description | F7: Price | G7: Yarn cost | H7: Packaging | I7: Cost / item | J7: Profit / item | K7: Margin | L7: Hours to make | M7: In stock | N7: Keep min. | O7: Stock status | P7: Photo / link
B8: CB-001 | C8: Amigurumi Bunny | D8: Toys & Amigurumi | E8: Soft cotton bunny with safety eyes | F8: 28 | G8: 4.2 | H8: 0.8 | I8: =IF($C8="","",ROUND(N($G8)+N($H8),2)) -> 5 | J8: =IF(OR($C8="",$F8=""),"",ROUND($F8-$I8,2)) -> 23 | K8: =IF(OR($C8="",$F8=""),"",IFERROR($J8/$F8,0)) -> 0.82142857 | L8: 2.5 | M8: =IF($C8="",0,SUMIFS('📦 Made & Stocked'!$J$8:$J$37,'📦 Made & Stocked'!$B$8:$B$37,$C8)) -> 5 | N8: 4 | O8: =IF($C8="","",IF(N($M8)<=0,"🔴 Out of stock",IF(N($M8)<$N8,"🟠 Low stock","🟢 In stock"))) -> 🟢 In stock | P8: photos/bunny.jpg
B9: CB-002 | C9: Chunky Beanie | D9: Wearables | E9: Super chunky merino beanie | F9: 24 | G9: 5.6 | H9: 0.7 | I9: =IF($C9="","",ROUND(N($G9)+N($H9),2)) -> 6.3 | J9: =IF(OR($C9="",$F9=""),"",ROUND($F9-$I9,2)) -> 17.7 | K9: =IF(OR($C9="",$F9=""),"",IFERROR($J9/$F9,0)) -> 0.7375 | L9: 1.5 | M9: =IF($C9="",0,SUMIFS('📦 Made & Stocked'!$J$8:$J$37,'📦 Made & Stocked'!$B$8:$B$37,$C9)) -> 10 | N9: 6 | O9: =IF($C9="","",IF(N($M9)<=0,"🔴 Out of stock",IF(N($M9)<$N9,"🟠 Low stock","🟢 In stock"))) -> 🟢 In stock | P9: photos/beanie.jpg
B10: CB-003 | C10: Granny Square Cardigan | D10: Wearables | E10: Hand-joined granny squares | F10: 95 | G10: 18.4 | H10: 2.2 | I10: =IF($C10="","",ROUND(N($G10)+N($H10),2)) -> 20.6 | J10: =IF(OR($C10="",$F10=""),"",ROUND($F10-$I10,2)) -> 74.4 | K10: =IF(OR($C10="",$F10=""),"",IFERROR($J10/$F10,0)) -> 0.78315789 | L10: 12 | M10: =IF($C10="",0,SUMIFS('📦 Made & Stocked'!$J$8:$J$37,'📦 Made & Stocked'!$B$8:$B$37,$C10)) -> 2 | N10: 2 | O10: =IF($C10="","",IF(N($M10)<=0,"🔴 Out of stock",IF(N($M10)<$N10,"🟠 Low stock","🟢 In stock"))) -> 🟢 In stock | P10: photos/cardigan.jpg
B11: CB-004 | C11: Market Tote Bag | D11: Accessories | E11: Sturdy cotton market tote | F11: 32 | G11: 6.1 | H11: 1 | I11: =IF($C11="","",ROUND(N($G11)+N($H11),2)) -> 7.1 | J11: =IF(OR($C11="",$F11=""),"",ROUND($F11-$I11,2)) -> 24.9 | K11: =IF(OR($C11="",$F11=""),"",IFERROR($J11/$F11,0)) -> 0.778125 | L11: 3 | M11: =IF($C11="",0,SUMIFS('📦 Made & Stocked'!$J$8:$J$37,'📦 Made & Stocked'!$B$8:$B$37,$C11)) -> 3 | N11: 5 | O11: =IF($C11="","",IF(N($M11)<=0,"🔴 Out of stock",IF(N($M11)<$N11,"🟠 Low stock","🟢 In stock"))) -> 🟠 Low stock | P11: photos/tote.jpg
B12: CB-005 | C12: Cozy Scarf | D12: Wearables | E12: Worsted wool scarf | F12: 38 | G12: 8.9 | H12: 1.1 | I12: =IF($C12="","",ROUND(N($G12)+N($H12),2)) -> 10 | J12: =IF(OR($C12="",$F12=""),"",ROUND($F12-$I12,2)) -> 28 | K12: =IF(OR($C12="",$F12=""),"",IFERROR($J12/$F12,0)) -> 0.73684211 | L12: 4 | M12: =IF($C12="",0,SUMIFS('📦 Made & Stocked'!$J$8:$J$37,'📦 Made & Stocked'!$B$8:$B$37,$C12)) -> 4 | N12: 4 | O12: =IF($C12="","",IF(N($M12)<=0,"🔴 Out of stock",IF(N($M12)<$N12,"🟠 Low stock","🟢 In stock"))) -> 🟢 In stock | P12: photos/scarf.jpg
B13: CB-006 | C13: Baby Booties | D13: Baby & Kids | E13: Tiny soft booties, pair | F13: 18 | G13: 2.6 | H13: 0.6 | I13: =IF($C13="","",ROUND(N($G13)+N($H13),2)) -> 3.2 | J13: =IF(OR($C13="",$F13=""),"",ROUND($F13-$I13,2)) -> 14.8 | K13: =IF(OR($C13="",$F13=""),"",IFERROR($J13/$F13,0)) -> 0.82222222 | L13: 1.2 | M13: =IF($C13="",0,SUMIFS('📦 Made & Stocked'!$J$8:$J$37,'📦 Made & Stocked'!$B$8:$B$37,$C13)) -> 3 | N13: 6 | O13: =IF($C13="","",IF(N($M13)<=0,"🔴 Out of stock",IF(N($M13)<$N13,"🟠 Low stock","🟢 In stock"))) -> 🟠 Low stock | P13: photos/booties.jpg
B14: CB-007 | C14: Flower Coaster Set | D14: Home & Decor | E14: Set of 4 cotton coasters | F14: 16 | G14: 2.2 | H14: 0.5 | I14: =IF($C14="","",ROUND(N($G14)+N($H14),2)) -> 2.7 | J14: =IF(OR($C14="",$F14=""),"",ROUND($F14-$I14,2)) -> 13.3 | K14: =IF(OR($C14="",$F14=""),"",IFERROR($J14/$F14,0)) -> 0.83125 | L14: 1 | M14: =IF($C14="",0,SUMIFS('📦 Made & Stocked'!$J$8:$J$37,'📦 Made & Stocked'!$B$8:$B$37,$C14)) -> 5 | N14: 8 | O14: =IF($C14="","",IF(N($M14)<=0,"🔴 Out of stock",IF(N($M14)<$N14,"🟠 Low stock","🟢 In stock"))) -> 🟠 Low stock | P14: photos/coasters.jpg
B15: CB-008 | C15: Lap Blanket | D15: Home & Decor | E15: Granny stripe lap blanket | F15: 75 | G15: 16.8 | H15: 2 | I15: =IF($C15="","",ROUND(N($G15)+N($H15),2)) -> 18.8 | J15: =IF(OR($C15="",$F15=""),"",ROUND($F15-$I15,2)) -> 56.2 | K15: =IF(OR($C15="",$F15=""),"",IFERROR($J15/$F15,0)) -> 0.74933333 | L15: 10 | M15: =IF($C15="",0,SUMIFS('📦 Made & Stocked'!$J$8:$J$37,'📦 Made & Stocked'!$B$8:$B$37,$C15)) -> 1 | N15: 2 | O15: =IF($C15="","",IF(N($M15)<=0,"🔴 Out of stock",IF(N($M15)<$N15,"🟠 Low stock","🟢 In stock"))) -> 🟠 Low stock | P15: photos/blanket.jpg
B16: CB-009 | C16: Ear Warmer Headband | D16: Accessories | E16: Twisted ear warmer | F16: 16 | G16: 2.9 | H16: 0.5 | I16: =IF($C16="","",ROUND(N($G16)+N($H16),2)) -> 3.4 | J16: =IF(OR($C16="",$F16=""),"",ROUND($F16-$I16,2)) -> 12.6 | K16: =IF(OR($C16="",$F16=""),"",IFERROR($J16/$F16,0)) -> 0.7875 | L16: 1 | M16: =IF($C16="",0,SUMIFS('📦 Made & Stocked'!$J$8:$J$37,'📦 Made & Stocked'!$B$8:$B$37,$C16)) -> 0 | N16: 4 | O16: =IF($C16="","",IF(N($M16)<=0,"🔴 Out of stock",IF(N($M16)<$N16,"🟠 Low stock","🟢 In stock"))) -> 🔴 Out of stock | P16: photos/earwarmer.jpg
B17: CB-010 | C17: Stuffed Octopus | D17: Toys & Amigurumi | E17: Squishy friend octopus | F17: 26 | G17: 4.6 | H17: 0.8 | I17: =IF($C17="","",ROUND(N($G17)+N($H17),2)) -> 5.4 | J17: =IF(OR($C17="",$F17=""),"",ROUND($F17-$I17,2)) -> 20.6 | K17: =IF(OR($C17="",$F17=""),"",IFERROR($J17/$F17,0)) -> 0.79230769 | L17: 2.5 | M17: =IF($C17="",0,SUMIFS('📦 Made & Stocked'!$J$8:$J$37,'📦 Made & Stocked'!$B$8:$B$37,$C17)) -> 7 | N17: 4 | O17: =IF($C17="","",IF(N($M17)<=0,"🔴 Out of stock",IF(N($M17)<$N17,"🟠 Low stock","🟢 In stock"))) -> 🟢 In stock | P17: photos/octopus.jpg
B18: CB-011 | C18: Table Runner | D18: Home & Decor | E18: Lacy cotton table runner | F18: 55 | G18: 10.4 | H18: 1.6 | I18: =IF($C18="","",ROUND(N($G18)+N($H18),2)) -> 12 | J18: =IF(OR($C18="",$F18=""),"",ROUND($F18-$I18,2)) -> 43 | K18: =IF(OR($C18="",$F18=""),"",IFERROR($J18/$F18,0)) -> 0.78181818 | L18: 7 | M18: =IF($C18="",0,SUMIFS('📦 Made & Stocked'!$J$8:$J$37,'📦 Made & Stocked'!$B$8:$B$37,$C18)) -> 0 | N18: 2 | O18: =IF($C18="","",IF(N($M18)<=0,"🔴 Out of stock",IF(N($M18)<$N18,"🟠 Low stock","🟢 In stock"))) -> 🔴 Out of stock | P18: photos/runner.jpg
B19: CB-012 | C19: Keychain Charm | D19: Accessories | E19: Mini amigurumi keychain | F19: 10 | G19: 1.1 | H19: 0.4 | I19: =IF($C19="","",ROUND(N($G19)+N($H19),2)) -> 1.5 | J19: =IF(OR($C19="",$F19=""),"",ROUND($F19-$I19,2)) -> 8.5 | K19: =IF(OR($C19="",$F19=""),"",IFERROR($J19/$F19,0)) -> 0.85 | L19: 0.5 | M19: =IF($C19="",0,SUMIFS('📦 Made & Stocked'!$J$8:$J$37,'📦 Made & Stocked'!$B$8:$B$37,$C19)) -> 0 | N19: 6 | O19: =IF($C19="","",IF(N($M19)<=0,"🔴 Out of stock",IF(N($M19)<$N19,"🟠 Low stock","🟢 In stock"))) -> 🔴 Out of stock | P19: photos/charm.jpg
I20: =IF($C20="","",ROUND(N($G20)+N($H20),2)) -> 0 | J20: =IF(OR($C20="",$F20=""),"",ROUND($F20-$I20,2)) -> 0 | K20: =IF(OR($C20="",$F20=""),"",IFERROR($J20/$F20,0)) -> 0 | M20: =IF($C20="",0,SUMIFS('📦 Made & Stocked'!$J$8:$J$37,'📦 Made & Stocked'!$B$8:$B$37,$C20)) -> 0 | O20: =IF($C20="","",IF(N($M20)<=0,"🔴 Out of stock",IF(N($M20)<$N20,"🟠 Low stock","🟢 In stock"))) -> 0
I21: =IF($C21="","",ROUND(N($G21)+N($H21),2)) -> 0 | J21: =IF(OR($C21="",$F21=""),"",ROUND($F21-$I21,2)) -> 0 | K21: =IF(OR($C21="",$F21=""),"",IFERROR($J21/$F21,0)) -> 0 | M21: =IF($C21="",0,SUMIFS('📦 Made & Stocked'!$J$8:$J$37,'📦 Made & Stocked'!$B$8:$B$37,$C21)) -> 0 | O21: =IF($C21="","",IF(N($M21)<=0,"🔴 Out of stock",IF(N($M21)<$N21,"🟠 Low stock","🟢 In stock"))) -> 0
I22: =IF($C22="","",ROUND(N($G22)+N($H22),2)) -> 0 | J22: =IF(OR($C22="",$F22=""),"",ROUND($F22-$I22,2)) -> 0 | K22: =IF(OR($C22="",$F22=""),"",IFERROR($J22/$F22,0)) -> 0 | M22: =IF($C22="",0,SUMIFS('📦 Made & Stocked'!$J$8:$J$37,'📦 Made & Stocked'!$B$8:$B$37,$C22)) -> 0 | O22: =IF($C22="","",IF(N($M22)<=0,"🔴 Out of stock",IF(N($M22)<$N22,"🟠 Low stock","🟢 In stock"))) -> 0
I23: =IF($C23="","",ROUND(N($G23)+N($H23),2)) -> 0 | J23: =IF(OR($C23="",$F23=""),"",ROUND($F23-$I23,2)) -> 0 | K23: =IF(OR($C23="",$F23=""),"",IFERROR($J23/$F23,0)) -> 0 | M23: =IF($C23="",0,SUMIFS('📦 Made & Stocked'!$J$8:$J$37,'📦 Made & Stocked'!$B$8:$B$37,$C23)) -> 0 | O23: =IF($C23="","",IF(N($M23)<=0,"🔴 Out of stock",IF(N($M23)<$N23,"🟠 Low stock","🟢 In stock"))) -> 0
I24: =IF($C24="","",ROUND(N($G24)+N($H24),2)) -> 0 | J24: =IF(OR($C24="",$F24=""),"",ROUND($F24-$I24,2)) -> 0 | K24: =IF(OR($C24="",$F24=""),"",IFERROR($J24/$F24,0)) -> 0 | M24: =IF($C24="",0,SUMIFS('📦 Made & Stocked'!$J$8:$J$37,'📦 Made & Stocked'!$B$8:$B$37,$C24)) -> 0 | O24: =IF($C24="","",IF(N($M24)<=0,"🔴 Out of stock",IF(N($M24)<$N24,"🟠 Low stock","🟢 In stock"))) -> 0
I25: =IF($C25="","",ROUND(N($G25)+N($H25),2)) -> 0 | J25: =IF(OR($C25="",$F25=""),"",ROUND($F25-$I25,2)) -> 0 | K25: =IF(OR($C25="",$F25=""),"",IFERROR($J25/$F25,0)) -> 0 | M25: =IF($C25="",0,SUMIFS('📦 Made & Stocked'!$J$8:$J$37,'📦 Made & Stocked'!$B$8:$B$37,$C25)) -> 0 | O25: =IF($C25="","",IF(N($M25)<=0,"🔴 Out of stock",IF(N($M25)<$N25,"🟠 Low stock","🟢 In stock"))) -> 0
I26: =IF($C26="","",ROUND(N($G26)+N($H26),2)) -> 0 | J26: =IF(OR($C26="",$F26=""),"",ROUND($F26-$I26,2)) -> 0 | K26: =IF(OR($C26="",$F26=""),"",IFERROR($J26/$F26,0)) -> 0 | M26: =IF($C26="",0,SUMIFS('📦 Made & Stocked'!$J$8:$J$37,'📦 Made & Stocked'!$B$8:$B$37,$C26)) -> 0 | O26: =IF($C26="","",IF(N($M26)<=0,"🔴 Out of stock",IF(N($M26)<$N26,"🟠 Low stock","🟢 In stock"))) -> 0
I27: =IF($C27="","",ROUND(N($G27)+N($H27),2)) -> 0 | J27: =IF(OR($C27="",$F27=""),"",ROUND($F27-$I27,2)) -> 0 | K27: =IF(OR($C27="",$F27=""),"",IFERROR($J27/$F27,0)) -> 0 | M27: =IF($C27="",0,SUMIFS('📦 Made & Stocked'!$J$8:$J$37,'📦 Made & Stocked'!$B$8:$B$37,$C27)) -> 0 | O27: =IF($C27="","",IF(N($M27)<=0,"🔴 Out of stock",IF(N($M27)<$N27,"🟠 Low stock","🟢 In stock"))) -> 0
I28: =IF($C28="","",ROUND(N($G28)+N($H28),2)) -> 0 | J28: =IF(OR($C28="",$F28=""),"",ROUND($F28-$I28,2)) -> 0 | K28: =IF(OR($C28="",$F28=""),"",IFERROR($J28/$F28,0)) -> 0 | M28: =IF($C28="",0,SUMIFS('📦 Made & Stocked'!$J$8:$J$37,'📦 Made & Stocked'!$B$8:$B$37,$C28)) -> 0 | O28: =IF($C28="","",IF(N($M28)<=0,"🔴 Out of stock",IF(N($M28)<$N28,"🟠 Low stock","🟢 In stock"))) -> 0
I29: =IF($C29="","",ROUND(N($G29)+N($H29),2)) -> 0 | J29: =IF(OR($C29="",$F29=""),"",ROUND($F29-$I29,2)) -> 0 | K29: =IF(OR($C29="",$F29=""),"",IFERROR($J29/$F29,0)) -> 0 | M29: =IF($C29="",0,SUMIFS('📦 Made & Stocked'!$J$8:$J$37,'📦 Made & Stocked'!$B$8:$B$37,$C29)) -> 0 | O29: =IF($C29="","",IF(N($M29)<=0,"🔴 Out of stock",IF(N($M29)<$N29,"🟠 Low stock","🟢 In stock"))) -> 0
I30: =IF($C30="","",ROUND(N($G30)+N($H30),2)) -> 0 | J30: =IF(OR($C30="",$F30=""),"",ROUND($F30-$I30,2)) -> 0 | K30: =IF(OR($C30="",$F30=""),"",IFERROR($J30/$F30,0)) -> 0 | M30: =IF($C30="",0,SUMIFS('📦 Made & Stocked'!$J$8:$J$37,'📦 Made & Stocked'!$B$8:$B$37,$C30)) -> 0 | O30: =IF($C30="","",IF(N($M30)<=0,"🔴 Out of stock",IF(N($M30)<$N30,"🟠 Low stock","🟢 In stock"))) -> 0
I31: =IF($C31="","",ROUND(N($G31)+N($H31),2)) -> 0 | J31: =IF(OR($C31="",$F31=""),"",ROUND($F31-$I31,2)) -> 0 | K31: =IF(OR($C31="",$F31=""),"",IFERROR($J31/$F31,0)) -> 0 | M31: =IF($C31="",0,SUMIFS('📦 Made & Stocked'!$J$8:$J$37,'📦 Made & Stocked'!$B$8:$B$37,$C31)) -> 0 | O31: =IF($C31="","",IF(N($M31)<=0,"🔴 Out of stock",IF(N($M31)<$N31,"🟠 Low stock","🟢 In stock"))) -> 0
C33: =COUNTA('🧶 Product Catalog'!$C$8:$C$31) -> 12 | F33: =IFERROR(AVERAGE('🧶 Product Catalog'!$F$8:$F$31),0) -> 36.08 | I33: =IFERROR(AVERAGE('🧶 Product Catalog'!$I$8:$I$31),0) -> 8 | J33: =IFERROR(AVERAGE('🧶 Product Catalog'!$J$8:$J$31),0) -> 28.08 | M33: =SUM('🧶 Product Catalog'!$M$8:$M$31) -> 40
B35: How this tab works
B36: Cost / item = yarn + packaging. Profit and margin follow your price automatically. In stock is live from the Made & Stocked tab - every batch you log updates it instantly. Keep min. is your reorder trigger - dip below it and the item appears on the Reorder List tab.
B40: 💡 Cream cells are yours to type in; white cells calculate. Dropdowns keep every column honest.
B42: Settings | D42: 🏠 Home | F42: ▶ Products | H42: Yarn | J42: Stock | L42: Fairs | N42: Sales
B43: Event $ | D43: Reorder | F43: Packing | H43: Pricing | J43: Monthly | L43: Help

Sheet 🧵 Yarn & Materials
B2: 🧵 Yarn & Materials
B3: Your whole stash with costs - and what's left on the shelf | L3: 🏠 Dashboard
B5: ="Materials: "&TEXT(COUNTA('🧵 Yarn & Materials'!$B$8:$B$31),"0") -> Materials: 10 | E5: ="Still on the shelf: "&TEXT(SUM('🧵 Yarn & Materials'!$K$8:$K$31),"#,##0") -> Still on the shelf: 74 | H5: ="Stash value: "&Currency&TEXT(SUM('🧵 Yarn & Materials'!$I$8:$I$31),"#,##0.00") -> Stash value: $360.30 | K5: =IF('_Data'!$AI$16>0,"! "&TEXT('_Data'!$AI$16,"0")&" materials running low","Stash looks healthy") -> ! 5 materials running low
A7: # | B7: Material | C7: Colour | D7: Brand | E7: Yarn weight | F7: Purchased | G7: Unit | H7: Cost / unit | I7: Total cost | J7: Used so far | K7: Remaining | L7: Supplier | M7: Low at | N7: Reorder?
B8: Cotton yarn - natural | C8: Natural | D8: Cotton Craft Co | E8: Worsted / aran | F8: 20 | G8: balls | H8: 3.4 | I8: =IF($B8="","",ROUND(N($F8)*N($H8),2)) -> 68 | J8: 16 | K8: =IF($B8="","",N($F8)-N($J8)) -> 4 | L8: Local yarn shop | M8: 5 | N8: =IF($B8="","",IF($K8<=$M8,"✅ Reorder","❌ OK")) -> ✅ Reorder
B9: Acrylic yarn - raspberry | C9: Raspberry | D9: Value Yarns | E9: Worsted / aran | F9: 15 | G9: balls | H9: 2.6 | I9: =IF($B9="","",ROUND(N($F9)*N($H9),2)) -> 39 | J9: 9 | K9: =IF($B9="","",N($F9)-N($J9)) -> 6 | L9: Online yarn store | M9: 4 | N9: =IF($B9="","",IF($K9<=$M9,"✅ Reorder","❌ OK")) -> ❌ OK
B10: Merino wool - sage | C10: Sage | D10: Highland Fibres | E10: DK / light | F10: 12 | G10: balls | H10: 6.8 | I10: =IF($B10="","",ROUND(N($F10)*N($H10),2)) -> 81.6 | J10: 10 | K10: =IF($B10="","",N($F10)-N($J10)) -> 2 | L10: Local yarn shop | M10: 4 | N10: =IF($B10="","",IF($K10<=$M10,"✅ Reorder","❌ OK")) -> ✅ Reorder
B11: Chenille chunky - cream | C11: Cream | D11: Snuggle Spun | E11: Super chunky | F11: 10 | G11: balls | H11: 4.9 | I11: =IF($B11="","",ROUND(N($F11)*N($H11),2)) -> 49 | J11: 6 | K11: =IF($B11="","",N($F11)-N($J11)) -> 4 | L11: Online yarn store | M11: 3 | N11: =IF($B11="","",IF($K11<=$M11,"✅ Reorder","❌ OK")) -> ❌ OK
B12: Cotton yarn - mustard | C12: Mustard | D12: Cotton Craft Co | E12: DK / light | F12: 8 | G12: balls | H12: 3.2 | I12: =IF($B12="","",ROUND(N($F12)*N($H12),2)) -> 25.6 | J12: 7 | K12: =IF($B12="","",N($F12)-N($J12)) -> 1 | L12: Local yarn shop | M12: 3 | N12: =IF($B12="","",IF($K12<=$M12,"✅ Reorder","❌ OK")) -> ✅ Reorder
B13: Wool blend - lavender | C13: Lavender | D13: Highland Fibres | E13: Worsted / aran | F13: 10 | G13: balls | H13: 5.4 | I13: =IF($B13="","",ROUND(N($F13)*N($H13),2)) -> 54 | J13: 4 | K13: =IF($B13="","",N($F13)-N($J13)) -> 6 | L13: Wholesale craft | M13: 3 | N13: =IF($B13="","",IF($K13<=$M13,"✅ Reorder","❌ OK")) -> ❌ OK
B14: Polyester stuffing | C14: White | D14: Craft Basics | E14: Mixed / other | F14: 6 | G14: pieces | H14: 2.1 | I14: =IF($B14="","",ROUND(N($F14)*N($H14),2)) -> 12.6 | J14: 4 | K14: =IF($B14="","",N($F14)-N($J14)) -> 2 | L14: Wholesale craft | M14: 2 | N14: =IF($B14="","",IF($K14<=$M14,"✅ Reorder","❌ OK")) -> ✅ Reorder
B15: Bamboo buttons | C15: Natural | D15: Craft Basics | E15: Mixed / other | F15: 40 | G15: pieces | H15: 0.35 | I15: =IF($B15="","",ROUND(N($F15)*N($H15),2)) -> 14 | J15: 22 | K15: =IF($B15="","",N($F15)-N($J15)) -> 18 | L15: Online yarn store | M15: 10 | N15: =IF($B15="","",IF($K15<=$M15,"✅ Reorder","❌ OK")) -> ❌ OK
B16: Safety eyes | C16: Black | D16: Craft Basics | E16: Mixed / other | F16: 30 | G16: pieces | H16: 0.25 | I16: =IF($B16="","",ROUND(N($F16)*N($H16),2)) -> 7.5 | J16: 24 | K16: =IF($B16="","",N($F16)-N($J16)) -> 6 | L16: Wholesale craft | M16: 10 | N16: =IF($B16="","",IF($K16<=$M16,"✅ Reorder","❌ OK")) -> ✅ Reorder
B17: Paper gift tags | C17: Kraft | D17: Print & Tag | E17: Mixed / other | F17: 60 | G17: pieces | H17: 0.15 | I17: =IF($B17="","",ROUND(N($F17)*N($H17),2)) -> 9 | J17: 35 | K17: =IF($B17="","",N($F17)-N($J17)) -> 25 | L17: Market stall | M17: 20 | N17: =IF($B17="","",IF($K17<=$M17,"✅ Reorder","❌ OK")) -> ❌ OK
I18: =IF($B18="","",ROUND(N($F18)*N($H18),2)) -> 0 | K18: =IF($B18="","",N($F18)-N($J18)) -> 0 | N18: =IF($B18="","",IF($K18<=$M18,"✅ Reorder","❌ OK")) -> 0
I19: =IF($B19="","",ROUND(N($F19)*N($H19),2)) -> 0 | K19: =IF($B19="","",N($F19)-N($J19)) -> 0 | N19: =IF($B19="","",IF($K19<=$M19,"✅ Reorder","❌ OK")) -> 0
I20: =IF($B20="","",ROUND(N($F20)*N($H20),2)) -> 0 | K20: =IF($B20="","",N($F20)-N($J20)) -> 0 | N20: =IF($B20="","",IF($K20<=$M20,"✅ Reorder","❌ OK")) -> 0
I21: =IF($B21="","",ROUND(N($F21)*N($H21),2)) -> 0 | K21: =IF($B21="","",N($F21)-N($J21)) -> 0 | N21: =IF($B21="","",IF($K21<=$M21,"✅ Reorder","❌ OK")) -> 0
I22: =IF($B22="","",ROUND(N($F22)*N($H22),2)) -> 0 | K22: =IF($B22="","",N($F22)-N($J22)) -> 0 | N22: =IF($B22="","",IF($K22<=$M22,"✅ Reorder","❌ OK")) -> 0
I23: =IF($B23="","",ROUND(N($F23)*N($H23),2)) -> 0 | K23: =IF($B23="","",N($F23)-N($J23)) -> 0 | N23: =IF($B23="","",IF($K23<=$M23,"✅ Reorder","❌ OK")) -> 0
I24: =IF($B24="","",ROUND(N($F24)*N($H24),2)) -> 0 | K24: =IF($B24="","",N($F24)-N($J24)) -> 0 | N24: =IF($B24="","",IF($K24<=$M24,"✅ Reorder","❌ OK")) -> 0
I25: =IF($B25="","",ROUND(N($F25)*N($H25),2)) -> 0 | K25: =IF($B25="","",N($F25)-N($J25)) -> 0 | N25: =IF($B25="","",IF($K25<=$M25,"✅ Reorder","❌ OK")) -> 0
I26: =IF($B26="","",ROUND(N($F26)*N($H26),2)) -> 0 | K26: =IF($B26="","",N($F26)-N($J26)) -> 0 | N26: =IF($B26="","",IF($K26<=$M26,"✅ Reorder","❌ OK")) -> 0
I27: =IF($B27="","",ROUND(N($F27)*N($H27),2)) -> 0 | K27: =IF($B27="","",N($F27)-N($J27)) -> 0 | N27: =IF($B27="","",IF($K27<=$M27,"✅ Reorder","❌ OK")) -> 0
I28: =IF($B28="","",ROUND(N($F28)*N($H28),2)) -> 0 | K28: =IF($B28="","",N($F28)-N($J28)) -> 0 | N28: =IF($B28="","",IF($K28<=$M28,"✅ Reorder","❌ OK")) -> 0
I29: =IF($B29="","",ROUND(N($F29)*N($H29),2)) -> 0 | K29: =IF($B29="","",N($F29)-N($J29)) -> 0 | N29: =IF($B29="","",IF($K29<=$M29,"✅ Reorder","❌ OK")) -> 0
... I31: =IF($B31="","",ROUND(N($F31)*N($H31),2)) -> 0 | K31: =IF($B31="","",N($F31)-N($J31)) -> 0 | N31: =IF($B31="","",IF($K31<=$M31,"✅ Reorder","❌ OK")) -> 0
B33: =COUNTA('🧵 Yarn & Materials'!$B$8:$B$31) -> 10 | C33: TOTALS | I33: =SUM('🧵 Yarn & Materials'!$I$8:$I$31) -> 360.3 | J33: =SUM('🧵 Yarn & Materials'!$J$8:$J$31) -> 137
B35: How this tab works
B36: Remaining = purchased - used. Update 'Used so far' as you work through a ball (rough counts are fine). When remaining drops to the 'Low at' number, the Reorder List tab adds it to your shopping list with an estimated cost.
B40: 💡 Cream cells are yours to type in; white cells calculate. Dropdowns keep every column honest.
B42: Settings | D42: 🏠 Home | F42: Products | H42: ▶ Yarn | J42: Stock | L42: Fairs
B43: Sales | D43: Event $ | F43: Reorder | H43: Packing | J43: Pricing | L43: Monthly
B44: Help

Sheet 📦 Made & Stocked
B2: 📦 Made & Stocked
B3: Log what you make - stock counts itself, batch by batch | J3: 🏠 Dashboard
B5: ="Batches: "&TEXT(COUNTA('📦 Made & Stocked'!$B$8:$B$37),"0") -> Batches: 12 | E5: ="Made this year: "&TEXT(SUM('📦 Made & Stocked'!$D$8:$D$37),"#,##0") -> Made this year: 118 | H5: ="Sold: "&TEXT(SUM('📦 Made & Stocked'!$G$8:$G$37),"#,##0") -> Sold: 77 | K5: ="On the shelf: "&TEXT(SUM('📦 Made & Stocked'!$J$8:$J$37),"#,##0") -> On the shelf: 40
A7: # | B7: Product | C7: Date made | D7: Made | E7: Reserved | F7: Taken to fair | G7: Sold | H7: Returned | I7: Damaged / gifted | J7: In stock now | K7: Free to sell | L7: Notes
B8: Amigurumi Bunny | C8: 46083 | D8: 11 | E8: 1 | F8: 10 | G8: 6 | H8: 0 | I8: 0 | J8: =IF($B8="","",N($D8)+N($H8)-N($G8)-N($I8)) -> 5 | K8: =IF($B8="","",$J8-N($E8)) -> 4 | L8: Best spring seller
B9: Chunky Beanie | C9: 46093 | D9: 15 | E9: 1 | F9: 12 | G9: 5 | H9: 0 | I9: 0 | J9: =IF($B9="","",N($D9)+N($H9)-N($G9)-N($I9)) -> 10 | K9: =IF($B9="","",$J9-N($E9)) -> 9
B10: Granny Square Cardigan | C10: 46130 | D10: 3 | E10: 0 | F10: 2 | G10: 1 | H10: 0 | I10: 0 | J10: =IF($B10="","",N($D10)+N($H10)-N($G10)-N($I10)) -> 2 | K10: =IF($B10="","",$J10-N($E10)) -> 2 | L10: Made to order
B11: Market Tote Bag | C11: 46114 | D11: 11 | E11: 1 | F11: 10 | G11: 8 | H11: 0 | I11: 0 | J11: =IF($B11="","",N($D11)+N($H11)-N($G11)-N($I11)) -> 3 | K11: =IF($B11="","",$J11-N($E11)) -> 2
B12: Cozy Scarf | C12: 46256 | D12: 6 | E12: 0 | F12: 4 | G12: 2 | H12: 0 | I12: 0 | J12: =IF($B12="","",N($D12)+N($H12)-N($G12)-N($I12)) -> 4 | K12: =IF($B12="","",$J12-N($E12)) -> 4 | L12: Autumn stock
B13: Baby Booties | C13: 46109 | D13: 8 | E13: 0 | F13: 6 | G13: 5 | H13: 0 | I13: 0 | J13: =IF($B13="","",N($D13)+N($H13)-N($G13)-N($I13)) -> 3 | K13: =IF($B13="","",$J13-N($E13)) -> 3
B14: Flower Coaster Set | C14: 46073 | D14: 20 | E14: 0 | F14: 16 | G14: 14 | H14: 0 | I14: 1 | J14: =IF($B14="","",N($D14)+N($H14)-N($G14)-N($I14)) -> 5 | K14: =IF($B14="","",$J14-N($E14)) -> 5 | L14: One water damaged
B15: Lap Blanket | C15: 46063 | D15: 3 | E15: 0 | F15: 3 | G15: 2 | H15: 0 | I15: 0 | J15: =IF($B15="","",N($D15)+N($H15)-N($G15)-N($I15)) -> 1 | K15: =IF($B15="","",$J15-N($E15)) -> 1 | L15: Sold out online
B16: Ear Warmer Headband | C16: 46144 | D16: 10 | E16: 0 | F16: 10 | G16: 10 | H16: 0 | I16: 0 | J16: =IF($B16="","",N($D16)+N($H16)-N($G16)-N($I16)) -> 0 | K16: =IF($B16="","",$J16-N($E16)) -> 0 | L16: Sold out at fete
B17: Stuffed Octopus | C17: 46259 | D17: 10 | E17: 2 | F17: 6 | G17: 3 | H17: 0 | I17: 0 | J17: =IF($B17="","",N($D17)+N($H17)-N($G17)-N($I17)) -> 7 | K17: =IF($B17="","",$J17-N($E17)) -> 5 | L17: Reserved for market
B18: Table Runner | C18: 46086 | D18: 3 | E18: 0 | F18: 3 | G18: 3 | H18: 0 | I18: 0 | J18: =IF($B18="","",N($D18)+N($H18)-N($G18)-N($I18)) -> 0 | K18: =IF($B18="","",$J18-N($E18)) -> 0
B19: Keychain Charm | C19: 46132 | D19: 18 | E19: 0 | F19: 16 | G19: 18 | H19: 0 | I19: 0 | J19: =IF($B19="","",N($D19)+N($H19)-N($G19)-N($I19)) -> 0 | K19: =IF($B19="","",$J19-N($E19)) -> 0 | L19: Impulse buy winner
J20: =IF($B20="","",N($D20)+N($H20)-N($G20)-N($I20)) -> 0 | K20: =IF($B20="","",$J20-N($E20)) -> 0
J21: =IF($B21="","",N($D21)+N($H21)-N($G21)-N($I21)) -> 0 | K21: =IF($B21="","",$J21-N($E21)) -> 0
J22: =IF($B22="","",N($D22)+N($H22)-N($G22)-N($I22)) -> 0 | K22: =IF($B22="","",$J22-N($E22)) -> 0
J23: =IF($B23="","",N($D23)+N($H23)-N($G23)-N($I23)) -> 0 | K23: =IF($B23="","",$J23-N($E23)) -> 0
J24: =IF($B24="","",N($D24)+N($H24)-N($G24)-N($I24)) -> 0 | K24: =IF($B24="","",$J24-N($E24)) -> 0
J25: =IF($B25="","",N($D25)+N($H25)-N($G25)-N($I25)) -> 0 | K25: =IF($B25="","",$J25-N($E25)) -> 0
J26: =IF($B26="","",N($D26)+N($H26)-N($G26)-N($I26)) -> 0 | K26: =IF($B26="","",$J26-N($E26)) -> 0
J27: =IF($B27="","",N($D27)+N($H27)-N($G27)-N($I27)) -> 0 | K27: =IF($B27="","",$J27-N($E27)) -> 0
J28: =IF($B28="","",N($D28)+N($H28)-N($G28)-N($I28)) -> 0 | K28: =IF($B28="","",$J28-N($E28)) -> 0
J29: =IF($B29="","",N($D29)+N($H29)-N($G29)-N($I29)) -> 0 | K29: =IF($B29="","",$J29-N($E29)) -> 0
J30: =IF($B30="","",N($D30)+N($H30)-N($G30)-N($I30)) -> 0 | K30: =IF($B30="","",$J30-N($E30)) -> 0
J31: =IF($B31="","",N($D31)+N($H31)-N($G31)-N($I31)) -> 0 | K31: =IF($B31="","",$J31-N($E31)) -> 0
... J37: =IF($B37="","",N($D37)+N($H37)-N($G37)-N($I37)) -> 0 | K37: =IF($B37="","",$J37-N($E37)) -> 0
C39: TOTALS | D39: =SUM('📦 Made & Stocked'!$D$8:$D$37) -> 118 | F39: =SUM('📦 Made & Stocked'!$F$8:$F$37) -> 98 | G39: =SUM('📦 Made & Stocked'!$G$8:$G$37) -> 77 | J39: =SUM('📦 Made & Stocked'!$J$8:$J$37) -> 40
B41: How this tab works
B42: In stock now = made + returned - sold - damaged. Free to sell also removes items you've reserved (custom orders, prizes). The same product can span several batches - the Product Catalog adds them all up automatically. Negative 'Free to sell' glows red: you've promised more than you made.
B46: 💡 Cream cells are yours to type in; white cells calculate. Dropdowns keep every column honest.
B48: Settings | D48: 🏠 Home | F48: Products | H48: Yarn | J48: ▶ Stock
B49: Fairs | D49: Sales | F49: Event $ | H49: Reorder | J49: Packing
B50: Pricing | D50: Monthly | F50: Help

Sheet 🏪 Craft Fairs
B2: 🏪 Craft Fairs
B3: Book the fair, log the costs - the profit maths runs itself | P3: 🏠 Dashboard
B5: ="Fairs booked: "&TEXT(COUNTA('🏪 Craft Fairs'!$B$8:$B$31),"0") -> Fairs booked: 8 | E5: ="Fair costs: "&Currency&TEXT(SUM('🏪 Craft Fairs'!$K$8:$K$31),"#,##0.00") -> Fair costs: $680.00 | H5: ="Sales: "&Currency&TEXT(SUM('🏪 Craft Fairs'!$N$8:$N$31),"#,##0.00") -> Sales: $1,760.00 | K5: ="Net: "&Currency&TEXT(SUM('🏪 Craft Fairs'!$P$8:$P$31),"#,##0.00") -> Net: $716.50
A7: # | B7: Craft fair | C7: Date | D7: Location | E7: Organiser | F7: Booth fee | G7: Travel | H7: Parking | I7: Food | J7: Display | K7: Fair cost | L7: Items taken | M7: Items sold | N7: Sales | O7: Cost of goods | P7: Net profit | Q7: Margin | R7: Top seller (fill in)
B8: Spring Makers Market | C8: 46095 | D8: Town Hall | E8: Makers Guild | F8: 45 | G8: 12 | H8: 5 | I8: 8 | J8: 20 | K8: =IF($B8="","",ROUND(N($F8)+N($G8)+N($H8)+N($I8)+N($J8),2)) -> 90 | L8: 38 | M8: =IF($B8="","",SUMIFS('💰 Sales Log'!$E$8:$E$67,'💰 Sales Log'!$C$8:$C$67,$B8)) -> 14 | N8: =IF($B8="","",SUMIFS('💰 Sales Log'!$H$8:$H$67,'💰 Sales Log'!$C$8:$C$67,$B8)) -> 300 | O8: =IF($B8="","",SUMIFS('💰 Sales Log'!$M$8:$M$67,'💰 Sales Log'!$C$8:$C$67,$B8)) -> 58.8 | P8: =IF($B8="","",ROUND($N8-$K8-$O8,2)) -> 151.2 | Q8: =IF(OR($B8="",$N8=0),"",IFERROR($P8/$N8,0)) -> 0.504 | R8: Flower Coaster Set
B9: Easter Craft Bazaar | C9: 46117 | D9: Church Hall | E9: St Mary's | F9: 30 | G9: 8 | H9: 0 | I9: 6 | J9: 10 | K9: =IF($B9="","",ROUND(N($F9)+N($G9)+N($H9)+N($I9)+N($J9),2)) -> 54 | L9: 20 | M9: =IF($B9="","",SUMIFS('💰 Sales Log'!$E$8:$E$67,'💰 Sales Log'!$C$8:$C$67,$B9)) -> 9 | N9: =IF($B9="","",SUMIFS('💰 Sales Log'!$H$8:$H$67,'💰 Sales Log'!$C$8:$C$67,$B9)) -> 174 | O9: =IF($B9="","",SUMIFS('💰 Sales Log'!$M$8:$M$67,'💰 Sales Log'!$C$8:$C$67,$B9)) -> 30.4 | P9: =IF($B9="","",ROUND($N9-$K9-$O9,2)) -> 89.6 | Q9: =IF(OR($B9="",$N9=0),"",IFERROR($P9/$N9,0)) -> 0.51494253 | R9: Flower Coaster Set
B10: School Fete Stall | C10: 46158 | D10: Primary School | E10: PTA | F10: 25 | G10: 6 | H10: 0 | I10: 5 | J10: 8 | K10: =IF($B10="","",ROUND(N($F10)+N($G10)+N($H10)+N($I10)+N($J10),2)) -> 44 | L10: 30 | M10: =IF($B10="","",SUMIFS('💰 Sales Log'!$E$8:$E$67,'💰 Sales Log'!$C$8:$C$67,$B10)) -> 19 | N10: =IF($B10="","",SUMIFS('💰 Sales Log'!$H$8:$H$67,'💰 Sales Log'!$C$8:$C$67,$B10)) -> 244 | O10: =IF($B10="","",SUMIFS('💰 Sales Log'!$M$8:$M$67,'💰 Sales Log'!$C$8:$C$67,$B10)) -> 43.5 | P10: =IF($B10="","",ROUND($N10-$K10-$O10,2)) -> 156.5 | Q10: =IF(OR($B10="",$N10=0),"",IFERROR($P10/$N10,0)) -> 0.64139344 | R10: Keychain Charm
B11: Summer Night Bazaar | C11: 46192 | D11: Riverside Park | E11: City Council | F11: 60 | G11: 15 | H11: 6 | I11: 10 | J11: 25 | K11: =IF($B11="","",ROUND(N($F11)+N($G11)+N($H11)+N($I11)+N($J11),2)) -> 116 | L11: 30 | M11: =IF($B11="","",SUMIFS('💰 Sales Log'!$E$8:$E$67,'💰 Sales Log'!$C$8:$C$67,$B11)) -> 21 | N11: =IF($B11="","",SUMIFS('💰 Sales Log'!$H$8:$H$67,'💰 Sales Log'!$C$8:$C$67,$B11)) -> 398 | O11: =IF($B11="","",SUMIFS('💰 Sales Log'!$M$8:$M$67,'💰 Sales Log'!$C$8:$C$67,$B11)) -> 82.8 | P11: =IF($B11="","",ROUND($N11-$K11-$O11,2)) -> 199.2 | Q11: =IF(OR($B11="",$N11=0),"",IFERROR($P11/$N11,0)) -> 0.50050251 | R11: Keychain Charm
B12: Farmers Market Pop-up | C12: 46228 | D12: Market Square | E12: Growers Co-op | F12: 40 | G12: 10 | H12: 4 | I12: 7 | J12: 12 | K12: =IF($B12="","",ROUND(N($F12)+N($G12)+N($H12)+N($I12)+N($J12),2)) -> 73 | L12: 16 | M12: =IF($B12="","",SUMIFS('💰 Sales Log'!$E$8:$E$67,'💰 Sales Log'!$C$8:$C$67,$B12)) -> 9 | N12: =IF($B12="","",SUMIFS('💰 Sales Log'!$H$8:$H$67,'💰 Sales Log'!$C$8:$C$67,$B12)) -> 309 | O12: =IF($B12="","",SUMIFS('💰 Sales Log'!$M$8:$M$67,'💰 Sales Log'!$C$8:$C$67,$B12)) -> 72.6 | P12: =IF($B12="","",ROUND($N12-$K12-$O12,2)) -> 163.4 | Q12: =IF(OR($B12="",$N12=0),"",IFERROR($P12/$N12,0)) -> 0.52880259 | R12: Market Tote Bag
B13: Online Order Batch | C13: 46264 | D13: Online | E13: Own shop | F13: 0 | G13: 0 | H13: 0 | I13: 0 | J13: 0 | K13: =IF($B13="","",ROUND(N($F13)+N($G13)+N($H13)+N($I13)+N($J13),2)) -> 0 | L13: 0 | M13: =IF($B13="","",SUMIFS('💰 Sales Log'!$E$8:$E$67,'💰 Sales Log'!$C$8:$C$67,$B13)) -> 5 | N13: =IF($B13="","",SUMIFS('💰 Sales Log'!$H$8:$H$67,'💰 Sales Log'!$C$8:$C$67,$B13)) -> 335 | O13: =IF($B13="","",SUMIFS('💰 Sales Log'!$M$8:$M$67,'💰 Sales Log'!$C$8:$C$67,$B13)) -> 75.4 | P13: =IF($B13="","",ROUND($N13-$K13-$O13,2)) -> 259.6 | Q13: =IF(OR($B13="",$N13=0),"",IFERROR($P13/$N13,0)) -> 0.77492537 | R13: Table Runner
B14: Autumn Craft Fair | C14: 46291 | D14: Exhibition Centre | E14: Craft Collective | F14: 75 | G14: 20 | H14: 8 | I14: 12 | J14: 30 | K14: =IF($B14="","",ROUND(N($F14)+N($G14)+N($H14)+N($I14)+N($J14),2)) -> 145 | L14: 0 | M14: =IF($B14="","",SUMIFS('💰 Sales Log'!$E$8:$E$67,'💰 Sales Log'!$C$8:$C$67,$B14)) -> 0 | N14: =IF($B14="","",SUMIFS('💰 Sales Log'!$H$8:$H$67,'💰 Sales Log'!$C$8:$C$67,$B14)) -> 0 | O14: =IF($B14="","",SUMIFS('💰 Sales Log'!$M$8:$M$67,'💰 Sales Log'!$C$8:$C$67,$B14)) -> 0 | P14: =IF($B14="","",ROUND($N14-$K14-$O14,2)) -> -145 | Q14: =IF(OR($B14="",$N14=0),"",IFERROR($P14/$N14,0)) -> 0
B15: Winter Holiday Market | C15: 46354 | D15: Civic Square | E15: City Council | F15: 85 | G15: 18 | H15: 8 | I15: 12 | J15: 35 | K15: =IF($B15="","",ROUND(N($F15)+N($G15)+N($H15)+N($I15)+N($J15),2)) -> 158 | L15: 0 | M15: =IF($B15="","",SUMIFS('💰 Sales Log'!$E$8:$E$67,'💰 Sales Log'!$C$8:$C$67,$B15)) -> 0 | N15: =IF($B15="","",SUMIFS('💰 Sales Log'!$H$8:$H$67,'💰 Sales Log'!$C$8:$C$67,$B15)) -> 0 | O15: =IF($B15="","",SUMIFS('💰 Sales Log'!$M$8:$M$67,'💰 Sales Log'!$C$8:$C$67,$B15)) -> 0 | P15: =IF($B15="","",ROUND($N15-$K15-$O15,2)) -> -158 | Q15: =IF(OR($B15="",$N15=0),"",IFERROR($P15/$N15,0)) -> 0
K16: =IF($B16="","",ROUND(N($F16)+N($G16)+N($H16)+N($I16)+N($J16),2)) -> 0 | M16: =IF($B16="","",SUMIFS('💰 Sales Log'!$E$8:$E$67,'💰 Sales Log'!$C$8:$C$67,$B16)) -> 0 | N16: =IF($B16="","",SUMIFS('💰 Sales Log'!$H$8:$H$67,'💰 Sales Log'!$C$8:$C$67,$B16)) -> 0 | O16: =IF($B16="","",SUMIFS('💰 Sales Log'!$M$8:$M$67,'💰 Sales Log'!$C$8:$C$67,$B16)) -> 0 | P16: =IF($B16="","",ROUND($N16-$K16-$O16,2)) -> 0 | Q16: =IF(OR($B16="",$N16=0),"",IFERROR($P16/$N16,0)) -> 0
K17: =IF($B17="","",ROUND(N($F17)+N($G17)+N($H17)+N($I17)+N($J17),2)) -> 0 | M17: =IF($B17="","",SUMIFS('💰 Sales Log'!$E$8:$E$67,'💰 Sales Log'!$C$8:$C$67,$B17)) -> 0 | N17: =IF($B17="","",SUMIFS('💰 Sales Log'!$H$8:$H$67,'💰 Sales Log'!$C$8:$C$67,$B17)) -> 0 | O17: =IF($B17="","",SUMIFS('💰 Sales Log'!$M$8:$M$67,'💰 Sales Log'!$C$8:$C$67,$B17)) -> 0 | P17: =IF($B17="","",ROUND($N17-$K17-$O17,2)) -> 0 | Q17: =IF(OR($B17="",$N17=0),"",IFERROR($P17/$N17,0)) -> 0
K18: =IF($B18="","",ROUND(N($F18)+N($G18)+N($H18)+N($I18)+N($J18),2)) -> 0 | M18: =IF($B18="","",SUMIFS('💰 Sales Log'!$E$8:$E$67,'💰 Sales Log'!$C$8:$C$67,$B18)) -> 0 | N18: =IF($B18="","",SUMIFS('💰 Sales Log'!$H$8:$H$67,'💰 Sales Log'!$C$8:$C$67,$B18)) -> 0 | O18: =IF($B18="","",SUMIFS('💰 Sales Log'!$M$8:$M$67,'💰 Sales Log'!$C$8:$C$67,$B18)) -> 0 | P18: =IF($B18="","",ROUND($N18-$K18-$O18,2)) -> 0 | Q18: =IF(OR($B18="",$N18=0),"",IFERROR($P18/$N18,0)) -> 0
K19: =IF($B19="","",ROUND(N($F19)+N($G19)+N($H19)+N($I19)+N($J19),2)) -> 0 | M19: =IF($B19="","",SUMIFS('💰 Sales Log'!$E$8:$E$67,'💰 Sales Log'!$C$8:$C$67,$B19)) -> 0 | N19: =IF($B19="","",SUMIFS('💰 Sales Log'!$H$8:$H$67,'💰 Sales Log'!$C$8:$C$67,$B19)) -> 0 | O19: =IF($B19="","",SUMIFS('💰 Sales Log'!$M$8:$M$67,'💰 Sales Log'!$C$8:$C$67,$B19)) -> 0 | P19: =IF($B19="","",ROUND($N19-$K19-$O19,2)) -> 0 | Q19: =IF(OR($B19="",$N19=0),"",IFERROR($P19/$N19,0)) -> 0
K20: =IF($B20="","",ROUND(N($F20)+N($G20)+N($H20)+N($I20)+N($J20),2)) -> 0 | M20: =IF($B20="","",SUMIFS('💰 Sales Log'!$E$8:$E$67,'💰 Sales Log'!$C$8:$C$67,$B20)) -> 0 | N20: =IF($B20="","",SUMIFS('💰 Sales Log'!$H$8:$H$67,'💰 Sales Log'!$C$8:$C$67,$B20)) -> 0 | O20: =IF($B20="","",SUMIFS('💰 Sales Log'!$M$8:$M$67,'💰 Sales Log'!$C$8:$C$67,$B20)) -> 0 | P20: =IF($B20="","",ROUND($N20-$K20-$O20,2)) -> 0 | Q20: =IF(OR($B20="",$N20=0),"",IFERROR($P20/$N20,0)) -> 0
K21: =IF($B21="","",ROUND(N($F21)+N($G21)+N($H21)+N($I21)+N($J21),2)) -> 0 | M21: =IF($B21="","",SUMIFS('💰 Sales Log'!$E$8:$E$67,'💰 Sales Log'!$C$8:$C$67,$B21)) -> 0 | N21: =IF($B21="","",SUMIFS('💰 Sales Log'!$H$8:$H$67,'💰 Sales Log'!$C$8:$C$67,$B21)) -> 0 | O21: =IF($B21="","",SUMIFS('💰 Sales Log'!$M$8:$M$67,'💰 Sales Log'!$C$8:$C$67,$B21)) -> 0 | P21: =IF($B21="","",ROUND($N21-$K21-$O21,2)) -> 0 | Q21: =IF(OR($B21="",$N21=0),"",IFERROR($P21/$N21,0)) -> 0
K22: =IF($B22="","",ROUND(N($F22)+N($G22)+N($H22)+N($I22)+N($J22),2)) -> 0 | M22: =IF($B22="","",SUMIFS('💰 Sales Log'!$E$8:$E$67,'💰 Sales Log'!$C$8:$C$67,$B22)) -> 0 | N22: =IF($B22="","",SUMIFS('💰 Sales Log'!$H$8:$H$67,'💰 Sales Log'!$C$8:$C$67,$B22)) -> 0 | O22: =IF($B22="","",SUMIFS('💰 Sales Log'!$M$8:$M$67,'💰 Sales Log'!$C$8:$C$67,$B22)) -> 0 | P22: =IF($B22="","",ROUND($N22-$K22-$O22,2)) -> 0 | Q22: =IF(OR($B22="",$N22=0),"",IFERROR($P22/$N22,0)) -> 0
K23: =IF($B23="","",ROUND(N($F23)+N($G23)+N($H23)+N($I23)+N($J23),2)) -> 0 | M23: =IF($B23="","",SUMIFS('💰 Sales Log'!$E$8:$E$67,'💰 Sales Log'!$C$8:$C$67,$B23)) -> 0 | N23: =IF($B23="","",SUMIFS('💰 Sales Log'!$H$8:$H$67,'💰 Sales Log'!$C$8:$C$67,$B23)) -> 0 | O23: =IF($B23="","",SUMIFS('💰 Sales Log'!$M$8:$M$67,'💰 Sales Log'!$C$8:$C$67,$B23)) -> 0 | P23: =IF($B23="","",ROUND($N23-$K23-$O23,2)) -> 0 | Q23: =IF(OR($B23="",$N23=0),"",IFERROR($P23/$N23,0)) -> 0
K24: =IF($B24="","",ROUND(N($F24)+N($G24)+N($H24)+N($I24)+N($J24),2)) -> 0 | M24: =IF($B24="","",SUMIFS('💰 Sales Log'!$E$8:$E$67,'💰 Sales Log'!$C$8:$C$67,$B24)) -> 0 | N24: =IF($B24="","",SUMIFS('💰 Sales Log'!$H$8:$H$67,'💰 Sales Log'!$C$8:$C$67,$B24)) -> 0 | O24: =IF($B24="","",SUMIFS('💰 Sales Log'!$M$8:$M$67,'💰 Sales Log'!$C$8:$C$67,$B24)) -> 0 | P24: =IF($B24="","",ROUND($N24-$K24-$O24,2)) -> 0 | Q24: =IF(OR($B24="",$N24=0),"",IFERROR($P24/$N24,0)) -> 0
K25: =IF($B25="","",ROUND(N($F25)+N($G25)+N($H25)+N($I25)+N($J25),2)) -> 0 | M25: =IF($B25="","",SUMIFS('💰 Sales Log'!$E$8:$E$67,'💰 Sales Log'!$C$8:$C$67,$B25)) -> 0 | N25: =IF($B25="","",SUMIFS('💰 Sales Log'!$H$8:$H$67,'💰 Sales Log'!$C$8:$C$67,$B25)) -> 0 | O25: =IF($B25="","",SUMIFS('💰 Sales Log'!$M$8:$M$67,'💰 Sales Log'!$C$8:$C$67,$B25)) -> 0 | P25: =IF($B25="","",ROUND($N25-$K25-$O25,2)) -> 0 | Q25: =IF(OR($B25="",$N25=0),"",IFERROR($P25/$N25,0)) -> 0
K26: =IF($B26="","",ROUND(N($F26)+N($G26)+N($H26)+N($I26)+N($J26),2)) -> 0 | M26: =IF($B26="","",SUMIFS('💰 Sales Log'!$E$8:$E$67,'💰 Sales Log'!$C$8:$C$67,$B26)) -> 0 | N26: =IF($B26="","",SUMIFS('💰 Sales Log'!$H$8:$H$67,'💰 Sales Log'!$C$8:$C$67,$B26)) -> 0 | O26: =IF($B26="","",SUMIFS('💰 Sales Log'!$M$8:$M$67,'💰 Sales Log'!$C$8:$C$67,$B26)) -> 0 | P26: =IF($B26="","",ROUND($N26-$K26-$O26,2)) -> 0 | Q26: =IF(OR($B26="",$N26=0),"",IFERROR($P26/$N26,0)) -> 0
K27: =IF($B27="","",ROUND(N($F27)+N($G27)+N($H27)+N($I27)+N($J27),2)) -> 0 | M27: =IF($B27="","",SUMIFS('💰 Sales Log'!$E$8:$E$67,'💰 Sales Log'!$C$8:$C$67,$B27)) -> 0 | N27: =IF($B27="","",SUMIFS('💰 Sales Log'!$H$8:$H$67,'💰 Sales Log'!$C$8:$C$67,$B27)) -> 0 | O27: =IF($B27="","",SUMIFS('💰 Sales Log'!$M$8:$M$67,'💰 Sales Log'!$C$8:$C$67,$B27)) -> 0 | P27: =IF($B27="","",ROUND($N27-$K27-$O27,2)) -> 0 | Q27: =IF(OR($B27="",$N27=0),"",IFERROR($P27/$N27,0)) -> 0
... K31: =IF($B31="","",ROUND(N($F31)+N($G31)+N($H31)+N($I31)+N($J31),2)) -> 0 | M31: =IF($B31="","",SUMIFS('💰 Sales Log'!$E$8:$E$67,'💰 Sales Log'!$C$8:$C$67,$B31)) -> 0 | N31: =IF($B31="","",SUMIFS('💰 Sales Log'!$H$8:$H$67,'💰 Sales Log'!$C$8:$C$67,$B31)) -> 0 | O31: =IF($B31="","",SUMIFS('💰 Sales Log'!$M$8:$M$67,'💰 Sales Log'!$C$8:$C$67,$B31)) -> 0 | P31: =IF($B31="","",ROUND($N31-$K31-$O31,2)) -> 0 | Q31: =IF(OR($B31="",$N31=0),"",IFERROR($P31/$N31,0)) -> 0
C33: TOTALS | K33: =SUM('🏪 Craft Fairs'!$K$8:$K$31) -> 680 | L33: =SUM('🏪 Craft Fairs'!$L$8:$L$31) -> 134 | M33: =SUM('🏪 Craft Fairs'!$M$8:$M$31) -> 77 | N33: =SUM('🏪 Craft Fairs'!$N$8:$N$31) -> 1760 | O33: =SUM('🏪 Craft Fairs'!$O$8:$O$31) -> 363.5 | P33: =SUM('🏪 Craft Fairs'!$P$8:$P$31) -> 716.5
B35: How this tab works
B36: Fair cost adds up the five expense columns; Sales, cost of goods and net profit pull straight from the Sales Log. Net = sales - fair cost - cost of goods. Red means that fair lost money - worth knowing before you book it again! The fair names you type here power the dropdowns on the Sales Log, Event Profit and Packing tabs.
B40: 💡 Cream cells are yours to type in; white cells calculate. Dropdowns keep every column honest.
B42: Settings | D42: 🏠 Home | F42: Products | H42: Yarn | J42: Stock | L42: ▶ Fairs | N42: Sales | P42: Event $
B43: Reorder | D43: Packing | F43: Pricing | H43: Monthly | J43: Help

Sheet 💰 Sales Log
B2: 💰 Sales Log
B3: Log every sale - totals, costs and dashboards update live | K3: 🏠 Dashboard
B5: ="Entries: "&TEXT(COUNTA('💰 Sales Log'!$B$8:$B$67),"0") -> Entries: 22 | E5: ="Units: "&TEXT(SUM('💰 Sales Log'!$E$8:$E$67),"#,##0") -> Units: 77 | H5: ="Gross: "&Currency&TEXT(SUM('💰 Sales Log'!$H$8:$H$67),"#,##0.00") -> Gross: $1,760.00 | K5: ="Avg sale: "&Currency&TEXT('_Data'!$AI$10,"#,##0.00") -> Avg sale: $80.00
A7: # | B7: Date | C7: Craft fair / channel | D7: Product | E7: Qty | F7: Unit price | G7: Discount | H7: Line total | I7: Payment | J7: Receipt / ref | K7: Notes | L7: Gift wrap ✓ | M7: Cost of goods
B8: 46095 | C8: Spring Makers Market | D8: Amigurumi Bunny | E8: 4 | F8: 28 | G8: 0 | H8: =IF(OR($D8="",$E8=""),"",ROUND($E8*N($F8)-N($G8),2)) -> 112 | I8: Card | J8: SPR-01 | M8: =IF($D8="","",ROUND(N($E8)*IFERROR(VLOOKUP($D8,'🧶 Product Catalog'!$C$8:$I$31,7,0),0),2)) -> 20
B9: 46095 | C9: Spring Makers Market | D9: Chunky Beanie | E9: 3 | F9: 24 | G9: 0 | H9: =IF(OR($D9="",$E9=""),"",ROUND($E9*N($F9)-N($G9),2)) -> 72 | I9: Cash | M9: =IF($D9="","",ROUND(N($E9)*IFERROR(VLOOKUP($D9,'🧶 Product Catalog'!$C$8:$I$31,7,0),0),2)) -> 18.9
B10: 46095 | C10: Spring Makers Market | D10: Flower Coaster Set | E10: 5 | F10: 16 | G10: 0 | H10: =IF(OR($D10="",$E10=""),"",ROUND($E10*N($F10)-N($G10),2)) -> 80 | I10: Cash | M10: =IF($D10="","",ROUND(N($E10)*IFERROR(VLOOKUP($D10,'🧶 Product Catalog'!$C$8:$I$31,7,0),0),2)) -> 13.5
B11: 46095 | C11: Spring Makers Market | D11: Baby Booties | E11: 2 | F11: 18 | G11: 0 | H11: =IF(OR($D11="",$E11=""),"",ROUND($E11*N($F11)-N($G11),2)) -> 36 | I11: Card | J11: SPR-02 | M11: =IF($D11="","",ROUND(N($E11)*IFERROR(VLOOKUP($D11,'🧶 Product Catalog'!$C$8:$I$31,7,0),0),2)) -> 6.4
B12: 46117 | C12: Easter Craft Bazaar | D12: Baby Booties | E12: 3 | F12: 18 | G12: 0 | H12: =IF(OR($D12="",$E12=""),"",ROUND($E12*N($F12)-N($G12),2)) -> 54 | I12: Cash | M12: =IF($D12="","",ROUND(N($E12)*IFERROR(VLOOKUP($D12,'🧶 Product Catalog'!$C$8:$I$31,7,0),0),2)) -> 9.6
B13: 46117 | C13: Easter Craft Bazaar | D13: Amigurumi Bunny | E13: 2 | F13: 28 | G13: 0 | H13: =IF(OR($D13="",$E13=""),"",ROUND($E13*N($F13)-N($G13),2)) -> 56 | I13: Card | J13: EAS-01 | M13: =IF($D13="","",ROUND(N($E13)*IFERROR(VLOOKUP($D13,'🧶 Product Catalog'!$C$8:$I$31,7,0),0),2)) -> 10
B14: 46117 | C14: Easter Craft Bazaar | D14: Flower Coaster Set | E14: 4 | F14: 16 | G14: 0 | H14: =IF(OR($D14="",$E14=""),"",ROUND($E14*N($F14)-N($G14),2)) -> 64 | I14: Cash | M14: =IF($D14="","",ROUND(N($E14)*IFERROR(VLOOKUP($D14,'🧶 Product Catalog'!$C$8:$I$31,7,0),0),2)) -> 10.8
B15: 46158 | C15: School Fete Stall | D15: Keychain Charm | E15: 10 | F15: 10 | G15: 0 | H15: =IF(OR($D15="",$E15=""),"",ROUND($E15*N($F15)-N($G15),2)) -> 100 | I15: Cash | K15: Kids loved these | M15: =IF($D15="","",ROUND(N($E15)*IFERROR(VLOOKUP($D15,'🧶 Product Catalog'!$C$8:$I$31,7,0),0),2)) -> 15
B16: 46158 | C16: School Fete Stall | D16: Ear Warmer Headband | E16: 6 | F16: 16 | G16: 0 | H16: =IF(OR($D16="",$E16=""),"",ROUND($E16*N($F16)-N($G16),2)) -> 96 | I16: Cash | M16: =IF($D16="","",ROUND(N($E16)*IFERROR(VLOOKUP($D16,'🧶 Product Catalog'!$C$8:$I$31,7,0),0),2)) -> 20.4
B17: 46158 | C17: School Fete Stall | D17: Flower Coaster Set | E17: 3 | F17: 16 | G17: 0 | H17: =IF(OR($D17="",$E17=""),"",ROUND($E17*N($F17)-N($G17),2)) -> 48 | I17: Cash | M17: =IF($D17="","",ROUND(N($E17)*IFERROR(VLOOKUP($D17,'🧶 Product Catalog'!$C$8:$I$31,7,0),0),2)) -> 8.1
B18: 46192 | C18: Summer Night Bazaar | D18: Market Tote Bag | E18: 4 | F18: 32 | G18: 0 | H18: =IF(OR($D18="",$E18=""),"",ROUND($E18*N($F18)-N($G18),2)) -> 128 | I18: Card | J18: SUM-01 | M18: =IF($D18="","",ROUND(N($E18)*IFERROR(VLOOKUP($D18,'🧶 Product Catalog'!$C$8:$I$31,7,0),0),2)) -> 28.4
B19: 46192 | C19: Summer Night Bazaar | D19: Ear Warmer Headband | E19: 4 | F19: 16 | G19: 0 | H19: =IF(OR($D19="",$E19=""),"",ROUND($E19*N($F19)-N($G19),2)) -> 64 | I19: Cash | M19: =IF($D19="","",ROUND(N($E19)*IFERROR(VLOOKUP($D19,'🧶 Product Catalog'!$C$8:$I$31,7,0),0),2)) -> 13.6
B20: 46192 | C20: Summer Night Bazaar | D20: Chunky Beanie | E20: 2 | F20: 24 | G20: 0 | H20: =IF(OR($D20="",$E20=""),"",ROUND($E20*N($F20)-N($G20),2)) -> 48 | I20: Card | J20: SUM-02 | M20: =IF($D20="","",ROUND(N($E20)*IFERROR(VLOOKUP($D20,'🧶 Product Catalog'!$C$8:$I$31,7,0),0),2)) -> 12.6
B21: 46192 | C21: Summer Night Bazaar | D21: Keychain Charm | E21: 8 | F21: 10 | G21: 0 | H21: =IF(OR($D21="",$E21=""),"",ROUND($E21*N($F21)-N($G21),2)) -> 80 | I21: Cash | M21: =IF($D21="","",ROUND(N($E21)*IFERROR(VLOOKUP($D21,'🧶 Product Catalog'!$C$8:$I$31,7,0),0),2)) -> 12
B22: 46192 | C22: Summer Night Bazaar | D22: Stuffed Octopus | E22: 3 | F22: 26 | G22: 0 | H22: =IF(OR($D22="",$E22=""),"",ROUND($E22*N($F22)-N($G22),2)) -> 78 | I22: Card | J22: SUM-03 | M22: =IF($D22="","",ROUND(N($E22)*IFERROR(VLOOKUP($D22,'🧶 Product Catalog'!$C$8:$I$31,7,0),0),2)) -> 16.2
B23: 46228 | C23: Farmers Market Pop-up | D23: Market Tote Bag | E23: 4 | F23: 32 | G23: 0 | H23: =IF(OR($D23="",$E23=""),"",ROUND($E23*N($F23)-N($G23),2)) -> 128 | I23: Cash | M23: =IF($D23="","",ROUND(N($E23)*IFERROR(VLOOKUP($D23,'🧶 Product Catalog'!$C$8:$I$31,7,0),0),2)) -> 28.4
B24: 46228 | C24: Farmers Market Pop-up | D24: Cozy Scarf | E24: 2 | F24: 38 | G24: 0 | H24: =IF(OR($D24="",$E24=""),"",ROUND($E24*N($F24)-N($G24),2)) -> 76 | I24: Card | J24: FAR-01 | M24: =IF($D24="","",ROUND(N($E24)*IFERROR(VLOOKUP($D24,'🧶 Product Catalog'!$C$8:$I$31,7,0),0),2)) -> 20
B25: 46228 | C25: Farmers Market Pop-up | D25: Lap Blanket | E25: 1 | F25: 75 | G25: 0 | H25: =IF(OR($D25="",$E25=""),"",ROUND($E25*N($F25)-N($G25),2)) -> 75 | I25: Card | J25: FAR-02 | M25: =IF($D25="","",ROUND(N($E25)*IFERROR(VLOOKUP($D25,'🧶 Product Catalog'!$C$8:$I$31,7,0),0),2)) -> 18.8
B26: 46228 | C26: Farmers Market Pop-up | D26: Flower Coaster Set | E26: 2 | F26: 16 | G26: 2 | H26: =IF(OR($D26="",$E26=""),"",ROUND($E26*N($F26)-N($G26),2)) -> 30 | I26: Cash | K26: Friend discount | M26: =IF($D26="","",ROUND(N($E26)*IFERROR(VLOOKUP($D26,'🧶 Product Catalog'!$C$8:$I$31,7,0),0),2)) -> 5.4
B27: 46264 | C27: Online Order Batch | D27: Granny Square Cardigan | E27: 1 | F27: 95 | G27: 0 | H27: =IF(OR($D27="",$E27=""),"",ROUND($E27*N($F27)-N($G27),2)) -> 95 | I27: Bank transfer | J27: INV-2041 | K27: Commission | M27: =IF($D27="","",ROUND(N($E27)*IFERROR(VLOOKUP($D27,'🧶 Product Catalog'!$C$8:$I$31,7,0),0),2)) -> 20.6
B28: 46264 | C28: Online Order Batch | D28: Lap Blanket | E28: 1 | F28: 75 | G28: 0 | H28: =IF(OR($D28="",$E28=""),"",ROUND($E28*N($F28)-N($G28),2)) -> 75 | I28: Bank transfer | J28: INV-2042 | M28: =IF($D28="","",ROUND(N($E28)*IFERROR(VLOOKUP($D28,'🧶 Product Catalog'!$C$8:$I$31,7,0),0),2)) -> 18.8
B29: 46264 | C29: Online Order Batch | D29: Table Runner | E29: 3 | F29: 55 | G29: 0 | H29: =IF(OR($D29="",$E29=""),"",ROUND($E29*N($F29)-N($G29),2)) -> 165 | I29: Online order | J29: INV-2043 | M29: =IF($D29="","",ROUND(N($E29)*IFERROR(VLOOKUP($D29,'🧶 Product Catalog'!$C$8:$I$31,7,0),0),2)) -> 36
H30: =IF(OR($D30="",$E30=""),"",ROUND($E30*N($F30)-N($G30),2)) -> 0 | M30: =IF($D30="","",ROUND(N($E30)*IFERROR(VLOOKUP($D30,'🧶 Product Catalog'!$C$8:$I$31,7,0),0),2)) -> 0
H31: =IF(OR($D31="",$E31=""),"",ROUND($E31*N($F31)-N($G31),2)) -> 0 | M31: =IF($D31="","",ROUND(N($E31)*IFERROR(VLOOKUP($D31,'🧶 Product Catalog'!$C$8:$I$31,7,0),0),2)) -> 0
H32: =IF(OR($D32="",$E32=""),"",ROUND($E32*N($F32)-N($G32),2)) -> 0 | M32: =IF($D32="","",ROUND(N($E32)*IFERROR(VLOOKUP($D32,'🧶 Product Catalog'!$C$8:$I$31,7,0),0),2)) -> 0
H33: =IF(OR($D33="",$E33=""),"",ROUND($E33*N($F33)-N($G33),2)) -> 0 | M33: =IF($D33="","",ROUND(N($E33)*IFERROR(VLOOKUP($D33,'🧶 Product Catalog'!$C$8:$I$31,7,0),0),2)) -> 0
H34: =IF(OR($D34="",$E34=""),"",ROUND($E34*N($F34)-N($G34),2)) -> 0 | M34: =IF($D34="","",ROUND(N($E34)*IFERROR(VLOOKUP($D34,'🧶 Product Catalog'!$C$8:$I$31,7,0),0),2)) -> 0
H35: =IF(OR($D35="",$E35=""),"",ROUND($E35*N($F35)-N($G35),2)) -> 0 | M35: =IF($D35="","",ROUND(N($E35)*IFERROR(VLOOKUP($D35,'🧶 Product Catalog'!$C$8:$I$31,7,0),0),2)) -> 0
H36: =IF(OR($D36="",$E36=""),"",ROUND($E36*N($F36)-N($G36),2)) -> 0 | M36: =IF($D36="","",ROUND(N($E36)*IFERROR(VLOOKUP($D36,'🧶 Product Catalog'!$C$8:$I$31,7,0),0),2)) -> 0
H37: =IF(OR($D37="",$E37=""),"",ROUND($E37*N($F37)-N($G37),2)) -> 0 | M37: =IF($D37="","",ROUND(N($E37)*IFERROR(VLOOKUP($D37,'🧶 Product Catalog'!$C$8:$I$31,7,0),0),2)) -> 0
H38: =IF(OR($D38="",$E38=""),"",ROUND($E38*N($F38)-N($G38),2)) -> 0 | M38: =IF($D38="","",ROUND(N($E38)*IFERROR(VLOOKUP($D38,'🧶 Product Catalog'!$C$8:$I$31,7,0),0),2)) -> 0
H39: =IF(OR($D39="",$E39=""),"",ROUND($E39*N($F39)-N($G39),2)) -> 0 | M39: =IF($D39="","",ROUND(N($E39)*IFERROR(VLOOKUP($D39,'🧶 Product Catalog'!$C$8:$I$31,7,0),0),2)) -> 0
H40: =IF(OR($D40="",$E40=""),"",ROUND($E40*N($F40)-N($G40),2)) -> 0 | M40: =IF($D40="","",ROUND(N($E40)*IFERROR(VLOOKUP($D40,'🧶 Product Catalog'!$C$8:$I$31,7,0),0),2)) -> 0
H41: =IF(OR($D41="",$E41=""),"",ROUND($E41*N($F41)-N($G41),2)) -> 0 | M41: =IF($D41="","",ROUND(N($E41)*IFERROR(VLOOKUP($D41,'🧶 Product Catalog'!$C$8:$I$31,7,0),0),2)) -> 0
... H67: =IF(OR($D67="",$E67=""),"",ROUND($E67*N($F67)-N($G67),2)) -> 0 | M67: =IF($D67="","",ROUND(N($E67)*IFERROR(VLOOKUP($D67,'🧶 Product Catalog'!$C$8:$I$31,7,0),0),2)) -> 0
C69: TOTALS | E69: =SUM('💰 Sales Log'!$E$8:$E$67) -> 77 | G69: =SUM('💰 Sales Log'!$G$8:$G$67) -> 2 | H69: =SUM('💰 Sales Log'!$H$8:$H$67) -> 1760 | M69: =SUM('💰 Sales Log'!$M$8:$M$67) -> 363.5
B71: How this tab works
B72: Line total = qty x unit price - discount. Cost of goods uses each product's cost from the Product Catalog. One row per product per sale - if someone buys two different things, that's two happy rows. Discounts glow amber so you can see how generous you've been this season.
B76: 💡 Cream cells are yours to type in; white cells calculate. Dropdowns keep every column honest.
B78: Settings | D78: 🏠 Home | F78: Products | H78: Yarn | J78: Stock | L78: Fairs
B79: ▶ Sales | D79: Event $ | F79: Reorder | H79: Packing | J79: Pricing | L79: Monthly
B80: Help

Sheet 🧮 Event Profit
B2: 🧮 Event Profit
B3: Pick a craft fair and see exactly what it earned you | H3: 🏠 Dashboard
B5: Pick a craft fair
B8: Craft fair: | C8: Summer Night Bazaar
B10: Money in
B11: Items sold | E11: =IF($C$8="",0,SUMIFS('💰 Sales Log'!$E$8:$E$67,'💰 Sales Log'!$C$8:$C$67,$C$8)) -> 21
B12: Gross sales | E12: =IF($C$8="",0,SUMIFS('💰 Sales Log'!$H$8:$H$67,'💰 Sales Log'!$C$8:$C$67,$C$8)) -> 398
B13: Discounts given | E13: =IF($C$8="",0,SUMIFS('💰 Sales Log'!$G$8:$G$67,'💰 Sales Log'!$C$8:$C$67,$C$8)) -> 0
B15: Money out
B16: Cost of goods sold | E16: =IF($C$8="",0,SUMIFS('💰 Sales Log'!$M$8:$M$67,'💰 Sales Log'!$C$8:$C$67,$C$8)) -> 82.8
B17: Booth fee | E17: =IFERROR(IF($C$8="",0,INDEX('🏪 Craft Fairs'!$F$8:$F$31,MATCH($C$8,'🏪 Craft Fairs'!$B$8:$B$31,0))),0) -> 60
B18: Travel | E18: =IFERROR(IF($C$8="",0,INDEX('🏪 Craft Fairs'!$G$8:$G$31,MATCH($C$8,'🏪 Craft Fairs'!$B$8:$B$31,0))),0) -> 15
B19: Parking | E19: =IFERROR(IF($C$8="",0,INDEX('🏪 Craft Fairs'!$H$8:$H$31,MATCH($C$8,'🏪 Craft Fairs'!$B$8:$B$31,0))),0) -> 6
B20: Food & drinks | E20: =IFERROR(IF($C$8="",0,INDEX('🏪 Craft Fairs'!$I$8:$I$31,MATCH($C$8,'🏪 Craft Fairs'!$B$8:$B$31,0))),0) -> 10
B21: Display & decor | E21: =IFERROR(IF($C$8="",0,INDEX('🏪 Craft Fairs'!$J$8:$J$31,MATCH($C$8,'🏪 Craft Fairs'!$B$8:$B$31,0))),0) -> 25
B23: The verdict
B24: Gross profit (sales - goods) | E24: =IF($C$8="",0,ROUND($E$12-$E$16,2)) -> 315.2
B25: True cost of the fair | E25: =IF($C$8="",0,ROUND(SUM($E$16:$E$21),2)) -> 198.8
B26: Net profit | E26: =IF($C$8="",0,ROUND($E$12-$E$25,2)) -> 199.2 | F26: =IF($C$8="","",Currency&TEXT($E$26,"#,##0.00")) -> $199.20
B27: Profit margin | E27: =IF($C$8="",0,IFERROR($E$26/$E$12,0)) -> 0.50050251
B28: Average sale | E28: =IF($C$8="",0,IFERROR($E$12/COUNTIFS('💰 Sales Log'!$C$8:$C$67,$C$8),0)) -> 79.6
B29: Breakeven sales | E29: =IF($C$8="",0,IFERROR(ROUND($E$25/($E$24/$E$12),2),0)) -> 251.02284
B30: Return on investment | E30: =IF($C$8="",0,IFERROR($E$26/$E$25,0)) -> 1.0020121
B35: Reading the numbers
B36: Gross profit = sales - cost of goods. True cost adds the booth, travel, parking, food and display you logged on the Craft Fairs tab. Breakeven is the sales figure where the fair stops costing you money - anything above it is profit. Return on investment: for every 1 of fair cost, how much profit came back. Above 100% = a very good day.
B40: 💡 Every number here is pulled live from your Sales Log and Craft Fairs tabs - nothing to re-type.
B42: Settings | D42: 🏠 Home | F42: Products | H42: Yarn
B43: Stock | D43: Fairs | F43: Sales | H43: ▶ Event $
B44: Reorder | D44: Packing | F44: Pricing | H44: Monthly
B45: Help

Sheet 🔄 Reorder List
B2: 🔄 Reorder List
B3: Everything running low, in one shopping list | H3: 🏠 Dashboard
B5: ="Need restocking: "&TEXT(COUNTIF($B$10:$B$21,"?*")+COUNTIF($B$25:$B$34,"?*"),"0") -> Need restocking: 12 | E5: ="Estimated bill: "&Currency&TEXT(SUM($G$10:$G$34),"#,##0.00") -> Estimated bill: $342.70 | H5: ="Urgent (sold out): "&TEXT(COUNTIF($H$10:$H$34,"🔴 Urgent"),"0") -> Urgent (sold out): 3
B8: Products to restitch
B9: Item | C9: Have now | D9: Low at | E9: Buy | F9: Supplier | G9: Est. cost | H9: Priority | I9: Ordered ✓ | J9: Ordered on
B10: =IF(OR('🧶 Product Catalog'!$C8="",'🧶 Product Catalog'!$M8>='🧶 Product Catalog'!$N8),"",'🧶 Product Catalog'!$C8) | C10: =IF($B10="","",'🧶 Product Catalog'!$M8) | D10: =IF($B10="","",'🧶 Product Catalog'!$N8) | E10: =IF($B10="","",MAX(0,$D10*2-$C10)) | G10: =IF($B10="","",ROUND($E10*IFERROR(VLOOKUP($B10,'🧶 Product Catalog'!$C8:$I31,7,0),0),2)) | H10: =IF($B10="","",IF($C10<=0,"🔴 Urgent","🟠 High"))
B11: =IF(OR('🧶 Product Catalog'!$C9="",'🧶 Product Catalog'!$M9>='🧶 Product Catalog'!$N9),"",'🧶 Product Catalog'!$C9) | C11: =IF($B11="","",'🧶 Product Catalog'!$M9) | D11: =IF($B11="","",'🧶 Product Catalog'!$N9) | E11: =IF($B11="","",MAX(0,$D11*2-$C11)) | G11: =IF($B11="","",ROUND($E11*IFERROR(VLOOKUP($B11,'🧶 Product Catalog'!$C8:$I31,7,0),0),2)) | H11: =IF($B11="","",IF($C11<=0,"🔴 Urgent","🟠 High"))
B12: =IF(OR('🧶 Product Catalog'!$C10="",'🧶 Product Catalog'!$M10>='🧶 Product Catalog'!$N10),"",'🧶 Product Catalog'!$C10) | C12: =IF($B12="","",'🧶 Product Catalog'!$M10) | D12: =IF($B12="","",'🧶 Product Catalog'!$N10) | E12: =IF($B12="","",MAX(0,$D12*2-$C12)) | G12: =IF($B12="","",ROUND($E12*IFERROR(VLOOKUP($B12,'🧶 Product Catalog'!$C8:$I31,7,0),0),2)) | H12: =IF($B12="","",IF($C12<=0,"🔴 Urgent","🟠 High"))
B13: =IF(OR('🧶 Product Catalog'!$C11="",'🧶 Product Catalog'!$M11>='🧶 Product Catalog'!$N11),"",'🧶 Product Catalog'!$C11) -> Market Tote Bag | C13: =IF($B13="","",'🧶 Product Catalog'!$M11) -> 3 | D13: =IF($B13="","",'🧶 Product Catalog'!$N11) -> 5 | E13: =IF($B13="","",MAX(0,$D13*2-$C13)) -> 7 | G13: =IF($B13="","",ROUND($E13*IFERROR(VLOOKUP($B13,'🧶 Product Catalog'!$C8:$I31,7,0),0),2)) -> 49.7 | H13: =IF($B13="","",IF($C13<=0,"🔴 Urgent","🟠 High")) -> 🟠 High
B14: =IF(OR('🧶 Product Catalog'!$C12="",'🧶 Product Catalog'!$M12>='🧶 Product Catalog'!$N12),"",'🧶 Product Catalog'!$C12) | C14: =IF($B14="","",'🧶 Product Catalog'!$M12) | D14: =IF($B14="","",'🧶 Product Catalog'!$N12) | E14: =IF($B14="","",MAX(0,$D14*2-$C14)) | G14: =IF($B14="","",ROUND($E14*IFERROR(VLOOKUP($B14,'🧶 Product Catalog'!$C8:$I31,7,0),0),2)) | H14: =IF($B14="","",IF($C14<=0,"🔴 Urgent","🟠 High"))
B15: =IF(OR('🧶 Product Catalog'!$C13="",'🧶 Product Catalog'!$M13>='🧶 Product Catalog'!$N13),"",'🧶 Product Catalog'!$C13) -> Baby Booties | C15: =IF($B15="","",'🧶 Product Catalog'!$M13) -> 3 | D15: =IF($B15="","",'🧶 Product Catalog'!$N13) -> 6 | E15: =IF($B15="","",MAX(0,$D15*2-$C15)) -> 9 | G15: =IF($B15="","",ROUND($E15*IFERROR(VLOOKUP($B15,'🧶 Product Catalog'!$C8:$I31,7,0),0),2)) -> 28.8 | H15: =IF($B15="","",IF($C15<=0,"🔴 Urgent","🟠 High")) -> 🟠 High
B16: =IF(OR('🧶 Product Catalog'!$C14="",'🧶 Product Catalog'!$M14>='🧶 Product Catalog'!$N14),"",'🧶 Product Catalog'!$C14) -> Flower Coaster Set | C16: =IF($B16="","",'🧶 Product Catalog'!$M14) -> 5 | D16: =IF($B16="","",'🧶 Product Catalog'!$N14) -> 8 | E16: =IF($B16="","",MAX(0,$D16*2-$C16)) -> 11 | G16: =IF($B16="","",ROUND($E16*IFERROR(VLOOKUP($B16,'🧶 Product Catalog'!$C8:$I31,7,0),0),2)) -> 29.7 | H16: =IF($B16="","",IF($C16<=0,"🔴 Urgent","🟠 High")) -> 🟠 High
B17: =IF(OR('🧶 Product Catalog'!$C15="",'🧶 Product Catalog'!$M15>='🧶 Product Catalog'!$N15),"",'🧶 Product Catalog'!$C15) -> Lap Blanket | C17: =IF($B17="","",'🧶 Product Catalog'!$M15) -> 1 | D17: =IF($B17="","",'🧶 Product Catalog'!$N15) -> 2 | E17: =IF($B17="","",MAX(0,$D17*2-$C17)) -> 3 | G17: =IF($B17="","",ROUND($E17*IFERROR(VLOOKUP($B17,'🧶 Product Catalog'!$C8:$I31,7,0),0),2)) -> 56.4 | H17: =IF($B17="","",IF($C17<=0,"🔴 Urgent","🟠 High")) -> 🟠 High
B18: =IF(OR('🧶 Product Catalog'!$C16="",'🧶 Product Catalog'!$M16>='🧶 Product Catalog'!$N16),"",'🧶 Product Catalog'!$C16) -> Ear Warmer Headband | C18: =IF($B18="","",'🧶 Product Catalog'!$M16) -> 0 | D18: =IF($B18="","",'🧶 Product Catalog'!$N16) -> 4 | E18: =IF($B18="","",MAX(0,$D18*2-$C18)) -> 8 | G18: =IF($B18="","",ROUND($E18*IFERROR(VLOOKUP($B18,'🧶 Product Catalog'!$C8:$I31,7,0),0),2)) -> 27.2 | H18: =IF($B18="","",IF($C18<=0,"🔴 Urgent","🟠 High")) -> 🔴 Urgent
B19: =IF(OR('🧶 Product Catalog'!$C17="",'🧶 Product Catalog'!$M17>='🧶 Product Catalog'!$N17),"",'🧶 Product Catalog'!$C17) | C19: =IF($B19="","",'🧶 Product Catalog'!$M17) | D19: =IF($B19="","",'🧶 Product Catalog'!$N17) | E19: =IF($B19="","",MAX(0,$D19*2-$C19)) | G19: =IF($B19="","",ROUND($E19*IFERROR(VLOOKUP($B19,'🧶 Product Catalog'!$C8:$I31,7,0),0),2)) | H19: =IF($B19="","",IF($C19<=0,"🔴 Urgent","🟠 High"))
B20: =IF(OR('🧶 Product Catalog'!$C18="",'🧶 Product Catalog'!$M18>='🧶 Product Catalog'!$N18),"",'🧶 Product Catalog'!$C18) -> Table Runner | C20: =IF($B20="","",'🧶 Product Catalog'!$M18) -> 0 | D20: =IF($B20="","",'🧶 Product Catalog'!$N18) -> 2 | E20: =IF($B20="","",MAX(0,$D20*2-$C20)) -> 4 | G20: =IF($B20="","",ROUND($E20*IFERROR(VLOOKUP($B20,'🧶 Product Catalog'!$C8:$I31,7,0),0),2)) -> 48 | H20: =IF($B20="","",IF($C20<=0,"🔴 Urgent","🟠 High")) -> 🔴 Urgent
B21: =IF(OR('🧶 Product Catalog'!$C19="",'🧶 Product Catalog'!$M19>='🧶 Product Catalog'!$N19),"",'🧶 Product Catalog'!$C19) -> Keychain Charm | C21: =IF($B21="","",'🧶 Product Catalog'!$M19) -> 0 | D21: =IF($B21="","",'🧶 Product Catalog'!$N19) -> 6 | E21: =IF($B21="","",MAX(0,$D21*2-$C21)) -> 12 | G21: =IF($B21="","",ROUND($E21*IFERROR(VLOOKUP($B21,'🧶 Product Catalog'!$C8:$I31,7,0),0),2)) -> 18 | H21: =IF($B21="","",IF($C21<=0,"🔴 Urgent","🟠 High")) -> 🔴 Urgent
B23: Yarn & materials to buy
B24: Item | C24: Have now | D24: Low at | E24: Buy | F24: Supplier | G24: Est. cost | H24: Priority | I24: Ordered ✓ | J24: Ordered on
B25: =IF(OR('🧵 Yarn & Materials'!$B8="",'🧵 Yarn & Materials'!$K8>'🧵 Yarn & Materials'!$M8),"",'🧵 Yarn & Materials'!$B8) -> Cotton yarn - natural | C25: =IF($B25="","",'🧵 Yarn & Materials'!$K8) -> 4 | D25: =IF($B25="","",'🧵 Yarn & Materials'!$M8) -> 5 | E25: =IF($B25="","",MAX(0,$D25*2-$C25)) -> 6 | F25: =IF($B25="","",'🧵 Yarn & Materials'!$L8) -> Local yarn shop | G25: =IF($B25="","",ROUND($E25*IFERROR(VLOOKUP($B25,'🧵 Yarn & Materials'!$B8:$H31,7,0),0),2)) -> 20.4 | H25: =IF($B25="","",IF($C25<=0,"🔴 Urgent","🟠 High")) -> 🟠 High
B26: =IF(OR('🧵 Yarn & Materials'!$B9="",'🧵 Yarn & Materials'!$K9>'🧵 Yarn & Materials'!$M9),"",'🧵 Yarn & Materials'!$B9) | C26: =IF($B26="","",'🧵 Yarn & Materials'!$K9) | D26: =IF($B26="","",'🧵 Yarn & Materials'!$M9) | E26: =IF($B26="","",MAX(0,$D26*2-$C26)) | F26: =IF($B26="","",'🧵 Yarn & Materials'!$L9) | G26: =IF($B26="","",ROUND($E26*IFERROR(VLOOKUP($B26,'🧵 Yarn & Materials'!$B8:$H31,7,0),0),2)) | H26: =IF($B26="","",IF($C26<=0,"🔴 Urgent","🟠 High"))
B27: =IF(OR('🧵 Yarn & Materials'!$B10="",'🧵 Yarn & Materials'!$K10>'🧵 Yarn & Materials'!$M10),"",'🧵 Yarn & Materials'!$B10) -> Merino wool - sage | C27: =IF($B27="","",'🧵 Yarn & Materials'!$K10) -> 2 | D27: =IF($B27="","",'🧵 Yarn & Materials'!$M10) -> 4 | E27: =IF($B27="","",MAX(0,$D27*2-$C27)) -> 6 | F27: =IF($B27="","",'🧵 Yarn & Materials'!$L10) -> Local yarn shop | G27: =IF($B27="","",ROUND($E27*IFERROR(VLOOKUP($B27,'🧵 Yarn & Materials'!$B8:$H31,7,0),0),2)) -> 40.8 | H27: =IF($B27="","",IF($C27<=0,"🔴 Urgent","🟠 High")) -> 🟠 High
B28: =IF(OR('🧵 Yarn & Materials'!$B11="",'🧵 Yarn & Materials'!$K11>'🧵 Yarn & Materials'!$M11),"",'🧵 Yarn & Materials'!$B11) | C28: =IF($B28="","",'🧵 Yarn & Materials'!$K11) | D28: =IF($B28="","",'🧵 Yarn & Materials'!$M11) | E28: =IF($B28="","",MAX(0,$D28*2-$C28)) | F28: =IF($B28="","",'🧵 Yarn & Materials'!$L11) | G28: =IF($B28="","",ROUND($E28*IFERROR(VLOOKUP($B28,'🧵 Yarn & Materials'!$B8:$H31,7,0),0),2)) | H28: =IF($B28="","",IF($C28<=0,"🔴 Urgent","🟠 High"))
B29: =IF(OR('🧵 Yarn & Materials'!$B12="",'🧵 Yarn & Materials'!$K12>'🧵 Yarn & Materials'!$M12),"",'🧵 Yarn & Materials'!$B12) -> Cotton yarn - mustard | C29: =IF($B29="","",'🧵 Yarn & Materials'!$K12) -> 1 | D29: =IF($B29="","",'🧵 Yarn & Materials'!$M12) -> 3 | E29: =IF($B29="","",MAX(0,$D29*2-$C29)) -> 5 | F29: =IF($B29="","",'🧵 Yarn & Materials'!$L12) -> Local yarn shop | G29: =IF($B29="","",ROUND($E29*IFERROR(VLOOKUP($B29,'🧵 Yarn & Materials'!$B8:$H31,7,0),0),2)) -> 16 | H29: =IF($B29="","",IF($C29<=0,"🔴 Urgent","🟠 High")) -> 🟠 High
B30: =IF(OR('🧵 Yarn & Materials'!$B13="",'🧵 Yarn & Materials'!$K13>'🧵 Yarn & Materials'!$M13),"",'🧵 Yarn & Materials'!$B13) | C30: =IF($B30="","",'🧵 Yarn & Materials'!$K13) | D30: =IF($B30="","",'🧵 Yarn & Materials'!$M13) | E30: =IF($B30="","",MAX(0,$D30*2-$C30)) | F30: =IF($B30="","",'🧵 Yarn & Materials'!$L13) | G30: =IF($B30="","",ROUND($E30*IFERROR(VLOOKUP($B30,'🧵 Yarn & Materials'!$B8:$H31,7,0),0),2)) | H30: =IF($B30="","",IF($C30<=0,"🔴 Urgent","🟠 High"))
B31: =IF(OR('🧵 Yarn & Materials'!$B14="",'🧵 Yarn & Materials'!$K14>'🧵 Yarn & Materials'!$M14),"",'🧵 Yarn & Materials'!$B14) -> Polyester stuffing | C31: =IF($B31="","",'🧵 Yarn & Materials'!$K14) -> 2 | D31: =IF($B31="","",'🧵 Yarn & Materials'!$M14) -> 2 | E31: =IF($B31="","",MAX(0,$D31*2-$C31)) -> 2 | F31: =IF($B31="","",'🧵 Yarn & Materials'!$L14) -> Wholesale craft | G31: =IF($B31="","",ROUND($E31*IFERROR(VLOOKUP($B31,'🧵 Yarn & Materials'!$B8:$H31,7,0),0),2)) -> 4.2 | H31: =IF($B31="","",IF($C31<=0,"🔴 Urgent","🟠 High")) -> 🟠 High
B32: =IF(OR('🧵 Yarn & Materials'!$B15="",'🧵 Yarn & Materials'!$K15>'🧵 Yarn & Materials'!$M15),"",'🧵 Yarn & Materials'!$B15) | C32: =IF($B32="","",'🧵 Yarn & Materials'!$K15) | D32: =IF($B32="","",'🧵 Yarn & Materials'!$M15) | E32: =IF($B32="","",MAX(0,$D32*2-$C32)) | F32: =IF($B32="","",'🧵 Yarn & Materials'!$L15) | G32: =IF($B32="","",ROUND($E32*IFERROR(VLOOKUP($B32,'🧵 Yarn & Materials'!$B8:$H31,7,0),0),2)) | H32: =IF($B32="","",IF($C32<=0,"🔴 Urgent","🟠 High"))
B33: =IF(OR('🧵 Yarn & Materials'!$B16="",'🧵 Yarn & Materials'!$K16>'🧵 Yarn & Materials'!$M16),"",'🧵 Yarn & Materials'!$B16) -> Safety eyes | C33: =IF($B33="","",'🧵 Yarn & Materials'!$K16) -> 6 | D33: =IF($B33="","",'🧵 Yarn & Materials'!$M16) -> 10 | E33: =IF($B33="","",MAX(0,$D33*2-$C33)) -> 14 | F33: =IF($B33="","",'🧵 Yarn & Materials'!$L16) -> Wholesale craft | G33: =IF($B33="","",ROUND($E33*IFERROR(VLOOKUP($B33,'🧵 Yarn & Materials'!$B8:$H31,7,0),0),2)) -> 3.5 | H33: =IF($B33="","",IF($C33<=0,"🔴 Urgent","🟠 High")) -> 🟠 High
B34: =IF(OR('🧵 Yarn & Materials'!$B17="",'🧵 Yarn & Materials'!$K17>'🧵 Yarn & Materials'!$M17),"",'🧵 Yarn & Materials'!$B17) | C34: =IF($B34="","",'🧵 Yarn & Materials'!$K17) | D34: =IF($B34="","",'🧵 Yarn & Materials'!$M17) | E34: =IF($B34="","",MAX(0,$D34*2-$C34)) | F34: =IF($B34="","",'🧵 Yarn & Materials'!$L17) | G34: =IF($B34="","",ROUND($E34*IFERROR(VLOOKUP($B34,'🧵 Yarn & Materials'!$B8:$H31,7,0),0),2)) | H34: =IF($B34="","",IF($C34<=0,"🔴 Urgent","🟠 High"))
C36: SHOPPING LIST TOTAL | E36: =SUM($E$10:$E$34) -> 87 | G36: =SUM($G$10:$G$34) -> 342.7
B38: How the list builds itself
B39: Products appear when stock drops below the 'Keep min.' level you set on the Product Catalog; materials when the stash reaches its 'Low at' number. Buy = double your minimum minus what's left - enough to rebuild the buffer without over-buying yarn. Tick the ✓ once it's ordered and add the date - the list becomes your paper trail.
B43: 💡 Cream cells are yours to type in; white cells calculate. Dropdowns keep every column honest.
B45: Settings | D45: 🏠 Home | F45: Products | H45: Yarn
B46: Stock | D46: Fairs | F46: Sales | H46: Event $
B47: ▶ Reorder | D47: Packing | F47: Pricing | H47: Monthly
B48: Help

Sheet 🎒 Packing Checklist
B2: 🎒 Packing Checklist
B3: Tick your way out the door - nothing left behind | D3: 🏠 Dashboard
B5: ="Packed: "&TEXT(COUNTIF($B$9:$B$35,"✓"),"0")&" of 21" -> Packed: 14 of 21 | E5: =IF(COUNTIF($B$9:$B$35,"✓")=21,"Ready for the fair!","Keep ticking...") -> Keep ticking...
C6: Packing for: | D6: Summer Night Bazaar
B7: # | C7: Item | D7: Where it lives | E7: Notes
B8: Products
B9: ✓ | C9: Finished products
B10: ✓ | C10: Extra inventory
B11: ✓ | C11: Price tags
B12: ✓ | C12: Product labels / care cards
B14: Booth
B15: ✓ | C15: Table
B16: ✓ | C16: Tablecloth
B17: ✓ | C17: Display stands / risers
B18: ✓ | C18: Baskets & bins
C19: Signage & banner
C20: Business cards
B22: Payments
B23: ✓ | C23: Cash float
B24: ✓ | C24: Card reader
B25: ✓ | C25: Phone / tablet
C26: Charger
C27: Payment QR code
B29: Supplies
B30: ✓ | C30: Shopping bags
B31: ✓ | C31: Tissue paper
B32: ✓ | C32: Tape & scissors
C33: Pens
C34: Receipt book
C35: Sticky tack / clips
B38: Packing pro tips
B39: Fill in 'Where it lives' once - next season you'll pack from muscle memory. Use ✗ Skip for things a specific fair doesn't need (some venues provide tables, some ban card readers).
B42: 💡 Cream cells are yours to type in; white cells calculate. Dropdowns keep every column honest.
B44: Settings | D44: 🏠 Home
B45: Products | D45: Yarn
B46: Stock | D46: Fairs
B47: Sales | D47: Event $
B48: Reorder | D48: ▶ Packing
B49: Pricing | D49: Monthly
B50: Help

Sheet 💵 Pricing Calculator
B2: 💵 Pricing Calculator
B3: Never underprice a hand-made item again | H3: 🏠 Dashboard
B5: What goes into one item
G7: What to charge
B10: Yarn cost for this item | E10: 4
B11: Packaging, labels, cards | E11: 1
B12: Hours to make | E12: 1.5
B13: Your hourly wage | E13: 14
B14: Overhead % | E14: 0.1 | G14: Your labour | J14: =N($E$12)*N($E$13) -> 21
B15: Target profit margin | E15: 0.45 | G15: Overhead | J15: =ROUND((N($E$10)+N($E$11)+$J$14)*N($E$14),2) -> 2.6
G16: True cost to make | J16: =ROUND(N($E$10)+N($E$11)+$J$14+$J$15,2) -> 28.6
G17: Price at your margin | J17: =IF(N($E$15)>=1,0,ROUND($J$16/(1-N($E$15)),2)) -> 52
G18: Charm price (….95) | J18: =IF($J$17<=0,0,CEILING($J$17,1)-0.05) -> 51.95
G19: Profit per item | J19: =ROUND($J$17-$J$16,2) -> 23.4
G20: Margin check | J20: =IFERROR($J$19/$J$17,0) -> 0.45
B23: How to use it
B24: True cost = yarn + packaging + your labour + overhead. The suggested price is true cost divided by (1 - margin), the classic retail formula. The charm price rounds up to the nearest .95 - prices ending in 5 or 9 feel friendlier and keep the difference in your pocket. Wage, overhead and margin start from your Lists & Settings values - overwrite them here any time for a one-off item.
B28: 💡 A quick sanity check: if the suggested price makes you wince, your hours or wage are telling you something.
B30: Settings | D30: 🏠 Home | F30: Products | H30: Yarn
B31: Stock | D31: Fairs | F31: Sales | H31: Event $
B32: Reorder | D32: Packing | F32: ▶ Pricing | H32: Monthly
B33: Help

Sheet 📅 Monthly Summary
B2: 📅 Monthly Summary
B3: Your whole year, one row per month | I3: 🏠 Dashboard
B5: ="Year revenue: "&Currency&TEXT(SUM('📅 Monthly Summary'!$C$8:$C$19),"#,##0.00") -> Year revenue: $1,760.00 | E5: ="Year net: "&Currency&TEXT(SUM('📅 Monthly Summary'!$F$8:$F$19),"#,##0.00") -> Year net: $716.50 | H5: ="Best month: "&IFERROR(INDEX('📅 Monthly Summary'!$F$8:$F$19,MATCH(MAX('📅 Monthly Summary'!$F$8:$F$19),'📅 Monthly Summary'!$F$8:$F$19,0)),"-") -> Best month: August | K5: ="Fairs this year: "&TEXT(SUM('📅 Monthly Summary'!$K$8:$K$19),"0") -> Fairs this year: 8
A7: # | B7: Month | C7: Revenue | D7: Cost of goods | E7: Fair fees | F7: Net profit | G7: Margin | H7: Units sold | I7: Avg sale | J7: Profit / item | K7: Fairs
B8: January | C8: ='_Data'!J2 -> 0 | D8: ='_Data'!K2 -> 0 | E8: ='_Data'!L2 -> 0 | F8: ='_Data'!M2 -> 0 | G8: =IFERROR($F8/$C8,0) -> 0 | H8: =SUMIFS('💰 Sales Log'!$E$8:$E$67,'💰 Sales Log'!$B$8:$B$67,">="&DATE(ReportYear,1,1),'💰 Sales Log'!$B$8:$B$67,"<"&EDATE(DATE(ReportYear,1,1),1)) -> 0 | I8: =IFERROR($C8/COUNTIFS('💰 Sales Log'!$B$8:$B$67,">="&DATE(ReportYear,1,1),'💰 Sales Log'!$B$8:$B$67,"<"&EDATE(DATE(ReportYear,1,1),1)),0) -> 0 | J8: =IFERROR($F8/$H8,0) -> 0 | K8: =SUMPRODUCT(('🏪 Craft Fairs'!$C$8:$C$31>=DATE(ReportYear,1,1))*('🏪 Craft Fairs'!$C$8:$C$31<EDATE(DATE(ReportYear,1,1),1))*('🏪 Craft Fairs'!$B$8:$B$31<>"")) -> 0
B9: February | C9: ='_Data'!J3 -> 0 | D9: ='_Data'!K3 -> 0 | E9: ='_Data'!L3 -> 0 | F9: ='_Data'!M3 -> 0 | G9: =IFERROR($F9/$C9,0) -> 0 | H9: =SUMIFS('💰 Sales Log'!$E$8:$E$67,'💰 Sales Log'!$B$8:$B$67,">="&DATE(ReportYear,2,1),'💰 Sales Log'!$B$8:$B$67,"<"&EDATE(DATE(ReportYear,2,1),1)) -> 0 | I9: =IFERROR($C9/COUNTIFS('💰 Sales Log'!$B$8:$B$67,">="&DATE(ReportYear,2,1),'💰 Sales Log'!$B$8:$B$67,"<"&EDATE(DATE(ReportYear,2,1),1)),0) -> 0 | J9: =IFERROR($F9/$H9,0) -> 0 | K9: =SUMPRODUCT(('🏪 Craft Fairs'!$C$8:$C$31>=DATE(ReportYear,2,1))*('🏪 Craft Fairs'!$C$8:$C$31<EDATE(DATE(ReportYear,2,1),1))*('🏪 Craft Fairs'!$B$8:$B$31<>"")) -> 0
B10: March | C10: ='_Data'!J4 -> 300 | D10: ='_Data'!K4 -> 58.8 | E10: ='_Data'!L4 -> 90 | F10: ='_Data'!M4 -> 151.2 | G10: =IFERROR($F10/$C10,0) -> 0.504 | H10: =SUMIFS('💰 Sales Log'!$E$8:$E$67,'💰 Sales Log'!$B$8:$B$67,">="&DATE(ReportYear,3,1),'💰 Sales Log'!$B$8:$B$67,"<"&EDATE(DATE(ReportYear,3,1),1)) -> 14 | I10: =IFERROR($C10/COUNTIFS('💰 Sales Log'!$B$8:$B$67,">="&DATE(ReportYear,3,1),'💰 Sales Log'!$B$8:$B$67,"<"&EDATE(DATE(ReportYear,3,1),1)),0) -> 75 | J10: =IFERROR($F10/$H10,0) -> 10.8 | K10: =SUMPRODUCT(('🏪 Craft Fairs'!$C$8:$C$31>=DATE(ReportYear,3,1))*('🏪 Craft Fairs'!$C$8:$C$31<EDATE(DATE(ReportYear,3,1),1))*('🏪 Craft Fairs'!$B$8:$B$31<>"")) -> 1
B11: April | C11: ='_Data'!J5 -> 174 | D11: ='_Data'!K5 -> 30.4 | E11: ='_Data'!L5 -> 54 | F11: ='_Data'!M5 -> 89.6 | G11: =IFERROR($F11/$C11,0) -> 0.5149 | H11: =SUMIFS('💰 Sales Log'!$E$8:$E$67,'💰 Sales Log'!$B$8:$B$67,">="&DATE(ReportYear,4,1),'💰 Sales Log'!$B$8:$B$67,"<"&EDATE(DATE(ReportYear,4,1),1)) -> 9 | I11: =IFERROR($C11/COUNTIFS('💰 Sales Log'!$B$8:$B$67,">="&DATE(ReportYear,4,1),'💰 Sales Log'!$B$8:$B$67,"<"&EDATE(DATE(ReportYear,4,1),1)),0) -> 58 | J11: =IFERROR($F11/$H11,0) -> 9.96 | K11: =SUMPRODUCT(('🏪 Craft Fairs'!$C$8:$C$31>=DATE(ReportYear,4,1))*('🏪 Craft Fairs'!$C$8:$C$31<EDATE(DATE(ReportYear,4,1),1))*('🏪 Craft Fairs'!$B$8:$B$31<>"")) -> 1
B12: May | C12: ='_Data'!J6 -> 244 | D12: ='_Data'!K6 -> 43.5 | E12: ='_Data'!L6 -> 44 | F12: ='_Data'!M6 -> 156.5 | G12: =IFERROR($F12/$C12,0) -> 0.6414 | H12: =SUMIFS('💰 Sales Log'!$E$8:$E$67,'💰 Sales Log'!$B$8:$B$67,">="&DATE(ReportYear,5,1),'💰 Sales Log'!$B$8:$B$67,"<"&EDATE(DATE(ReportYear,5,1),1)) -> 19 | I12: =IFERROR($C12/COUNTIFS('💰 Sales Log'!$B$8:$B$67,">="&DATE(ReportYear,5,1),'💰 Sales Log'!$B$8:$B$67,"<"&EDATE(DATE(ReportYear,5,1),1)),0) -> 81.33 | J12: =IFERROR($F12/$H12,0) -> 8.24 | K12: =SUMPRODUCT(('🏪 Craft Fairs'!$C$8:$C$31>=DATE(ReportYear,5,1))*('🏪 Craft Fairs'!$C$8:$C$31<EDATE(DATE(ReportYear,5,1),1))*('🏪 Craft Fairs'!$B$8:$B$31<>"")) -> 1
B13: June | C13: ='_Data'!J7 -> 398 | D13: ='_Data'!K7 -> 82.8 | E13: ='_Data'!L7 -> 116 | F13: ='_Data'!M7 -> 199.2 | G13: =IFERROR($F13/$C13,0) -> 0.5005 | H13: =SUMIFS('💰 Sales Log'!$E$8:$E$67,'💰 Sales Log'!$B$8:$B$67,">="&DATE(ReportYear,6,1),'💰 Sales Log'!$B$8:$B$67,"<"&EDATE(DATE(ReportYear,6,1),1)) -> 21 | I13: =IFERROR($C13/COUNTIFS('💰 Sales Log'!$B$8:$B$67,">="&DATE(ReportYear,6,1),'💰 Sales Log'!$B$8:$B$67,"<"&EDATE(DATE(ReportYear,6,1),1)),0) -> 79.6 | J13: =IFERROR($F13/$H13,0) -> 9.49 | K13: =SUMPRODUCT(('🏪 Craft Fairs'!$C$8:$C$31>=DATE(ReportYear,6,1))*('🏪 Craft Fairs'!$C$8:$C$31<EDATE(DATE(ReportYear,6,1),1))*('🏪 Craft Fairs'!$B$8:$B$31<>"")) -> 1
B14: July | C14: ='_Data'!J8 -> 309 | D14: ='_Data'!K8 -> 72.6 | E14: ='_Data'!L8 -> 73 | F14: ='_Data'!M8 -> 163.4 | G14: =IFERROR($F14/$C14,0) -> 0.5288 | H14: =SUMIFS('💰 Sales Log'!$E$8:$E$67,'💰 Sales Log'!$B$8:$B$67,">="&DATE(ReportYear,7,1),'💰 Sales Log'!$B$8:$B$67,"<"&EDATE(DATE(ReportYear,7,1),1)) -> 9 | I14: =IFERROR($C14/COUNTIFS('💰 Sales Log'!$B$8:$B$67,">="&DATE(ReportYear,7,1),'💰 Sales Log'!$B$8:$B$67,"<"&EDATE(DATE(ReportYear,7,1),1)),0) -> 77.25 | J14: =IFERROR($F14/$H14,0) -> 18.16 | K14: =SUMPRODUCT(('🏪 Craft Fairs'!$C$8:$C$31>=DATE(ReportYear,7,1))*('🏪 Craft Fairs'!$C$8:$C$31<EDATE(DATE(ReportYear,7,1),1))*('🏪 Craft Fairs'!$B$8:$B$31<>"")) -> 1
B15: August | C15: ='_Data'!J9 -> 335 | D15: ='_Data'!K9 -> 75.4 | E15: ='_Data'!L9 -> 0 | F15: ='_Data'!M9 -> 259.6 | G15: =IFERROR($F15/$C15,0) -> 0.7749 | H15: =SUMIFS('💰 Sales Log'!$E$8:$E$67,'💰 Sales Log'!$B$8:$B$67,">="&DATE(ReportYear,8,1),'💰 Sales Log'!$B$8:$B$67,"<"&EDATE(DATE(ReportYear,8,1),1)) -> 5 | I15: =IFERROR($C15/COUNTIFS('💰 Sales Log'!$B$8:$B$67,">="&DATE(ReportYear,8,1),'💰 Sales Log'!$B$8:$B$67,"<"&EDATE(DATE(ReportYear,8,1),1)),0) -> 111.67 | J15: =IFERROR($F15/$H15,0) -> 51.92 | K15: =SUMPRODUCT(('🏪 Craft Fairs'!$C$8:$C$31>=DATE(ReportYear,8,1))*('🏪 Craft Fairs'!$C$8:$C$31<EDATE(DATE(ReportYear,8,1),1))*('🏪 Craft Fairs'!$B$8:$B$31<>"")) -> 1
B16: September | C16: ='_Data'!J10 -> 0 | D16: ='_Data'!K10 -> 0 | E16: ='_Data'!L10 -> 145 | F16: ='_Data'!M10 -> -145 | G16: =IFERROR($F16/$C16,0) -> 0 | H16: =SUMIFS('💰 Sales Log'!$E$8:$E$67,'💰 Sales Log'!$B$8:$B$67,">="&DATE(ReportYear,9,1),'💰 Sales Log'!$B$8:$B$67,"<"&EDATE(DATE(ReportYear,9,1),1)) -> 0 | I16: =IFERROR($C16/COUNTIFS('💰 Sales Log'!$B$8:$B$67,">="&DATE(ReportYear,9,1),'💰 Sales Log'!$B$8:$B$67,"<"&EDATE(DATE(ReportYear,9,1),1)),0) -> 0 | J16: =IFERROR($F16/$H16,0) -> 0 | K16: =SUMPRODUCT(('🏪 Craft Fairs'!$C$8:$C$31>=DATE(ReportYear,9,1))*('🏪 Craft Fairs'!$C$8:$C$31<EDATE(DATE(ReportYear,9,1),1))*('🏪 Craft Fairs'!$B$8:$B$31<>"")) -> 1
B17: October | C17: ='_Data'!J11 -> 0 | D17: ='_Data'!K11 -> 0 | E17: ='_Data'!L11 -> 0 | F17: ='_Data'!M11 -> 0 | G17: =IFERROR($F17/$C17,0) -> 0 | H17: =SUMIFS('💰 Sales Log'!$E$8:$E$67,'💰 Sales Log'!$B$8:$B$67,">="&DATE(ReportYear,10,1),'💰 Sales Log'!$B$8:$B$67,"<"&EDATE(DATE(ReportYear,10,1),1)) -> 0 | I17: =IFERROR($C17/COUNTIFS('💰 Sales Log'!$B$8:$B$67,">="&DATE(ReportYear,10,1),'💰 Sales Log'!$B$8:$B$67,"<"&EDATE(DATE(ReportYear,10,1),1)),0) -> 0 | J17: =IFERROR($F17/$H17,0) -> 0 | K17: =SUMPRODUCT(('🏪 Craft Fairs'!$C$8:$C$31>=DATE(ReportYear,10,1))*('🏪 Craft Fairs'!$C$8:$C$31<EDATE(DATE(ReportYear,10,1),1))*('🏪 Craft Fairs'!$B$8:$B$31<>"")) -> 0
B18: November | C18: ='_Data'!J12 -> 0 | D18: ='_Data'!K12 -> 0 | E18: ='_Data'!L12 -> 158 | F18: ='_Data'!M12 -> -158 | G18: =IFERROR($F18/$C18,0) -> 0 | H18: =SUMIFS('💰 Sales Log'!$E$8:$E$67,'💰 Sales Log'!$B$8:$B$67,">="&DATE(ReportYear,11,1),'💰 Sales Log'!$B$8:$B$67,"<"&EDATE(DATE(ReportYear,11,1),1)) -> 0 | I18: =IFERROR($C18/COUNTIFS('💰 Sales Log'!$B$8:$B$67,">="&DATE(ReportYear,11,1),'💰 Sales Log'!$B$8:$B$67,"<"&EDATE(DATE(ReportYear,11,1),1)),0) -> 0 | J18: =IFERROR($F18/$H18,0) -> 0 | K18: =SUMPRODUCT(('🏪 Craft Fairs'!$C$8:$C$31>=DATE(ReportYear,11,1))*('🏪 Craft Fairs'!$C$8:$C$31<EDATE(DATE(ReportYear,11,1),1))*('🏪 Craft Fairs'!$B$8:$B$31<>"")) -> 1
B19: December | C19: ='_Data'!J13 -> 0 | D19: ='_Data'!K13 -> 0 | E19: ='_Data'!L13 -> 0 | F19: ='_Data'!M13 -> 0 | G19: =IFERROR($F19/$C19,0) -> 0 | H19: =SUMIFS('💰 Sales Log'!$E$8:$E$67,'💰 Sales Log'!$B$8:$B$67,">="&DATE(ReportYear,12,1),'💰 Sales Log'!$B$8:$B$67,"<"&EDATE(DATE(ReportYear,12,1),1)) -> 0 | I19: =IFERROR($C19/COUNTIFS('💰 Sales Log'!$B$8:$B$67,">="&DATE(ReportYear,12,1),'💰 Sales Log'!$B$8:$B$67,"<"&EDATE(DATE(ReportYear,12,1),1)),0) -> 0 | J19: =IFERROR($F19/$H19,0) -> 0 | K19: =SUMPRODUCT(('🏪 Craft Fairs'!$C$8:$C$31>=DATE(ReportYear,12,1))*('🏪 Craft Fairs'!$C$8:$C$31<EDATE(DATE(ReportYear,12,1),1))*('🏪 Craft Fairs'!$B$8:$B$31<>"")) -> 0
B20: YEAR TOTAL | C20: =SUM('📅 Monthly Summary'!$C$8:$C$19) -> 1760 | D20: =SUM('📅 Monthly Summary'!$D$8:$D$19) -> 363.5 | E20: =SUM('📅 Monthly Summary'!$E$8:$E$19) -> 680 | F20: =SUM('📅 Monthly Summary'!$F$8:$F$19) -> 716.5 | H20: =SUM('📅 Monthly Summary'!$H$8:$H$19) -> 77 | K20: =SUM('📅 Monthly Summary'!$K$8:$K$19) -> 8
B22: Reading the months
B23: Months follow the Report year on your Lists & Settings tab. Red net months usually mean fair fees paid before the fair happened - they catch up next month. Fair fees land in the month of the fair itself, so a booked Autumn fair shows its booth fee in September.
B27: 💡 Cream cells are yours to type in; white cells calculate. Dropdowns keep every column honest.
B29: Settings | D29: 🏠 Home | F29: Products | H29: Yarn | J29: Stock
B30: Fairs | D30: Sales | F30: Event $ | H30: Reorder | J30: Packing
B31: Pricing | D31: ▶ Monthly | F31: Help

Sheet 📖 Start Here
H20: 🏠 Dashboard
B22: Ultimate Crochet Craft Fair Tracker is a complete little business system for crochet sellers: products and pricing, yarn stash, stock, craft fairs, sales and profit - all in one tidy workbook that does the maths for you.
B24: PREMIUM EDITION • 14 tabs | E24: Berry theme | G24: Excel 2016+ • Google Sheets | J24: No macros
B26: Set up in three minutes
B27: 1. Tell it about your studio
B28: Open Lists & Settings: type your business name, pick your currency symbol, set the report year, your hourly wage, overhead % and target margin. Rename any dropdown list while you're there - categories, payment methods, yarn weights, suppliers.
B30: 2. List what you make
B31: On the Product Catalog tab, add one row per product with its price, yarn cost and packaging. Cost per item, profit and margin calculate themselves. Set a 'Keep min.' level for each - that's your reorder trigger.
B33: 3. Book a fair and sell
B34: Add the fair (and its costs) on the Craft Fairs tab, then log every sale on the Sales Log - pick the fair and product from the dropdowns. The Dashboard, Event Profit and Monthly Summary update instantly.
B36: Your tabs, left to right
B37: Tab | E37: What it does
B38: ⚙️ Lists & Settings | E38: Your studio name, money settings and every dropdown list.
B39: 🏠 Dashboard | E39: Live KPIs, charts and your top products.
B40: 🧶 Product Catalog | E40: One row per product: price, costs, margin, stock.
B41: 🧵 Yarn & Materials | E41: Your whole stash with costs and what's left.
B42: 📦 Made & Stocked | E42: Log making sessions; stock counts itself.
B43: 🏪 Craft Fairs | E43: Book fairs and their costs; profit maths runs itself.
B44: 💰 Sales Log | E44: One row per line item sold - at fairs or online.
B45: 🧮 Event Profit | E45: Was that fair worth it? Net, breakeven and ROI.
B46: 🔄 Reorder List | E46: An auto-built shopping list for stock and yarn.
B47: 🎒 Packing Checklist | E47: Tick your way out the door - nothing left behind.
B48: 💵 Pricing Calculator | E48: Price items so crafting actually pays you.
B49: 📅 Monthly Summary | E49: Your whole year, one row per month.
B51: The golden rules
B52: • White cells are yours to type in. Tinted cells calculate themselves and are locked, so a stray keystroke can't break the maths.
B53: • Dropdown lists are yours: rename, add or delete entries on the Lists & Settings tab and every dropdown follows.
B54: • Type new data in the blank rows inside each table - the formulas are already waiting for you there.
B55: • The _Data tab is the engine room that feeds the Dashboard and charts. It stays hidden on purpose and needs no attention.
B56: • No macros, nothing to install: works in Microsoft Excel 2016 and newer, and uploads cleanly to Google Sheets (Drive → open with Google Sheets).
B58: Work like a pro
B59: • Price before you stitch: run every new design through the Pricing Calculator so your wage and overhead are inside the price, not wishes.
B60: • Log production on Made & Stocked as you finish items - stock levels, the status pills and the Reorder List all follow automatically.
B61: • Check the Reorder List a fortnight before a fair: buy what the list suggests and you won't sell out of your bestseller at 11am.
B62: • After each fair, open Event Profit and compare net profit and ROI. Book the winners again next season; let the losers go.
B63: • Once a month, glance at the Monthly Summary - a red net month usually just means a fair fee paid before the fair happened.
... B71: 💡 Start on the Dashboard tab - it's the front door to everything else.
B73: Settings | D73: 🏠 Home | F73: Products | H73: Yarn
B74: Stock | D74: Fairs | F74: Sales | H74: Event $
B75: Reorder | D75: Packing | F75: Pricing | H75: Monthly
B76: ▶ Help
